Workbook

Sheet AUM
A1: Date | B1: Total AUM | C1: #Accts | D1: MTD +/- | E1: YTD +/-
A2: 41274 | B2: ='Strategy&Account'!B2 -> 16097798 | C2: ='Strategy&Account'!C2 -> 2 | E2: =B2 -> 16097798
A3: 41305 | B3: ='Strategy&Account'!B3 -> 20591061 | C3: ='Strategy&Account'!C3 -> 2 | D3: =B3-B2 -> 4493263.1
A4: 41333 | B4: ='Strategy&Account'!B4 -> 25153160 | C4: ='Strategy&Account'!C4 -> 2 | D4: =B4-B3 -> 4562099.5
A5: 41364 | B5: ='Strategy&Account'!B5 -> 31870607 | C5: ='Strategy&Account'!C5 -> 2 | D5: =B5-B4 -> 6717447
A6: 41394 | B6: ='Strategy&Account'!B6 -> 43261752 | C6: ='Strategy&Account'!C6 -> 2 | D6: =B6-B5 -> 11391145
A7: 41425 | B7: ='Strategy&Account'!B7 -> 53175554 | C7: ='Strategy&Account'!C7 -> 2 | D7: =B7-B6 -> 9913801.9
A8: 41455 | B8: ='Strategy&Account'!B8 -> 59663773 | C8: ='Strategy&Account'!C8 -> 2 | D8: =B8-B7 -> 6488219.3
A9: 41486 | B9: ='Strategy&Account'!B9 -> 74569204 | C9: ='Strategy&Account'!C9 -> 2 | D9: =B9-B8 -> 14905430
A10: 41517 | B10: ='Strategy&Account'!B10 -> 85315152 | C10: ='Strategy&Account'!C10 -> 264 | D10: =B10-B9 -> 10745948
A11: 41547 | B11: ='Strategy&Account'!B11 -> 97529992 | C11: ='Strategy&Account'!C11 -> 301 | D11: =B11-B10 -> 12214840
A12: 41578 | B12: ='Strategy&Account'!B12 -> 1.1223885e+08 | C12: ='Strategy&Account'!C12 -> 361 | D12: =B12-B11 -> 14708854
A13: 41608 | B13: ='Strategy&Account'!B13 -> 1.2427645e+08 | C13: ='Strategy&Account'!C13 -> 398 | D13: =B13-B12 -> 12037600
A14: 41639 | B14: ='Strategy&Account'!B14 -> 1.3471577e+08 | C14: ='Strategy&Account'!C14 -> 439 | D14: =B14-B13 -> 10439320 | E14: =B14-B2 -> 1.1861797e+08
A15: 41670 | B15: ='Strategy&Account'!B15 -> 1.3781396e+08 | C15: ='Strategy&Account'!C15 -> 478 | D15: =B15-B14 -> 3098194.6
A16: 41698 | B16: ='Strategy&Account'!B16 -> 1.4693008e+08 | C16: ='Strategy&Account'!C16 -> 499 | D16: =B16-B15 -> 9116121
A17: 41729 | B17: ='Strategy&Account'!B17 -> 1.5554248e+08 | C17: ='Strategy&Account'!C17 -> 514 | D17: =B17-B16 -> 8612395.8
A18: 41759 | B18: ='Strategy&Account'!B18 -> 1.6240997e+08 | C18: ='Strategy&Account'!C18 -> 521 | D18: =B18-B17 -> 6867493.8
A19: 41790 | B19: ='Strategy&Account'!B19 -> 1.677813e+08 | C19: ='Strategy&Account'!C19 -> 566 | D19: =B19-B18 -> 5371334.1
A20: 41820 | B20: ='Strategy&Account'!B20 -> 1.7451183e+08 | C20: ='Strategy&Account'!C20 -> 584 | D20: =B20-B19 -> 6730526.1
A21: 41851 | B21: ='Strategy&Account'!B21 -> 1.768834e+08 | C21: ='Strategy&Account'!C21 -> 605 | D21: =B21-B20 -> 2371566.1
A22: 41882 | B22: ='Strategy&Account'!B22 -> 1.8671688e+08 | C22: ='Strategy&Account'!C22 -> 619 | D22: =B22-B$21 -> 9833482.6
A23: 41912 | B23: ='Strategy&Account'!B23 -> 1.8719638e+08 | C23: ='Strategy&Account'!C23 -> 632 | D23: =B23-B$22 -> 479495.48
A24: 41943 | B24: ='Strategy&Account'!B24 -> 1.984258e+08 | C24: ='Strategy&Account'!C24 -> 656 | D24: =B24-B$23 -> 11229423
A25: 41973 | B25: ='Strategy&Account'!B25 -> 2.1542342e+08 | C25: ='Strategy&Account'!C25 -> 670 | D25: =B25-B$24 -> 16997627
A26: 42004 | B26: ='Strategy&Account'!B26 -> 2.2268911e+08 | C26: ='Strategy&Account'!C26 -> 660 | D26: =B26-B$25 -> 7265681.8 | E26: =B26-B14 -> 87973341
A27: 42035 | B27: ='Strategy&Account'!B27 -> 2.3063648e+08 | C27: ='Strategy&Account'!C27 -> 697 | D27: =B27-B$26 -> 7947376.2
A28: 42063 | B28: ='Strategy&Account'!B28 -> 2.4880608e+08 | C28: ='Strategy&Account'!C28 -> 716 | D28: =B28-B$27 -> 18169596
A29: 42094 | B29: ='Strategy&Account'!B29 -> 2.6056483e+08 | C29: ='Strategy&Account'!C29 -> 743 | D29: =B29-B$28 -> 11758756
A30: 42124 | B30: ='Strategy&Account'!B30 -> 2.7059347e+08 | C30: ='Strategy&Account'!C30 -> 764 | D30: =B30-B$29 -> 10028634
A31: 42155 | B31: ='Strategy&Account'!B31 -> 2.8375676e+08 | C31: ='Strategy&Account'!C31 -> 765 | D31: =B31-B$30 -> 13163290
A32: 42185 | B32: ='Strategy&Account'!B32 -> 2.7979975e+08 | C32: ='Strategy&Account'!C32 -> 783 | D32: =B32-B$31 -> -3957004.1
A33: 42216 | B33: ='Strategy&Account'!B33 -> 3.0558192e+08 | C33: ='Strategy&Account'!C33 -> 795 | D33: =B33-B$32 -> 25782167
A34: 42247 | B34: ='Strategy&Account'!B34 -> 2.9712704e+08 | C34: ='Strategy&Account'!C34 -> 806 | D34: =B34-B$33 -> -8454884.5
A35: 42277 | B35: ='Strategy&Account'!B35 -> 3.0023612e+08 | C35: ='Strategy&Account'!C35 -> 810 | D35: =B35-B$34 -> 3109085.1
A36: 42308 | B36: ='Strategy&Account'!B36 -> 3.3097015e+08 | C36: ='Strategy&Account'!C36 -> 822 | D36: =B36-B$35 -> 30734031
A37: 42338 | B37: ='Strategy&Account'!B37 -> 3.3180873e+08 | C37: ='Strategy&Account'!C37 -> 812 | D37: =B37-B$36 -> 838577.69
A38: 42369 | B38: ='Strategy&Account'!B38 -> 3.3229184e+08 | C38: ='Strategy&Account'!C38 -> 807 | D38: =B38-B$37 -> 483112.53 | E38: =B38-B26 -> 1.0960274e+08
A39: 42400 | B39: ='Strategy&Account'!B39 -> 3.9631938e+08 | C39: ='Strategy&Account'!C39 -> 798 | D39: =B39-B$38 -> 64027538
A40: 42429 | B40: ='Strategy&Account'!B40 -> 4.3188242e+08 | C40: ='Strategy&Account'!C40 -> 796 | D40: =B40-B$39 -> 35563042
A41: 42460 | B41: ='Strategy&Account'!B41 -> 5.5371888e+08 | C41: ='Strategy&Account'!C41 -> 813 | D41: =B41-B$40 -> 1.2183646e+08
A42: 42490 | B42: ='Strategy&Account'!B42 -> 5.6409047e+08 | C42: ='Strategy&Account'!C42 -> 824 | D42: =B42-$B41 -> 10371591
A43: 42521 | B43: ='Strategy&Account'!B43 -> 5.8791184e+08 | C43: ='Strategy&Account'!C43 -> 807 | D43: =B43-$B42 -> 23821367
A44: 42551 | B44: ='Strategy&Account'!B44 -> 6.2048246e+08 | C44: ='Strategy&Account'!C44 -> 770 | D44: =B44-$B43 -> 32570621
A45: 42582 | B45: ='Strategy&Account'!B45 -> 6.4942262e+08 | C45: ='Strategy&Account'!C45 -> 772 | D45: =B45-$B44 -> 28940155
A46: 42613 | B46: ='Strategy&Account'!B46 -> 6.5382968e+08 | C46: ='Strategy&Account'!C46 -> 746 | D46: =B46-$B45 -> 4407067.3
A47: 42643 | B47: ='Strategy&Account'!B47 -> 6.4280753e+08 | C47: ='Strategy&Account'!C47 -> 747 | D47: =B47-$B46 -> -11022150
A48: 42674 | B48: ='Strategy&Account'!B48 -> 6.2041962e+08 | C48: ='Strategy&Account'!C48 -> 751 | D48: =B48-$B47 -> -22387919
A49: 42704 | B49: ='Strategy&Account'!B49 -> 6.3931919e+08 | C49: ='Strategy&Account'!C49 -> 757 | D49: =B49-$B48 -> 18899576
A50: 42735 | B50: ='Strategy&Account'!B50 -> 6.5309062e+08 | C50: ='Strategy&Account'!C50 -> 747 | D50: =B50-$B49 -> 13771431 | E50: =B50-B38 -> 3.2079878e+08
A51: 42766 | B51: ='Strategy&Account'!B51 -> 6.6950403e+08 | C51: ='Strategy&Account'!C51 -> 754 | D51: =B51-$B50 -> 16413408
A52: 42794 | B52: ='Strategy&Account'!B52 -> 6.8328576e+08 | C52: ='Strategy&Account'!C52 -> 760 | D52: =B52-$B51 -> 13781735
A53: 42825 | B53: ='Strategy&Account'!B53 -> 7.0037861e+08 | C53: ='Strategy&Account'!C53 -> 750 | D53: =B53-$B52 -> 17092849
A54: 42855 | B54: ='Strategy&Account'!B54 -> 7.0319676e+08 | C54: ='Strategy&Account'!C54 -> 772 | D54: =B54-$B53 -> 2818148.5
A55: 42886 | B55: ='Strategy&Account'!B55 -> 7.107173e+08 | C55: ='Strategy&Account'!C55 -> 778 | D55: =B55-$B54 -> 7520538.2
A56: 42916 | B56: ='Strategy&Account'!B56 -> 7.1935202e+08 | C56: ='Strategy&Account'!C56 -> 780 | D56: =B56-$B55 -> 8634723.4
A57: 42947 | B57: ='Strategy&Account'!B57 -> 7.2320575e+08 | C57: ='Strategy&Account'!C57 -> 778 | D57: =B57-$B56 -> 3853726.3
A58: 42978 | B58: ='Strategy&Account'!B58 -> 7.3409084e+08 | C58: ='Strategy&Account'!C58 -> 785 | D58: =B58-$B57 -> 10885089
A59: 43008 | B59: ='Strategy&Account'!B59 -> 7.0701063e+08 | C59: ='Strategy&Account'!C59 -> 790 | D59: =B59-$B58 -> -27080205
A60: 43039 | B60: ='Strategy&Account'!B60 -> 7.1567963e+08 | C60: ='Strategy&Account'!C60 -> 790 | D60: =B60-$B59 -> 8668996.9 | F60: Lost LACERA in Sept 2017 account due to Northern Trust
A61: 43069 | B61: ='Strategy&Account'!B61 -> 7.0804236e+08 | C61: ='Strategy&Account'!C61 -> 797 | D61: =B61-$B60 -> -7637266.5 | F61: Lost Some of Gallaway Financial Accounts
A62: 43100 | B62: ='Strategy&Account'!B62 -> 7.0981867e+08 | C62: ='Strategy&Account'!C62 -> 787 | D62: =B62-$B61 -> 1776304.8 | E62: =B62-B50 -> 56728047
A63: 43131 | B63: ='Strategy&Account'!B63 -> 7.2815268e+08 | C63: ='Strategy&Account'!C63 -> 796 | D63: =B63-$B62 -> 18334008
A64: 43159 | B64: ='Strategy&Account'!B64 -> 7.1541751e+08 | C64: ='Strategy&Account'!C64 -> 811 | D64: =B64-$B63 -> -12735170
A65: 43190 | B65: ='Strategy&Account'!B65 -> 7.1117603e+08 | C65: ='Strategy&Account'!C65 -> 896 | D65: =B65-$B64 -> -4241478.7
A66: 43220 | B66: ='Strategy&Account'!B66 -> 7.1860191e+08 | C66: ='Strategy&Account'!C66 -> 921 | D66: =B66-$B65 -> 7425878.2
A67: 43251 | B67: ='Strategy&Account'!B67 -> 7.3177894e+08 | C67: ='Strategy&Account'!C67 -> 932 | D67: =B67-$B66 -> 13177033
A68: 43281 | B68: ='Strategy&Account'!B68 -> 7.4596352e+08 | C68: ='Strategy&Account'!C68 -> 886 | D68: =B68-$B67 -> 14184579
A69: 43312 | B69: ='Strategy&Account'!B69 -> 7.7870983e+08 | C69: ='Strategy&Account'!C69 -> 861 | D69: =B69-$B68 -> 32746316
A70: 43343 | B70: ='Strategy&Account'!B70 -> 8.2615281e+08 | C70: ='Strategy&Account'!C70 -> 871 | D70: =B70-$B69 -> 47442971
A71: 43373 | B71: ='Strategy&Account'!B71 -> 8.3460999e+08 | C71: ='Strategy&Account'!C71 -> 879 | D71: =B71-$B70 -> 8457183.5
A72: 43404 | B72: ='Strategy&Account'!B72 -> 7.8198793e+08 | C72: ='Strategy&Account'!C72 -> 899 | D72: =B72-$B71 -> -52622060
A73: 43434 | B73: ='Strategy&Account'!B73 -> 8.0683793e+08 | C73: ='Strategy&Account'!C73 -> 899 | D73: =B73-$B72 -> 24849997
A74: 43465 | B74: ='Strategy&Account'!B74 -> 7.3628402e+08 | C74: ='Strategy&Account'!C74 -> 916 | D74: =B74-$B73 -> -70553904
... A94: 44074 | B94: ='Strategy&Account'!B94 -> 1.3624484e+09 | C94: ='Strategy&Account'!C94 -> 1714 | D94: =B94-$B93 -> 71754044
A95: 44104 | B95: ='Strategy&Account'!B95 -> 1.3353677e+09 | C95: ='Strategy&Account'!C95 -> 1760 | D95: =B95-$B94 -> -27080641 | E95: =B95-B89 -> 3.2327909e+08
A96: 44135 | B96: ='Strategy&Account'!B96 -> 1.3094149e+09 | C96: ='Strategy&Account'!C96 -> 1790 | D96: =B96-$B95 -> -25952796
A97: 44165 | B97: ='Strategy&Account'!B97 -> 1.4163024e+09 | C97: ='Strategy&Account'!C97 -> 1819 | D97: =B97-$B96 -> 1.0688748e+08
A98: 44196 | B98: ='Strategy&Account'!B98 -> 1.4967813e+09 | C98: ='Strategy&Account'!C98 -> 1877 | D98: =B98-$B97 -> 80478877
A99: 44227 | B99: ='Strategy&Account'!B99 -> 1.6154749e+09 | C99: ='Strategy&Account'!C99 -> 2109 | D99: =B99-$B98 -> 1.1869356e+08
A100: 44255 | B100: ='Strategy&Account'!B100 -> 1.6191368e+09 | C100: ='Strategy&Account'!C100 -> 2165 | D100: =B100-$B99 -> 3661972
A101: 44286 | B101: ='Strategy&Account'!B101 -> 1.7472793e+09 | C101: ='Strategy&Account'!C101 -> 2277 | D101: =B101-$B100 -> 1.2814246e+08
A102: 44316 | B102: ='Strategy&Account'!B102 -> 1.8216559e+09 | C102: ='Strategy&Account'!C102 -> 2359 | D102: =B102-$B101 -> 74376622
A103: 44347 | B103: ='Strategy&Account'!B103 -> 1.8149149e+09 | C103: ='Strategy&Account'!C103 -> 2393 | D103: =B103-$B102 -> -6741040.3
A104: 44377 | B104: ='Strategy&Account'!B104 -> 1.8579162e+09 | C104: ='Strategy&Account'!C104 -> 2446 | D104: =B104-$B103 -> 43001362
A105: 44408 | B105: ='Strategy&Account'!B105 -> 1.6084676e+09 | C105: ='Strategy&Account'!C105 -> 2506 | D105: =B105-$B104 -> -2.494486e+08
A106: 44439 | B106: ='Strategy&Account'!B106 -> 1.6479819e+09 | C106: ='Strategy&Account'!C106 -> 2544 | D106: =B106-$B105 -> 39514282
A107: 44469 | B107: ='Strategy&Account'!B107 -> 1.5864534e+09 | C107: ='Strategy&Account'!C107 -> 2592 | D107: =B107-$B106 -> -61528554
... A116: 44742 | B116: ='Strategy&Account'!B116 -> 1.5139377e+09 | C116: ='Strategy&Account'!C116 -> 3177 | D116: =B116-$B115 -> -85613032

Sheet Strategy&Account
A1: Date | B1: Total AUM | C1: Accts | D1: Large Cap | E1: Accts | F1: Small Cap | G1: Accts | H1: Global | I1: Accts | J1: AA | K1: Accts | L1: Other | M1: Accts | O1: SILVX | P1: Accts | Q1: SGLIX | R1: Accts | S1: BOGIX | T1: Accts | U1: Funds of Funds | V1: Accts | W1: DYTA | X1: Accts | Y1: SGLC | Z1: Accts | AA1: GINX | AB1: Accts | AC1: USDX | AD1: Accts | AE1: QXQ | AF1: Accts | AG1: LDRX | AH1: Accts | AI1: Timpanogos | AJ1: Accts | AK1: Interactive Brokers | AL1: Accts | AM1: Schwab | AN1: Accts | AO1: Fidelity | AP1: Accts | AQ1: Empower | AR1: Accts | AS1: Betterment | AT1: Accts | AU1: GPB Capital | AV1: Accts | AW1: GS-Folio | AX1: Accts | AY1: ePlan | AZ1: Accts | BA1: TFA USLV | BB1: Accts | BC1: TFA CLV | BD1: Accts | BE1: TFA Tactical | BG1: UNC LC | BH1: Accts | BI1: Schwab LC | BJ1: Accts | BK1: American Funds | BL1: Accts | BM1: Empower 401k | BN1: Accts | BO1: Human Interest | BP1: Accts | BQ1: Paychex | BR1: Accts | BS1: Transamerica401k | BT1: Accts | BU1: Ascensus | BV1: Accts | BW1: Matrix/Mid-Atlantic | BX1: Accts | BY1: Nationwide | BZ1: Accts | CA1: TIAA | CB1: Accts | CC1: Fidelity Workplace Investing | CD1: Accts | CE1: Jackson | CF1: Accts | CG1: Betterment 401k | CH1: Accts | CI1: NC State | CJ1: Accts | CK1: Holiday Oil | CL1: Accts | CM1: SCLVX | CN1: Accts | CO1: Stifel | CP1: Accts | CQ1: TDA | CR1: Accts | CS1: UNC SC | CT1: Accts | CU1: Asbestos Workers | CV1: Accts | CW1: TUG | CX1: Accts | CY1: Cline | CZ1: Accts | DA1: Prudential | DB1: Accts | DC1: LACERA | DD1: Accts | DE1: Folio | DF1: Accts | DG1: Vanguard | DH1: Accts
A2: 41274 | B2: =O2+CM2+Q2+AM2+CQ2+AO2+DA2+BA2+BC2+CO2+BG2+CS2+BI2+CY2+CK2+DC2+DE2 -> 16097798 | C2: =P2+CN2+R2+AN2+CR2+AP2+DB2+BB2+BD2+CP2+BH2+CT2+BJ2+CZ2+CL2+DD2+DF2 -> 2 | D2: =O2+BA2+CO2+BG2+BI2+DC2 -> 15737148 | E2: =P2+BB2+CP2+BH2+BJ2+DD2 -> 2 | F2: =CM2+CS2 -> 0 | H2: =Q2+CY2 -> 0 | J2: =AM2+CQ2+AO2+DA2 -> 360649.55 | K2: =AN2+CR2+AP2+DB2 -> 0 | L2: =BC2+CK2+DE2 -> 0 | O2: =SILVX!B9 -> 9486552.3 | P2: =SILVX!G9 -> 1 | AO2: =Fidelity!P2 -> 360649.55 | AP2: =Fidelity!O2 -> 0 | BA2: ='TFA - Folio'!H7 -> 6250596 | BB2: ='TFA - Folio'!I2 -> 1
A3: 41305 | B3: =O3+CM3+Q3+AM3+CQ3+AO3+DA3+BA3+BC3+CO3+BG3+CS3+BI3+CY3+CK3+DC3+DE3 -> 20591061 | C3: =P3+CN3+R3+AN3+CR3+AP3+DB3+BB3+BD3+CP3+BH3+CT3+BJ3+CZ3+CL3+DD3+DF3 -> 2 | D3: =O3+BA3+CO3+BG3+BI3+DC3 -> 19854280 | E3: =P3+BB3+CP3+BH3+BJ3+DD3 -> 2 | F3: =CM3+CS3 -> 0 | H3: =Q3+CY3 -> 0 | J3: =AM3+CQ3+AO3+DA3 -> 736781.34 | K3: =AN3+CR3+AP3+DB3 -> 0 | L3: =BC3+CK3+DE3 -> 0 | O3: =SILVX!B10 -> 10810338 | P3: =SILVX!G10 -> 1 | AO3: =Fidelity!P3 -> 736781.34 | AP3: =Fidelity!O3 -> 0 | BA3: ='TFA - Folio'!H8 -> 9043941.1 | BB3: ='TFA - Folio'!I3 -> 1
A4: 41333 | B4: =O4+CM4+Q4+AM4+CQ4+AO4+DA4+BA4+BC4+CO4+BG4+CS4+BI4+CY4+CK4+DC4+DE4 -> 25153160 | C4: =P4+CN4+R4+AN4+CR4+AP4+DB4+BB4+BD4+CP4+BH4+CT4+BJ4+CZ4+CL4+DD4+DF4 -> 2 | D4: =O4+BA4+CO4+BG4+BI4+DC4 -> 24387901 | E4: =P4+BB4+CP4+BH4+BJ4+DD4 -> 2 | F4: =CM4+CS4 -> 0 | H4: =Q4+CY4 -> 0 | J4: =AM4+CQ4+AO4+DA4 -> 765259.8 | K4: =AN4+CR4+AP4+DB4 -> 0 | L4: =BC4+CK4+DE4 -> 0 | O4: =SILVX!B11 -> 11771288 | P4: =SILVX!G11 -> 1 | AO4: =Fidelity!P4 -> 765259.8 | AP4: =Fidelity!O4 -> 0 | BA4: ='TFA - Folio'!H9 -> 12616613 | BB4: ='TFA - Folio'!I4 -> 1
A5: 41364 | B5: =O5+CM5+Q5+AM5+CQ5+AO5+DA5+BA5+BC5+CO5+BG5+CS5+BI5+CY5+CK5+DC5+DE5 -> 31870607 | C5: =P5+CN5+R5+AN5+CR5+AP5+DB5+BB5+BD5+CP5+BH5+CT5+BJ5+CZ5+CL5+DD5+DF5 -> 2 | D5: =O5+BA5+CO5+BG5+BI5+DC5 -> 31059851 | E5: =P5+BB5+CP5+BH5+BJ5+DD5 -> 2 | F5: =CM5+CS5 -> 0 | H5: =Q5+CY5 -> 0 | J5: =AM5+CQ5+AO5+DA5 -> 810756.3 | K5: =AN5+CR5+AP5+DB5 -> 0 | L5: =BC5+CK5+DE5 -> 0 | O5: =SILVX!B12 -> 13089271 | P5: =SILVX!G12 -> 1 | AO5: =Fidelity!P5 -> 810756.3 | AP5: =Fidelity!O5 -> 0 | BA5: ='TFA - Folio'!H10 -> 17970580 | BB5: ='TFA - Folio'!I5 -> 1
A6: 41394 | B6: =O6+CM6+Q6+AM6+CQ6+AO6+DA6+BA6+BC6+CO6+BG6+CS6+BI6+CY6+CK6+DC6+DE6 -> 43261752 | C6: =P6+CN6+R6+AN6+CR6+AP6+DB6+BB6+BD6+CP6+BH6+CT6+BJ6+CZ6+CL6+DD6+DF6 -> 2 | D6: =O6+BA6+CO6+BG6+BI6+DC6 -> 42436074 | E6: =P6+BB6+CP6+BH6+BJ6+DD6 -> 2 | F6: =CM6+CS6 -> 0 | H6: =Q6+CY6 -> 0 | J6: =AM6+CQ6+AO6+DA6 -> 825678.33 | K6: =AN6+CR6+AP6+DB6 -> 0 | L6: =BC6+CK6+DE6 -> 0 | O6: =SILVX!B13 -> 16958369 | P6: =SILVX!G13 -> 1 | AO6: =Fidelity!P6 -> 825678.33 | AP6: =Fidelity!O6 -> 0 | BA6: ='TFA - Folio'!H11 -> 25477705 | BB6: ='TFA - Folio'!I6 -> 1
A7: 41425 | B7: =O7+CM7+Q7+AM7+CQ7+AO7+DA7+BA7+BC7+CO7+BG7+CS7+BI7+CY7+CK7+DC7+DE7 -> 53175554 | C7: =P7+CN7+R7+AN7+CR7+AP7+DB7+BB7+BD7+CP7+BH7+CT7+BJ7+CZ7+CL7+DD7+DF7 -> 2 | D7: =O7+BA7+CO7+BG7+BI7+DC7 -> 50925776 | E7: =P7+BB7+CP7+BH7+BJ7+DD7 -> 2 | F7: =CM7+CS7 -> 0 | H7: =Q7+CY7 -> 0 | J7: =AM7+CQ7+AO7+DA7 -> 2249778 | K7: =AN7+CR7+AP7+DB7 -> 0 | L7: =BC7+CK7+DE7 -> 0 | O7: =SILVX!B14 -> 17899655 | P7: =SILVX!G14 -> 1 | AM7: =Schwab!S2 -> 1398649.8 | AN7: =Schwab!Q2 -> 0 | AO7: =Fidelity!P7 -> 851128.19 | AP7: =Fidelity!O7 -> 0 | BA7: ='TFA - Folio'!H12 -> 33026121 | BB7: ='TFA - Folio'!I7 -> 1
A8: 41455 | B8: =O8+CM8+Q8+AM8+CQ8+AO8+DA8+BA8+BC8+CO8+BG8+CS8+BI8+CY8+CK8+DC8+DE8 -> 59663773 | C8: =P8+CN8+R8+AN8+CR8+AP8+DB8+BB8+BD8+CP8+BH8+CT8+BJ8+CZ8+CL8+DD8+DF8 -> 2 | D8: =O8+BA8+CO8+BG8+BI8+DC8 -> 56450118 | E8: =P8+BB8+CP8+BH8+BJ8+DD8 -> 2 | F8: =CM8+CS8 -> 0 | H8: =Q8+CY8 -> 0 | J8: =AM8+CQ8+AO8+DA8 -> 3213655.1 | K8: =AN8+CR8+AP8+DB8 -> 0 | L8: =BC8+CK8+DE8 -> 0 | O8: =SILVX!B15 -> 18417136 | P8: =SILVX!G15 -> 1 | AM8: =Schwab!S3 -> 2362526.9 | AN8: =Schwab!Q3 -> 0 | AO8: =Fidelity!P8 -> 851128.19 | AP8: =Fidelity!O8 -> 0 | BA8: ='TFA - Folio'!H13 -> 38032982 | BB8: ='TFA - Folio'!I8 -> 1
A9: 41486 | B9: =O9+CM9+Q9+AM9+CQ9+AO9+DA9+BA9+BC9+CO9+BG9+CS9+BI9+CY9+CK9+DC9+DE9 -> 74569204 | C9: =P9+CN9+R9+AN9+CR9+AP9+DB9+BB9+BD9+CP9+BH9+CT9+BJ9+CZ9+CL9+DD9+DF9 -> 2 | D9: =O9+BA9+CO9+BG9+BI9+DC9 -> 66850098 | E9: =P9+BB9+CP9+BH9+BJ9+DD9 -> 2 | F9: =CM9+CS9 -> 0 | H9: =Q9+CY9 -> 0 | J9: =AM9+CQ9+AO9+DA9 -> 7719105.8 | K9: =AN9+CR9+AP9+DB9 -> 0 | L9: =BC9+CK9+DE9 -> 0 | O9: =SILVX!B16 -> 23781673 | P9: =SILVX!G16 -> 1 | AM9: =Schwab!S4 -> 6867977.6 | AN9: =Schwab!Q4 -> 0 | AO9: =Fidelity!P9 -> 851128.19 | AP9: =Fidelity!O9 -> 0 | BA9: ='TFA - Folio'!H14 -> 43068425 | BB9: ='TFA - Folio'!I9 -> 1
A10: 41517 | B10: =O10+CM10+Q10+AM10+CQ10+AO10+DA10+BA10+BC10+CO10+BG10+CS10+BI10+CY10+CK10+DC10+DE10 -> 85315152 | C10: =P10+CN10+R10+AN10+CR10+AP10+DB10+BB10+BD10+CP10+BH10+CT10+BJ10+CZ10+CL10+DD10+DF10 -> 264 | D10: =O10+BA10+CO10+BG10+BI10+DC10 -> 74606688 | E10: =P10+BB10+CP10+BH10+BJ10+DD10 -> 2 | F10: =CM10+CS10 -> 0 | H10: =Q10+CY10 -> 0 | J10: =AM10+CQ10+AO10+DA10 -> 10708464 | K10: =AN10+CR10+AP10+DB10 -> 262 | L10: =BC10+CK10+DE10 -> 0 | O10: =SILVX!B17 -> 25620949 | P10: =SILVX!G17 -> 1 | AM10: =Schwab!S5 -> 9857335.7 | AN10: =Schwab!Q5 -> 262 | AO10: =Fidelity!P10 -> 851128.19 | AP10: =Fidelity!O10 -> 0 | BA10: ='TFA - Folio'!H15 -> 48985739 | BB10: ='TFA - Folio'!I10 -> 1
A11: 41547 | B11: =O11+CM11+Q11+AM11+CQ11+AO11+DA11+BA11+BC11+CO11+BG11+CS11+BI11+CY11+CK11+DC11+DE11 -> 97529992 | C11: =P11+CN11+R11+AN11+CR11+AP11+DB11+BB11+BD11+CP11+BH11+CT11+BJ11+CZ11+CL11+DD11+DF11 -> 301 | D11: =O11+BA11+CO11+BG11+BI11+DC11 -> 85851808 | E11: =P11+BB11+CP11+BH11+BJ11+DD11 -> 2 | F11: =CM11+CS11 -> 0 | H11: =Q11+CY11 -> 0 | J11: =AM11+CQ11+AO11+DA11 -> 11678184 | K11: =AN11+CR11+AP11+DB11 -> 299 | L11: =BC11+CK11+DE11 -> 0 | O11: =SILVX!B18 -> 30750157 | P11: =SILVX!G18 -> 1 | AM11: =Schwab!S6 -> 10474450 | AN11: =Schwab!Q6 -> 299 | AO11: =Fidelity!P11 -> 1203734.2 | AP11: =Fidelity!O11 -> 0 | BA11: ='TFA - Folio'!H16 -> 55101650 | BB11: ='TFA - Folio'!I11 -> 1
A12: 41578 | B12: =O12+CM12+Q12+AM12+CQ12+AO12+DA12+BA12+BC12+CO12+BG12+CS12+BI12+CY12+CK12+DC12+DE12 -> 1.1223885e+08 | C12: =P12+CN12+R12+AN12+CR12+AP12+DB12+BB12+BD12+CP12+BH12+CT12+BJ12+CZ12+CL12+DD12+DF12 -> 361 | D12: =O12+BA12+CO12+BG12+BI12+DC12 -> 98338071 | E12: =P12+BB12+CP12+BH12+BJ12+DD12 -> 2 | F12: =CM12+CS12 -> 0 | H12: =Q12+CY12 -> 0 | J12: =AM12+CQ12+AO12+DA12 -> 13900775 | K12: =AN12+CR12+AP12+DB12 -> 359 | L12: =BC12+CK12+DE12 -> 0 | O12: =SILVX!B19 -> 34983487 | P12: =SILVX!G19 -> 1 | AM12: =Schwab!S7 -> 12624431 | AN12: =Schwab!Q7 -> 358 | AO12: =Fidelity!P12 -> 1247725.3 | AP12: =Fidelity!O12 -> 0 | BA12: ='TFA - Folio'!H17 -> 63354584 | BB12: ='TFA - Folio'!I12 -> 1 | CQ12: =TDA!O2 -> 28618.9 | CR12: =TDA!N2 -> 1
A13: 41608 | B13: =O13+CM13+Q13+AM13+CQ13+AO13+DA13+BA13+BC13+CO13+BG13+CS13+BI13+CY13+CK13+DC13+DE13 -> 1.2427645e+08 | C13: =P13+CN13+R13+AN13+CR13+AP13+DB13+BB13+BD13+CP13+BH13+CT13+BJ13+CZ13+CL13+DD13+DF13 -> 398 | D13: =O13+BA13+CO13+BG13+BI13+DC13 -> 1.0879169e+08 | E13: =P13+BB13+CP13+BH13+BJ13+DD13 -> 2 | F13: =CM13+CS13 -> 0 | H13: =Q13+CY13 -> 0 | J13: =AM13+CQ13+AO13+DA13 -> 15484753 | K13: =AN13+CR13+AP13+DB13 -> 396 | L13: =BC13+CK13+DE13 -> 0 | O13: =SILVX!B20 -> 38040703 | P13: =SILVX!G20 -> 1 | AM13: =Schwab!S8 -> 13896473 | AN13: =Schwab!Q8 -> 395 | AO13: =Fidelity!P13 -> 1559660.7 | AP13: =Fidelity!O13 -> 0 | BA13: ='TFA - Folio'!H18 -> 70750990 | BB13: ='TFA - Folio'!I13 -> 1 | CQ13: =TDA!O3 -> 28618.9 | CR13: =TDA!N3 -> 1
A14: 41639 | B14: =O14+CM14+Q14+AM14+CQ14+AO14+DA14+BA14+BC14+CO14+BG14+CS14+BI14+CY14+CK14+DC14+DE14 -> 1.3471577e+08 | C14: =P14+CN14+R14+AN14+CR14+AP14+DB14+BB14+BD14+CP14+BH14+CT14+BJ14+CZ14+CL14+DD14+DF14 -> 439 | D14: =O14+BA14+CO14+BG14+BI14+DC14 -> 1.1750897e+08 | E14: =P14+BB14+CP14+BH14+BJ14+DD14 -> 2 | F14: =CM14+CS14 -> 0 | H14: =Q14+CY14 -> 0 | J14: =AM14+CQ14+AO14+DA14 -> 17206800 | K14: =AN14+CR14+AP14+DB14 -> 437 | L14: =BC14+CK14+DE14 -> 0 | O14: =SILVX!B21 -> 40565492 | P14: =SILVX!G21 -> 1 | AM14: =Schwab!S9 -> 15885894 | AN14: =Schwab!Q9 -> 436 | AO14: =Fidelity!P14 -> 1293301.8 | AP14: =Fidelity!O14 -> 0 | BA14: ='TFA - Folio'!H19 -> 76943473 | BB14: ='TFA - Folio'!I14 -> 1 | CQ14: =TDA!O4 -> 27604.99 | CR14: =TDA!N4 -> 1
A15: 41670 | B15: =O15+CM15+Q15+AM15+CQ15+AO15+DA15+BA15+BC15+CO15+BG15+CS15+BI15+CY15+CK15+DC15+DE15 -> 1.3781396e+08 | C15: =P15+CN15+R15+AN15+CR15+AP15+DB15+BB15+BD15+CP15+BH15+CT15+BJ15+CZ15+CL15+DD15+DF15 -> 478 | D15: =O15+BA15+CO15+BG15+BI15+DC15 -> 1.2258792e+08 | E15: =P15+BB15+CP15+BH15+BJ15+DD15 -> 2 | F15: =CM15+CS15 -> 0 | H15: =Q15+CY15 -> 0 | J15: =AM15+CQ15+AO15+DA15 -> 15226041 | K15: =AN15+CR15+AP15+DB15 -> 476 | L15: =BC15+CK15+DE15 -> 0 | O15: =SILVX!B22 -> 44164273 | P15: =SILVX!G22 -> 1 | AM15: =Schwab!S10 -> 13704419 | AN15: =Schwab!Q10 -> 473 | AO15: =Fidelity!P15 -> 1302130.3 | AP15: =Fidelity!O15 -> 0 | BA15: ='TFA - Folio'!H20 -> 78423646 | BB15: ='TFA - Folio'!I15 -> 1 | CQ15: =TDA!O5 -> 219492.31 | CR15: =TDA!N5 -> 3
A16: 41698 | B16: =O16+CM16+Q16+AM16+CQ16+AO16+DA16+BA16+BC16+CO16+BG16+CS16+BI16+CY16+CK16+DC16+DE16 -> 1.4693008e+08 | C16: =P16+CN16+R16+AN16+CR16+AP16+DB16+BB16+BD16+CP16+BH16+CT16+BJ16+CZ16+CL16+DD16+DF16 -> 499 | D16: =O16+BA16+CO16+BG16+BI16+DC16 -> 1.3129856e+08 | E16: =P16+BB16+CP16+BH16+BJ16+DD16 -> 2 | F16: =CM16+CS16 -> 0 | H16: =Q16+CY16 -> 0 | J16: =AM16+CQ16+AO16+DA16 -> 15631522 | K16: =AN16+CR16+AP16+DB16 -> 497 | L16: =BC16+CK16+DE16 -> 0 | O16: =SILVX!B23 -> 48302398 | P16: =SILVX!G23 -> 1 | AM16: =Schwab!S11 -> 13936786 | AN16: =Schwab!Q11 -> 492 | AO16: =Fidelity!P16 -> 1356520.3 | AP16: =Fidelity!O16 -> 0 | BA16: ='TFA - Folio'!H21 -> 82996161 | BB16: ='TFA - Folio'!I16 -> 1 | CQ16: =TDA!O6 -> 338215.8 | CR16: =TDA!N6 -> 5
A17: 41729 | B17: =O17+CM17+Q17+AM17+CQ17+AO17+DA17+BA17+BC17+CO17+BG17+CS17+BI17+CY17+CK17+DC17+DE17 -> 1.5554248e+08 | C17: =P17+CN17+R17+AN17+CR17+AP17+DB17+BB17+BD17+CP17+BH17+CT17+BJ17+CZ17+CL17+DD17+DF17 -> 514 | D17: =O17+BA17+CO17+BG17+BI17+DC17 -> 1.3979722e+08 | E17: =P17+BB17+CP17+BH17+BJ17+DD17 -> 2 | F17: =CM17+CS17 -> 0 | H17: =Q17+CY17 -> 0 | J17: =AM17+CQ17+AO17+DA17 -> 15745262 | K17: =AN17+CR17+AP17+DB17 -> 512 | L17: =BC17+CK17+DE17 -> 0 | O17: =SILVX!B24 -> 50613401 | P17: =SILVX!G24 -> 1 | AM17: =Schwab!S12 -> 14063159 | AN17: =Schwab!Q12 -> 507 | AO17: =Fidelity!P17 -> 1526939.8 | AP17: =Fidelity!O17 -> 0 | BA17: ='TFA - Folio'!H22 -> 89183815 | BB17: ='TFA - Folio'!I17 -> 1 | CQ17: =TDA!O7 -> 155162.64 | CR17: =TDA!N7 -> 5
A18: 41759 | B18: =O18+CM18+Q18+AM18+CQ18+AO18+DA18+BA18+BC18+CO18+BG18+CS18+BI18+CY18+CK18+DC18+DE18 -> 1.6240997e+08 | C18: =P18+CN18+R18+AN18+CR18+AP18+DB18+BB18+BD18+CP18+BH18+CT18+BJ18+CZ18+CL18+DD18+DF18 -> 521 | D18: =O18+BA18+CO18+BG18+BI18+DC18 -> 1.4557765e+08 | E18: =P18+BB18+CP18+BH18+BJ18+DD18 -> 2 | F18: =CM18+CS18 -> 0 | H18: =Q18+CY18 -> 0 | J18: =AM18+CQ18+AO18+DA18 -> 16832319 | K18: =AN18+CR18+AP18+DB18 -> 519 | L18: =BC18+CK18+DE18 -> 0 | O18: =SILVX!B25 -> 52180096 | P18: =SILVX!G25 -> 1 | AM18: =Schwab!S13 -> 15019029 | AN18: =Schwab!Q13 -> 514 | AO18: =Fidelity!P18 -> 1671651.6 | AP18: =Fidelity!O18 -> 0 | BA18: ='TFA - Folio'!H23 -> 93397556 | BB18: ='TFA - Folio'!I18 -> 1 | CQ18: =TDA!O8 -> 141637.82 | CR18: =TDA!N8 -> 5
A19: 41790 | B19: =O19+CM19+Q19+AM19+CQ19+AO19+DA19+BA19+BC19+CO19+BG19+CS19+BI19+CY19+CK19+DC19+DE19 -> 1.677813e+08 | C19: =P19+CN19+R19+AN19+CR19+AP19+DB19+BB19+BD19+CP19+BH19+CT19+BJ19+CZ19+CL19+DD19+DF19 -> 566 | D19: =O19+BA19+CO19+BG19+BI19+DC19 -> 1.5032794e+08 | E19: =P19+BB19+CP19+BH19+BJ19+DD19 -> 2 | F19: =CM19+CS19 -> 0 | H19: =Q19+CY19 -> 0 | J19: =AM19+CQ19+AO19+DA19 -> 17453360 | K19: =AN19+CR19+AP19+DB19 -> 564 | L19: =BC19+CK19+DE19 -> 0 | O19: =SILVX!B26 -> 53150044 | P19: =SILVX!G26 -> 1 | AM19: =Schwab!S14 -> 15039826 | AN19: =Schwab!Q14 -> 525 | AO19: =Fidelity!P19 -> 1633634.5 | AP19: =Fidelity!O19 -> 0 | BA19: ='TFA - Folio'!H24 -> 97177900 | BB19: ='TFA - Folio'!I19 -> 1 | CQ19: =TDA!O9 -> 779900.08 | CR19: =TDA!N9 -> 39
A20: 41820 | B20: =O20+CM20+Q20+AM20+CQ20+AO20+DA20+BA20+BC20+CO20+BG20+CS20+BI20+CY20+CK20+DC20+DE20 -> 1.7451183e+08 | C20: =P20+CN20+R20+AN20+CR20+AP20+DB20+BB20+BD20+CP20+BH20+CT20+BJ20+CZ20+CL20+DD20+DF20 -> 584 | D20: =O20+BA20+CO20+BG20+BI20+DC20 -> 1.5642297e+08 | E20: =P20+BB20+CP20+BH20+BJ20+DD20 -> 2 | F20: =CM20+CS20 -> 0 | H20: =Q20+CY20 -> 0 | J20: =AM20+CQ20+AO20+DA20 -> 18088858 | K20: =AN20+CR20+AP20+DB20 -> 582 | L20: =BC20+CK20+DE20 -> 0 | O20: =SILVX!B27 -> 55639070 | P20: =SILVX!G27 -> 1 | AM20: =Schwab!S15 -> 15728815 | AN20: =Schwab!Q15 -> 516 | AO20: =Fidelity!P20 -> 1554074.6 | AP20: =Fidelity!O20 -> 27 | BA20: ='TFA - Folio'!H25 -> 1.007839e+08 | BB20: ='TFA - Folio'!I20 -> 1 | CQ20: =TDA!O10 -> 805967.89 | CR20: =TDA!N10 -> 39
A21: 41851 | B21: =O21+CM21+Q21+AM21+CQ21+AO21+DA21+BA21+BC21+CO21+BG21+CS21+BI21+CY21+CK21+DC21+DE21 -> 1.768834e+08 | C21: =P21+CN21+R21+AN21+CR21+AP21+DB21+BB21+BD21+CP21+BH21+CT21+BJ21+CZ21+CL21+DD21+DF21 -> 605 | D21: =O21+BA21+CO21+BG21+BI21+DC21 -> 1.5938824e+08 | E21: =P21+BB21+CP21+BH21+BJ21+DD21 -> 2 | F21: =CM21+CS21 -> 0 | H21: =Q21+CY21 -> 0 | J21: =AM21+CQ21+AO21+DA21 -> 17495160 | K21: =AN21+CR21+AP21+DB21 -> 603 | L21: =BC21+CK21+DE21 -> 0 | O21: =SILVX!B28 -> 57860065 | P21: =SILVX!G28 -> 1 | AM21: =Schwab!S16 -> 15182148 | AN21: =Schwab!Q16 -> 533 | AO21: =Fidelity!P21 -> 1547908.6 | AP21: =Fidelity!O21 -> 32 | BA21: ='TFA - Folio'!H26 -> 1.0152817e+08 | BB21: ='TFA - Folio'!I21 -> 1 | CQ21: =TDA!O11 -> 765104.15 | CR21: =TDA!N11 -> 38
A22: 41882 | B22: =O22+CM22+Q22+AM22+CQ22+AO22+DA22+BA22+BC22+CO22+BG22+CS22+BI22+CY22+CK22+DC22+DE22 -> 1.8671688e+08 | C22: =P22+CN22+R22+AN22+CR22+AP22+DB22+BB22+BD22+CP22+BH22+CT22+BJ22+CZ22+CL22+DD22+DF22 -> 619 | D22: =O22+BA22+CO22+BG22+BI22+DC22 -> 1.677052e+08 | E22: =P22+BB22+CP22+BH22+BJ22+DD22 -> 2 | F22: =CM22+CS22 -> 0 | H22: =Q22+CY22 -> 0 | J22: =AM22+CQ22+AO22+DA22 -> 19011682 | K22: =AN22+CR22+AP22+DB22 -> 617 | L22: =BC22+CK22+DE22 -> 0 | O22: =SILVX!B29 -> 60275807 | P22: =SILVX!G29 -> 1 | AM22: =Schwab!S17 -> 16414264 | AN22: =Schwab!Q17 -> 546 | AO22: =Fidelity!P22 -> 1874144.3 | AP22: =Fidelity!O22 -> 33 | BA22: ='TFA - Folio'!H27 -> 1.0742939e+08 | BB22: ='TFA - Folio'!I22 -> 1 | CQ22: =TDA!O12 -> 723273.51 | CR22: =TDA!N12 -> 38
A23: 41912 | B23: =O23+CM23+Q23+AM23+CQ23+AO23+DA23+BA23+BC23+CO23+BG23+CS23+BI23+CY23+CK23+DC23+DE23 -> 1.8719638e+08 | C23: =P23+CN23+R23+AN23+CR23+AP23+DB23+BB23+BD23+CP23+BH23+CT23+BJ23+CZ23+CL23+DD23+DF23 -> 632 | D23: =O23+BA23+CO23+BG23+BI23+DC23 -> 1.6852857e+08 | E23: =P23+BB23+CP23+BH23+BJ23+DD23 -> 2 | F23: =CM23+CS23 -> 0 | H23: =Q23+CY23 -> 0 | J23: =AM23+CQ23+AO23+DA23 -> 18667800 | K23: =AN23+CR23+AP23+DB23 -> 630 | L23: =BC23+CK23+DE23 -> 0 | O23: =SILVX!B30 -> 59967277 | P23: =SILVX!G30 -> 1 | AM23: =Schwab!S18 -> 15775027 | AN23: =Schwab!Q18 -> 554 | AO23: =Fidelity!P23 -> 2054813 | AP23: =Fidelity!O23 -> 34 | BA23: ='TFA - Folio'!H28 -> 1.085613e+08 | BB23: ='TFA - Folio'!I23 -> 1 | CQ23: =TDA!O13 -> 837959.96 | CR23: =TDA!N13 -> 42
... A27: 42035 | B27: =O27+CM27+Q27+AM27+CQ27+AO27+DA27+BA27+BC27+CO27+BG27+CS27+BI27+CY27+CK27+DC27+DE27 -> 2.3063648e+08 | C27: =P27+CN27+R27+AN27+CR27+AP27+DB27+BB27+BD27+CP27+BH27+CT27+BJ27+CZ27+CL27+DD27+DF27 -> 697 | D27: =O27+BA27+CO27+BG27+BI27+DC27 -> 2.0454237e+08 | E27: =P27+BB27+CP27+BH27+BJ27+DD27 -> 2 | F27: =CM27+CS27 -> 0 | H27: =Q27+CY27 -> 0 | J27: =AM27+CQ27+AO27+DA27 -> 26094108 | K27: =AN27+CR27+AP27+DB27 -> 695 | L27: =BC27+CK27+DE27 -> 0 | O27: =SILVX!B34 -> 66896741 | P27: =SILVX!G34 -> 1 | AM27: =Schwab!S22 -> 22619568 | AN27: =Schwab!Q22 -> 605 | AO27: =Fidelity!P27 -> 2363912.3 | AP27: =Fidelity!O27 -> 40 | BA27: ='TFA - Folio'!H32 -> 1.3764563e+08 | BB27: ='TFA - Folio'!I27 -> 1 | CQ27: =TDA!O17 -> 1110627 | CR27: =TDA!N17 -> 50
A28: 42063 | B28: =O28+CM28+Q28+AM28+CQ28+AO28+DA28+BA28+BC28+CO28+BG28+CS28+BI28+CY28+CK28+DC28+DE28 -> 2.4880608e+08 | C28: =P28+CN28+R28+AN28+CR28+AP28+DB28+BB28+BD28+CP28+BH28+CT28+BJ28+CZ28+CL28+DD28+DF28 -> 716 | D28: =O28+BA28+CO28+BG28+BI28+DC28 -> 2.2340973e+08 | E28: =P28+BB28+CP28+BH28+BJ28+DD28 -> 3 | F28: =CM28+CS28 -> 0 | H28: =Q28+CY28 -> 0 | J28: =AM28+CQ28+AO28+DA28 -> 25396345 | K28: =AN28+CR28+AP28+DB28 -> 713 | L28: =BC28+CK28+DE28 -> 0 | O28: =SILVX!B35 -> 69872904 | P28: =SILVX!G35 -> 1 | AM28: =Schwab!S23 -> 21747082 | AN28: =Schwab!Q23 -> 626 | AO28: =Fidelity!P28 -> 2400679.4 | AP28: =Fidelity!O28 -> 38 | BA28: ='TFA - Folio'!H33 -> 1.5303516e+08 | BB28: ='TFA - Folio'!I28 -> 1 | CO28: =Stifel!B2 -> 501672.76 | CP28: =Stifel!K2 -> 1 | CQ28: =TDA!O18 -> 1133295.8 | CR28: =TDA!N18 -> 48 | DA28: =Prudential!E2 -> 115287.29 | DB28: =Prudential!D2 -> 1
A29: 42094 | B29: =O29+CM29+Q29+AM29+CQ29+AO29+DA29+BA29+BC29+CO29+BG29+CS29+BI29+CY29+CK29+DC29+DE29 -> 2.6056483e+08 | C29: =P29+CN29+R29+AN29+CR29+AP29+DB29+BB29+BD29+CP29+BH29+CT29+BJ29+CZ29+CL29+DD29+DF29 -> 743 | D29: =O29+BA29+CO29+BG29+BI29+DC29 -> 2.3344826e+08 | E29: =P29+BB29+CP29+BH29+BJ29+DD29 -> 3 | F29: =CM29+CS29 -> 0 | H29: =Q29+CY29 -> 0 | J29: =AM29+CQ29+AO29+DA29 -> 27116574 | K29: =AN29+CR29+AP29+DB29 -> 740 | L29: =BC29+CK29+DE29 -> 0 | O29: =SILVX!B36 -> 71575874 | P29: =SILVX!G36 -> 1 | AM29: =Schwab!S24 -> 23436501 | AN29: =Schwab!Q24 -> 651 | AO29: =Fidelity!P29 -> 2417360.4 | AP29: =Fidelity!O29 -> 38 | BA29: ='TFA - Folio'!H34 -> 1.6137072e+08 | BB29: ='TFA - Folio'!I29 -> 1 | CO29: =Stifel!B3 -> 501670.61 | CP29: =Stifel!K3 -> 1 | CQ29: =TDA!O19 -> 1147289.8 | CR29: =TDA!N19 -> 50 | DA29: =Prudential!E3 -> 115422.93 | DB29: =Prudential!D3 -> 1
A30: 42124 | B30: =O30+CM30+Q30+AM30+CQ30+AO30+DA30+BA30+BC30+CO30+BG30+CS30+BI30+CY30+CK30+DC30+DE30 -> 2.7059347e+08 | C30: =P30+CN30+R30+AN30+CR30+AP30+DB30+BB30+BD30+CP30+BH30+CT30+BJ30+CZ30+CL30+DD30+DF30 -> 764 | D30: =O30+BA30+CO30+BG30+BI30+DC30 -> 2.3754686e+08 | E30: =P30+BB30+CP30+BH30+BJ30+DD30 -> 3 | F30: =CM30+CS30 -> 0 | H30: =Q30+CY30 -> 0 | J30: =AM30+CQ30+AO30+DA30 -> 27602800 | K30: =AN30+CR30+AP30+DB30 -> 760 | L30: =BC30+CK30+DE30 -> 5443804 | M30: =BD30+CL30+DF30 -> 1 | O30: =SILVX!B37 -> 71483082 | P30: =SILVX!G37 -> 1 | AM30: =Schwab!S25 -> 23895032 | AN30: =Schwab!Q25 -> 671 | AO30: =Fidelity!P30 -> 2454965 | AP30: =Fidelity!O30 -> 38 | BA30: ='TFA - Folio'!H35 -> 1.6557246e+08 | BB30: ='TFA - Folio'!I30 -> 1 | BC30: ='TFA - Folio'!K35 -> 5443804 | BD30: ='TFA - Folio'!N35 -> 1 | CO30: =Stifel!B4 -> 491317.13 | CP30: =Stifel!K4 -> 1 | CQ30: =TDA!O20 -> 1139169.9 | CR30: =TDA!N20 -> 50 | DA30: =Prudential!E4 -> 113633.13 | DB30: =Prudential!D4 -> 1
A31: 42155 | B31: =O31+CM31+Q31+AM31+CQ31+AO31+DA31+BA31+BC31+CO31+BG31+CS31+BI31+CY31+CK31+DC31+DE31 -> 2.8375676e+08 | C31: =P31+CN31+R31+AN31+CR31+AP31+DB31+BB31+BD31+CP31+BH31+CT31+BJ31+CZ31+CL31+DD31+DF31 -> 765 | D31: =O31+BA31+CO31+BG31+BI31+DC31 -> 2.4373243e+08 | E31: =P31+BB31+CP31+BH31+BJ31+DD31 -> 3 | F31: =CM31+CS31 -> 0 | H31: =Q31+CY31 -> 0 | J31: =AM31+CQ31+AO31+DA31 -> 28854710 | K31: =AN31+CR31+AP31+DB31 -> 761 | L31: =BC31+CK31+DE31 -> 11169615 | M31: =BD31+CL31+DF31 -> 1 | O31: =SILVX!B38 -> 72089141 | P31: =SILVX!G38 -> 1 | AM31: =Schwab!S26 -> 25130832 | AN31: =Schwab!Q26 -> 671 | AO31: =Fidelity!P31 -> 2465735.6 | AP31: =Fidelity!O31 -> 39 | BA31: ='TFA - Folio'!H36 -> 171145806 | BB31: ='TFA - Folio'!I31 -> 1 | BC31: ='TFA - Folio'!K36 -> 11169615 | BD31: ='TFA - Folio'!N36 -> 1 | CO31: =Stifel!B5 -> 497485.88 | CP31: =Stifel!K5 -> 1 | CQ31: =TDA!O21 -> 1144996.6 | CR31: =TDA!N21 -> 50 | DA31: =Prudential!E5 -> 113146.36 | DB31: =Prudential!D5 -> 1
A32: 42185 | B32: =O32+CM32+Q32+AM32+CQ32+AO32+DA32+BA32+BC32+CO32+BG32+CS32+BI32+CY32+CK32+DC32+DE32 -> 2.7979975e+08 | C32: =P32+CN32+R32+AN32+CR32+AP32+DB32+BB32+BD32+CP32+BH32+CT32+BJ32+CZ32+CL32+DD32+DF32 -> 783 | D32: =O32+BA32+CO32+BG32+BI32+DC32 -> 2.386637e+08 | E32: =P32+BB32+CP32+BH32+BJ32+DD32 -> 3 | F32: =CM32+CS32 -> 0 | H32: =Q32+CY32 -> 0 | J32: =AM32+CQ32+AO32+DA32 -> 27147640 | K32: =AN32+CR32+AP32+DB32 -> 779 | L32: =BC32+CK32+DE32 -> 13988418 | M32: =BD32+CL32+DF32 -> 1 | O32: =SILVX!B39 -> 71051329 | P32: =SILVX!G39 -> 1 | AM32: =Schwab!S27 -> 23346862 | AN32: =Schwab!Q27 -> 688 | AO32: =Fidelity!P32 -> 2421279.6 | AP32: =Fidelity!O32 -> 40 | BA32: ='TFA - Folio'!H37 -> 1.6712556e+08 | BB32: ='TFA - Folio'!I32 -> 1 | BC32: ='TFA - Folio'!K37 -> 13988418 | BD32: ='TFA - Folio'!N37 -> 1 | CO32: =Stifel!B6 -> 486805.53 | CP32: =Stifel!K6 -> 1 | CQ32: =TDA!O22 -> 1269038.9 | CR32: =TDA!N22 -> 50 | DA32: =Prudential!E6 -> 110459.19 | DB32: =Prudential!D6 -> 1
A33: 42216 | B33: =O33+CM33+Q33+AM33+CQ33+AO33+DA33+BA33+BC33+CO33+BG33+CS33+BI33+CY33+CK33+DC33+DE33 -> 3.0558192e+08 | C33: =P33+CN33+R33+AN33+CR33+AP33+DB33+BB33+BD33+CP33+BH33+CT33+BJ33+CZ33+CL33+DD33+DF33 -> 795 | D33: =O33+BA33+CO33+BG33+BI33+DC33 -> 2.5640275e+08 | E33: =P33+BB33+CP33+BH33+BJ33+DD33 -> 3 | F33: =CM33+CS33 -> 0 | H33: =Q33+CY33 -> 0 | J33: =AM33+CQ33+AO33+DA33 -> 29844049 | K33: =AN33+CR33+AP33+DB33 -> 791 | L33: =BC33+CK33+DE33 -> 19335117 | M33: =BD33+CL33+DF33 -> 1 | O33: =SILVX!B40 -> 75409202 | P33: =SILVX!G40 -> 1 | AM33: =Schwab!S28 -> 25984135 | AN33: =Schwab!Q28 -> 703 | AO33: =Fidelity!P33 -> 2464372.9 | AP33: =Fidelity!O33 -> 37 | BA33: ='TFA - Folio'!H38 -> 1.804826e+08 | BB33: ='TFA - Folio'!I33 -> 1 | BC33: ='TFA - Folio'!K38 -> 19335117 | BD33: ='TFA - Folio'!N38 -> 1 | CO33: =Stifel!B7 -> 510948.34 | CP33: =Stifel!K7 -> 1 | CQ33: =TDA!O23 -> 1285511.9 | CR33: =TDA!N23 -> 50 | DA33: =Prudential!E7 -> 110029.88 | DB33: =Prudential!D7 -> 1
A34: 42247 | B34: =O34+CM34+Q34+AM34+CQ34+AO34+DA34+BA34+BC34+CO34+BG34+CS34+BI34+CY34+CK34+DC34+DE34 -> 2.9712704e+08 | C34: =P34+CN34+R34+AN34+CR34+AP34+DB34+BB34+BD34+CP34+BH34+CT34+BJ34+CZ34+CL34+DD34+DF34 -> 806 | D34: =O34+BA34+CO34+BG34+BI34+DC34 -> 2.4511105e+08 | E34: =P34+BB34+CP34+BH34+BJ34+DD34 -> 3 | F34: =CM34+CS34 -> 0 | H34: =Q34+CY34 -> 0 | J34: =AM34+CQ34+AO34+DA34 -> 30642172 | K34: =AN34+CR34+AP34+DB34 -> 802 | L34: =BC34+CK34+DE34 -> 21373816 | M34: =BD34+CL34+DF34 -> 1 | O34: =SILVX!B41 -> 72553876 | P34: =SILVX!G41 -> 1 | AM34: =Schwab!S29 -> 26503267 | AN34: =Schwab!Q29 -> 711 | AO34: =Fidelity!P34 -> 2740839.8 | AP34: =Fidelity!O34 -> 39 | BA34: ='TFA - Folio'!H39 -> 1.7207041e+08 | BB34: ='TFA - Folio'!I34 -> 1 | BC34: ='TFA - Folio'!K39 -> 21373816 | BD34: ='TFA - Folio'!N39 -> 1 | CO34: =Stifel!B8 -> 486766.64 | CP34: =Stifel!K8 -> 1 | CQ34: =TDA!O24 -> 1288767.5 | CR34: =TDA!N24 -> 51 | DA34: =Prudential!E8 -> 109297.71 | DB34: =Prudential!D8 -> 1
A35: 42277 | B35: =O35+CM35+Q35+AM35+CQ35+AO35+DA35+BA35+BC35+CO35+BG35+CS35+BI35+CY35+CK35+DC35+DE35 -> 3.0023612e+08 | C35: =P35+CN35+R35+AN35+CR35+AP35+DB35+BB35+BD35+CP35+BH35+CT35+BJ35+CZ35+CL35+DD35+DF35 -> 810 | D35: =O35+BA35+CO35+BG35+BI35+DC35 -> 2.4800922e+08 | E35: =P35+BB35+CP35+BH35+BJ35+DD35 -> 3 | F35: =CM35+CS35 -> 0 | H35: =Q35+CY35 -> 0 | J35: =AM35+CQ35+AO35+DA35 -> 29796249 | K35: =AN35+CR35+AP35+DB35 -> 806 | L35: =BC35+CK35+DE35 -> 22430654 | M35: =BD35+CL35+DF35 -> 1 | O35: =SILVX!B42 -> 72933072 | P35: =SILVX!G42 -> 1 | AM35: =Schwab!S30 -> 25911677 | AN35: =Schwab!Q30 -> 715 | AO35: =Fidelity!P35 -> 2459675.1 | AP35: =Fidelity!O35 -> 39 | BA35: ='TFA - Folio'!H40 -> 1.745868e+08 | BB35: ='TFA - Folio'!I35 -> 1 | BC35: ='TFA - Folio'!K40 -> 22430654 | BD35: ='TFA - Folio'!N40 -> 1 | CO35: =Stifel!B9 -> 489346.34 | CP35: =Stifel!K9 -> 1 | CQ35: =TDA!O25 -> 1317738 | CR35: =TDA!N25 -> 51 | DA35: =Prudential!E9 -> 107158.79 | DB35: =Prudential!D9 -> 1
A36: 42308 | B36: =O36+CM36+Q36+AM36+CQ36+AO36+DA36+BA36+BC36+CO36+BG36+CS36+BI36+CY36+CK36+DC36+DE36 -> 3.3097015e+08 | C36: =P36+CN36+R36+AN36+CR36+AP36+DB36+BB36+BD36+CP36+BH36+CT36+BJ36+CZ36+CL36+DD36+DF36 -> 822 | D36: =O36+BA36+CO36+BG36+BI36+DC36 -> 2.7357862e+08 | E36: =P36+BB36+CP36+BH36+BJ36+DD36 -> 3 | F36: =CM36+CS36 -> 0 | H36: =Q36+CY36 -> 0 | J36: =AM36+CQ36+AO36+DA36 -> 32098575 | K36: =AN36+CR36+AP36+DB36 -> 813 | L36: =BC36+CK36+DE36 -> 25292959 | M36: =BD36+CL36+DF36 -> 6 | O36: =SILVX!B43 -> 81294138 | P36: =SILVX!G43 -> 1 | AM36: =Schwab!S31 -> 27604223 | AN36: =Schwab!Q31 -> 719 | AO36: =Fidelity!P36 -> 2773930.8 | AP36: =Fidelity!O36 -> 39 | BA36: ='TFA - Folio'!H41 -> 1.9176278e+08 | BB36: ='TFA - Folio'!I36 -> 1 | BC36: ='TFA - Folio'!K41 -> 24691379 | BD36: ='TFA - Folio'!N41 -> 1 | CO36: =Stifel!B10 -> 521704.76 | CP36: =Stifel!K10 -> 1 | CQ36: =TDA!O26 -> 1610256.2 | CR36: =TDA!N26 -> 54 | DA36: =Prudential!E10 -> 110164.2 | DB36: =Prudential!D10 -> 1 | DE36: =Folio!B2 -> 601579.94 | DF36: =Folio!C2 -> 5
A37: 42338 | B37: =O37+CM37+Q37+AM37+CQ37+AO37+DA37+BA37+BC37+CO37+BG37+CS37+BI37+CY37+CK37+DC37+DE37 -> 3.3180873e+08 | C37: =P37+CN37+R37+AN37+CR37+AP37+DB37+BB37+BD37+CP37+BH37+CT37+BJ37+CZ37+CL37+DD37+DF37 -> 812 | D37: =O37+BA37+CO37+BG37+BI37+DC37 -> 2.7323413e+08 | E37: =P37+BB37+CP37+BH37+BJ37+DD37 -> 3 | F37: =CM37+CS37 -> 0 | H37: =Q37+CY37 -> 0 | J37: =AM37+CQ37+AO37+DA37 -> 32634033 | K37: =AN37+CR37+AP37+DB37 -> 803 | L37: =BC37+CK37+DE37 -> 25940571 | M37: =BD37+CL37+DF37 -> 6 | O37: =SILVX!B44 -> 80390280 | P37: =SILVX!G44 -> 1 | AM37: =Schwab!S32 -> 28237672 | AN37: =Schwab!Q32 -> 708 | AO37: =Fidelity!P37 -> 2731964.8 | AP37: =Fidelity!O37 -> 38 | BA37: ='TFA - Folio'!H42 -> 1.9232183e+08 | BB37: ='TFA - Folio'!I37 -> 1 | BC37: ='TFA - Folio'!K42 -> 25345002 | BD37: ='TFA - Folio'!N42 -> 1 | CO37: =Stifel!B11 -> 522017.14 | CP37: =Stifel!K11 -> 1 | CQ37: =TDA!O27 -> 1555557.5 | CR37: =TDA!N27 -> 56 | DA37: =Prudential!E11 -> 108839.34 | DB37: =Prudential!D11 -> 1 | DE37: =Folio!B3 -> 595568.38 | DF37: =Folio!C3 -> 5
A38: 42369 | B38: =O38+CM38+Q38+AM38+CQ38+AO38+DA38+BA38+BC38+CO38+BG38+CS38+BI38+CY38+CK38+DC38+DE38 -> 3.3229184e+08 | C38: =P38+CN38+R38+AN38+CR38+AP38+DB38+BB38+BD38+CP38+BH38+CT38+BJ38+CZ38+CL38+DD38+DF38 -> 807 | D38: =O38+BA38+CO38+BG38+BI38+DC38 -> 2.7481298e+08 | E38: =P38+BB38+CP38+BH38+BJ38+DD38 -> 3 | F38: =CM38+CS38 -> 0 | H38: =Q38+CY38 -> 0 | J38: =AM38+CQ38+AO38+DA38 -> 31523436 | K38: =AN38+CR38+AP38+DB38 -> 798 | L38: =BC38+CK38+DE38 -> 25955429 | M38: =BD38+CL38+DF38 -> 6 | O38: =SILVX!B45 -> 80182147 | P38: =SILVX!G45 -> 1 | AM38: =Schwab!S33 -> 27097924 | AN38: =Schwab!Q33 -> 701 | AO38: =Fidelity!P38 -> 2746597.6 | AP38: =Fidelity!O38 -> 38 | BA38: ='TFA - Folio'!H43 -> 1.941075e+08 | BB38: ='TFA - Folio'!I38 -> 1 | BC38: ='TFA - Folio'!K43 -> 25368789 | BD38: ='TFA - Folio'!N43 -> 1 | CO38: =Stifel!B12 -> 523327.45 | CP38: =Stifel!K12 -> 1 | CQ38: =TDA!O28 -> 1570764.8 | CR38: =TDA!N28 -> 58 | DA38: =Prudential!E12 -> 108149.1 | DB38: =Prudential!D12 -> 1 | DE38: =Folio!B4 -> 586639.56 | DF38: =Folio!C4 -> 5
A39: 42400 | B39: =O39+CM39+Q39+AM39+CQ39+AO39+DA39+BA39+BC39+CO39+BG39+CS39+BI39+CY39+CK39+DC39+DE39 -> 3.9631938e+08 | C39: =P39+CN39+R39+AN39+CR39+AP39+DB39+BB39+BD39+CP39+BH39+CT39+BJ39+CZ39+CL39+DD39+DF39 -> 798 | D39: =O39+BA39+CO39+BG39+BI39+DC39 -> 3.3656558e+08 | E39: =P39+BB39+CP39+BH39+BJ39+DD39 -> 4 | F39: =CM39+CS39 -> 0 | H39: =Q39+CY39 -> 0 | J39: =AM39+CQ39+AO39+DA39 -> 29267067 | K39: =AN39+CR39+AP39+DB39 -> 788 | L39: =BC39+CK39+DE39 -> 30486730 | M39: =BD39+CL39+DF39 -> 6 | O39: =SILVX!B46 -> 79613453 | P39: =SILVX!G46 -> 1 | AM39: =Schwab!S34 -> 24725092 | AN39: =Schwab!Q34 -> 691 | AO39: =Fidelity!P39 -> 2625482.4 | AP39: =Fidelity!O39 -> 38 | BA39: ='TFA - Folio'!H44 -> 1.959236e+08 | BB39: ='TFA - Folio'!I39 -> 1 | BC39: ='TFA - Folio'!K44 -> 29896321 | BD39: ='TFA - Folio'!N44 -> 1 | BG39: =UNC!B2 -> 60512888 | BH39: =UNC!C2 -> 1 | CO39: =Stifel!B13 -> 515644.95 | CP39: =Stifel!K13 -> 1 | CQ39: =TDA!O29 -> 1809504.4 | CR39: =TDA!N29 -> 58 | DA39: =Prudential!E13 -> 106987.57 | DB39: =Prudential!D13 -> 1 | DE39: =Folio!B5 -> 590409.06 | DF39: =Folio!C5 -> 5
A40: 42429 | B40: =O40+CM40+Q40+AM40+CQ40+AO40+DA40+BA40+BC40+CO40+BG40+CS40+BI40+CY40+CK40+DC40+DE40 -> 4.3188242e+08 | C40: =P40+CN40+R40+AN40+CR40+AP40+DB40+BB40+BD40+CP40+BH40+CT40+BJ40+CZ40+CL40+DD40+DF40 -> 796 | D40: =O40+BA40+CO40+BG40+BI40+DC40 -> 3.6594404e+08 | E40: =P40+BB40+CP40+BH40+BJ40+DD40 -> 6 | F40: =CM40+CS40 -> 0 | H40: =Q40+CY40 -> 0 | J40: =AM40+CQ40+AO40+DA40 -> 31268321 | K40: =AN40+CR40+AP40+DB40 -> 784 | L40: =BC40+CK40+DE40 -> 34670059 | M40: =BD40+CL40+DF40 -> 6 | O40: =SILVX!B47 -> 92880465 | P40: =SILVX!G47 -> 1 | AM40: =Schwab!S35 -> 26838836 | AN40: =Schwab!Q35 -> 696 | AO40: =Fidelity!P40 -> 2775074.7 | AP40: =Fidelity!O40 -> 33 | BA40: ='TFA - Folio'!H45 -> 2.0881877e+08 | BB40: ='TFA - Folio'!I40 -> 1 | BC40: ='TFA - Folio'!K45 -> 34079650 | BD40: ='TFA - Folio'!N45 -> 1 | BG40: =UNC!B3 -> 61869873 | BH40: =UNC!C3 -> 1 | CO40: =Stifel!B14 -> 2374938.7 | CP40: =Stifel!K14 -> 3 | CQ40: =TDA!O30 -> 1546479.5 | CR40: =TDA!N30 -> 54 | DA40: =Prudential!E14 -> 107931.44 | DB40: =Prudential!D14 -> 1 | DE40: =Folio!B6 -> 590409.06 | DF40: =Folio!C6 -> 5
A41: 42460 | B41: =O41+CM41+Q41+AM41+CQ41+AO41+DA41+BA41+BC41+CO41+BG41+CS41+BI41+CY41+CK41+DC41+DE41 -> 5.5371888e+08 | C41: =P41+CN41+R41+AN41+CR41+AP41+DB41+BB41+BD41+CP41+BH41+CT41+BJ41+CZ41+CL41+DD41+DF41 -> 813 | D41: =O41+BA41+CO41+BG41+BI41+DC41 -> 4.4960782e+08 | E41: =P41+BB41+CP41+BH41+BJ41+DD41 -> 6 | F41: =CM41+CS41 -> 26636105 | G41: =CN41+CT41 -> 1 | H41: =Q41+CY41 -> 0 | J41: =AM41+CQ41+AO41+DA41 -> 33214194 | K41: =AN41+CR41+AP41+DB41 -> 800 | L41: =BC41+CK41+DE41 -> 44260767 | M41: =BD41+CL41+DF41 -> 6 | O41: =SILVX!B48 -> 1.015352e+08 | P41: =SILVX!G48 -> 1 | AM41: =Schwab!S36 -> 28589054 | AN41: =Schwab!Q36 -> 712 | AO41: =Fidelity!P41 -> 2878941.7 | AP41: =Fidelity!O41 -> 33 | BA41: ='TFA - Folio'!H46 -> 2.4314565e+08 | BB41: ='TFA - Folio'!I41 -> 1 | BC41: ='TFA - Folio'!K46 -> 43670358 | BD41: ='TFA - Folio'!N46 -> 1 | BG41: =UNC!B4 -> 1.024606e+08 | BH41: =UNC!C4 -> 1 | CO41: =Stifel!B15 -> 2466364.9 | CP41: =Stifel!K15 -> 3 | CQ41: =TDA!O31 -> 1634301.8 | CR41: =TDA!N31 -> 54 | CS41: =UNC!D4 -> 26636105 | CT41: =UNC!E4 -> 1 | DA41: =Prudential!E15 -> 111896.92 | DB41: =Prudential!D15 -> 1 | DE41: =Folio!B7 -> 590409.06 | DF41: =Folio!C7 -> 5
A42: 42490 | B42: =O42+CM42+Q42+AM42+CQ42+AO42+DA42+BA42+BC42+CO42+BG42+CS42+BI42+CY42+CK42+DC42+DE42 -> 5.6409047e+08 | C42: =P42+CN42+R42+AN42+CR42+AP42+DB42+BB42+BD42+CP42+BH42+CT42+BJ42+CZ42+CL42+DD42+DF42 -> 824 | D42: =O42+BA42+CO42+BG42+BI42+DC42 -> 4.5566241e+08 | E42: =P42+BB42+CP42+BH42+BJ42+DD42 -> 7 | F42: =CM42+CS42 -> 26649522 | G42: =CN42+CT42 -> 2 | H42: =Q42+CY42 -> 0 | J42: =AM42+CQ42+AO42+DA42 -> 32794993 | K42: =AN42+CR42+AP42+DB42 -> 809 | L42: =BC42+CK42+DE42 -> 48983553 | M42: =BD42+CL42+DF42 -> 6 | O42: =SILVX!B49 -> 1.021536e+08 | P42: =SILVX!G49 -> 1 | AM42: =Schwab!S37 -> 28212576 | AN42: =Schwab!Q37 -> 721 | AO42: =Fidelity!P42 -> 2879856.7 | AP42: =Fidelity!O42 -> 33 | BA42: ='TFA - Folio'!H47 -> 2.4912137e+08 | BB42: ='TFA - Folio'!I42 -> 1 | BC42: ='TFA - Folio'!K47 -> 48393144 | BD42: ='TFA - Folio'!N47 -> 1 | BG42: =UNC!B5 -> 1.0099205e+08 | BH42: =UNC!C5 -> 1 | BI42: ='Schwab LC'!D2 -> 983504.05 | BJ42: ='Schwab LC'!E2 -> 1 | CM42: =SCLVX!B3 -> 292845.33 | CN42: =SCLVX!G3 -> 1 | CO42: =Stifel!B16 -> 2411877.3 | CP42: =Stifel!K16 -> 3 | CQ42: =TDA!O32 -> 1590409.4 | CR42: =TDA!N32 -> 54 | CS42: =UNC!D5 -> 26356677 | CT42: =UNC!E5 -> 1 | DA42: =Prudential!E16 -> 112150.66 | DB42: =Prudential!D16 -> 1 | DE42: =Folio!B8 -> 590409.06 | DF42: =Folio!C8 -> 5
A43: 42521 | B43: =O43+CM43+Q43+AM43+CQ43+AO43+DA43+BA43+BC43+CO43+BG43+CS43+BI43+CY43+CK43+DC43+DE43 -> 5.8791184e+08 | C43: =P43+CN43+R43+AN43+CR43+AP43+DB43+BB43+BD43+CP43+BH43+CT43+BJ43+CZ43+CL43+DD43+DF43 -> 807 | D43: =O43+BA43+CO43+BG43+BI43+DC43 -> 4.7744573e+08 | E43: =P43+BB43+CP43+BH43+BJ43+DD43 -> 11 | F43: =CM43+CS43 -> 38203241 | G43: =CN43+CT43 -> 2 | H43: =Q43+CY43 -> 0 | J43: =AM43+CQ43+AO43+DA43 -> 19983210 | K43: =AN43+CR43+AP43+DB43 -> 788 | L43: =BC43+CK43+DE43 -> 52279655 | M43: =BD43+CL43+DF43 -> 6 | O43: =SILVX!B50 -> 1.1000237e+08 | P43: =SILVX!G50 -> 1 | AM43: =Schwab!S38 -> 15694541 | AN43: =Schwab!Q38 -> 699 | AO43: =Fidelity!P43 -> 2861990.1 | AP43: =Fidelity!O43 -> 32 | BA43: ='TFA - Folio'!H48 -> 2.59697e+08 | BB43: ='TFA - Folio'!I43 -> 1 | BC43: ='TFA - Folio'!K48 -> 51689246 | BD43: ='TFA - Folio'!N48 -> 1 | BG43: =UNC!B6 -> 102949466 | BH43: =UNC!C6 -> 1 | BI43: ='Schwab LC'!D3 -> 1505135.9 | BJ43: ='Schwab LC'!E3 -> 2 | CM43: =SCLVX!B4 -> 11273789 | CN43: =SCLVX!G4 -> 1 | CO43: =Stifel!B17 -> 3291756.5 | CP43: =Stifel!K17 -> 6 | CQ43: =TDA!O33 -> 1315648.9 | CR43: =TDA!N33 -> 56 | CS43: =UNC!D6 -> 26929452 | CT43: =UNC!E6 -> 1 | DA43: =Prudential!E17 -> 111030.35 | DB43: =Prudential!D17 -> 1 | DE43: =Folio!B9 -> 590409.06 | DF43: =Folio!C9 -> 5
A44: 42551 | B44: =O44+CM44+Q44+AM44+CQ44+AO44+DA44+BA44+BC44+CO44+BG44+CS44+BI44+CY44+CK44+DC44+DE44 -> 6.2048246e+08 | C44: =P44+CN44+R44+AN44+CR44+AP44+DB44+BB44+BD44+CP44+BH44+CT44+BJ44+CZ44+CL44+DD44+DF44 -> 770 | D44: =O44+BA44+CO44+BG44+BI44+DC44 -> 5.0752686e+08 | E44: =P44+BB44+CP44+BH44+BJ44+DD44 -> 11 | F44: =CM44+CS44 -> 39531911 | G44: =CN44+CT44 -> 2 | H44: =Q44+CY44 -> 0 | J44: =AM44+CQ44+AO44+DA44 -> 20690594 | K44: =AN44+CR44+AP44+DB44 -> 751 | L44: =BC44+CK44+DE44 -> 52733099 | M44: =BD44+CL44+DF44 -> 6 | O44: =SILVX!B51 -> 1.2492058e+08 | P44: =SILVX!G51 -> 1 | AM44: =Schwab!S39 -> 16352790 | AN44: =Schwab!Q39 -> 664 | AO44: =Fidelity!P44 -> 2873908.1 | AP44: =Fidelity!O44 -> 31 | BA44: ='TFA - Folio'!H49 -> 2.7100501e+08 | BB44: ='TFA - Folio'!I44 -> 1 | BC44: ='TFA - Folio'!K49 -> 52142690 | BD44: ='TFA - Folio'!N49 -> 1 | BG44: =UNC!B7 -> 106503332 | BH44: =UNC!C7 -> 1 | BI44: ='Schwab LC'!D4 -> 1567343.4 | BJ44: ='Schwab LC'!E4 -> 2 | CM44: =SCLVX!B5 -> 11434376 | CN44: =SCLVX!G5 -> 1 | CO44: =Stifel!B18 -> 3530592.6 | CP44: =Stifel!K18 -> 6 | CQ44: =TDA!O34 -> 1346912.8 | CR44: =TDA!N34 -> 55 | CS44: =UNC!D7 -> 28097535 | CT44: =UNC!E7 -> 1 | DA44: =Prudential!E18 -> 116982.63 | DB44: =Prudential!D18 -> 1 | DE44: =Folio!B10 -> 590409.06 | DF44: =Folio!C10 -> 5
A45: 42582 | B45: =O45+CM45+Q45+AM45+CQ45+AO45+DA45+BA45+BC45+CO45+BG45+CS45+BI45+CY45+CK45+DC45+DE45 -> 6.4942262e+08 | C45: =P45+CN45+R45+AN45+CR45+AP45+DB45+BB45+BD45+CP45+BH45+CT45+BJ45+CZ45+CL45+DD45+DF45 -> 772 | D45: =O45+BA45+CO45+BG45+BI45+DC45 -> 5.292574e+08 | E45: =P45+BB45+CP45+BH45+BJ45+DD45 -> 12 | F45: =CM45+CS45 -> 40527284 | G45: =CN45+CT45 -> 2 | H45: =Q45+CY45 -> 0 | J45: =AM45+CQ45+AO45+DA45 -> 21712796 | K45: =AN45+CR45+AP45+DB45 -> 752 | L45: =BC45+CK45+DE45 -> 57925139 | M45: =BD45+CL45+DF45 -> 6 | O45: =SILVX!B52 -> 1.276482e+08 | P45: =SILVX!G52 -> 1 | AM45: =Schwab!S40 -> 17289712 | AN45: =Schwab!Q40 -> 664 | AO45: =Fidelity!P45 -> 2946401.8 | AP45: =Fidelity!O45 -> 32 | BA45: ='TFA - Folio'!H50 -> 2.8765591e+08 | BB45: ='TFA - Folio'!I45 -> 1 | BC45: ='TFA - Folio'!K50 -> 57334730 | BD45: ='TFA - Folio'!N50 -> 1 | BG45: =UNC!B8 -> 108346736 | BH45: =UNC!C8 -> 1 | BI45: ='Schwab LC'!D5 -> 1590064.1 | BJ45: ='Schwab LC'!E5 -> 2 | CM45: =SCLVX!B6 -> 11915017 | CN45: =SCLVX!G6 -> 1 | CO45: =Stifel!B19 -> 4016479.2 | CP45: =Stifel!K19 -> 7 | CQ45: =TDA!O35 -> 1359785.4 | CR45: =TDA!N35 -> 55 | CS45: =UNC!D8 -> 28612267 | CT45: =UNC!E8 -> 1 | DA45: =Prudential!E19 -> 116896.71 | DB45: =Prudential!D19 -> 1 | DE45: =Folio!B11 -> 590409.06 | DF45: =Folio!C11 -> 5
A46: 42613 | B46: =O46+CM46+Q46+AM46+CQ46+AO46+DA46+BA46+BC46+CO46+BG46+CS46+BI46+CY46+CK46+DC46+DE46 -> 6.5382968e+08 | C46: =P46+CN46+R46+AN46+CR46+AP46+DB46+BB46+BD46+CP46+BH46+CT46+BJ46+CZ46+CL46+DD46+DF46 -> 746 | D46: =O46+BA46+CO46+BG46+BI46+DC46 -> 5.3175638e+08 | E46: =P46+BB46+CP46+BH46+BJ46+DD46 -> 12 | F46: =CM46+CS46 -> 40765288 | G46: =CN46+CT46 -> 2 | H46: =Q46+CY46 -> 0 | J46: =AM46+CQ46+AO46+DA46 -> 21553148 | K46: =AN46+CR46+AP46+DB46 -> 726 | L46: =BC46+CK46+DE46 -> 59754867 | M46: =BD46+CL46+DF46 -> 6 | O46: =SILVX!B53 -> 128637685 | P46: =SILVX!G53 -> 1 | AM46: =Schwab!S41 -> 17140348 | AN46: =Schwab!Q41 -> 639 | AO46: =Fidelity!P46 -> 2899822.4 | AP46: =Fidelity!O46 -> 31 | BA46: ='TFA - Folio'!H51 -> 2.9096316e+08 | BB46: ='TFA - Folio'!I46 -> 1 | BC46: ='TFA - Folio'!K51 -> 59164458 | BD46: ='TFA - Folio'!N51 -> 1 | BG46: =UNC!B9 -> 106554191 | BH46: =UNC!C9 -> 1 | BI46: ='Schwab LC'!D6 -> 1564552.6 | BJ46: ='Schwab LC'!E6 -> 2 | CM46: =SCLVX!B7 -> 12096876 | CN46: =SCLVX!G7 -> 1 | CO46: =Stifel!B20 -> 4036789.2 | CP46: =Stifel!K20 -> 7 | CQ46: =TDA!O36 -> 1397452.4 | CR46: =TDA!N36 -> 55 | CS46: =UNC!D9 -> 28668412 | CT46: =UNC!E9 -> 1 | DA46: =Prudential!E20 -> 115525.88 | DB46: =Prudential!D20 -> 1 | DE46: =Folio!B12 -> 590409.06 | DF46: =Folio!C12 -> 5
A47: 42643 | B47: =O47+CM47+Q47+AM47+CQ47+AO47+DA47+BA47+BC47+CO47+BG47+CS47+BI47+CY47+CK47+DC47+DE47 -> 6.4280753e+08 | C47: =P47+CN47+R47+AN47+CR47+AP47+DB47+BB47+BD47+CP47+BH47+CT47+BJ47+CZ47+CL47+DD47+DF47 -> 747 | D47: =O47+BA47+CO47+BG47+BI47+DC47 -> 5.1979195e+08 | E47: =P47+BB47+CP47+BH47+BJ47+DD47 -> 12 | F47: =CM47+CS47 -> 41274810 | G47: =CN47+CT47 -> 2 | H47: =Q47+CY47 -> 0 | J47: =AM47+CQ47+AO47+DA47 -> 20422979 | K47: =AN47+CR47+AP47+DB47 -> 727 | L47: =BC47+CK47+DE47 -> 61317799 | M47: =BD47+CL47+DF47 -> 6 | O47: =SILVX!B54 -> 1.188664e+08 | P47: =SILVX!G54 -> 1 | AM47: =Schwab!S42 -> 16193782 | AN47: =Schwab!Q42 -> 638 | AO47: =Fidelity!P47 -> 2819675.5 | AP47: =Fidelity!O47 -> 32 | BA47: ='TFA - Folio'!H52 -> 2.8989576e+08 | BB47: ='TFA - Folio'!I47 -> 1 | BC47: ='TFA - Folio'!K52 -> 60727390 | BD47: ='TFA - Folio'!N52 -> 1 | BG47: =UNC!B10 -> 105353798 | BH47: =UNC!C10 -> 1 | BI47: ='Schwab LC'!D7 -> 1563657.3 | BJ47: ='Schwab LC'!E7 -> 2 | CM47: =SCLVX!B8 -> 12437810 | CN47: =SCLVX!G8 -> 1 | CO47: =Stifel!B21 -> 4112325.5 | CP47: =Stifel!K21 -> 7 | CQ47: =TDA!O37 -> 1298986.9 | CR47: =TDA!N37 -> 56 | CS47: =UNC!D10 -> 28837000 | CT47: =UNC!E10 -> 1 | DA47: =Prudential!E21 -> 110534.28 | DB47: =Prudential!D21 -> 1 | DE47: =Folio!B13 -> 590409.06 | DF47: =Folio!C13 -> 5
A48: 42674 | B48: =O48+CM48+Q48+AM48+CQ48+AO48+DA48+BA48+BC48+CO48+BG48+CS48+BI48+CY48+CK48+DC48+DE48 -> 6.2041962e+08 | C48: =P48+CN48+R48+AN48+CR48+AP48+DB48+BB48+BD48+CP48+BH48+CT48+BJ48+CZ48+CL48+DD48+DF48 -> 751 | D48: =O48+BA48+CO48+BG48+BI48+DC48 -> 4.9705019e+08 | E48: =P48+BB48+CP48+BH48+BJ48+DD48 -> 12 | F48: =CM48+CS48 -> 40770824 | G48: =CN48+CT48 -> 2 | H48: =Q48+CY48 -> 0 | J48: =AM48+CQ48+AO48+DA48 -> 21258279 | K48: =AN48+CR48+AP48+DB48 -> 731 | L48: =BC48+CK48+DE48 -> 61340320 | M48: =BD48+CL48+DF48 -> 6 | O48: =SILVX!B55 -> 1.1000028e+08 | P48: =SILVX!G55 -> 1 | AM48: =Schwab!S43 -> 16932753 | AN48: =Schwab!Q43 -> 642 | AO48: =Fidelity!P48 -> 2819676.5 | AP48: =Fidelity!O48 -> 32 | BA48: ='TFA - Folio'!H53 -> 2.7904885e+08 | BB48: ='TFA - Folio'!I48 -> 1 | BC48: ='TFA - Folio'!K53 -> 60749911 | BD48: ='TFA - Folio'!N53 -> 1 | BG48: =UNC!B11 -> 102506111 | BH48: =UNC!C11 -> 1 | BI48: ='Schwab LC'!D8 -> 1513736.1 | BJ48: ='Schwab LC'!E8 -> 2 | CM48: =SCLVX!B9 -> 12311760 | CN48: =SCLVX!G9 -> 1 | CO48: =Stifel!B22 -> 3981213.5 | CP48: =Stifel!K22 -> 7 | CQ48: =TDA!O38 -> 1390225.9 | CR48: =TDA!N38 -> 56 | CS48: =UNC!D11 -> 28459064 | CT48: =UNC!E11 -> 1 | DA48: =Prudential!E22 -> 115623.53 | DB48: =Prudential!D22 -> 1 | DE48: =Folio!B14 -> 590409.06 | DF48: =Folio!C14 -> 5
A49: 42704 | B49: =O49+CM49+Q49+AM49+CQ49+AO49+DA49+BA49+BC49+CO49+BG49+CS49+BI49+CY49+CK49+DC49+DE49 -> 6.3931919e+08 | C49: =P49+CN49+R49+AN49+CR49+AP49+DB49+BB49+BD49+CP49+BH49+CT49+BJ49+CZ49+CL49+DD49+DF49 -> 757 | D49: =O49+BA49+CO49+BG49+BI49+DC49 -> 5.1337878e+08 | E49: =P49+BB49+CP49+BH49+BJ49+DD49 -> 12 | F49: =CM49+CS49 -> 44409691 | G49: =CN49+CT49 -> 2 | H49: =Q49+CY49 -> 0 | J49: =AM49+CQ49+AO49+DA49 -> 23032394 | K49: =AN49+CR49+AP49+DB49 -> 742 | L49: =BC49+CK49+DE49 -> 58498323 | M49: =BD49+CL49+DF49 -> 1 | O49: =SILVX!B56 -> 1.132745e+08 | P49: =SILVX!G56 -> 1 | AM49: =Schwab!S44 -> 18703662 | AN49: =Schwab!Q44 -> 653 | AO49: =Fidelity!P49 -> 2905519 | AP49: =Fidelity!O49 -> 32 | BA49: ='TFA - Folio'!H54 -> 2.879834e+08 | BB49: ='TFA - Folio'!I49 -> 1 | BC49: ='TFA - Folio'!K54 -> 58498323 | BD49: ='TFA - Folio'!N54 -> 1 | BG49: =UNC!B12 -> 106540191 | BH49: =UNC!C12 -> 1 | BI49: ='Schwab LC'!D9 -> 1523356.8 | BJ49: ='Schwab LC'!E9 -> 2 | CM49: =SCLVX!B10 -> 13443512 | CN49: =SCLVX!G10 -> 1 | CO49: =Stifel!B23 -> 4057331.9 | CP49: =Stifel!K23 -> 7 | CQ49: =TDA!O39 -> 1317356 | CR49: =TDA!N39 -> 56 | CS49: =UNC!D12 -> 30966179 | CT49: =UNC!E12 -> 1 | DA49: =Prudential!E23 -> 105857.35 | DB49: =Prudential!D23 -> 1
A50: 42735 | B50: =O50+CM50+Q50+AM50+CQ50+AO50+DA50+BA50+BC50+CO50+BG50+CS50+BI50+CY50+CK50+DC50+DE50 -> 6.5309062e+08 | C50: =P50+CN50+R50+AN50+CR50+AP50+DB50+BB50+BD50+CP50+BH50+CT50+BJ50+CZ50+CL50+DD50+DF50 -> 747 | D50: =O50+BA50+CO50+BG50+BI50+DC50 -> 5.2314267e+08 | E50: =P50+BB50+CP50+BH50+BJ50+DD50 -> 12 | F50: =CM50+CS50 -> 46874484 | G50: =CN50+CT50 -> 2 | H50: =Q50+CY50 -> 0 | J50: =AM50+CQ50+AO50+DA50 -> 23585397 | K50: =AN50+CR50+AP50+DB50 -> 732 | L50: =BC50+CK50+DE50 -> 59488069 | M50: =BD50+CL50+DF50 -> 1 | O50: =SILVX!B57 -> 1.1583137e+08 | P50: =SILVX!G57 -> 1 | AM50: =Schwab!S45 -> 20085008 | AN50: =Schwab!Q45 -> 644 | AO50: =Fidelity!P50 -> 2297922.6 | AP50: =Fidelity!O50 -> 32 | BA50: ='TFA - Folio'!H55 -> 2.9520296e+08 | BB50: ='TFA - Folio'!I50 -> 1 | BC50: ='TFA - Folio'!K55 -> 59488069 | BD50: ='TFA - Folio'!N55 -> 1 | BG50: =UNC!B13 -> 1.0644017e+08 | BH50: =UNC!C13 -> 1 | BI50: ='Schwab LC'!D10 -> 1544165.1 | BJ50: ='Schwab LC'!E10 -> 2 | CM50: =SCLVX!B11 -> 14332582 | CN50: =SCLVX!G11 -> 1 | CO50: =Stifel!B24 -> 4124007.2 | CP50: =Stifel!K24 -> 7 | CQ50: =TDA!O40 -> 1096124.5 | CR50: =TDA!N40 -> 55 | CS50: =UNC!D13 -> 32541902 | CT50: =UNC!E13 -> 1 | DA50: =Prudential!E24 -> 106342.26 | DB50: =Prudential!D24 -> 1
A51: 42766 | B51: =O51+CM51+Q51+AM51+CQ51+AO51+DA51+BA51+BC51+CO51+BG51+CS51+BI51+CY51+CK51+DC51+DE51 -> 6.6950403e+08 | C51: =P51+CN51+R51+AN51+CR51+AP51+DB51+BB51+BD51+CP51+BH51+CT51+BJ51+CZ51+CL51+DD51+DF51 -> 754 | D51: =O51+BA51+CO51+BG51+BI51+DC51 -> 5.1961215e+08 | E51: =P51+BB51+CP51+BH51+BJ51+DD51 -> 12 | F51: =CM51+CS51 -> 45799863 | G51: =CN51+CT51 -> 2 | H51: =Q51+CY51 -> 26074095 | I51: =R51+CZ51 -> 1 | J51: =AM51+CQ51+AO51+DA51 -> 20537971 | K51: =AN51+CR51+AP51+DB51 -> 738 | L51: =BC51+CK51+DE51 -> 57479949 | M51: =BD51+CL51+DF51 -> 1 | O51: =SILVX!B58 -> 1.1645838e+08 | P51: =SILVX!G58 -> 1 | Q51: =SGLIX!B3 -> 26074095 | R51: =SGLIX!G3 -> 1 | AM51: =Schwab!S46 -> 17034215 | AN51: =Schwab!Q46 -> 651 | AO51: =Fidelity!P51 -> 2367455.2 | AP51: =Fidelity!O51 -> 31 | BA51: ='TFA - Folio'!H56 -> 2.9092597e+08 | BB51: ='TFA - Folio'!I51 -> 1 | BC51: ='TFA - Folio'!K56 -> 57479949 | BD51: ='TFA - Folio'!N56 -> 1 | BG51: =UNC!B14 -> 106551075 | BH51: =UNC!C14 -> 1 | BI51: ='Schwab LC'!D11 -> 1547390.5 | BJ51: ='Schwab LC'!E11 -> 2 | CM51: =SCLVX!B12 -> 14035668 | CN51: =SCLVX!G12 -> 1 | CO51: =Stifel!B25 -> 4129335.7 | CP51: =Stifel!K25 -> 7 | CQ51: =TDA!O41 -> 1028268.7 | CR51: =TDA!N41 -> 55 | CS51: =UNC!D14 -> 31764195 | CT51: =UNC!E14 -> 1 | DA51: =Prudential!E25 -> 108032.58 | DB51: =Prudential!D25 -> 1
A52: 42794 | B52: =O52+CM52+Q52+AM52+CQ52+AO52+DA52+BA52+BC52+CO52+BG52+CS52+BI52+CY52+CK52+DC52+DE52 -> 6.8328576e+08 | C52: =P52+CN52+R52+AN52+CR52+AP52+DB52+BB52+BD52+CP52+BH52+CT52+BJ52+CZ52+CL52+DD52+DF52 -> 760 | D52: =O52+BA52+CO52+BG52+BI52+DC52 -> 5.3351482e+08 | E52: =P52+BB52+CP52+BH52+BJ52+DD52 -> 12 | F52: =CM52+CS52 -> 46199672 | G52: =CN52+CT52 -> 2 | H52: =Q52+CY52 -> 24556813 | I52: =R52+CZ52 -> 1 | J52: =AM52+CQ52+AO52+DA52 -> 21592433 | K52: =AN52+CR52+AP52+DB52 -> 744 | L52: =BC52+CK52+DE52 -> 57422030 | M52: =BD52+CL52+DF52 -> 1 | O52: =SILVX!B59 -> 1.1320426e+08 | P52: =SILVX!G59 -> 1 | Q52: =SGLIX!B4 -> 24556813 | R52: =SGLIX!G4 -> 1 | AM52: =Schwab!S47 -> 18171761 | AN52: =Schwab!Q47 -> 657 | AO52: =Fidelity!P52 -> 2278714.9 | AP52: =Fidelity!O52 -> 31 | BA52: ='TFA - Folio'!H57 -> 3.0359029e+08 | BB52: ='TFA - Folio'!I52 -> 1 | BC52: ='TFA - Folio'!K57 -> 57422030 | BD52: ='TFA - Folio'!N57 -> 1 | BG52: =UNC!B15 -> 1.1085012e+08 | BH52: =UNC!C15 -> 1 | BI52: ='Schwab LC'!D12 -> 1595924.8 | BJ52: ='Schwab LC'!E12 -> 2 | CM52: =SCLVX!B13 -> 14165872 | CN52: =SCLVX!G13 -> 1 | CO52: =Stifel!B26 -> 4274216.8 | CP52: =Stifel!K26 -> 7 | CQ52: =TDA!O42 -> 1032984.3 | CR52: =TDA!N42 -> 55 | CS52: =UNC!D15 -> 32033800 | CT52: =UNC!E15 -> 1 | DA52: =Prudential!E26 -> 108972.54 | DB52: =Prudential!D26 -> 1
A53: 42825 | B53: =O53+CM53+Q53+AM53+CQ53+AO53+DA53+BA53+BC53+CO53+BG53+CS53+BI53+CY53+CK53+DC53+DE53 -> 7.0037861e+08 | C53: =P53+CN53+R53+AN53+CR53+AP53+DB53+BB53+BD53+CP53+BH53+CT53+BJ53+CZ53+CL53+DD53+DF53 -> 750 | D53: =O53+BA53+CO53+BG53+BI53+DC53 -> 5.52885e+08 | E53: =P53+BB53+CP53+BH53+BJ53+DD53 -> 13 | F53: =CM53+CS53 -> 46267200 | G53: =CN53+CT53 -> 2 | H53: =Q53+CY53 -> 23502174 | I53: =R53+CZ53 -> 1 | J53: =AM53+CQ53+AO53+DA53 -> 21121469 | K53: =AN53+CR53+AP53+DB53 -> 733 | L53: =BC53+CK53+DE53 -> 56602774 | M53: =BD53+CL53+DF53 -> 1 | O53: =SILVX!B60 -> 1.1258416e+08 | P53: =SILVX!G60 -> 1 | Q53: =SGLIX!B5 -> 23502174 | R53: =SGLIX!G5 -> 1 | AM53: =Schwab!S48 -> 16792285 | AN53: =Schwab!Q48 -> 649 | AO53: =Fidelity!P53 -> 3232038.3 | AP53: =Fidelity!O53 -> 31 | BA53: ='TFA - Folio'!H58 -> 3.0376266e+08 | BB53: ='TFA - Folio'!I53 -> 1 | BC53: ='TFA - Folio'!K58 -> 56602774 | BD53: ='TFA - Folio'!N58 -> 1 | BG53: =UNC!B16 -> 1.1054588e+08 | BH53: =UNC!C16 -> 1 | BI53: ='Schwab LC'!D13 -> 1588770.1 | BJ53: ='Schwab LC'!E13 -> 2 | CM53: =SCLVX!B14 -> 14155179 | CN53: =SCLVX!G14 -> 1 | CO53: =Stifel!B27 -> 4257359.4 | CP53: =Stifel!K27 -> 7 | CQ53: =TDA!O43 -> 988340.76 | CR53: =TDA!N43 -> 52 | CS53: =UNC!D16 -> 32112020 | CT53: =UNC!E16 -> 1 | DA53: =Prudential!E27 -> 108805.3 | DB53: =Prudential!D27 -> 1 | DC53: =LACERA!B2 -> 20146171 | DD53: =LACERA!C2 -> 1
A54: 42855 | B54: =O54+CM54+Q54+AM54+CQ54+AO54+DA54+BA54+BC54+CO54+BG54+CS54+BI54+CY54+CK54+DC54+DE54 -> 7.0319676e+08 | C54: =P54+CN54+R54+AN54+CR54+AP54+DB54+BB54+BD54+CP54+BH54+CT54+BJ54+CZ54+CL54+DD54+DF54 -> 772 | D54: =O54+BA54+CO54+BG54+BI54+DC54 -> 5.5718778e+08 | E54: =P54+BB54+CP54+BH54+BJ54+DD54 -> 13 | F54: =CM54+CS54 -> 46114542 | G54: =CN54+CT54 -> 2 | H54: =Q54+CY54 -> 22855948 | I54: =R54+CZ54 -> 1 | J54: =AM54+CQ54+AO54+DA54 -> 19687233 | K54: =AN54+CR54+AP54+DB54 -> 755 | L54: =BC54+CK54+DE54 -> 57351263 | M54: =BD54+CL54+DF54 -> 1 | O54: =SILVX!B61 -> 1.1197279e+08 | P54: =SILVX!G61 -> 1 | Q54: =SGLIX!B6 -> 22855948 | R54: =SGLIX!G6 -> 1 | AM54: =Schwab!S49 -> 15801367 | AN54: =Schwab!Q49 -> 669 | AO54: =Fidelity!P54 -> 2181421.8 | AP54: =Fidelity!O54 -> 31 | BA54: ='TFA - Folio'!H59 -> 3.0357427e+08 | BB54: ='TFA - Folio'!I54 -> 1 | BC54: ='TFA - Folio'!K59 -> 57351263 | BD54: ='TFA - Folio'!N59 -> 1 | BG54: =UNC!B17 -> 1.1054588e+08 | BH54: =UNC!C17 -> 1 | BI54: ='Schwab LC'!D14 -> 1596414.5 | BJ54: ='Schwab LC'!E14 -> 2 | CM54: =SCLVX!B15 -> 14002520 | CN54: =SCLVX!G15 -> 1 | CO54: =Stifel!B28 -> 4287070.4 | CP54: =Stifel!K28 -> 7 | CQ54: =TDA!O44 -> 1595254.1 | CR54: =TDA!N44 -> 54 | CS54: =UNC!D17 -> 32112021 | CT54: =UNC!E17 -> 1 | DA54: =Prudential!E28 -> 109190.2 | DB54: =Prudential!D28 -> 1 | DC54: =LACERA!B3 -> 25211353 | DD54: =LACERA!C3 -> 1
A55: 42886 | B55: =O55+CM55+Q55+AM55+CQ55+AO55+DA55+BA55+BC55+CO55+BG55+CS55+BI55+CY55+CK55+DC55+DE55 -> 7.107173e+08 | C55: =P55+CN55+R55+AN55+CR55+AP55+DB55+BB55+BD55+CP55+BH55+CT55+BJ55+CZ55+CL55+DD55+DF55 -> 778 | D55: =O55+BA55+CO55+BG55+BI55+DC55 -> 5.6211209e+08 | E55: =P55+BB55+CP55+BH55+BJ55+DD55 -> 13 | F55: =CM55+CS55 -> 49309309 | G55: =CN55+CT55 -> 2 | H55: =Q55+CY55 -> 22435710 | I55: =R55+CZ55 -> 1 | J55: =AM55+CQ55+AO55+DA55 -> 20355977 | K55: =AN55+CR55+AP55+DB55 -> 761 | L55: =BC55+CK55+DE55 -> 56504214 | M55: =BD55+CL55+DF55 -> 1 | O55: =SILVX!B62 -> 1.1357593e+08 | P55: =SILVX!G62 -> 1 | Q55: =SGLIX!B7 -> 22435710 | R55: =SGLIX!G7 -> 1 | AM55: =Schwab!S50 -> 16550790 | AN55: =Schwab!Q50 -> 675 | AO55: =Fidelity!P55 -> 2175287.2 | AP55: =Fidelity!O55 -> 31 | BA55: ='TFA - Folio'!H60 -> 3.0446464e+08 | BB55: ='TFA - Folio'!I55 -> 1 | BC55: ='TFA - Folio'!K60 -> 56504214 | BD55: ='TFA - Folio'!N60 -> 1 | BG55: =UNC!B18 -> 1.1276167e+08 | BH55: =UNC!C18 -> 1 | BI55: ='Schwab LC'!D15 -> 1613083.2 | BJ55: ='Schwab LC'!E15 -> 2 | CM55: =SCLVX!B16 -> 16286886 | CN55: =SCLVX!G16 -> 1 | CO55: =Stifel!B29 -> 4340622.5 | CP55: =Stifel!K29 -> 7 | CQ55: =TDA!O45 -> 1519237 | CR55: =TDA!N45 -> 54 | CS55: =UNC!D18 -> 33022424 | CT55: =UNC!E18 -> 1 | DA55: =Prudential!E29 -> 110663.38 | DB55: =Prudential!D29 -> 1 | DC55: =LACERA!B4 -> 25356140 | DD55: =LACERA!C4 -> 1
A56: 42916 | B56: =O56+CM56+Q56+AM56+CQ56+AO56+DA56+BA56+BC56+CO56+BG56+CS56+BI56+CY56+CK56+DC56+DE56 -> 7.1935202e+08 | C56: =P56+CN56+R56+AN56+CR56+AP56+DB56+BB56+BD56+CP56+BH56+CT56+BJ56+CZ56+CL56+DD56+DF56 -> 780 | D56: =O56+BA56+CO56+BG56+BI56+DC56 -> 5.6221688e+08 | E56: =P56+BB56+CP56+BH56+BJ56+DD56 -> 13 | F56: =CM56+CS56 -> 49857150 | G56: =CN56+CT56 -> 2 | H56: =Q56+CY56 -> 32392905 | I56: =R56+CZ56 -> 2 | J56: =AM56+CQ56+AO56+DA56 -> 19421259 | K56: =AN56+CR56+AP56+DB56 -> 762 | L56: =BC56+CK56+DE56 -> 55463827 | M56: =BD56+CL56+DF56 -> 1 | O56: =SILVX!B63 -> 1.1428113e+08 | P56: =SILVX!G63 -> 1 | Q56: =SGLIX!B8 -> 22484295 | R56: =SGLIX!G8 -> 1 | AM56: =Schwab!S51 -> 15931701 | AN56: =Schwab!Q51 -> 676 | AO56: =Fidelity!P56 -> 2189645 | AP56: =Fidelity!O56 -> 31 | BA56: ='TFA - Folio'!H61 -> 3.0349572e+08 | BB56: ='TFA - Folio'!I56 -> 1 | BC56: ='TFA - Folio'!K61 -> 55463827 | BD56: ='TFA - Folio'!N61 -> 1 | BG56: =UNC!B19 -> 1.1298606e+08 | BH56: =UNC!C19 -> 1 | BI56: ='Schwab LC'!D16 -> 1614176.3 | BJ56: ='Schwab LC'!E16 -> 2 | CM56: =SCLVX!B17 -> 16585056 | CN56: =SCLVX!G17 -> 1 | CO56: =Stifel!B30 -> 4348894.3 | CP56: =Stifel!K30 -> 7 | CQ56: =TDA!O46 -> 1189385.1 | CR56: =TDA!N46 -> 54 | CS56: =UNC!D19 -> 33272095 | CT56: =UNC!E19 -> 1 | CY56: =Cline!B2 -> 9908609.9 | CZ56: =Cline!C2 -> 1 | DA56: =Prudential!E30 -> 110528.21 | DB56: =Prudential!D30 -> 1 | DC56: =LACERA!B5 -> 25490897 | DD56: =LACERA!C5 -> 1
A57: 42947 | B57: =O57+CM57+Q57+AM57+CQ57+AO57+DA57+BA57+BC57+CO57+BG57+CS57+BI57+CY57+CK57+DC57+DE57 -> 7.2320575e+08 | C57: =P57+CN57+R57+AN57+CR57+AP57+DB57+BB57+BD57+CP57+BH57+CT57+BJ57+CZ57+CL57+DD57+DF57 -> 778 | D57: =O57+BA57+CO57+BG57+BI57+DC57 -> 5.6518303e+08 | E57: =P57+BB57+CP57+BH57+BJ57+DD57 -> 13 | F57: =CM57+CS57 -> 50196766 | G57: =CN57+CT57 -> 2 | H57: =Q57+CY57 -> 32554580 | I57: =R57+CZ57 -> 2 | J57: =AM57+CQ57+AO57+DA57 -> 20423299 | K57: =AN57+CR57+AP57+DB57 -> 760 | L57: =BC57+CK57+DE57 -> 54848078 | M57: =BD57+CL57+DF57 -> 1 | O57: =SILVX!B64 -> 1.1357593e+08 | P57: =SILVX!G64 -> 1 | Q57: =SGLIX!B9 -> 22532879 | R57: =SGLIX!G9 -> 1 | AM57: =Schwab!S52 -> 16923460 | AN57: =Schwab!Q52 -> 674 | AO57: =Fidelity!P57 -> 2191575.1 | AP57: =Fidelity!O57 -> 31 | BA57: ='TFA - Folio'!H62 -> 3.0478093e+08 | BB57: ='TFA - Folio'!I57 -> 1 | BC57: ='TFA - Folio'!K62 -> 54848078 | BD57: ='TFA - Folio'!N62 -> 1 | BG57: =UNC!B20 -> 1.1488212e+08 | BH57: =UNC!C20 -> 1 | BI57: ='Schwab LC'!D17 -> 1637157.4 | BJ57: ='Schwab LC'!E17 -> 2 | CM57: =SCLVX!B18 -> 16286886 | CN57: =SCLVX!G18 -> 1 | CO57: =Stifel!B31 -> 4413096.1 | CP57: =Stifel!K31 -> 7 | CQ57: =TDA!O47 -> 1196497.7 | CR57: =TDA!N47 -> 54 | CS57: =UNC!D20 -> 33909880 | CT57: =UNC!E20 -> 1 | CY57: =Cline!B3 -> 10021701 | CZ57: =Cline!C3 -> 1 | DA57: =Prudential!E31 -> 111765.89 | DB57: =Prudential!D31 -> 1 | DC57: =LACERA!B6 -> 25893794 | DD57: =LACERA!C6 -> 1
A58: 42978 | B58: =O58+CM58+Q58+AM58+CQ58+AO58+DA58+BA58+BC58+CO58+BG58+CS58+BI58+CY58+CK58+DC58+DE58 -> 7.3409084e+08 | C58: =P58+CN58+R58+AN58+CR58+AP58+DB58+BB58+BD58+CP58+BH58+CT58+BJ58+CZ58+CL58+DD58+DF58 -> 785 | D58: =O58+BA58+CO58+BG58+BI58+DC58 -> 5.7140271e+08 | E58: =P58+BB58+CP58+BH58+BJ58+DD58 -> 13 | F58: =CM58+CS58 -> 49517793 | G58: =CN58+CT58 -> 2 | H58: =Q58+CY58 -> 37985275 | I58: =R58+CZ58 -> 2 | J58: =AM58+CQ58+AO58+DA58 -> 20685972 | K58: =AN58+CR58+AP58+DB58 -> 767 | L58: =BC58+CK58+DE58 -> 54499086 | M58: =BD58+CL58+DF58 -> 1 | O58: =SILVX!B65 -> 1.1543128e+08 | P58: =SILVX!G65 -> 1 | Q58: =SGLIX!B10 -> 22786318 | R58: =SGLIX!G10 -> 1 | AM58: =Schwab!S53 -> 16998892 | AN58: =Schwab!Q53 -> 679 | AO58: =Fidelity!P58 -> 2260471 | AP58: =Fidelity!O58 -> 33 | BA58: ='TFA - Folio'!H63 -> 3.0184957e+08 | BB58: ='TFA - Folio'!I58 -> 1 | BC58: ='TFA - Folio'!K63 -> 54499086 | BD58: ='TFA - Folio'!N63 -> 1 | BG58: =UNC!B21 -> 1.1481588e+08 | BH58: =UNC!C21 -> 1 | BI58: ='Schwab LC'!D18 -> 1632884.9 | BJ58: ='Schwab LC'!E18 -> 2 | CM58: =SCLVX!B19 -> 16207390 | CN58: =SCLVX!G19 -> 1 | CO58: =Stifel!B32 -> 4411112.6 | CP58: =Stifel!K32 -> 7 | CQ58: =TDA!O48 -> 1314674.3 | CR58: =TDA!N48 -> 54 | CS58: =UNC!D21 -> 33310403 | CT58: =UNC!E21 -> 1 | CY58: =Cline!B4 -> 15198957 | CZ58: =Cline!C4 -> 1 | DA58: =Prudential!E32 -> 111934.59 | DB58: =Prudential!D32 -> 1 | DC58: =LACERA!B7 -> 33261985 | DD58: =LACERA!C7 -> 1
A59: 43008 | B59: =O59+CM59+Q59+AM59+CQ59+AO59+DA59+BA59+BC59+CO59+BG59+CS59+BI59+CY59+CK59+DC59+DE59 -> 7.0701063e+08 | C59: =P59+CN59+R59+AN59+CR59+AP59+DB59+BB59+BD59+CP59+BH59+CT59+BJ59+CZ59+CL59+DD59+DF59 -> 790 | D59: =O59+BA59+CO59+BG59+BI59+DC59 -> 5.4152379e+08 | E59: =P59+BB59+CP59+BH59+BJ59 -> 12 | F59: =CM59+CS59 -> 52921699 | G59: =CN59+CT59 -> 2 | H59: =Q59+CY59 -> 37871447 | I59: =R59+CZ59 -> 2 | J59: =AM59+CQ59+AO59+DA59 -> 20015084 | K59: =AN59+CR59+AP59+DB59 -> 773 | L59: =BC59+CK59+DE59 -> 54678615 | M59: =BD59+CL59+DF59 -> 1 | O59: =SILVX!B66 -> 1.1674508e+08 | P59: =SILVX!G66 -> 1 | Q59: =SGLIX!B11 -> 22416582 | R59: =SGLIX!G11 -> 1 | AM59: =Schwab!S54 -> 16403784 | AN59: =Schwab!Q54 -> 684 | AO59: =Fidelity!P59 -> 2306090.7 | AP59: =Fidelity!O59 -> 34 | BA59: ='TFA - Folio'!H64 -> 3.0228499e+08 | BB59: ='TFA - Folio'!I59 -> 1 | BC59: ='TFA - Folio'!K64 -> 54678615 | BD59: ='TFA - Folio'!N64 -> 1 | BG59: =UNC!B22 -> 1.1636539e+08 | BH59: =UNC!C22 -> 1 | BI59: ='Schwab LC'!D19 -> 1654582.1 | BJ59: ='Schwab LC'!E19 -> 2 | CM59: =SCLVX!B20 -> 17491909 | CN59: =SCLVX!G20 -> 1 | CO59: =Stifel!B33 -> 4473747.3 | CP59: =Stifel!K33 -> 7 | CQ59: =TDA!O49 -> 1196268.7 | CR59: =TDA!N49 -> 54 | CS59: =UNC!D22 -> 35429790 | CT59: =UNC!E22 -> 1 | CY59: =Cline!B5 -> 15454865 | CZ59: =Cline!C5 -> 1 | DA59: =Prudential!E33 -> 108940.42 | DB59: =Prudential!D33 -> 1
A60: 43039 | B60: =O60+CM60+Q60+AM60+CQ60+AO60+DA60+BA60+BC60+CO60+BG60+CS60+BI60+CY60+CK60+DC60+DE60 -> 7.1567963e+08 | C60: =P60+CN60+R60+AN60+CR60+AP60+DB60+BB60+BD60+CP60+BH60+CT60+BJ60+CZ60+CL60+DD60+DF60 -> 790 | D60: =O60+BA60+CO60+BG60+BI60+DC60 -> 5.4540692e+08 | E60: =P60+BB60+CP60+BH60+BJ60 -> 12 | F60: =CM60+CS60 -> 55703821 | G60: =CN60+CT60 -> 2 | H60: =Q60+CY60 -> 37819537 | I60: =R60+CZ60 -> 2 | J60: =AM60+CQ60+AO60+DA60 -> 23669557 | K60: =AN60+CR60+AP60+DB60 -> 773 | L60: =BC60+CK60+DE60 -> 53079798 | M60: =BD60+CL60+DF60 -> 1 | O60: =SILVX!B67 -> 1.1644179e+08 | P60: =SILVX!G67 -> 1 | Q60: =SGLIX!B12 -> 22155044 | R60: =SGLIX!G12 -> 1 | AM60: =Schwab!S55 -> 20203955 | AN60: =Schwab!Q55 -> 684 | AO60: =Fidelity!P60 -> 2263073.8 | AP60: =Fidelity!O60 -> 34 | BA60: ='TFA - Folio'!H65 -> 3.0440312e+08 | BB60: ='TFA - Folio'!I60 -> 1 | BC60: ='TFA - Folio'!K65 -> 53079798 | BD60: ='TFA - Folio'!N65 -> 1 | BG60: =UNC!B23 -> 1.1838468e+08 | BH60: =UNC!C23 -> 1 | BI60: ='Schwab LC'!D20 -> 1661916.2 | BJ60: ='Schwab LC'!E20 -> 2 | CM60: =SCLVX!B21 -> 19931936 | CN60: =SCLVX!G21 -> 1 | CO60: =Stifel!B34 -> 4515412.8 | CP60: =Stifel!K34 -> 7 | CQ60: =TDA!O50 -> 1091045.4 | CR60: =TDA!N50 -> 54 | CS60: =UNC!D23 -> 35771885 | CT60: =UNC!E23 -> 1 | CY60: =Cline!B6 -> 15664493 | CZ60: =Cline!C6 -> 1 | DA60: =Prudential!E34 -> 111482.79 | DB60: =Prudential!D34 -> 1
A61: 43069 | B61: =O61+CM61+Q61+AM61+CQ61+AO61+DA61+BA61+BC61+CO61+BG61+CS61+BI61+CY61+CK61+DC61+DE61 -> 7.0804236e+08 | C61: =P61+CN61+R61+AN61+CR61+AP61+DB61+BB61+BD61+CP61+BH61+CT61+BJ61+CZ61+CL61+DD61+DF61 -> 797 | D61: =O61+BA61+CO61+BG61+BI61+DC61 -> 5.3996343e+08 | E61: =P61+BB61+CP61+BH61+BJ61 -> 12 | F61: =CM61+CS61 -> 57454069 | G61: =CN61+CT61 -> 2 | H61: =Q61+CY61 -> 38557856 | I61: =R61+CZ61 -> 2 | J61: =AM61+CQ61+AO61+DA61 -> 18281702 | K61: =AN61+CR61+AP61+DB61 -> 780 | L61: =BC61+CK61+DE61 -> 53785302 | M61: =BD61+CL61+DF61 -> 1 | O61: =SILVX!B68 -> 1.0483007e+08 | P61: =SILVX!G68 -> 1 | Q61: =SGLIX!B13 -> 22545615 | R61: =SGLIX!G13 -> 1 | AM61: =Schwab!S56 -> 14750836 | AN61: =Schwab!Q56 -> 691 | AO61: =Fidelity!P61 -> 2346898.3 | AP61: =Fidelity!O61 -> 34 | BA61: ='TFA - Folio'!H66 -> 3.1633624e+08 | BB61: ='TFA - Folio'!I61 -> 1 | BC61: ='TFA - Folio'!K66 -> 53785302 | BD61: ='TFA - Folio'!N66 -> 1 | BG61: =UNC!B24 -> 1.1234801e+08 | BH61: =UNC!C24 -> 1 | BI61: ='Schwab LC'!D21 -> 1734391.9 | BJ61: ='Schwab LC'!E21 -> 2 | CM61: =SCLVX!B22 -> 21249097 | CN61: =SCLVX!G22 -> 1 | CO61: =Stifel!B35 -> 4714722.5 | CP61: =Stifel!K35 -> 7 | CQ61: =TDA!O51 -> 1073197.4 | CR61: =TDA!N51 -> 54 | CS61: =UNC!D24 -> 36204972 | CT61: =UNC!E24 -> 1 | CY61: =Cline!B7 -> 16012242 | CZ61: =Cline!C7 -> 1 | DA61: =Prudential!E35 -> 110770 | DB61: =Prudential!D35 -> 1
A62: 43100 | B62: =O62+CM62+Q62+AM62+CQ62+AO62+DA62+BA62+BC62+CO62+BG62+CS62+BI62+CY62+CK62+DC62+DE62 -> 7.0981867e+08 | C62: =P62+CN62+R62+AN62+CR62+AP62+DB62+BB62+BD62+CP62+BH62+CT62+BJ62+CZ62+CL62+DD62+DF62 -> 787 | D62: =O62+BA62+CO62+BG62+BI62+DC62 -> 5.4134274e+08 | E62: =P62+BB62+CP62+BH62+BJ62 -> 12 | F62: =CM62+CS62 -> 56836704 | G62: =CN62+CT62 -> 2 | H62: =Q62+CY62 -> 38767508 | I62: =R62+CZ62 -> 2 | J62: =AM62+CQ62+AO62+DA62 -> 19619609 | K62: =AN62+CR62+AP62+DB62 -> 770 | L62: =BC62+CK62+DE62 -> 53252111 | M62: =BD62+CL62+DF62 -> 1 | O62: =SILVX!B69 -> 1.0346836e+08 | P62: =SILVX!G69 -> 1 | Q62: =SGLIX!B14 -> 22581175 | R62: =SGLIX!G14 -> 1 | AM62: =Schwab!S57 -> 16093446 | AN62: =Schwab!Q57 -> 681 | AO62: =Fidelity!P62 -> 2402291.1 | AP62: =Fidelity!O62 -> 34 | BA62: ='TFA - Folio'!H67 -> 3.1718028e+08 | BB62: ='TFA - Folio'!I62 -> 1 | BC62: ='TFA - Folio'!K67 -> 53252111 | BD62: ='TFA - Folio'!N67 -> 1 | BG62: =UNC!B25 -> 1.1418147e+08 | BH62: =UNC!C25 -> 1 | BI62: ='Schwab LC'!D22 -> 1757153.3 | BJ62: ='Schwab LC'!E22 -> 2 | CM62: =SCLVX!B23 -> 21152071 | CN62: =SCLVX!G23 -> 1 | CO62: =Stifel!B36 -> 4755468.4 | CP62: =Stifel!K36 -> 7 | CQ62: =TDA!O52 -> 1011729.2 | CR62: =TDA!N52 -> 54 | CS62: =UNC!D25 -> 35684633 | CT62: =UNC!E25 -> 1 | CY62: =Cline!B8 -> 16186333 | CZ62: =Cline!C8 -> 1 | DA62: =Prudential!E36 -> 112142.57 | DB62: =Prudential!D36 -> 1
A63: 43131 | B63: =O63+CM63+Q63+AM63+CQ63+AO63+DA63+BA63+BC63+CO63+BG63+CS63+BI63+CY63+CK63+DC63+DE63 -> 7.2815268e+08 | C63: =P63+CN63+R63+AN63+CR63+AP63+DB63+BB63+BD63+CP63+BH63+CT63+BJ63+CZ63+CL63+DD63+DF63 -> 796 | D63: =O63+BA63+CO63+BG63+BI63+DC63 -> 5.5957258e+08 | E63: =P63+BB63+CP63+BH63+BJ63 -> 12 | F63: =CM63+CS63 -> 57355209 | G63: =CN63+CT63 -> 2 | H63: =Q63+CY63 -> 39301130 | I63: =R63+CZ63 -> 2 | J63: =AM63+CQ63+AO63+DA63 -> 18135082 | K63: =AN63+CR63+AP63+DB63 -> 779 | L63: =BC63+CK63+DE63 -> 53788678 | M63: =BD63+CL63+DF63 -> 1 | O63: =SILVX!B70 -> 1.0663257e+08 | P63: =SILVX!G70 -> 1 | Q63: =SGLIX!B15 -> 22567923 | R63: =SGLIX!G15 -> 1 | AM63: =Schwab!S58 -> 14678086 | AN63: =Schwab!Q58 -> 690 | AO63: =Fidelity!P63 -> 2433543.6 | AP63: =Fidelity!O63 -> 35 | BA63: ='TFA - Folio'!H68 -> 3.2657141e+08 | BB63: ='TFA - Folio'!I63 -> 1 | BC63: ='TFA - Folio'!K68 -> 53788678 | BD63: ='TFA - Folio'!N68 -> 1 | BG63: =UNC!B26 -> 1.1959575e+08 | BH63: =UNC!C26 -> 1 | BI63: ='Schwab LC'!D23 -> 1828415.4 | BJ63: ='Schwab LC'!E23 -> 2 | CM63: =SCLVX!B24 -> 21419695 | CN63: =SCLVX!G24 -> 1 | CO63: =Stifel!B37 -> 4944437.2 | CP63: =Stifel!K37 -> 7 | CQ63: =TDA!O53 -> 912352.5 | CR63: =TDA!N53 -> 53 | CS63: =UNC!D26 -> 35935514 | CT63: =UNC!E26 -> 1 | CY63: =Cline!B9 -> 16733207 | CZ63: =Cline!C9 -> 1 | DA63: =Prudential!E37 -> 111099.83 | DB63: =Prudential!D37 -> 1
A64: 43159 | B64: =O64+CM64+Q64+AM64+CQ64+AO64+DA64+BA64+BC64+CO64+BG64+CS64+BI64+CY64+CK64+DC64+DE64 -> 7.1541751e+08 | C64: =P64+CN64+R64+AN64+CR64+AP64+DB64+BB64+BD64+CP64+BH64+CT64+BJ64+CZ64+CL64+DD64+DF64 -> 811 | D64: =O64+BA64+CO64+BG64+BI64+DC64 -> 5.3655462e+08 | E64: =P64+BB64+CP64+BH64+BJ64 -> 12 | F64: =CM64+CS64 -> 55094662 | G64: =CN64+CT64 -> 2 | H64: =Q64+CY64 -> 37420768 | I64: =R64+CZ64 -> 2 | J64: =AM64+CQ64+AO64+DA64 -> 18641548 | K64: =AN64+CR64+AP64+DB64 -> 793 | L64: =BC64+CK64+DE64 -> 67705910 | M64: =BD64+CL64+DF64 -> 2 | O64: =SILVX!B71 -> 1.0156336e+08 | P64: =SILVX!G71 -> 1 | Q64: =SGLIX!B16 -> 21278277 | R64: =SGLIX!G16 -> 1 | AM64: =Schwab!S59 -> 15259984 | AN64: =Schwab!Q59 -> 703 | AO64: =Fidelity!P64 -> 2325604.3 | AP64: =Fidelity!O64 -> 36 | BA64: ='TFA - Folio'!H69 -> 3.1250259e+08 | BB64: ='TFA - Folio'!I64 -> 1 | BC64: ='TFA - Folio'!K69 -> 52305822 | BD64: ='TFA - Folio'!N69 -> 1 | BG64: =UNC!B27 -> 1.1592096e+08 | BH64: =UNC!C27 -> 1 | BI64: ='Schwab LC'!D24 -> 1772440.2 | BJ64: ='Schwab LC'!E24 -> 2 | CK64: ='Holiday Oil'!G2 -> 15400088 | CL64: ='Holiday Oil'!H2 -> 1 | CM64: =SCLVX!B25 -> 20693893 | CN64: =SCLVX!G25 -> 1 | CO64: =Stifel!B38 -> 4795260.1 | CP64: =Stifel!K38 -> 7 | CQ64: =TDA!O54 -> 947917.1 | CR64: =TDA!N54 -> 53 | CS64: =UNC!D27 -> 34400770 | CT64: =UNC!E27 -> 1 | CY64: =Cline!B10 -> 16142491 | CZ64: =Cline!C10 -> 1 | DA64: =Prudential!E38 -> 108042.87 | DB64: =Prudential!D38 -> 1
A65: 43190 | B65: =O65+CM65+Q65+AM65+CQ65+AO65+DA65+BA65+BC65+CO65+BG65+CS65+BI65+CY65+CK65+DC65+DE65 -> 7.1117603e+08 | C65: =P65+CN65+R65+AN65+CR65+AP65+DB65+BB65+BD65+CP65+BH65+CT65+BJ65+CZ65+CL65+DD65+DF65 -> 896 | D65: =O65+BA65+CO65+BG65+BI65+DC65 -> 5.2188475e+08 | E65: =P65+BB65+CP65+BH65+BJ65 -> 11 | F65: =CM65+CS65 -> 58319600 | G65: =CN65+CT65 -> 2 | H65: =Q65+CY65 -> 36875586 | I65: =R65+CZ65 -> 2 | J65: =AM65+CQ65+AO65+DA65 -> 28789150 | K65: =AN65+CR65+AP65+DB65 -> 879 | L65: =BC65+CK65+DE65 -> 65306943 | M65: =BD65+CL65+DF65 -> 2 | O65: =SILVX!B72 -> 1.3531654e+08 | P65: =SILVX!G72 -> 1 | Q65: =SGLIX!B17 -> 20822421 | R65: =SGLIX!G17 -> 1 | AM65: =Schwab!S60 -> 17593882 | AN65: =Schwab!Q60 -> 727 | AO65: =Fidelity!P65 -> 10118286 | AP65: =Fidelity!O65 -> 97 | BA65: ='TFA - Folio'!H70 -> 2.6499349e+08 | BB65: ='TFA - Folio'!I65 -> 1 | BC65: ='TFA - Folio'!K70 -> 49805943 | BD65: ='TFA - Folio'!N70 -> 1 | BG65: =UNC!B28 -> 1.1493362e+08 | BH65: =UNC!C28 -> 1 | BI65: ='Schwab LC'!D25 -> 2437992.9 | BJ65: ='Schwab LC'!E25 -> 2 | CK65: ='Holiday Oil'!G3 -> 15501001 | CL65: ='Holiday Oil'!H3 -> 1 | CM65: =SCLVX!B26 -> 22851229 | CN65: =SCLVX!G26 -> 1 | CO65: =Stifel!B39 -> 4203115.6 | CP65: =Stifel!K39 -> 6 | CQ65: =TDA!O55 -> 967703.94 | CR65: =TDA!N55 -> 54 | CS65: =UNC!D28 -> 35468371 | CT65: =UNC!E28 -> 1 | CY65: =Cline!B11 -> 16053166 | CZ65: =Cline!C11 -> 1 | DA65: =Prudential!E39 -> 109278.11 | DB65: =Prudential!D39 -> 1
A66: 43220 | B66: =O66+CM66+Q66+AM66+CQ66+AO66+DA66+BA66+BC66+CO66+BG66+CS66+BI66+CY66+CK66+DC66+DE66 -> 7.1860191e+08 | C66: =P66+CN66+R66+AN66+CR66+AP66+DB66+BB66+BD66+CP66+BH66+CT66+BJ66+CZ66+CL66+DD66+DF66 -> 921 | D66: =O66+BA66+CO66+BG66+BI66+DC66 -> 5.2829531e+08 | E66: =P66+BB66+CP66+BH66+BJ66 -> 11 | F66: =CM66+CS66 -> 59746827 | G66: =CN66+CT66 -> 2 | H66: =Q66+CY66 -> 36083397 | I66: =R66+CZ66 -> 2 | J66: =AM66+CQ66+AO66+DA66 -> 28748616 | K66: =AN66+CR66+AP66+DB66 -> 904 | L66: =BC66+CK66+DE66 -> 65727761 | M66: =BD66+CL66+DF66 -> 2 | O66: =SILVX!B73 -> 2.4396862e+08 | P66: =SILVX!G73 -> 1 | Q66: =SGLIX!B18 -> 20159723 | R66: =SGLIX!G18 -> 1 | AM66: =Schwab!S61 -> 17467069 | AN66: =Schwab!Q61 -> 749 | AO66: =Fidelity!P66 -> 10230727 | AP66: =Fidelity!O66 -> 102 | BA66: ='TFA - Folio'!H71 -> 1.602738e+08 | BB66: ='TFA - Folio'!I66 -> 1 | BC66: ='TFA - Folio'!K71 -> 50335440 | BD66: ='TFA - Folio'!N71 -> 1 | BG66: =UNC!B29 -> 1.1731198e+08 | BH66: =UNC!C29 -> 1 | BI66: ='Schwab LC'!D26 -> 2474473.4 | BJ66: ='Schwab LC'!E26 -> 2 | CK66: ='Holiday Oil'!G4 -> 15392321 | CL66: ='Holiday Oil'!H4 -> 1 | CM66: =SCLVX!B27 -> 23885530 | CN66: =SCLVX!G27 -> 1 | CO66: =Stifel!B40 -> 4266426.7 | CP66: =Stifel!K40 -> 6 | CQ66: =TDA!O56 -> 941928.21 | CR66: =TDA!N56 -> 52 | CS66: =UNC!D29 -> 35861297 | CT66: =UNC!E29 -> 1 | CY66: =Cline!B12 -> 15923674 | CZ66: =Cline!C12 -> 1 | DA66: =Prudential!E40 -> 108891.96 | DB66: =Prudential!D40 -> 1
A67: 43251 | B67: =O67+CM67+Q67+AM67+CQ67+AO67+DA67+BA67+BC67+CO67+BG67+CS67+BI67+CY67+CK67+DC67+DE67 -> 7.3177894e+08 | C67: =P67+CN67+R67+AN67+CR67+AP67+DB67+BB67+BD67+CP67+BH67+CT67+BJ67+CZ67+CL67+DD67+DF67 -> 932 | D67: =O67+BA67+CO67+BG67+BI67+DC67 -> 5.3591797e+08 | E67: =P67+BB67+CP67+BH67+BJ67 -> 11 | F67: =CM67+CS67 -> 64334607 | G67: =CN67+CT67 -> 2 | H67: =Q67+CY67 -> 35774514 | I67: =R67+CZ67 -> 2 | J67: =AM67+CQ67+AO67+DA67 -> 29716400 | K67: =AN67+CR67+AP67+DB67 -> 915 | L67: =BC67+CK67+DE67 -> 66035453 | M67: =BD67+CL67+DF67 -> 2 | O67: =SILVX!B74 -> 3.8538892e+08 | P67: =SILVX!G74 -> 1 | Q67: =SGLIX!B19 -> 19672503 | R67: =SGLIX!G19 -> 1 | AM67: =Schwab!S62 -> 18197219 | AN67: =Schwab!Q62 -> 752 | AO67: =Fidelity!P67 -> 10455316 | AP67: =Fidelity!O67 -> 112 | BA67: ='TFA - Folio'!H72 -> 24050924 | BB67: ='TFA - Folio'!I67 -> 1 | BC67: ='TFA - Folio'!K72 -> 50674106 | BD67: ='TFA - Folio'!N72 -> 1 | BG67: =UNC!B30 -> 1.1959884e+08 | BH67: =UNC!C30 -> 1 | BI67: ='Schwab LC'!D27 -> 2522024.7 | BJ67: ='Schwab LC'!E27 -> 2 | CK67: ='Holiday Oil'!G5 -> 15361346 | CL67: ='Holiday Oil'!H5 -> 1 | CM67: =SCLVX!B28 -> 26602137 | CN67: =SCLVX!G28 -> 1 | CO67: =Stifel!B41 -> 4357253.5 | CP67: =Stifel!K41 -> 6 | CQ67: =TDA!O57 -> 954433.28 | CR67: =TDA!N57 -> 50 | CS67: =UNC!D30 -> 37732470 | CT67: =UNC!E30 -> 1 | CY67: =Cline!B13 -> 16102012 | CZ67: =Cline!C13 -> 1 | DA67: =Prudential!E41 -> 109432.36 | DB67: =Prudential!D41 -> 1
A68: 43281 | B68: =O68+CM68+Q68+AM68+CQ68+AO68+DA68+BA68+BC68+CO68+BG68+CS68+BI68+CY68+CK68+DC68+DE68 -> 7.4596352e+08 | C68: =P68+CN68+R68+AN68+CR68+AP68+DB68+BB68+BD68+CP68+BH68+CT68+BJ68+CZ68+CL68+DD68+DF68 -> 886 | D68: =O68+BA68+CO68+BG68+BI68+DC68 -> 5.5178471e+08 | E68: =P68+BB68+CP68+BH68+BJ68 -> 11 | F68: =CM68+CS68 -> 67198045 | G68: =CN68+CT68 -> 2 | H68: =Q68+CY68 -> 35575046 | I68: =R68+CZ68 -> 2 | J68: =AM68+CQ68+AO68+DA68 -> 27558266 | K68: =AN68+CR68+AP68+DB68 -> 869 | L68: =BC68+CK68+DE68 -> 63847448 | M68: =BD68+CL68+DF68 -> 2 | O68: =SILVX!B75 -> 3.9804281e+08 | P68: =SILVX!G75 -> 1 | Q68: =SGLIX!B20 -> 19437260 | R68: =SGLIX!G20 -> 1 | AM68: =Schwab!S63 -> 16027519 | AN68: =Schwab!Q63 -> 689 | AO68: =Fidelity!P68 -> 10490798 | AP68: =Fidelity!O68 -> 128 | BA68: ='TFA - Folio'!H73 -> 24529100 | BB68: ='TFA - Folio'!I68 -> 1 | BC68: ='TFA - Folio'!K73 -> 50497918 | BD68: ='TFA - Folio'!N73 -> 1 | BG68: =UNC!B31 -> 1.2219755e+08 | BH68: =UNC!C31 -> 1 | BI68: ='Schwab LC'!D28 -> 2570847.5 | BJ68: ='Schwab LC'!E28 -> 2 | CK68: ='Holiday Oil'!G6 -> 13349530 | CL68: ='Holiday Oil'!H6 -> 1 | CM68: =SCLVX!B29 -> 28902763 | CN68: =SCLVX!G29 -> 1 | CO68: =Stifel!B42 -> 4444404.6 | CP68: =Stifel!K42 -> 6 | CQ68: =TDA!O58 -> 930694.05 | CR68: =TDA!N58 -> 51 | CS68: =UNC!D31 -> 38295282 | CT68: =UNC!E31 -> 1 | CY68: =Cline!B14 -> 16137786 | CZ68: =Cline!C14 -> 1 | DA68: =Prudential!E42 -> 109255.21 | DB68: =Prudential!D42 -> 1
A69: 43312 | B69: =O69+CM69+Q69+AM69+CQ69+AO69+DA69+BA69+BC69+CO69+BG69+CS69+BI69+CY69+CK69+CI69+DC69+DE69 -> 7.7870983e+08 | C69: =P69+CN69+R69+AN69+CR69+AP69+DB69+BB69+BD69+CP69+BH69+CT69+BJ69+CZ69+CL69+DD69+DF69 -> 861 | D69: =O69+BA69+CO69+BG69+BI69+DC69 -> 5.7308787e+08 | E69: =P69+BB69+CP69+BH69+BJ69 -> 11 | F69: =CM69+CS69 -> 70458850 | G69: =CN69+CT69 -> 2 | H69: =Q69+CY69+CI69 -> 42725519 | I69: =R69+CZ69+CJ69 -> 3 | J69: =AM69+CQ69+AO69+DA69 -> 28496389 | K69: =AN69+CR69+AP69+DB69 -> 844 | L69: =BC69+CK69+DE69 -> 63941209 | M69: =BD69+CL69+DF69 -> 2 | O69: =SILVX!B76 -> 4.1417588e+08 | P69: =SILVX!G76 -> 1 | Q69: =SGLIX!B21 -> 19910036 | R69: =SGLIX!G21 -> 1 | AM69: =Schwab!S64 -> 16503950 | AN69: =Schwab!Q64 -> 663 | AO69: =Fidelity!P69 -> 10912035 | AP69: =Fidelity!O69 -> 129 | BA69: ='TFA - Folio'!H74 -> 25028910 | BB69: ='TFA - Folio'!I69 -> 1 | BC69: ='TFA - Folio'!K74 -> 50566902 | BD69: ='TFA - Folio'!N74 -> 1 | BG69: =UNC!B32 -> 1.2661289e+08 | BH69: =UNC!C32 -> 1 | BI69: ='Schwab LC'!D29 -> 2662789.1 | BJ69: ='Schwab LC'!E29 -> 2 | CI69: ='NC State'!B2 -> 6091935 | CJ69: ='NC State'!C2 -> 1 | CK69: ='Holiday Oil'!G7 -> 13374307 | CL69: ='Holiday Oil'!H7 -> 1 | CM69: =SCLVX!B30 -> 31246169 | CN69: =SCLVX!G30 -> 1 | CO69: =Stifel!B43 -> 4607406.7 | CP69: =Stifel!K43 -> 6 | CQ69: =TDA!O59 -> 970212.1 | CR69: =TDA!N59 -> 51 | CS69: =UNC!D32 -> 39212680 | CT69: =UNC!E32 -> 1 | CY69: =Cline!B15 -> 16723548 | CZ69: =Cline!C15 -> 1 | DA69: =Prudential!E43 -> 110192.13 | DB69: =Prudential!D43 -> 1
A70: 43343 | B70: =O70+CM70+Q70+AM70+CQ70+AO70+DA70+BA70+BC70+CO70+BG70+CS70+BI70+CY70+CK70+CI70+DC70+DE70 -> 8.2615281e+08 | C70: =P70+CN70+R70+AN70+CR70+AP70+DB70+BB70+BD70+CP70+BH70+CT70+BJ70+CZ70+CL70+DD70+DF70 -> 871 | D70: =O70+BA70+CO70+BG70+BI70+DC70 -> 6.1291045e+08 | E70: =P70+BB70+CP70+BH70+BJ70 -> 11 | F70: =CM70+CS70 -> 76696654 | G70: =CN70+CT70 -> 2 | H70: =Q70+CY70+CI70 -> 42716166 | I70: =R70+CZ70+CJ70 -> 3 | J70: =AM70+CQ70+AO70+DA70 -> 29189132 | K70: =AN70+CR70+AP70+DB70 -> 854 | L70: =BC70+CK70+DE70 -> 64640405 | M70: =BD70+CL70+DF70 -> 2 | O70: =SILVX!B77 -> 4.4738347e+08 | P70: =SILVX!G77 -> 1 | Q70: =SGLIX!B22 -> 19561940 | R70: =SGLIX!G22 -> 1 | AM70: =Schwab!S65 -> 17023906 | AN70: =Schwab!Q65 -> 670 | AO70: =Fidelity!P70 -> 11272849 | AP70: =Fidelity!O70 -> 130 | BA70: ='TFA - Folio'!H75 -> 25908196 | BB70: ='TFA - Folio'!I70 -> 1 | BC70: ='TFA - Folio'!K75 -> 51290704 | BD70: ='TFA - Folio'!N75 -> 1 | BG70: =UNC!B33 -> 1.3203177e+08 | BH70: =UNC!C33 -> 1 | BI70: ='Schwab LC'!D30 -> 2770271.1 | BJ70: ='Schwab LC'!E30 -> 2 | CI70: ='NC State'!B3 -> 6177187.1 | CJ70: ='NC State'!C3 -> 1 | CK70: ='Holiday Oil'!G8 -> 13349701 | CL70: ='Holiday Oil'!H8 -> 1 | CM70: =SCLVX!B31 -> 35168761 | CN70: =SCLVX!G31 -> 1 | CO70: =Stifel!B44 -> 4816744.7 | CP70: =Stifel!K44 -> 6 | CQ70: =TDA!O60 -> 892376.21 | CR70: =TDA!N60 -> 54 | CS70: =UNC!D33 -> 41527893 | CT70: =UNC!E33 -> 1 | CY70: =Cline!B16 -> 16977040 | CZ70: =Cline!C16 -> 1
A71: 43373 | B71: =O71+CM71+Q71+AM71+CQ71+AO71+DA71+BA71+BC71+CO71+BG71+CS71+BI71+CY71+CK71+CI71+DC71+DE71 -> 8.3460999e+08 | C71: =P71+CN71+R71+AN71+CR71+AP71+DB71+BB71+BD71+CP71+BH71+CT71+BJ71+CZ71+CL71+DD71+DF71 -> 879 | D71: =O71+BA71+CO71+BG71+BI71+DC71 -> 6.2368152e+08 | E71: =P71+BB71+CP71+BH71+BJ71 -> 11 | F71: =CM71+CS71 -> 76678652 | G71: =CN71+CT71 -> 2 | H71: =Q71+CY71+CI71 -> 42960020 | I71: =R71+CZ71+CJ71 -> 3 | J71: =AM71+CQ71+AO71+DA71 -> 26547080 | K71: =AN71+CR71+AP71+DB71 -> 862 | L71: =BC71+CK71+DE71 -> 64742723 | M71: =BD71+CL71+DF71 -> 2 | O71: =SILVX!B78 -> 4.5870091e+08 | P71: =SILVX!G78 -> 1 | Q71: =SGLIX!B23 -> 19452300 | R71: =SGLIX!G23 -> 1 | AM71: =Schwab!S66 -> 16942579 | AN71: =Schwab!Q66 -> 676 | AO71: =Fidelity!P71 -> 8702890.3 | AP71: =Fidelity!O71 -> 134 | BA71: ='TFA - Folio'!H76 -> 25114299 | BB71: ='TFA - Folio'!I71 -> 1 | BC71: ='TFA - Folio'!K76 -> 51416689 | BD71: ='TFA - Folio'!N76 -> 1 | BG71: =UNC!B34 -> 1.3248346e+08 | BH71: =UNC!C34 -> 1 | BI71: ='Schwab LC'!D31 -> 2780096.1 | BJ71: ='Schwab LC'!E31 -> 2 | CI71: ='NC State'!B4 -> 6271226.3 | CJ71: ='NC State'!C4 -> 1 | CK71: ='Holiday Oil'!G9 -> 13326034 | CL71: ='Holiday Oil'!H9 -> 1 | CM71: =SCLVX!B32 -> 36129215 | CN71: =SCLVX!G32 -> 1 | CO71: =Stifel!B45 -> 4602753.1 | CP71: =Stifel!K45 -> 6 | CQ71: =TDA!O61 -> 901610.92 | CR71: =TDA!N61 -> 52 | CS71: =UNC!D34 -> 40549437 | CT71: =UNC!E34 -> 1 | CY71: =Cline!B17 -> 17236493 | CZ71: =Cline!C17 -> 1
A72: 43404 | B72: =O72+CM72+Q72+AM72+CQ72+AO72+DA72+BA72+BC72+CO72+BG72+CS72+BI72+CY72+CK72+CI72+DC72+DE72 -> 7.8198793e+08 | C72: =P72+CN72+R72+AN72+CR72+AP72+DB72+BB72+BD72+CP72+BH72+CT72+BJ72+CZ72+CL72+DD72+DF72 -> 899 | D72: =O72+BA72+CO72+BG72+BI72+DC72 -> 5.7977648e+08 | E72: =P72+BB72+CP72+BH72+BJ72 -> 11 | F72: =CM72+CS72 -> 69899978 | G72: =CN72+CT72 -> 2 | H72: =Q72+CY72+CI72 -> 39947098 | I72: =R72+CZ72+CJ72 -> 3 | J72: =AM72+CQ72+AO72+DA72 -> 29343536 | K72: =AN72+CR72+AP72+DB72 -> 882 | L72: =BC72+CK72+DE72 -> 63020839 | M72: =BD72+CL72+DF72 -> 2 | O72: =SILVX!B79 -> 4.2727047e+08 | P72: =SILVX!G79 -> 1 | Q72: =SGLIX!B24 -> 18322540 | R72: =SGLIX!G24 -> 1 | AM72: =Schwab!S67 -> 19465955 | AN72: =Schwab!Q67 -> 686 | AO72: =Fidelity!P72 -> 8844307 | AP72: =Fidelity!O72 -> 138 | BA72: ='TFA - Folio'!H77 -> 22916349 | BB72: ='TFA - Folio'!I72 -> 1 | BC72: ='TFA - Folio'!K77 -> 49765663 | BD72: ='TFA - Folio'!N77 -> 1 | BG72: =UNC!B35 -> 1.2268927e+08 | BH72: =UNC!C35 -> 1 | BI72: ='Schwab LC'!D32 -> 2639005.3 | BJ72: ='Schwab LC'!E32 -> 2 | CI72: ='NC State'!B5 -> 5916871.4 | CJ72: ='NC State'!C5 -> 1 | CK72: ='Holiday Oil'!G10 -> 13255176 | CL72: ='Holiday Oil'!H10 -> 1 | CM72: =SCLVX!B33 -> 33824711 | CN72: =SCLVX!G33 -> 1 | CO72: =Stifel!B46 -> 4261385.4 | CP72: =Stifel!K46 -> 6 | CQ72: =TDA!O62 -> 1033274.3 | CR72: =TDA!N62 -> 58 | CS72: =UNC!D35 -> 36075267 | CT72: =UNC!E35 -> 1 | CY72: =Cline!B18 -> 15707687 | CZ72: =Cline!C18 -> 1
A73: 43434 | B73: =O73+CM73+Q73+AM73+CQ73+AO73+DA73+BA73+BC73+CO73+BG73+CS73+BI73+CY73+CK73+CI73+DC73+DE73 -> 8.0683793e+08 | C73: =P73+CN73+R73+AN73+CR73+AP73+DB73+BB73+BD73+CP73+BH73+CT73+BJ73+CZ73+CL73+DD73+DF73 -> 899 | D73: =O73+BA73+CO73+BG73+BI73+DC73 -> 6.0191209e+08 | E73: =P73+BB73+CP73+BH73+BJ73 -> 11 | F73: =CM73+CS73 -> 70800513 | G73: =CN73+CT73 -> 2 | H73: =Q73+CY73+CI73 -> 41465149 | I73: =R73+CZ73+CJ73 -> 3 | J73: =AM73+CQ73+AO73+DA73 -> 29947291 | K73: =AN73+CR73+AP73+DB73 -> 882 | L73: =BC73+CK73+DE73 -> 62712884 | M73: =BD73+CL73+DF73 -> 2 | O73: =SILVX!B80 -> 4.4745957e+08 | P73: =SILVX!G80 -> 1 | Q73: =SGLIX!B25 -> 19092665 | R73: =SGLIX!G25 -> 1 | AM73: =Schwab!S68 -> 19413755 | AN73: =Schwab!Q68 -> 684 | AO73: =Fidelity!P73 -> 9497605.8 | AP73: =Fidelity!O73 -> 139 | BA73: ='TFA - Folio'!H78 -> 22582915 | BB73: ='TFA - Folio'!I73 -> 1 | BC73: ='TFA - Folio'!K78 -> 49385646 | BD73: ='TFA - Folio'!N78 -> 1 | BG73: =UNC!B36 -> 1.2486479e+08 | BH73: =UNC!C36 -> 1 | BI73: ='Schwab LC'!D33 -> 2676554.6 | BJ73: ='Schwab LC'!E33 -> 2 | CI73: ='NC State'!B6 -> 6143310.2 | CJ73: ='NC State'!C6 -> 1 | CK73: ='Holiday Oil'!G11 -> 13327238 | CL73: ='Holiday Oil'!H11 -> 1 | CM73: =SCLVX!B34 -> 34434962 | CN73: =SCLVX!G34 -> 1 | CO73: =Stifel!B47 -> 4328260.7 | CP73: =Stifel!K47 -> 6 | CQ73: =TDA!O63 -> 1035930.4 | CR73: =TDA!N63 -> 59 | CS73: =UNC!D36 -> 36365551 | CT73: =UNC!E36 -> 1 | CY73: =Cline!B19 -> 16229173 | CZ73: =Cline!C19 -> 1
A74: 43465 | B74: =O74+CM74+Q74+AM74+CQ74+AO74+DA74+BA74+BC74+CO74+BG74+CS74+BI74+CY74+CK74+CI74+DC74+DE74 -> 7.3628402e+08 | C74: =P74+CN74+R74+AN74+CR74+AP74+DB74+BB74+BD74+CP74+BH74+CT74+BJ74+CZ74+CL74+DD74+DF74 -> 916 | D74: =O74+BA74+CO74+BG74+BI74+DC74 -> 5.3807847e+08 | E74: =P74+BB74+CP74+BH74+BJ74 -> 11 | F74: =CM74+CS74 -> 63315571 | G74: =CN74+CT74 -> 2 | H74: =Q74+CY74+CI74 -> 38482520 | I74: =R74+CZ74+CJ74 -> 3 | J74: =AM74+CQ74+AO74+DA74 -> 30637984 | K74: =AN74+CR74+AP74+DB74 -> 899 | L74: =BC74+CK74+DE74 -> 65769476 | M74: =BD74+CL74+DF74 -> 2 | O74: =SILVX!B81 -> 4.0023683e+08 | P74: =SILVX!G81 -> 1 | Q74: =SGLIX!B26 -> 17632438 | R74: =SGLIX!G26 -> 1 | AM74: =Schwab!S69 -> 20301285 | AN74: =Schwab!Q69 -> 694 | AO74: =Fidelity!P74 -> 9218402.3 | AP74: =Fidelity!O74 -> 146 | BA74: ='TFA - Folio'!H79 -> 16328604 | BB74: ='TFA - Folio'!I74 -> 1 | BC74: ='TFA - Folio'!K79 -> 52274540 | BD74: ='TFA - Folio'!N79 -> 1 | BG74: =UNC!B37 -> 1.1504982e+08 | BH74: =UNC!C37 -> 1 | BI74: ='Schwab LC'!D34 -> 2465445.8 | BJ74: ='Schwab LC'!E34 -> 2 | CI74: ='NC State'!B7 -> 5726375.6 | CJ74: ='NC State'!C7 -> 1 | CK74: ='Holiday Oil'!G12 -> 13494936 | CL74: ='Holiday Oil'!H12 -> 1 | CM74: =SCLVX!B35 -> 30939369 | CN74: =SCLVX!G35 -> 1 | CO74: =Stifel!B48 -> 3997769.3 | CP74: =Stifel!K48 -> 6 | CQ74: =TDA!O64 -> 1118296.5 | CR74: =TDA!N64 -> 59 | CS74: =UNC!D37 -> 32376202 | CT74: =UNC!E37 -> 1 | CY74: =Cline!B20 -> 15123707 | CZ74: =Cline!C20 -> 1
A75: 43496 | B75: =O75+CM75+Q75+AM75+CQ75+AO75+DA75+BA75+BC75+CO75+BG75+CS75+BI75+CY75+CK75+CI75+DC75+DE75+CU75 -> 7.948129e+08 | C75: =P75+CN75+R75+AN75+CR75+AP75+DB75+BB75+BD75+CP75+BH75+CT75+BJ75+CZ75+CL75+DD75+DF75+CJ75+CV75 -> 918 | D75: =O75+BA75+CO75+BG75+BI75+DC75+CU75 -> 5.8756997e+08 | E75: =P75+BB75+CP75+BH75+BJ75+CV75 -> 12 | F75: =CM75+CS75 -> 68047979 | G75: =CN75+CT75 -> 2 | H75: =Q75+CY75+CI75 -> 40462986 | I75: =R75+CZ75+CJ75 -> 3 | J75: =AM75+CQ75+AO75+DA75 -> 30602017 | K75: =AN75+CR75+AP75+DB75 -> 899 | L75: =BC75+CK75+DE75 -> 68129953 | M75: =BD75+CL75+DF75 -> 2 | O75: =SILVX!B82 -> 4.2858197e+08 | P75: =SILVX!G82 -> 1 | Q75: =SGLIX!B27 -> 18474074 | R75: =SGLIX!G27 -> 1 | AM75: =Schwab!S70 -> 19832555 | AN75: =Schwab!Q70 -> 694 | AO75: =Fidelity!P75 -> 9401176.1 | AP75: =Fidelity!O75 -> 146 | BA75: ='TFA - Folio'!H80 -> 17428387 | BB75: ='TFA - Folio'!I75 -> 1 | BC75: ='TFA - Folio'!K80 -> 54496279 | BD75: ='TFA - Folio'!N80 -> 1 | BG75: =UNC!B38 -> 1.2342222e+08 | BH75: =UNC!C38 -> 1 | BI75: ='Schwab LC'!D35 -> 2639242.8 | BJ75: ='Schwab LC'!E35 -> 2 | CI75: ='NC State'!B8 -> 6042987.5 | CJ75: ='NC State'!C8 -> 1 | CK75: ='Holiday Oil'!G13 -> 13633674 | CL75: ='Holiday Oil'!H13 -> 1 | CM75: =SCLVX!B36 -> 32806928 | CN75: =SCLVX!G36 -> 1 | CO75: =Stifel!B49 -> 4281434.5 | CP75: =Stifel!K49 -> 6 | CQ75: =TDA!O65 -> 1368285.9 | CR75: =TDA!N65 -> 59 | CS75: =UNC!D38 -> 35241051 | CT75: =UNC!E38 -> 1 | CU75: =Asbestos!B2 -> 11216717 | CV75: =Asbestos!C2 -> 1 | CY75: =Cline!B21 -> 15945924 | CZ75: =Cline!C21 -> 1
A76: 43524 | B76: =O76+CM76+Q76+AM76+CQ76+AO76+DA76+BA76+BC76+CO76+BG76+CS76+BI76+CY76+CK76+CI76+DC76+DE76+CU76 -> 8.2997684e+08 | C76: =P76+CN76+R76+AN76+CR76+AP76+DB76+BB76+BD76+CP76+BH76+CT76+BJ76+CZ76+CL76+DD76+DF76+CJ76+CV76 -> 938 | D76: =O76+BA76+CO76+BG76+BI76+DC76+CU76 -> 6.1503757e+08 | E76: =P76+BB76+CP76+BH76+BJ76+CV76 -> 12 | F76: =CM76+CS76 -> 71557286 | G76: =CN76+CT76 -> 2 | H76: =Q76+CY76+CI76 -> 41958294 | I76: =R76+CZ76+CJ76 -> 3 | J76: =AM76+CQ76+AO76+DA76 -> 31328996 | K76: =AN76+CR76+AP76+DB76 -> 919 | L76: =BC76+CK76+DE76 -> 70094699 | M76: =BD76+CL76+DF76 -> 2 | O76: =SILVX!B83 -> 4.4886731e+08 | P76: =SILVX!G83 -> 1 | Q76: =SGLIX!B28 -> 19109488 | R76: =SGLIX!G28 -> 1 | AM76: =Schwab!S71 -> 20480227 | AN76: =Schwab!Q71 -> 712 | AO76: =Fidelity!P76 -> 9816964.5 | AP76: =Fidelity!O76 -> 148 | BA76: ='TFA - Folio'!H81 -> 18756502 | BB76: ='TFA - Folio'!I76 -> 1 | BC76: ='TFA - Folio'!K81 -> 56468464 | BD76: ='TFA - Folio'!N81 -> 1 | BG76: =UNC!B39 -> 1.2858603e+08 | BH76: =UNC!C39 -> 1 | BI76: ='Schwab LC'!D36 -> 2748011.8 | BJ76: ='Schwab LC'!E36 -> 2 | CI76: ='NC State'!B9 -> 6280615.7 | CJ76: ='NC State'!C9 -> 1 | CK76: ='Holiday Oil'!G14 -> 13626235 | CL76: ='Holiday Oil'!H14 -> 1 | CM76: =SCLVX!B37 -> 34742655 | CN76: =SCLVX!G37 -> 1 | CO76: =Stifel!B50 -> 4464057.3 | CP76: =Stifel!K50 -> 6 | CQ76: =TDA!O66 -> 1031804.5 | CR76: =TDA!N66 -> 59 | CS76: =UNC!D39 -> 36814631 | CT76: =UNC!E39 -> 1 | CU76: =Asbestos!B3 -> 11615657 | CV76: =Asbestos!C3 -> 1 | CY76: =Cline!B22 -> 16568190 | CZ76: =Cline!C22 -> 1
A77: 43555 | B77: =O77+CM77+Q77+AM77+CQ77+AO77+DA77+BA77+BC77+CO77+BG77+CS77+BI77+CY77+CK77+CI77+DC77+DE77+CU77 -> 8.4818159e+08 | C77: =P77+CN77+R77+AN77+CR77+AP77+DB77+BB77+BD77+CP77+BH77+CT77+BJ77+CZ77+CL77+DD77+DF77+CJ77+CV77 -> 954 | D77: =O77+BA77+CO77+BG77+BI77+DC77+CU77 -> 6.2930176e+08 | E77: =P77+BB77+CP77+BH77+BJ77+CV77 -> 12 | F77: =CM77+CS77 -> 71520396 | G77: =CN77+CT77 -> 2 | H77: =Q77+CY77+CI77 -> 43065755 | I77: =R77+CZ77+CJ77 -> 3 | J77: =AM77+CQ77+AO77+DA77 -> 32526143 | K77: =AN77+CR77+AP77+DB77 -> 935 | L77: =BC77+CK77+DE77 -> 71767536 | M77: =BD77+CL77+DF77 -> 2 | O77: =SILVX!B84 -> 4.6012176e+08 | P77: =SILVX!G84 -> 1 | Q77: =SGLIX!B29 -> 19789283 | R77: =SGLIX!G29 -> 1 | AM77: =Schwab!S72 -> 21379858 | AN77: =Schwab!Q72 -> 726 | AO77: =Fidelity!P77 -> 10090747 | AP77: =Fidelity!O77 -> 150 | BA77: ='TFA - Folio'!H82 -> 18775727 | BB77: ='TFA - Folio'!I77 -> 1 | BC77: ='TFA - Folio'!K82 -> 57966836 | BD77: ='TFA - Folio'!N82 -> 1 | BG77: =UNC!B40 -> 1.3077917e+08 | BH77: =UNC!C40 -> 1 | BI77: ='Schwab LC'!D37 -> 3304392.5 | BJ77: ='Schwab LC'!E37 -> 2 | CI77: ='NC State'!B10 -> 6398349 | CJ77: ='NC State'!C10 -> 1 | CK77: ='Holiday Oil'!G15 -> 13800700 | CL77: ='Holiday Oil'!H15 -> 1 | CM77: =SCLVX!B38 -> 35454493 | CN77: =SCLVX!G38 -> 1 | CO77: =Stifel!B51 -> 4542748.4 | CP77: =Stifel!K51 -> 6 | CQ77: =TDA!O67 -> 1055537.9 | CR77: =TDA!N67 -> 59 | CS77: =UNC!D40 -> 36065904 | CT77: =UNC!E40 -> 1 | CU77: =Asbestos!B4 -> 11777963 | CV77: =Asbestos!C4 -> 1 | CY77: =Cline!B23 -> 16878123 | CZ77: =Cline!C23 -> 1
A78: 43585 | B78: =O78+CM78+Q78+AM78+CQ78+AO78+DA78+BA78+BC78+CO78+BG78+CS78+BI78+CY78+CK78+CI78+DC78+DE78+CU78 -> 8.7973946e+08 | C78: =P78+CN78+R78+AN78+CR78+AP78+DB78+BB78+BD78+CP78+BH78+CT78+BJ78+CZ78+CL78+DD78+DF78+CJ78+CV78 -> 970 | D78: =O78+BA78+CO78+BG78+BI78+DC78+CU78 -> 6.5707066e+08 | E78: =P78+BB78+CP78+BH78+BJ78+CV78 -> 12 | F78: =CM78+CS78 -> 74787741 | G78: =CN78+CT78 -> 2 | H78: =Q78+CY78+CI78 -> 44369261 | I78: =R78+CZ78+CJ78 -> 3 | J78: =AM78+CQ78+AO78+DA78 -> 32506849 | K78: =AN78+CR78+AP78+DB78 -> 951 | L78: =BC78+CK78+DE78 -> 71004949 | M78: =BD78+CL78+DF78 -> 2 | O78: =SILVX!B85 -> 4.8251346e+08 | P78: =SILVX!G85 -> 1 | Q78: =SGLIX!B30 -> 20423188 | R78: =SGLIX!G30 -> 1 | AM78: =Schwab!S73 -> 21008127 | AN78: =Schwab!Q73 -> 738 | AO78: =Fidelity!P78 -> 10625311 | AP78: =Fidelity!O78 -> 156 | BA78: ='TFA - Folio'!H83 -> 18782085 | BB78: ='TFA - Folio'!I78 -> 1 | BC78: ='TFA - Folio'!K83 -> 59212129 | BD78: ='TFA - Folio'!N83 -> 1 | BG78: =UNC!B41 -> 1.3550443e+08 | BH78: =UNC!C41 -> 1 | BI78: ='Schwab LC'!D38 -> 3411836 | BJ78: ='Schwab LC'!E38 -> 2 | CI78: ='NC State'!B11 -> 6586840.1 | CJ78: ='NC State'!C11 -> 1 | CK78: ='Holiday Oil'!G16 -> 11792820 | CL78: ='Holiday Oil'!H16 -> 1 | CM78: =SCLVX!B39 -> 37574293 | CN78: =SCLVX!G39 -> 1 | CO78: =Stifel!B52 -> 4701545.4 | CP78: =Stifel!K52 -> 6 | CQ78: =TDA!O68 -> 873410.62 | CR78: =TDA!N68 -> 57 | CS78: =UNC!D41 -> 37213448 | CT78: =UNC!E41 -> 1 | CU78: =Asbestos!B5 -> 12157306 | CV78: =Asbestos!C5 -> 1 | CY78: =Cline!B24 -> 17359233 | CZ78: =Cline!C24 -> 1
A79: 43616 | B79: =O79+CM79+Q79+AM79+CQ79+AO79+DA79+BA79+BC79+CO79+BG79+CS79+BI79+CY79+CK79+CI79+DC79+DE79+CU79 -> 8.4684097e+08 | C79: =P79+CN79+R79+AN79+CR79+AP79+DB79+BB79+BD79+CP79+BH79+CT79+BJ79+CZ79+CL79+DD79+DF79+CJ79+CV79 -> 981 | D79: =O79+BA79+CO79+BG79+BI79+DC79+CU79 -> 6.2497379e+08 | E79: =P79+BB79+CP79+BH79+BJ79+CV79 -> 12 | F79: =CM79+CS79 -> 71787914 | G79: =CN79+CT79 -> 2 | H79: =Q79+CY79+CI79 -> 39250681 | I79: =R79+CZ79+CJ79 -> 3 | J79: =AM79+CQ79+AO79+DA79 -> 39102334 | K79: =AN79+CR79+AP79+DB79 -> 962 | L79: =BC79+CK79+DE79 -> 71726251 | M79: =BD79+CL79+DF79 -> 2 | O79: =SILVX!B86 -> 4.6109984e+08 | P79: =SILVX!G86 -> 1 | Q79: =SGLIX!B31 -> 20700371 | R79: =SGLIX!G31 -> 1 | AM79: =Schwab!S74 -> 22165337 | AN79: =Schwab!Q74 -> 749 | AO79: =Fidelity!P79 -> 15877116 | AP79: =Fidelity!O79 -> 156 | BA79: ='TFA - Folio'!H84 -> 16091225 | BB79: ='TFA - Folio'!I79 -> 1 | BC79: ='TFA - Folio'!K84 -> 60278849 | BD79: ='TFA - Folio'!N84 -> 1 | BG79: =UNC!B42 -> 1.2889435e+08 | BH79: =UNC!C42 -> 1 | BI79: ='Schwab LC'!D39 -> 3166566.1 | BJ79: ='Schwab LC'!E39 -> 2 | CI79: ='NC State'!B12 -> 6453582.1 | CJ79: ='NC State'!C12 -> 1 | CK79: ='Holiday Oil'!G17 -> 11447401 | CL79: ='Holiday Oil'!H17 -> 1 | CM79: =SCLVX!B40 -> 36739948 | CN79: =SCLVX!G40 -> 1 | CO79: =Stifel!B53 -> 4234424.8 | CP79: =Stifel!K53 -> 6 | CQ79: =TDA!O69 -> 1059880.6 | CR79: =TDA!N69 -> 57 | CS79: =UNC!D42 -> 35047967 | CT79: =UNC!E42 -> 1 | CU79: =Asbestos!B6 -> 11487379 | CV79: =Asbestos!C6 -> 1 | CY79: =Cline!B25 -> 12096729 | CZ79: =Cline!C25 -> 1
A80: 43646 | B80: =O80+CM80+Q80+AM80+CQ80+AO80+DA80+BA80+BC80+CO80+BG80+CS80+BI80+CY80+CK80+CI80+DC80+DE80+CU80 -> 8.8782445e+08 | C80: =P80+CN80+R80+AN80+CR80+AP80+DB80+BB80+BD80+CP80+BH80+CT80+BJ80+CZ80+CL80+DD80+DF80+CJ80+CV80 -> 954 | D80: =O80+BA80+CO80+BG80+BI80+DC80+CU80 -> 6.5936531e+08 | E80: =P80+BB80+CP80+BH80+BJ80+CV80 -> 12 | F80: =CM80+CS80 -> 75422345 | G80: =CN80+CT80 -> 2 | H80: =Q80+CY80+CI80 -> 41158271 | I80: =R80+CZ80+CJ80 -> 3 | J80: =AM80+CQ80+AO80+DA80 -> 36998885 | K80: =AN80+CR80+AP80+DB80 -> 935 | L80: =BC80+CK80+DE80 -> 74879633 | M80: =BD80+CL80+DF80 -> 2 | O80: =SILVX!B87 -> 4.8631875e+08 | P80: =SILVX!G87 -> 1 | Q80: =SGLIX!B32 -> 21749593 | R80: =SGLIX!G32 -> 1 | AM80: =Schwab!S75 -> 21253276 | AN80: =Schwab!Q75 -> 729 | AO80: =Fidelity!P80 -> 14727157 | AP80: =Fidelity!O80 -> 152 | BA80: ='TFA - Folio'!H85 -> 16725712 | BB80: ='TFA - Folio'!I80 -> 1 | BC80: ='TFA - Folio'!K85 -> 63261335 | BD80: ='TFA - Folio'!N85 -> 1 | BG80: =UNC!B43 -> 1.3635741e+08 | BH80: =UNC!C43 -> 1 | BI80: ='Schwab LC'!D40 -> 3347644.1 | BJ80: ='Schwab LC'!E40 -> 2 | CI80: ='NC State'!B13 -> 6750065.8 | CJ80: ='NC State'!C13 -> 1 | CK80: ='Holiday Oil'!G18 -> 11618299 | CL80: ='Holiday Oil'!H18 -> 1 | CM80: =SCLVX!B41 -> 38576422 | CN80: =SCLVX!G41 -> 1 | CO80: =Stifel!B54 -> 4480957.2 | CP80: =Stifel!K54 -> 6 | CQ80: =TDA!O70 -> 1018452.6 | CR80: =TDA!N70 -> 54 | CS80: =UNC!D43 -> 36845923 | CT80: =UNC!E43 -> 1 | CU80: =Asbestos!B7 -> 12134834 | CV80: =Asbestos!C7 -> 1 | CY80: =Cline!B26 -> 12658612 | CZ80: =Cline!C26 -> 1
A81: 43677 | B81: =O81+CM81+Q81+AM81+CQ81+AO81+DA81+BA81+BC81+CO81+BG81+CS81+BI81+CY81+CK81+CI81+DC81+DE81+CU81 -> 9.3261564e+08 | C81: =P81+CN81+R81+AN81+CR81+AP81+DB81+BB81+BD81+CP81+BH81+CT81+BJ81+CZ81+CL81+DD81+DF81+CJ81+CV81 -> 960 | D81: =O81+BA81+CO81+BG81+BI81+DC81+CU81 -> 6.7661281e+08 | E81: =P81+BB81+CP81+BH81+BJ81+CV81 -> 12 | F81: =CM81+CS81 -> 76825470 | G81: =CN81+CT81 -> 2 | H81: =Q81+CY81+CI81 -> 40943987 | I81: =R81+CZ81+CJ81 -> 3 | J81: =AM81+CQ81+AO81+DA81 -> 60616454 | K81: =AN81+CR81+AP81+DB81 -> 941 | L81: =BC81+CK81+DE81 -> 77616923 | M81: =BD81+CL81+DF81 -> 2 | O81: =SILVX!B88 -> 5.0017524e+08 | P81: =SILVX!G88 -> 1 | Q81: =SGLIX!B33 -> 21542735 | R81: =SGLIX!G33 -> 1 | AM81: =Schwab!S76 -> 21073180 | AN81: =Schwab!Q76 -> 735 | AO81: =Fidelity!P81 -> 38682631 | AP81: =Fidelity!O81 -> 154 | BA81: ='TFA - Folio'!H86 -> 16918633 | BB81: ='TFA - Folio'!I81 -> 1 | BC81: ='TFA - Folio'!K86 -> 65965401 | BD81: ='TFA - Folio'!N86 -> 1 | BG81: =UNC!B44 -> 1.3918042e+08 | BH81: =UNC!C44 -> 1 | BI81: ='Schwab LC'!D41 -> 3407991.5 | BJ81: ='Schwab LC'!E41 -> 2 | CI81: ='NC State'!B14 -> 6744852.6 | CJ81: ='NC State'!C14 -> 1 | CK81: ='Holiday Oil'!G19 -> 11651522 | CL81: ='Holiday Oil'!H19 -> 1 | CM81: =SCLVX!B42 -> 39239673 | CN81: =SCLVX!G42 -> 1 | CO81: =Stifel!B55 -> 4571394.4 | CP81: =Stifel!K55 -> 6 | CQ81: =TDA!O71 -> 860642.69 | CR81: =TDA!N71 -> 52 | CS81: =UNC!D44 -> 37585797 | CT81: =UNC!E44 -> 1 | CU81: =Asbestos!B8 -> 12359127 | CV81: =Asbestos!C8 -> 1 | CY81: =Cline!B27 -> 12656399 | CZ81: =Cline!C27 -> 1
A82: 43708 | B82: =O82+CM82+Q82+AM82+CQ82+AO82+DA82+BA82+BC82+CO82+BG82+CS82+BI82+CY82+CK82+CI82+DC82+DE82+CU82 -> 9.4809884e+08 | C82: =P82+CN82+R82+AN82+CR82+AP82+DB82+BB82+BD82+CP82+BH82+CT82+BJ82+CZ82+CL82+DD82+DF82+CJ82+CV82 -> 980 | D82: =O82+BA82+CO82+BG82+BI82+DC82+CU82 -> 6.8977677e+08 | E82: =P82+BB82+CP82+BH82+BJ82+CV82 -> 12 | F82: =CM82+CS82 -> 73694319 | G82: =CN82+CT82 -> 2 | H82: =Q82+CY82+CI82 -> 40943561 | I82: =R82+CZ82+CJ82 -> 3 | J82: =AM82+CQ82+AO82+DA82 -> 63196958 | K82: =AN82+CR82+AP82+DB82 -> 961 | L82: =BC82+CK82+DE82 -> 80487229 | M82: =BD82+CL82+DF82 -> 2 | O82: =SILVX!B89 -> 5.1179511e+08 | P82: =SILVX!G89 -> 1 | Q82: =SGLIX!B34 -> 21489263 | R82: =SGLIX!G34 -> 1 | AM82: =Schwab!S77 -> 23353200 | AN82: =Schwab!Q77 -> 748 | AO82: =Fidelity!P82 -> 38989742 | AP82: =Fidelity!O82 -> 161 | BA82: ='TFA - Folio'!H87 -> 17063080 | BB82: ='TFA - Folio'!I82 -> 1 | BC82: ='TFA - Folio'!K87 -> 68634146 | BD82: ='TFA - Folio'!N87 -> 1 | BG82: =UNC!B45 -> 1.404366e+08 | BH82: =UNC!C45 -> 1 | BI82: ='Schwab LC'!D42 -> 3431164.7 | BJ82: ='Schwab LC'!E42 -> 2 | CI82: ='NC State'!B15 -> 6763276.3 | CJ82: ='NC State'!C15 -> 1 | CK82: ='Holiday Oil'!G20 -> 11853083 | CL82: ='Holiday Oil'!H20 -> 1 | CM82: =SCLVX!B43 -> 37375529 | CN82: =SCLVX!G43 -> 1 | CO82: =Stifel!B56 -> 4608199.9 | CP82: =Stifel!K56 -> 6 | CQ82: =TDA!O72 -> 854015.77 | CR82: =TDA!N72 -> 52 | CS82: =UNC!D45 -> 36318790 | CT82: =UNC!E45 -> 1 | CU82: =Asbestos!B9 -> 12442617 | CV82: =Asbestos!C9 -> 1 | CY82: =Cline!B28 -> 12691022 | CZ82: =Cline!C28 -> 1
A83: 43738 | B83: =O83+CM83+Q83+AM83+CQ83+AO83+DA83+BA83+BC83+CO83+BG83+CS83+BI83+CY83+CK83+CI83+DC83+DE83+CU83+CW83 -> 1.0422188e+09 | C83: =P83+CN83+R83+AN83+CR83+AP83+DB83+BB83+BD83+CP83+BH83+CT83+BJ83+CZ83+CL83+DD83+DF83+CJ83+CV83+CX83 -> 1049 | D83: =O83+BA83+CO83+BG83+BI83+DC83+CU83 -> 7.0556375e+08 | E83: =P83+BB83+CP83+BH83+BJ83+CV83 -> 12 | F83: =CM83+CS83 -> 78721513 | G83: =CN83+CT83 -> 2 | H83: =Q83+CY83+CI83 -> 40813560 | I83: =R83+CZ83+CJ83 -> 3 | J83: =AM83+CQ83+AO83+DA83 -> 67224584 | K83: =AN83+CR83+AP83+DB83 -> 1027 | L83: =BC83+CK83+DE83+CW83 -> 1.4989536e+08 | M83: =BD83+CL83+DF83+CX83 -> 5 | O83: =SILVX!B90 -> 5.2610905e+08 | P83: =SILVX!G90 -> 1 | Q83: =SGLIX!B35 -> 21045555 | R83: =SGLIX!G35 -> 1 | AM83: =Schwab!S78 -> 25030947 | AN83: =Schwab!Q78 -> 806 | AO83: =Fidelity!P83 -> 41252045 | AP83: =Fidelity!O83 -> 164 | BA83: ='TFA - Folio'!H88 -> 16872098 | BB83: ='TFA - Folio'!I83 -> 1 | BC83: ='TFA - Folio'!K88 -> 68719196 | BD83: ='TFA - Folio'!N88 -> 1 | BG83: =UNC!B46 -> 1.4194447e+08 | BH83: =UNC!C46 -> 1 | BI83: ='Schwab LC'!D43 -> 3464208.5 | BJ83: ='Schwab LC'!E43 -> 2 | CI83: ='NC State'!B16 -> 6872756 | CJ83: ='NC State'!C16 -> 1 | CK83: ='Holiday Oil'!G21 -> 11802342 | CL83: ='Holiday Oil'!H21 -> 1 | CM83: =SCLVX!B44 -> 40887730 | CN83: =SCLVX!G44 -> 1 | CO83: =Stifel!B57 -> 4657985.2 | CP83: =Stifel!K57 -> 6 | CQ83: =TDA!O73 -> 941592.28 | CR83: =TDA!N73 -> 57 | CS83: =UNC!D46 -> 37833783 | CT83: =UNC!E46 -> 1 | CU83: =Asbestos!B10 -> 12515936 | CV83: =Asbestos!C10 -> 1 | CW83: =TUG!H2 -> 69373818 | CX83: =TUG!I2 -> 3 | CY83: =Cline!B29 -> 12895249 | CZ83: =Cline!C29 -> 1
A84: 43769 | B84: =O84+CM84+Q84+AM84+CQ84+AO84+DA84+BA84+BC84+CO84+BG84+CS84+BI84+CY84+CK84+CI84+DC84+DE84+CU84+CW84 -> 1.0645499e+09 | C84: =P84+CN84+R84+AN84+CR84+AP84+DB84+BB84+BD84+CP84+BH84+CT84+BJ84+CZ84+CL84+DD84+DF84+CJ84+CV84+CX84 -> 1093 | D84: =O84+BA84+CO84+BG84+BI84+DC84+CU84 -> 7.141893e+08 | E84: =P84+BB84+CP84+BH84+BJ84+CV84 -> 12 | F84: =CM84+CS84 -> 81135790 | G84: =CN84+CT84 -> 2 | H84: =Q84+CY84+CI84 -> 43829674 | I84: =R84+CZ84+CJ84 -> 3 | J84: =AM84+CQ84+AO84+DA84 -> 69559118 | K84: =AN84+CR84+AP84+DB84 -> 1073 | L84: =BC84+CK84+DE84+CW84 -> 1.5583597e+08 | M84: =BD84+CL84+DF84+CX84 -> 3 | O84: =SILVX!B91 -> 5.3510717e+08 | P84: =SILVX!G91 -> 1 | Q84: =SGLIX!B36 -> 27554963 | R84: =SGLIX!G36 -> 1 | AM84: =Schwab!S79 -> 27192978 | AN84: =Schwab!Q79 -> 841 | AO84: =Fidelity!P84 -> 41237266 | AP84: =Fidelity!O84 -> 168 | BA84: ='TFA - Folio'!H89 -> 16953280 | BB84: ='TFA - Folio'!I84 -> 1 | BC84: ='TFA - Folio'!K89 -> 74695459 | BD84: ='TFA - Folio'!N89 -> 1 | BG84: =UNC!B47 -> 1.4148386e+08 | BH84: =UNC!C47 -> 1 | BI84: ='Schwab LC'!D44 -> 3440046 | BJ84: ='Schwab LC'!E44 -> 2 | CI84: ='NC State'!B17 -> 6869168.2 | CJ84: ='NC State'!C17 -> 1 | CK84: ='Holiday Oil'!G22 -> 22361904 | CL84: ='Holiday Oil'!H22 -> 1 | CM84: =SCLVX!B45 -> 42644167 | CN84: =SCLVX!G45 -> 1 | CO84: =Stifel!B58 -> 4732255.3 | CP84: =Stifel!K58 -> 6 | CQ84: =TDA!O74 -> 1128873.6 | CR84: =TDA!N74 -> 64 | CS84: =UNC!D47 -> 38491623 | CT84: =UNC!E47 -> 1 | CU84: =Asbestos!B11 -> 12472689 | CV84: =Asbestos!C11 -> 1 | CW84: =TUG!H3 -> 58778606 | CX84: =TUG!I3 -> 1 | CY84: =Cline!B30 -> 9405543.3 | CZ84: =Cline!C30 -> 1
A85: 43799 | B85: =O85+CM85+Q85+AM85+CQ85+AO85+DA85+BA85+BC85+CO85+BG85+CS85+BI85+CY85+CK85+CI85+DC85+DE85+CU85+CW85 -> 1.0961759e+09 | C85: =P85+CN85+R85+AN85+CR85+AP85+DB85+BB85+BD85+CP85+BH85+CT85+BJ85+CZ85+CL85+DD85+DF85+CJ85+CV85+CX85 -> 1142 | D85: =O85+BA85+CO85+BG85+BI85+DC85+CU85 -> 7.3846225e+08 | E85: =P85+BB85+CP85+BH85+BJ85+CV85 -> 12 | F85: =CM85+CS85 -> 84051746 | G85: =CN85+CT85 -> 2 | H85: =Q85+CY85+CI85 -> 41325660 | I85: =R85+CZ85+CJ85 -> 3 | J85: =AM85+CQ85+AO85+DA85 -> 70095542 | K85: =AN85+CR85+AP85+DB85 -> 1122 | L85: =BC85+CK85+DE85+CW85 -> 1.6224065e+08 | M85: =BD85+CL85+DF85+CX85 -> 3 | O85: =SILVX!B92 -> 5.5427017e+08 | P85: =SILVX!G92 -> 1 | Q85: =SGLIX!B37 -> 28342017 | R85: =SGLIX!G37 -> 1 | AM85: =Schwab!S80 -> 26990293 | AN85: =Schwab!Q80 -> 878 | AO85: =Fidelity!P85 -> 41691528 | AP85: =Fidelity!O85 -> 170 | BA85: ='TFA - Folio'!H90 -> 19090411 | BB85: ='TFA - Folio'!I85 -> 1 | BC85: ='TFA - Folio'!K90 -> 76147906 | BD85: ='TFA - Folio'!N90 -> 1 | BG85: =UNC!B48 -> 144123331 | BH85: =UNC!C48 -> 1 | BI85: ='Schwab LC'!D45 -> 3504327.2 | BJ85: ='Schwab LC'!E45 -> 2 | CI85: ='NC State'!B18 -> 6977337.4 | CJ85: ='NC State'!C18 -> 1 | CK85: ='Holiday Oil'!G23 -> 22354285 | CL85: ='Holiday Oil'!H23 -> 1 | CM85: =SCLVX!B46 -> 45117689 | CN85: =SCLVX!G46 -> 1 | CO85: =Stifel!B59 -> 4826188.2 | CP85: =Stifel!K59 -> 6 | CQ85: =TDA!O75 -> 1413721 | CR85: =TDA!N75 -> 74 | CS85: =UNC!D48 -> 38934057 | CT85: =UNC!E48 -> 1 | CU85: =Asbestos!B12 -> 12647819 | CV85: =Asbestos!C12 -> 1 | CW85: =TUG!H4 -> 63738463 | CX85: =TUG!I4 -> 1 | CY85: =Cline!B31 -> 6006305.4 | CZ85: =Cline!C31 -> 1
A86: 43830 | B86: =O86+CM86+Q86+AM86+CQ86+AO86+DA86+BA86+BC86+CO86+BG86+CS86+BI86+CY86+CK86+CI86+DC86+DE86+CU86+CW86 -> 1.1196176e+09 | C86: =P86+CN86+R86+AN86+CR86+AP86+DB86+BB86+BD86+CP86+BH86+CT86+BJ86+CZ86+CL86+DD86+DF86+CJ86+CV86+CX86 -> 1203 | D86: =O86+BA86+CO86+BG86+BI86+DC86+CU86 -> 7.555931e+08 | E86: =P86+BB86+CP86+BH86+BJ86+CV86 -> 12 | F86: =CM86+CS86 -> 86992366 | G86: =CN86+CT86 -> 2 | H86: =Q86+CY86+CI86 -> 40901535 | I86: =R86+CZ86+CJ86 -> 3 | J86: =AM86+CQ86+AO86+DA86 -> 67210888 | K86: =AN86+CR86+AP86+DB86 -> 1183 | L86: =BC86+CK86+DE86+CW86 -> 1.6891969e+08 | M86: =BD86+CL86+DF86+CX86 -> 3 | O86: =SILVX!B93 -> 5.6781142e+08 | P86: =SILVX!G93 -> 1 | Q86: =SGLIX!B38 -> 28649715 | R86: =SGLIX!G38 -> 1 | AM86: =Schwab!S81 -> 28724863 | AN86: =Schwab!Q81 -> 934 | AO86: =Fidelity!P86 -> 37049126 | AP86: =Fidelity!O86 -> 174 | BA86: ='TFA - Folio'!H91 -> 19512538 | BB86: ='TFA - Folio'!I86 -> 1 | BC86: ='TFA - Folio'!K91 -> 78046980 | BD86: ='TFA - Folio'!N91 -> 1 | BG86: =UNC!B49 -> 1.4704005e+08 | BH86: =UNC!C49 -> 1 | BI86: ='Schwab LC'!D46 -> 3566598.8 | BJ86: ='Schwab LC'!E46 -> 2 | CI86: ='NC State'!B19 -> 7132270.3 | CJ86: ='NC State'!C19 -> 1 | CK86: ='Holiday Oil'!G24 -> 22416654 | CL86: ='Holiday Oil'!H24 -> 1 | CM86: =SCLVX!B47 -> 47470286 | CN86: =SCLVX!G47 -> 1 | CO86: =Stifel!B60 -> 4923053.5 | CP86: =Stifel!K60 -> 6 | CQ86: =TDA!O76 -> 1436898.3 | CR86: =TDA!N76 -> 75 | CS86: =UNC!D49 -> 39522081 | CT86: =UNC!E49 -> 1 | CU86: =Asbestos!B13 -> 12739440 | CV86: =Asbestos!C13 -> 1 | CW86: =TUG!H5 -> 68456054 | CX86: =TUG!I5 -> 1 | CY86: =Cline!B32 -> 5119549.5 | CZ86: =Cline!C32 -> 1
A87: 43861 | B87: =O87+CM87+Q87+AM87+CQ87+AO87+DA87+BA87+BC87+CO87+BG87+CS87+BI87+CY87+CK87+CI87+DC87+DE87+CU87+CW87 -> 1.1831056e+09 | C87: =P87+CN87+R87+AN87+CR87+AP87+DB87+BB87+BD87+CP87+BH87+CT87+BJ87+CZ87+CL87+DD87+DF87+CJ87+CV87+CX87 -> 1249 | D87: =O87+BA87+CO87+BG87+BI87+DC87+CU87 -> 7.9304322e+08 | E87: =P87+BB87+CP87+BH87+BJ87+CV87 -> 12 | F87: =CM87+CS87 -> 88415021 | G87: =CN87+CT87 -> 2 | H87: =Q87+CY87+CI87 -> 46137404 | I87: =R87+CZ87+CJ87 -> 3 | J87: =AM87+CQ87+AO87+DA87 -> 77846594 | K87: =AN87+CR87+AP87+DB87 -> 1229 | L87: =BC87+CK87+DE87+CW87 -> 1.7766335e+08 | M87: =BD87+CL87+DF87+CX87 -> 3 | O87: =SILVX!B94 -> 6.0382933e+08 | P87: =SILVX!G94 -> 1 | Q87: =SGLIX!B39 -> 33761564 | R87: =SGLIX!G39 -> 1 | AM87: =Schwab!S82 -> 39812781 | AN87: =Schwab!Q82 -> 964 | AO87: =Fidelity!P87 -> 34897801 | AP87: =Fidelity!O87 -> 187 | BA87: ='TFA - Folio'!H92 -> 17915749 | BB87: ='TFA - Folio'!I87 -> 1 | BC87: ='TFA - Folio'!K92 -> 81613694 | BD87: ='TFA - Folio'!N92 -> 1 | BG87: =UNC!B50 -> 1.4968331e+08 | BH87: =UNC!C50 -> 1 | BI87: ='Schwab LC'!D47 -> 3631711.4 | BJ87: ='Schwab LC'!E47 -> 2 | CI87: ='NC State'!B20 -> 7203667.9 | CJ87: ='NC State'!C20 -> 1 | CK87: ='Holiday Oil'!G25 -> 22584562 | CL87: ='Holiday Oil'!H25 -> 1 | CM87: =SCLVX!B48 -> 50030491 | CN87: =SCLVX!G48 -> 1 | CO87: =Stifel!B61 -> 5010902.2 | CP87: =Stifel!K61 -> 6 | CQ87: =TDA!O77 -> 3136011.5 | CR87: =TDA!N77 -> 78 | CS87: =UNC!D50 -> 38384529 | CT87: =UNC!E50 -> 1 | CU87: =Asbestos!B14 -> 12972225 | CV87: =Asbestos!C14 -> 1 | CW87: =TUG!H6 -> 73465096 | CX87: =TUG!I6 -> 1 | CY87: =Cline!B33 -> 5172171.7 | CZ87: =Cline!C33 -> 1
A88: 43890 | B88: =O88+CM88+Q88+AM88+CQ88+AO88+DA88+BA88+BC88+CO88+BG88+CS88+BI88+CY88+CK88+CI88+DC88+DE88+CU88+CW88 -> 1.1296185e+09 | C88: =P88+CN88+R88+AN88+CR88+AP88+DB88+BB88+BD88+CP88+BH88+CT88+BJ88+CZ88+CL88+DD88+DF88+CJ88+CV88+CX88 -> 1338 | D88: =O88+BA88+CO88+BG88+BI88+DC88+CU88 -> 7.4083775e+08 | E88: =P88+BB88+CP88+BH88+BJ88+CV88 -> 12 | F88: =CM88+CS88 -> 80086366 | G88: =CN88+CT88 -> 2 | H88: =Q88+CY88+CI88 -> 42305903 | I88: =R88+CZ88+CJ88 -> 3 | J88: =AM88+CQ88+AO88+DA88 -> 81994026 | K88: =AN88+CR88+AP88+DB88 -> 1318 | L88: =BC88+CK88+DE88+CW88 -> 1.8439447e+08 | M88: =BD88+CL88+DF88+CX88 -> 3 | O88: =SILVX!B95 -> 5.6632523e+08 | P88: =SILVX!G95 -> 1 | Q88: =SGLIX!B40 -> 30871543 | R88: =SGLIX!G40 -> 1 | AM88: =Schwab!S83 -> 44338469 | AN88: =Schwab!Q83 -> 1036 | AO88: =Fidelity!P88 -> 34338528 | AP88: =Fidelity!O88 -> 203 | BA88: ='TFA - Folio'!H93 -> 16556412 | BB88: ='TFA - Folio'!I88 -> 1 | BC88: ='TFA - Folio'!K93 -> 84383102 | BD88: ='TFA - Folio'!N93 -> 1 | BG88: =UNC!B51 -> 1.3790368e+08 | BH88: =UNC!C51 -> 1 | BI88: ='Schwab LC'!D48 -> 3295509.8 | BJ88: ='Schwab LC'!E48 -> 2 | CI88: ='NC State'!B21 -> 6647942.9 | CJ88: ='NC State'!C21 -> 1 | CK88: ='Holiday Oil'!G26 -> 22151374 | CL88: ='Holiday Oil'!H26 -> 1 | CM88: =SCLVX!B49 -> 45438869 | CN88: =SCLVX!G49 -> 1 | CO88: =Stifel!B62 -> 4797910.4 | CP88: =Stifel!K62 -> 6 | CQ88: =TDA!O78 -> 3317028.7 | CR88: =TDA!N78 -> 79 | CS88: =UNC!D51 -> 34647497 | CT88: =UNC!E51 -> 1 | CU88: =Asbestos!B15 -> 11959009 | CV88: =Asbestos!C15 -> 1 | CW88: =TUG!H7 -> 77859998 | CX88: =TUG!I7 -> 1 | CY88: =Cline!B34 -> 4786417.4 | CZ88: =Cline!C34 -> 1
A89: 43921 | B89: =O89+CM89+Q89+AM89+CQ89+AO89+DA89+BA89+BC89+CO89+BG89+CS89+BI89+CY89+CK89+CI89+DC89+DE89+CU89+CW89 -> 1.0120887e+09 | C89: =P89+CN89+R89+AN89+CR89+AP89+DB89+BB89+BD89+CP89+BH89+CT89+BJ89+CZ89+CL89+DD89+DF89+CJ89+CV89+CX89 -> 1427 | D89: =O89+BA89+CO89+BG89+BI89+DC89+CU89 -> 6.2005467e+08 | E89: =P89+BB89+CP89+BH89+BJ89+CV89 -> 12 | F89: =CM89+CS89 -> 63250117 | G89: =CN89+CT89 -> 2 | H89: =Q89+CY89+CI89 -> 39295156 | I89: =R89+CZ89+CJ89 -> 3 | J89: =AM89+CQ89+AO89+DA89 -> 83215568 | K89: =AN89+CR89+AP89+DB89 -> 1407 | L89: =BC89+CK89+DE89+CW89 -> 2.0627315e+08 | M89: =BD89+CL89+DF89+CX89 -> 3 | O89: =SILVX!B96 -> 4.6566712e+08 | P89: =SILVX!G96 -> 1 | Q89: =SGLIX!B41 -> 29459262 | R89: =SGLIX!G41 -> 1 | AM89: =Schwab!S84 -> 47101637 | AN89: =Schwab!Q84 -> 1108 | AO89: =Fidelity!P89 -> 32868940 | AP89: =Fidelity!O89 -> 216 | BA89: ='TFA - Folio'!H94 -> 15514862 | BB89: ='TFA - Folio'!I89 -> 1 | BC89: ='TFA - Folio'!K94 -> 89303050 | BD89: ='TFA - Folio'!N94 -> 1 | BG89: =UNC!B52 -> 1.2114264e+08 | BH89: =UNC!C52 -> 1 | BI89: ='Schwab LC'!D49 -> 2897537.5 | BJ89: ='Schwab LC'!E49 -> 2 | CI89: ='NC State'!B22 -> 5715754.5 | CJ89: ='NC State'!C22 -> 1 | CK89: ='Holiday Oil'!G27 -> 21117831 | CL89: ='Holiday Oil'!H27 -> 1 | CM89: =SCLVX!B50 -> 35990238 | CN89: =SCLVX!G50 -> 1 | CO89: =Stifel!B63 -> 4247229.3 | CP89: =Stifel!K63 -> 6 | CQ89: =TDA!O79 -> 3244991.7 | CR89: =TDA!N79 -> 83 | CS89: =UNC!D52 -> 27259879 | CT89: =UNC!E52 -> 1 | CU89: =Asbestos!B16 -> 10585271 | CV89: =Asbestos!C16 -> 1 | CW89: =TUG!H8 -> 95852266 | CX89: =TUG!I8 -> 1 | CY89: =Cline!B35 -> 4120139.4 | CZ89: =Cline!C35 -> 1
A90: 43951 | B90: =O90+CM90+Q90+AM90+CQ90+AO90+DA90+BA90+BC90+CO90+BG90+CS90+BI90+CY90+CK90+CI90+DC90+DE90+CU90+CW90 -> 1.1039135e+09 | C90: =P90+CN90+R90+AN90+CR90+AP90+DB90+BB90+BD90+CP90+BH90+CT90+BJ90+CZ90+CL90+DD90+DF90+CJ90+CV90+CX90 -> 1503 | D90: =O90+BA90+CO90+BG90+BI90+DC90+CU90 -> 6.6851906e+08 | E90: =P90+BB90+CP90+BH90+BJ90+CV90 -> 12 | F90: =CM90+CS90 -> 69414008 | G90: =CN90+CT90 -> 2 | H90: =Q90+CY90+CI90 -> 51547457 | I90: =R90+CZ90+CJ90 -> 3 | J90: =AM90+CQ90+AO90+DA90 -> 89946963 | K90: =AN90+CR90+AP90+DB90 -> 1483 | L90: =BC90+CK90+DE90+CW90 -> 2.2448599e+08 | M90: =BD90+CL90+DF90+CX90 -> 3 | O90: =SILVX!B97 -> 4.9933941e+08 | P90: =SILVX!G97 -> 1 | Q90: =SGLIX!B42 -> 40981878 | R90: =SGLIX!G42 -> 1 | AM90: =Schwab!S85 -> 51029259 | AN90: =Schwab!Q85 -> 1163 | AO90: =Fidelity!P90 -> 35333092 | AP90: =Fidelity!O90 -> 232 | BA90: ='TFA - Folio'!H95 -> 16916276 | BB90: ='TFA - Folio'!I90 -> 1 | BC90: ='TFA - Folio'!K95 -> 95703091 | BD90: ='TFA - Folio'!N95 -> 1 | BG90: =UNC!B53 -> 1.3178147e+08 | BH90: =UNC!C53 -> 1 | BI90: ='Schwab LC'!D50 -> 3134699.8 | BJ90: ='Schwab LC'!E50 -> 2 | CI90: ='NC State'!B23 -> 6155638.4 | CJ90: ='NC State'!C23 -> 1 | CK90: ='Holiday Oil'!G28 -> 21328668 | CL90: ='Holiday Oil'!H28 -> 1 | CM90: =SCLVX!B51 -> 40620810 | CN90: =SCLVX!G51 -> 1 | CO90: =Stifel!B64 -> 5856700.5 | CP90: =Stifel!K64 -> 6 | CQ90: =TDA!O80 -> 3584610.9 | CR90: =TDA!N80 -> 88 | CS90: =UNC!D53 -> 28793197 | CT90: =UNC!E53 -> 1 | CU90: =Asbestos!B17 -> 11490508 | CV90: =Asbestos!C17 -> 1 | CW90: =TUG!H9 -> 1.0745423e+08 | CX90: =TUG!I9 -> 1 | CY90: =Cline!B36 -> 4409940.7 | CZ90: =Cline!C36 -> 1
A91: 43982 | B91: =O91+CM91+Q91+AM91+CQ91+AO91+DA91+BA91+BC91+CO91+BG91+CS91+BI91+CY91+CK91+CI91+DC91+DE91+CU91+CW91 -> 1.1817859e+09 | C91: =P91+CN91+R91+AN91+CR91+AP91+DB91+BB91+BD91+CP91+BH91+CT91+BJ91+CZ91+CL91+DD91+DF91+CJ91+CV91+CX91 -> 1583 | D91: =O91+BA91+CO91+BG91+BI91+DC91+CU91 -> 7.1925066e+08 | E91: =P91+BB91+CP91+BH91+BJ91+CV91 -> 12 | F91: =CM91+CS91 -> 74381913 | G91: =CN91+CT91 -> 2 | H91: =Q91+CY91+CI91 -> 54977187 | I91: =R91+CZ91+CJ91 -> 3 | J91: =AM91+CQ91+AO91+DA91 -> 99314393 | K91: =AN91+CR91+AP91+DB91 -> 1563 | L91: =BC91+CK91+DE91+CW91 -> 2.338617e+08 | M91: =BD91+CL91+DF91+CX91 -> 3 | O91: =SILVX!B98 -> 5.3810008e+08 | P91: =SILVX!G98 -> 1 | Q91: =SGLIX!B43 -> 44021799 | R91: =SGLIX!G43 -> 1 | AM91: =Schwab!S86 -> 56834258 | AN91: =Schwab!Q86 -> 1221 | AO91: =Fidelity!P91 -> 38880392 | AP91: =Fidelity!O91 -> 254 | BA91: ='TFA - Folio'!H96 -> 21385802 | BB91: ='TFA - Folio'!I91 -> 1 | BC91: ='TFA - Folio'!K96 -> 1.0056972e+08 | BD91: ='TFA - Folio'!N96 -> 1 | BG91: =UNC!B54 -> 1.3917672e+08 | BH91: =UNC!C54 -> 1 | BI91: ='Schwab LC'!D51 -> 3295541.2 | BJ91: ='Schwab LC'!E51 -> 2 | CI91: ='NC State'!B24 -> 6386784.1 | CJ91: ='NC State'!C24 -> 1 | CK91: ='Holiday Oil'!G29 -> 21459836 | CL91: ='Holiday Oil'!H29 -> 1 | CM91: =SCLVX!B52 -> 44066075 | CN91: =SCLVX!G52 -> 1 | CO91: =Stifel!B65 -> 6184182.9 | CP91: =Stifel!K65 -> 6 | CQ91: =TDA!O81 -> 3599742.5 | CR91: =TDA!N81 -> 88 | CS91: =UNC!D54 -> 30315838 | CT91: =UNC!E54 -> 1 | CU91: =Asbestos!B18 -> 11108335 | CV91: =Asbestos!C18 -> 1 | CW91: =TUG!H10 -> 1.1183214e+08 | CX91: =TUG!I10 -> 1 | CY91: =Cline!B37 -> 4568603.9 | CZ91: =Cline!C37 -> 1
A92: 44012 | B92: =O92+CM92+Q92+AM92+CQ92+AO92+DA92+BA92+BC92+CO92+BG92+CS92+BI92+CY92+CK92+CI92+DC92+DE92+CU92+CW92+U92 -> 1.2171715e+09 | C92: =P92+CN92+R92+AN92+CR92+AP92+DB92+BB92+BD92+CP92+BH92+CT92+BJ92+CZ92+CL92+DD92+DF92+CJ92+CV92+CX92+V92 -> 1616 | D92: =O92+BA92+CO92+BG92+BI92+DC92+CU92 -> 7.2584907e+08 | E92: =P92+BB92+CP92+BH92+BJ92+CV92 -> 12 | F92: =CM92+CS92 -> 76165421 | G92: =CN92+CT92 -> 2 | H92: =Q92+CY92+CI92 -> 60146526 | I92: =R92+CZ92+CJ92 -> 3 | J92: =AM92+CQ92+AO92+DA92+U92 -> 1.0796e+08 | K92: =AN92+CR92+AP92+DB92+V92 -> 1596 | L92: =BC92+CK92+DE92+CW92 -> 2.4705053e+08 | M92: =BD92+CL92+DF92+CX92 -> 3 | O92: =SILVX!B99 -> 5.4056309e+08 | P92: =SILVX!G99 -> 1 | Q92: =SGLIX!B44 -> 49114435 | R92: =SGLIX!G44 -> 1 | U92: =FoF!AD2 -> 3805632.4 | V92: =FoF!AE2 -> 3 | AM92: =Schwab!S87 -> 63176902 | AN92: =Schwab!Q87 -> 1248 | AO92: =Fidelity!P92 -> 37332359 | AP92: =Fidelity!O92 -> 257 | BA92: ='TFA - Folio'!H97 -> 24542951 | BB92: ='TFA - Folio'!I92 -> 1 | BC92: ='TFA - Folio'!K97 -> 1.0488828e+08 | BD92: ='TFA - Folio'!N97 -> 1 | BG92: =UNC!B55 -> 1.4003077e+08 | BH92: =UNC!C55 -> 1 | BI92: ='Schwab LC'!D52 -> 3313316 | BJ92: ='Schwab LC'!E52 -> 2 | CI92: ='NC State'!B25 -> 6433354.2 | CJ92: ='NC State'!C25 -> 1 | CK92: ='Holiday Oil'!G30 -> 18701894 | CL92: ='Holiday Oil'!H30 -> 1 | CM92: =SCLVX!B53 -> 45700702 | CN92: =SCLVX!G53 -> 1 | CO92: =Stifel!B66 -> 6219191.9 | CP92: =Stifel!K66 -> 6 | CQ92: =TDA!O82 -> 3645109.5 | CR92: =TDA!N82 -> 88 | CS92: =UNC!D55 -> 30464719 | CT92: =UNC!E55 -> 1 | CU92: =Asbestos!B19 -> 11179757 | CV92: =Asbestos!C19 -> 1 | CW92: =TUG!H11 -> 1.2346035e+08 | CX92: =TUG!I11 -> 1 | CY92: =Cline!B38 -> 4598736.7 | CZ92: =Cline!C38 -> 1
A93: 44043 | B93: =O93+CM93+Q93+AM93+CQ93+AO93+DA93+BA93+BC93+CO93+BG93+CS93+BI93+CY93+CK93+CI93+DC93+DE93+CU93+CW93+U93 -> 1.2906943e+09 | C93: =P93+CN93+R93+AN93+CR93+AP93+DB93+BB93+BD93+CP93+BH93+CT93+BJ93+CZ93+CL93+DD93+DF93+CJ93+CV93+CX93+V93 -> 1660 | D93: =O93+BA93+CO93+BG93+BI93+DC93+CU93 -> 7.686504e+08 | E93: =P93+BB93+CP93+BH93+BJ93+CV93 -> 12 | F93: =CM93+CS93 -> 80650561 | G93: =CN93+CT93 -> 2 | H93: =Q93+CY93+CI93 -> 63936526 | I93: =R93+CZ93+CJ93 -> 3 | J93: =AM93+CQ93+AO93+DA93+U93 -> 1.1057991e+08 | K93: =AN93+CR93+AP93+DB93+V93 -> 1640 | L93: =BC93+CK93+DE93+CW93 -> 2.6687695e+08 | M93: =BD93+CL93+DF93+CX93 -> 3 | O93: =SILVX!B100 -> 5.7018164e+08 | P93: =SILVX!G100 -> 1 | Q93: =SGLIX!B45 -> 52417082 | R93: =SGLIX!G45 -> 1 | U93: =FoF!AD3 -> 4771356.2 | V93: =FoF!AE3 -> 3 | AM93: =Schwab!S88 -> 62023336 | AN93: =Schwab!Q88 -> 1274 | AO93: =Fidelity!P93 -> 39261923 | AP93: =Fidelity!O93 -> 271 | BA93: ='TFA - Folio'!H98 -> 27740080 | BB93: ='TFA - Folio'!I93 -> 1 | BC93: ='TFA - Folio'!K98 -> 1.0978816e+08 | BD93: ='TFA - Folio'!N98 -> 1 | BG93: =UNC!B56 -> 1.4876744e+08 | BH93: =UNC!C56 -> 1 | BI93: ='Schwab LC'!D53 -> 3509439.7 | BJ93: ='Schwab LC'!E53 -> 2 | CI93: ='NC State'!B26 -> 6719765.5 | CJ93: ='NC State'!C26 -> 1 | CK93: ='Holiday Oil'!G31 -> 18947011 | CL93: ='Holiday Oil'!H31 -> 1 | CM93: =SCLVX!B54 -> 48523554 | CN93: =SCLVX!G54 -> 1 | CO93: =Stifel!B67 -> 6594685.5 | CP93: =Stifel!K67 -> 6 | CQ93: =TDA!O83 -> 4523290.7 | CR93: =TDA!N83 -> 92 | CS93: =UNC!D56 -> 32127007 | CT93: =UNC!E56 -> 1 | CU93: =Asbestos!B20 -> 11857113 | CV93: =Asbestos!C20 -> 1 | CW93: =TUG!H12 -> 1.3814178e+08 | CX93: =TUG!I12 -> 1 | CY93: =Cline!B39 -> 4799678.2 | CZ93: =Cline!C39 -> 1
A94: 44074 | B94: =O94+CM94+Q94+AM94+CQ94+AO94+DA94+BA94+BC94+CO94+BG94+CS94+BI94+CY94+CK94+CI94+DC94+DE94+CU94+CW94+U94 -> 1.3624484e+09 | C94: =P94+CN94+R94+AN94+CR94+AP94+DB94+BB94+BD94+CP94+BH94+CT94+BJ94+CZ94+CL94+DD94+DF94+CJ94+CV94+CX94+V94 -> 1714 | D94: =O94+BA94+CO94+BG94+BI94+DC94+CU94 -> 7.9505285e+08 | E94: =P94+BB94+CP94+BH94+BJ94+CV94 -> 12 | F94: =CM94+CS94 -> 82278267 | G94: =CN94+CT94 -> 2 | H94: =Q94+CY94+CI94 -> 70299091 | I94: =R94+CZ94+CJ94 -> 3 | J94: =AM94+CQ94+AO94+DA94+U94 -> 1.1637001e+08 | K94: =AN94+CR94+AP94+DB94+V94 -> 1694 | L94: =BC94+CK94+DE94+CW94 -> 2.9844816e+08 | M94: =BD94+CL94+DF94+CX94 -> 3 | O94: =SILVX!B101 -> 5.8323224e+08 | P94: =SILVX!G101 -> 1 | Q94: =SGLIX!B46 -> 58188593 | R94: =SGLIX!G46 -> 1 | U94: =FoF!AD4 -> 4963670.9 | V94: =FoF!AE4 -> 3 | AM94: =Schwab!S89 -> 64768305 | AN94: =Schwab!Q89 -> 1311 | AO94: =Fidelity!P94 -> 41971827 | AP94: =Fidelity!O94 -> 286 | BA94: ='TFA - Folio'!H99 -> 33400974 | BB94: ='TFA - Folio'!I94 -> 1 | BC94: ='TFA - Folio'!K99 -> 1.1042307e+08 | BD94: ='TFA - Folio'!N99 -> 1 | BG94: =UNC!B57 -> 1.5556262e+08 | BH94: =UNC!C57 -> 1 | BI94: ='Schwab LC'!D54 -> 3574832.2 | BJ94: ='Schwab LC'!E54 -> 2 | CI94: ='NC State'!B27 -> 7064875.7 | CJ94: ='NC State'!C27 -> 1 | CK94: ='Holiday Oil'!G32 -> 18853977 | CL94: ='Holiday Oil'!H32 -> 1 | CM94: =SCLVX!B55 -> 49904616 | CN94: =SCLVX!G55 -> 1 | CO94: =Stifel!B68 -> 6892859.8 | CP94: =Stifel!K68 -> 6 | CQ94: =TDA!O84 -> 4666208.9 | CR94: =TDA!N84 -> 94 | CS94: =UNC!D57 -> 32373651 | CT94: =UNC!E57 -> 1 | CU94: =Asbestos!B21 -> 12389329 | CV94: =Asbestos!C21 -> 1 | CW94: =TUG!H13 -> 1.6917112e+08 | CX94: =TUG!I13 -> 1 | CY94: =Cline!B40 -> 5045622.6 | CZ94: =Cline!C40 -> 1
A95: 44104 | B95: =O95+CM95+Q95+AM95+CQ95+AO95+DA95+BA95+BC95+CO95+BG95+CS95+BI95+CY95+CK95+CI95+DC95+DE95+CU95+CW95+U95 -> 1.3353677e+09 | C95: =P95+CN95+R95+AN95+CR95+AP95+DB95+BB95+BD95+CP95+BH95+CT95+BJ95+CZ95+CL95+DD95+DF95+CJ95+CV95+CX95+V95 -> 1760 | D95: =O95+BA95+CO95+BG95+BI95+DC95+CU95 -> 7.6840205e+08 | E95: =P95+BB95+CP95+BH95+BJ95+CV95 -> 12 | F95: =CM95+CS95 -> 79483932 | G95: =CN95+CT95 -> 2 | H95: =Q95+CY95+CI95 -> 68969624 | I95: =R95+CZ95+CJ95 -> 3 | J95: =AM95+CQ95+AO95+DA95+U95 -> 1.145318e+08 | K95: =AN95+CR95+AP95+DB95+V95 -> 1740 | L95: =BC95+CK95+DE95+CW95 -> 3.0398034e+08 | M95: =BD95+CL95+DF95+CX95 -> 3 | O95: =SILVX!B102 -> 5.5891131e+08 | P95: =SILVX!G102 -> 1 | Q95: =SGLIX!B47 -> 57170363 | R95: =SGLIX!G47 -> 1 | U95: =FoF!AD5 -> 5586975.1 | V95: =FoF!AE5 -> 3 | AM95: =Schwab!S90 -> 64915870 | AN95: =Schwab!Q90 -> 1338 | AO95: =Fidelity!P95 -> 39388567 | AP95: =Fidelity!O95 -> 302 | BA95: ='TFA - Folio'!H100 -> 35740759 | BB95: ='TFA - Folio'!I95 -> 1 | BC95: ='TFA - Folio'!K100 -> 1.1129215e+08 | BD95: ='TFA - Folio'!N100 -> 1 | BG95: =UNC!B58 -> 1.5148138e+08 | BH95: =UNC!C58 -> 1 | BI95: ='Schwab LC'!D55 -> 3482382.4 | BJ95: ='Schwab LC'!E55 -> 2 | CI95: ='NC State'!B28 -> 6883381.8 | CJ95: ='NC State'!C28 -> 1 | CK95: ='Holiday Oil'!G33 -> 18825652 | CL95: ='Holiday Oil'!H33 -> 1 | CM95: =SCLVX!B56 -> 48260549 | CN95: =SCLVX!G56 -> 1 | CO95: =Stifel!B69 -> 6717103.4 | CP95: =Stifel!K69 -> 6 | CQ95: =TDA!O85 -> 4640389.4 | CR95: =TDA!N85 -> 97 | CS95: =UNC!D58 -> 31223383 | CT95: =UNC!E58 -> 1 | CU95: =Asbestos!B22 -> 12069111 | CV95: =Asbestos!C22 -> 1 | CW95: =TUG!H14 -> 1.7386253e+08 | CX95: =TUG!I14 -> 1 | CY95: =Cline!B41 -> 4915878.5 | CZ95: =Cline!C41 -> 1
A96: 44135 | B96: =O96+CM96+Q96+AM96+CQ96+AO96+DA96+BA96+BC96+CO96+BG96+CS96+BI96+CY96+CK96+CI96+DC96+DE96+CU96+CW96+U96 -> 1.3094149e+09 | C96: =P96+CN96+R96+AN96+CR96+AP96+DB96+BB96+BD96+CP96+BH96+CT96+BJ96+CZ96+CL96+DD96+DF96+CJ96+CV96+CX96+V96 -> 1790 | D96: =O96+BA96+CO96+BG96+BI96+DC96+CU96 -> 7.3954001e+08 | E96: =P96+BB96+CP96+BH96+BJ96+CV96 -> 12 | F96: =CM96+CS96 -> 81154760 | G96: =CN96+CT96 -> 2 | H96: =Q96+CY96+CI96 -> 67955122 | I96: =R96+CZ96+CJ96 -> 3 | J96: =AM96+CQ96+AO96+DA96+U96 -> 1.0663567e+08 | K96: =AN96+CR96+AP96+DB96+V96 -> 1770 | L96: =BC96+CK96+DE96+CW96 -> 3.1412939e+08 | M96: =BD96+CL96+DF96+CX96 -> 3 | O96: =SILVX!B103 -> 5.2891783e+08 | P96: =SILVX!G103 -> 1 | Q96: =SGLIX!B48 -> 56536450 | R96: =SGLIX!G48 -> 1 | U96: =FoF!AD6 -> 6161104.4 | V96: =FoF!AE6 -> 3 | AM96: =Schwab!S91 -> 64399478 | AN96: =Schwab!Q91 -> 1355 | AO96: =Fidelity!P96 -> 31203744 | AP96: =Fidelity!O96 -> 313 | BA96: ='TFA - Folio'!H101 -> 40587819 | BB96: ='TFA - Folio'!I96 -> 1 | BC96: ='TFA - Folio'!K101 -> 1.1039245e+08 | BD96: ='TFA - Folio'!N101 -> 1 | BG96: =UNC!B59 -> 1.4838526e+08 | BH96: =UNC!C59 -> 1 | BI96: ='Schwab LC'!D56 -> 3403246.8 | BJ96: ='Schwab LC'!E56 -> 2 | CI96: ='NC State'!B29 -> 6659315.5 | CJ96: ='NC State'!C29 -> 1 | CK96: ='Holiday Oil'!G34 -> 18745633 | CL96: ='Holiday Oil'!H34 -> 1 | CM96: =SCLVX!B57 -> 49411422 | CN96: =SCLVX!G57 -> 1 | CO96: =Stifel!B70 -> 6427175.8 | CP96: =Stifel!K70 -> 6 | CQ96: =TDA!O86 -> 4871339.9 | CR96: =TDA!N86 -> 99 | CS96: =UNC!D59 -> 31743338 | CT96: =UNC!E59 -> 1 | CU96: =Asbestos!B23 -> 11818684 | CV96: =Asbestos!C23 -> 1 | CW96: =TUG!H15 -> 1.8499131e+08 | CX96: =TUG!I15 -> 1 | CY96: =Cline!B42 -> 4759357 | CZ96: =Cline!C42 -> 1
A97: 44165 | B97: =O97+CM97+Q97+AM97+CQ97+AO97+DA97+BA97+BC97+CO97+BG97+CS97+BI97+CY97+CK97+CI97+DC97+DE97+CU97+CW97+U97 -> 1.4163024e+09 | C97: =P97+CN97+R97+AN97+CR97+AP97+DB97+BB97+BD97+CP97+BH97+CT97+BJ97+CZ97+CL97+DD97+DF97+CJ97+CV97+CX97+V97 -> 1819 | D97: =O97+BA97+CO97+BG97+BI97+DC97+CU97 -> 7.5400293e+08 | E97: =P97+BB97+CP97+BH97+BJ97+CV97 -> 12 | F97: =CM97+CS97 -> 88354075 | G97: =CN97+CT97 -> 2 | H97: =Q97+CY97+CI97 -> 95835485 | I97: =R97+CZ97+CJ97 -> 3 | J97: =AM97+CQ97+AO97+DA97+U97 -> 1.3372234e+08 | K97: =AN97+CR97+AP97+DB97+V97 -> 1799 | L97: =BC97+CK97+DE97+CW97 -> 3.4438759e+08 | M97: =BD97+CL97+DF97+CX97 -> 3 | O97: =SILVX!B104 -> 5.2607793e+08 | P97: =SILVX!G104 -> 1 | Q97: =SGLIX!B49 -> 83496555 | R97: =SGLIX!G49 -> 1 | U97: =FoF!AD7 -> 6571433 | V97: =FoF!AE7 -> 3 | AM97: =Schwab!S92 -> 80751469 | AN97: =Schwab!Q92 -> 1371 | AO97: =Fidelity!P97 -> 40469756 | AP97: =Fidelity!O97 -> 327 | BA97: ='TFA - Folio'!H102 -> 46001325 | BB97: ='TFA - Folio'!I97 -> 1 | BC97: ='TFA - Folio'!K102 -> 1.1221274e+08 | BD97: ='TFA - Folio'!N102 -> 1 | BG97: =UNC!B60 -> 1.5875262e+08 | BH97: =UNC!C60 -> 1 | BI97: ='Schwab LC'!D57 -> 3640606.9 | BJ97: ='Schwab LC'!E57 -> 2 | CI97: ='NC State'!B30 -> 7196380.1 | CJ97: ='NC State'!C30 -> 1 | CK97: ='Holiday Oil'!G35 -> 18988987 | CL97: ='Holiday Oil'!H35 -> 1 | CM97: =SCLVX!B58 -> 55058447 | CN97: =SCLVX!G58 -> 1 | CO97: =Stifel!B71 -> 6878108.7 | CP97: =Stifel!K71 -> 6 | CQ97: =TDA!O87 -> 5929686 | CR97: =TDA!N87 -> 98 | CS97: =UNC!D60 -> 33295628 | CT97: =UNC!E60 -> 1 | CU97: =Asbestos!B24 -> 12652334 | CV97: =Asbestos!C24 -> 1 | CW97: =TUG!H16 -> 2.1318586e+08 | CX97: =TUG!I16 -> 1 | CY97: =Cline!B43 -> 5142549.9 | CZ97: =Cline!C43 -> 1
A98: 44196 | B98: =O98+CM98+Q98+AM98+CQ98+AO98+DA98+BA98+BC98+CO98+BG98+CS98+BI98+CY98+CK98+CI98+DC98+DE98+CU98+CW98+U98+AI98 -> 1.4967813e+09 | C98: =P98+CN98+R98+AN98+CR98+AP98+DB98+BB98+BD98+CP98+BH98+CT98+BJ98+CZ98+CL98+DD98+DF98+CJ98+CV98+CX98+AJ98+V98 -> 1877 | D98: =O98+BA98+CO98+BG98+BI98+DC98+CU98 -> 7.7763564e+08 | E98: =P98+BB98+CP98+BH98+BJ98+CV98 -> 12 | F98: =CM98+CS98 -> 90895089 | G98: =CN98+CT98 -> 2 | H98: =Q98+CY98+CI98 -> 1.0029501e+08 | I98: =R98+CZ98+CJ98 -> 3 | J98: =AM98+CQ98+AO98+DA98+U98 -> 1.5872686e+08 | K98: =AN98+CR98+AP98+DB98+V98 -> 1856 | L98: =BC98+CK98+DE98+CW98+AI98 -> 3.6922871e+08 | M98: =BD98+CL98+DF98+CX98+AJ98 -> 4 | O98: =SILVX!B105 -> 5.4053105e+08 | P98: =SILVX!G105 -> 1 | Q98: =SGLIX!B50 -> 87559534 | R98: =SGLIX!G50 -> 1 | U98: =FoF!AD8 -> 7025614.1 | V98: =FoF!AE8 -> 3 | AI98: =HF!B2 -> 3392455 | AJ98: =HF!C2 -> 1 | AM98: =Schwab!S93 -> 81715111 | AN98: =Schwab!Q93 -> 1398 | AO98: =Fidelity!P98 -> 63589359 | AP98: =Fidelity!O98 -> 356 | AY98: =BA98-BA86 -> 28721313 | BA98: ='TFA - Folio'!H103 -> 48233851 | BB98: ='TFA - Folio'!I98 -> 1 | BC98: ='TFA - Folio'!K103 -> 1.0646577e+08 | BD98: ='TFA - Folio'!N103 -> 1 | BG98: =UNC!B61 -> 1.648243e+08 | BH98: =UNC!C61 -> 1 | BI98: ='Schwab LC'!D58 -> 3777952.9 | BJ98: ='Schwab LC'!E58 -> 2 | CI98: ='NC State'!B31 -> 7428529.6 | CJ98: ='NC State'!C31 -> 1 | CK98: ='Holiday Oil'!G36 -> 22517547 | CL98: ='Holiday Oil'!H36 -> 1 | CM98: =SCLVX!B59 -> 55550816 | CN98: =SCLVX!G59 -> 1 | CO98: =Stifel!B72 -> 7137589.1 | CP98: =Stifel!K72 -> 6 | CQ98: =TDA!O88 -> 6396771.7 | CR98: =TDA!N88 -> 99 | CS98: =UNC!D61 -> 35344273 | CT98: =UNC!E61 -> 1 | CU98: =Asbestos!B25 -> 13130903 | CV98: =Asbestos!C25 -> 1 | CW98: =TUG!H17 -> 2.3685294e+08 | CX98: =TUG!I17 -> 1 | CY98: =Cline!B44 -> 5306950.1 | CZ98: =Cline!C44 -> 1
A99: 44227 | B99: =O99+CM99+Q99+AM99+CQ99+AO99+DA99+BA99+BC99+CO99+BG99+CS99+BI99+CY99+CK99+CI99+DC99+DE99+CU99+CW99+U99+AI99 -> 1.6154749e+09 | C99: =P99+CN99+R99+AN99+CR99+AP99+DB99+BB99+BD99+CP99+BH99+CT99+BJ99+CZ99+CL99+DD99+DF99+CJ99+CV99+CX99+AJ99+V99 -> 2109 | D99: =O99+BA99+CO99+BG99+BI99+DC99+CU99 -> 7.4819062e+08 | E99: =P99+BB99+CP99+BH99+BJ99+CV99 -> 11 | F99: =CM99+CS99 -> 93068161 | G99: =CN99+CT99 -> 2 | H99: =Q99+CY99+CI99 -> 96787808 | I99: =R99+CZ99+CJ99 -> 3 | J99: =AM99+CQ99+AO99+DA99+U99 -> 2.9601546e+08 | K99: =AN99+CR99+AP99+DB99+V99 -> 2089 | L99: =BC99+CK99+DE99+CW99+AI99 -> 3.8141282e+08 | M99: =BD99+CL99+DF99+CX99+AJ99 -> 4 | O99: =SILVX!B106 -> 5.1512306e+08 | P99: =SILVX!G106 -> 1 | Q99: =SGLIX!B51 -> 84319105 | R99: =SGLIX!G51 -> 1 | U99: =FoF!AD9 -> 6937860.6 | V99: =FoF!AE9 -> 3 | AI99: =HF!B3 -> 3307153.1 | AJ99: =HF!C3 -> 1 | AM99: =Schwab!S94 -> 1.5572013e+08 | AN99: =Schwab!Q94 -> 1564 | AO99: =Fidelity!P99 -> 1.2707086e+08 | AP99: =Fidelity!O99 -> 424 | BA99: ='TFA - Folio'!H104 -> 50139389 | BB99: ='TFA - Folio'!I99 -> 1 | BC99: ='TFA - Folio'!K104 -> 1.0208233e+08 | BD99: ='TFA - Folio'!N104 -> 1 | BG99: =UNC!B62 -> 1.5991655e+08 | BH99: =UNC!C62 -> 1 | BI99: ='Schwab LC'!D59 -> 3649541.2 | BJ99: ='Schwab LC'!E59 -> 2 | CI99: ='NC State'!B32 -> 7270684.1 | CJ99: ='NC State'!C32 -> 1 | CK99: ='Holiday Oil'!G37 -> 22343111 | CL99: ='Holiday Oil'!H37 -> 1 | CM99: =SCLVX!B60 -> 56912012 | CN99: =SCLVX!G60 -> 1 | CO99: =Stifel!B73 -> 6622220.5 | CP99: =Stifel!K73 -> 5 | CQ99: =TDA!O89 -> 6286602.9 | CR99: =TDA!N89 -> 98 | CS99: =UNC!D62 -> 36156149 | CT99: =UNC!E62 -> 1 | CU99: =Asbestos!B26 -> 12739854 | CV99: =Asbestos!C26 -> 1 | CW99: =TUG!H18 -> 2.5368023e+08 | CX99: =TUG!I18 -> 1 | CY99: =Cline!B45 -> 5198019.1 | CZ99: =Cline!C45 -> 1
A100: 44255 | B100: =O100+CM100+Q100+AM100+CQ100+AO100+DA100+BA100+BC100+CO100+BG100+CS100+BI100+CY100+CK100+CI100+DC100+DE100+CU100+CW100+U100+AI100 -> 1.6191368e+09 | C100: =P100+CN100+R100+AN100+CR100+AP100+DB100+BB100+BD100+CP100+BH100+CT100+BJ100+CZ100+CL100+DD100+DF100+CJ100+CV100+CX100+AJ100+V100 -> 2165 | D100: =O100+BA100+CO100+BG100+BI100+DC100+CU100 -> 7.2024415e+08 | E100: =P100+BB100+CP100+BH100+BJ100+CV100 -> 11 | F100: =CM100+CS100 -> 73496741 | G100: =CN100+CT100 -> 2 | H100: =Q100+CY100+CI100 -> 1.0509591e+08 | I100: =R100+CZ100+CJ100 -> 3 | J100: =AM100+CQ100+AO100+DA100+U100 -> 3.3287077e+08 | K100: =AN100+CR100+AP100+DB100+V100 -> 2145 | L100: =BC100+CK100+DE100+CW100+AI100 -> 3.8742927e+08 | M100: =BD100+CL100+DF100+CX100+AJ100 -> 4 | O100: =SILVX!B107 -> 4.8725566e+08 | P100: =SILVX!G107 -> 1 | Q100: =SGLIX!B52 -> 92600703 | R100: =SGLIX!G52 -> 1 | U100: =FoF!AD10 -> 10248955 | V100: =FoF!AE10 -> 3 | AI100: =HF!B4 -> 3723092.3 | AJ100: =HF!C4 -> 1 | AM100: =Schwab!S95 -> 1.8037349e+08 | AN100: =Schwab!Q95 -> 1592 | AO100: =Fidelity!P100 -> 1.3392515e+08 | AP100: =Fidelity!O100 -> 447 | BA100: ='TFA - Folio'!H105 -> 49808912 | BB100: ='TFA - Folio'!I100 -> 1 | BC100: ='TFA - Folio'!K105 -> 98862039 | BD100: ='TFA - Folio'!N105 -> 1 | BG100: =UNC!B63 -> 1.6008748e+08 | BH100: =UNC!C63 -> 1 | BI100: ='Schwab LC'!D60 -> 3652803.5 | BJ100: ='Schwab LC'!E60 -> 2 | CI100: ='NC State'!B33 -> 7286401.4 | CJ100: ='NC State'!C33 -> 1 | CK100: ='Holiday Oil'!G38 -> 22051166 | CL100: ='Holiday Oil'!H38 -> 1 | CM100: =SCLVX!B61 -> 36792127 | CN100: =SCLVX!G61 -> 1 | CO100: =Stifel!B74 -> 6682539 | CP100: =Stifel!K74 -> 5 | CQ100: =TDA!O90 -> 8323170.5 | CR100: =TDA!N90 -> 103 | CS100: =UNC!D63 -> 36704614 | CT100: =UNC!E63 -> 1 | CU100: =Asbestos!B27 -> 12756756 | CV100: =Asbestos!C27 -> 1 | CW100: =TUG!H19 -> 2.6279297e+08 | CX100: =TUG!I19 -> 1 | CY100: =Cline!B46 -> 5208802.6 | CZ100: =Cline!C46 -> 1
A101: 44286 | B101: =O101+CM101+Q101+AM101+CQ101+AO101+AU101+BA101+BC101+CO101+BG101+CS101+BI101+CY101+CK101+CI101+CU101+CW101+U101+AI101+S101 -> 1.7472793e+09 | C101: =P101+CN101+R101+AN101+CR101+AP101+DB101+BB101+BD101+CP101+BH101+CT101+BJ101+CZ101+CL101+DD101+DF101+CJ101+CV101+CX101+AJ101+V101+T101 -> 2277 | D101: =O101+BA101+CO101+BG101+BI101+DC101+CU101 -> 7.3493911e+08 | E101: =P101+BB101+CP101+BH101+BJ101+CV101 -> 11 | F101: =CM101+CS101 -> 74856978 | G101: =CN101+CT101 -> 2 | H101: =Q101+CY101+CI101 -> 1.1002406e+08 | I101: =R101+CZ101+CJ101 -> 3 | J101: =AM101+CQ101+AO101+DA101+U101 -> 3.4101942e+08 | K101: =AN101+CR101+AP101+DB101+V101 -> 2256 | L101: =BC101+CK101+DE101+CW101+AI101+S101 -> 4.8249974e+08 | M101: =BD101+CL101+DF101+CX101+AJ101+T101 -> 5 | O101: =SILVX!B108 -> 4.9462568e+08 | P101: =SILVX!G108 -> 1 | Q101: =SGLIX!B53 -> 97179911 | R101: =SGLIX!G53 -> 1 | S101: =BOGIX!B2 -> 85117891 | T101: =BOGIX!G2 -> 1 | U101: =FoF!AD11 -> 8391573.7 | V101: =FoF!AE11 -> 3 | AI101: =HF!B5 -> 3944018.3 | AJ101: =HF!C5 -> 1 | AM101: =Schwab!S96 -> 1.7188324e+08 | AN101: =Schwab!Q96 -> 1665 | AO101: =Fidelity!P101 -> 1.5301065e+08 | AP101: =Fidelity!O101 -> 484 | AU101: 3939978.5 | AV101: 49 | BA101: ='TFA - Folio'!H106 -> 52695863 | BB101: ='TFA - Folio'!I101 -> 1 | BC101: ='TFA - Folio'!K106 -> 98920231 | BD101: ='TFA - Folio'!N106 -> 1 | BG101: =UNC!B64 -> 1.6396994e+08 | BH101: =UNC!C64 -> 1 | BI101: ='Schwab LC'!D61 -> 3738954.7 | BJ101: ='Schwab LC'!E61 -> 2 | CI101: ='NC State'!B34 -> 7483153.8 | CJ101: ='NC State'!C34 -> 1 | CK101: ='Holiday Oil'!G39 -> 21121008 | CL101: ='Holiday Oil'!H39 -> 1 | CM101: =SCLVX!B62 -> 37752424 | CN101: =SCLVX!G62 -> 1 | CO101: =Stifel!B75 -> 6841327.9 | CP101: =Stifel!K75 -> 5 | CQ101: =TDA!O91 -> 7733949.5 | CR101: =TDA!N91 -> 104 | CS101: =UNC!D64 -> 37104554 | CT101: =UNC!E64 -> 1 | CU101: =Asbestos!B28 -> 13067346 | CV101: =Asbestos!C28 -> 1 | CW101: =TUG!H20 -> 2.733966e+08 | CX101: =TUG!I20 -> 1 | CY101: =Cline!B47 -> 5360998.2 | CZ101: =Cline!C47 -> 1
A102: 44316 | B102: =O102+CM102+Q102+AM102+CQ102+AO102+AU102+BA102+BC102+CO102+BG102+CS102+BI102+CY102+CK102+CI102+CU102+CW102+U102+AI102+S102 -> 1.8216559e+09 | C102: =P102+CN102+R102+AN102+CR102+AP102+DB102+BB102+BD102+CP102+BH102+CT102+BJ102+CZ102+CL102+DD102+DF102+CJ102+CV102+CX102+AJ102+V102+T102 -> 2359 | D102: =O102+BA102+CO102+BG102+BI102+DC102+CU102 -> 7.6625745e+08 | E102: =P102+BB102+CP102+BH102+BJ102+CV102 -> 11 | F102: =CM102+CS102 -> 78503016 | G102: =CN102+CT102 -> 2 | H102: =Q102+CI102 -> 1.1108019e+08 | I102: =R102+CZ102+CJ102 -> 2 | J102: =AM102+CQ102+AO102+DA102+U102 -> 3.5458708e+08 | K102: =AN102+CR102+AP102+DB102+V102 -> 2339 | L102: =BC102+CK102+DE102+CW102+AI102+S102 -> 5.072882e+08 | M102: =BD102+CL102+DF102+CX102+AJ102+T102 -> 5 | O102: =SILVX!B109 -> 5.1532155e+08 | P102: =SILVX!G109 -> 1 | Q102: =SGLIX!B54 -> 1.0329719e+08 | R102: =SGLIX!G54 -> 1 | S102: =BOGIX!B3 -> 86420239 | T102: =BOGIX!G3 -> 1 | U102: =FoF!AD12 -> 9096610 | V102: =FoF!AE12 -> 3 | AI102: =HF!B6 -> 4420027.5 | AJ102: =HF!C6 -> 1 | AM102: =Schwab!S97 -> 1.7815869e+08 | AN102: =Schwab!Q97 -> 1722 | AO102: =Fidelity!P102 -> 1.5975316e+08 | AP102: =Fidelity!O102 -> 507 | AU102: 3939978.5 | AV102: 49 | BA102: ='TFA - Folio'!H107 -> 54222107 | BB102: ='TFA - Folio'!I102 -> 1 | BC102: ='TFA - Folio'!K107 -> 1.0099688e+08 | BD102: ='TFA - Folio'!N107 -> 1 | BG102: =UNC!B65 -> 1.7192491e+08 | BH102: =UNC!C65 -> 1 | BI102: ='Schwab LC'!D62 -> 3909303 | BJ102: ='Schwab LC'!E62 -> 2 | CI102: ='NC State'!B35 -> 7782996.5 | CJ102: ='NC State'!C35 -> 1 | CK102: ='Holiday Oil'!G40 -> 21401744 | CL102: ='Holiday Oil'!H40 -> 1 | CM102: =SCLVX!B63 -> 40464577 | CN102: =SCLVX!G63 -> 1 | CO102: =Stifel!B76 -> 7167241.6 | CP102: =Stifel!K76 -> 5 | CQ102: =TDA!O92 -> 7578616.9 | CR102: =TDA!N92 -> 107 | CS102: =UNC!D65 -> 38038440 | CT102: =UNC!E65 -> 1 | CU102: =Asbestos!B29 -> 13712342 | CV102: =Asbestos!C29 -> 1 | CW102: =TUG!H21 -> 2.9404931e+08 | CX102: =TUG!I21 -> 1
A103: 44347 | B103: =O103+CM103+Q103+AM103+CQ103+AO103+AU103+BA103+BC103+CO103+BG103+CS103+BI103+CY103+CK103+CI103+CU103+CW103+U103+AI103+S103 -> 1.8149149e+09 | C103: =P103+CN103+R103+AN103+CR103+AP103+BB103+BD103+CP103+BH103+CT103+BJ103+CL103+CJ103+CV103+CX103+AJ103+V103+T103 -> 2393 | D103: =O103+BA103+CO103+BG103+BI103+DC103+CU103 -> 7.6011315e+08 | E103: =P103+BB103+CP103+BH103+BJ103+CV103 -> 10 | F103: =CM103+CS103 -> 78934661 | G103: =CN103+CT103 -> 2 | H103: =Q103+CI103 -> 1.1217181e+08 | I103: =R103+CZ103+CJ103 -> 2 | J103: =AM103+CQ103+AO103+DA103+U103 -> 3.5437177e+08 | K103: =AN103+CR103+AP103+DB103+V103 -> 2374 | L103: =BC103+CK103+DE103+CW103+AI103+S103 -> 5.0538351e+08 | M103: =BD103+CL103+DF103+CX103+AJ103+T103 -> 5 | O103: =SILVX!B110 -> 5.0904428e+08 | P103: =SILVX!G110 -> 1 | Q103: =SGLIX!B55 -> 1.0430228e+08 | R103: =SGLIX!G55 -> 1 | S103: =BOGIX!B4 -> 86603054 | T103: =BOGIX!G4 -> 1 | U103: =FoF!AD13 -> 9094614.9 | V103: =FoF!AE13 -> 3 | AI103: =HF!B7 -> 4308010 | AJ103: =HF!C7 -> 1 | AM103: =Schwab!S98 -> 1.7836015e+08 | AN103: =Schwab!Q98 -> 1747 | AO103: =Fidelity!P103 -> 1.592696e+08 | AP103: =Fidelity!O103 -> 514 | AU103: 3939978.5 | AV103: 49 | BA103: ='TFA - Folio'!H108 -> 55237671 | BB103: ='TFA - Folio'!I103 -> 1 | BC103: ='TFA - Folio'!K108 -> 1.0036003e+08 | BD103: ='TFA - Folio'!N108 -> 1 | BG103: =UNC!B66 -> 1.7201486e+08 | BH103: =UNC!C66 -> 1 | BI103: ='Schwab LC'!D63 -> 3913618.8 | BJ103: ='Schwab LC'!E63 -> 2 | CI103: ='NC State'!B36 -> 7869532.9 | CJ103: ='NC State'!C36 -> 1 | CK103: ='Holiday Oil'!G41 -> 21450620 | CL103: ='Holiday Oil'!H41 -> 1 | CM103: =SCLVX!B64 -> 41098027 | CN103: =SCLVX!G64 -> 1 | CO103: =Stifel!B77 -> 6190663.5 | CP103: =Stifel!K77 -> 4 | CQ103: =TDA!O93 -> 7647404.2 | CR103: =TDA!N93 -> 110 | CS103: =UNC!D66 -> 37836634 | CT103: =UNC!E66 -> 1 | CU103: =Asbestos!B30 -> 13712053 | CV103: =Asbestos!C30 -> 1 | CW103: =TUG!H22 -> 2.926618e+08 | CX103: =TUG!I22 -> 1
...

Sheet SILVX
A1: Date | B1: $$$ | C1: Ret % | D1: Ret $$ | E1: Contribution +/- | F1: Total | G1: Accts | H1: SILVX Nav | K1: Avg. Assets
A2: 41060 | B2: 3126485.8 | G2: 1 | J2: 2012 | K2: =AVERAGE(B2:B9) -> 5189635
A3: 41090 | B3: 2325832.7 | G3: 1 | J3: 2013 | K3: =AVERAGE(B10:B21) -> 23557376
A4: 41121 | B4: 3567730.7 | G4: 1 | J4: 2014 | K4: =AVERAGE(B22:B33) -> 56651692
A5: 41152 | B5: 3561857.1 | G5: 1 | J5: 2015 | K5: =AVERAGE(B34:B45) -> 73810982
A6: 41182 | B6: 5001232.2 | G6: 1 | J6: 2016 | K6: =AVERAGE(B46:B57) -> 1.1044701e+08
A7: 41213 | B7: 6130044.1 | G7: 1 | J7: 2017 | K7: =AVERAGE(B58:B69) -> 1.127141e+08
A8: 41243 | B8: 8317344.8 | G8: 1 | J8: 2018
A9: 41274 | B9: 9486552.3 | G9: 1 | J9: 2019
A10: 41305 | B10: 10810338 | C10: 0.048 | D10: =SUM(C10*B9) -> 455354.51 | E10: =B10-(B9+D10) -> 868431.64 | F10: =D10+E10 -> 1323786.1 | G10: 1 | J10: 2020
A11: =AUM!A4 -> 41333 | B11: 11771288 | C11: 0.0384 | D11: =SUM(C11*B10) -> 415117 | E11: =B11-(B10+D11) -> 545832.17 | F11: =D11+E11 -> 960949.17 | G11: 1
A12: =AUM!A5 -> 41364 | B12: 13089271 | C12: 0.0432 | D12: =SUM(C12*B11) -> 508519.63 | E12: =B12-(B11+D12) -> 809463.9 | F12: =D12+E12 -> 1317983.5 | G12: 1
A13: =AUM!A6 -> 41394 | B13: 16958369 | C13: 0.025 | D13: =SUM(C13*B12) -> 327231.78 | E13: =B13-(B12+D13) -> 3541865.6 | F13: =D13+E13 -> 3869097.4 | G13: 1
A14: =AUM!A7 -> 41425 | B14: 17899655 | C14: -0.0135 | D14: =SUM(C14*B13) -> -228937.98 | E14: =B14-(B13+D14) -> 1170224.8 | F14: =D14+E14 -> 941286.84 | G14: 1
A15: =AUM!A8 -> 41455 | B15: 18417136 | C15: 0.0043 | D15: =SUM(C15*B14) -> 76968.518 | E15: =B15-(B14+D15) -> 440512.32 | F15: =D15+E15 -> 517480.84 | G15: 1
A16: =AUM!A9 -> 41486 | B16: 23781673 | C16: 0.0451 | D16: =SUM(C16*B15) -> 830612.84 | E16: =B16-(B15+D16) -> 4533923.5 | F16: =D16+E16 -> 5364536.4 | G16: 1
A17: =AUM!A10 -> 41517 | B17: 25620949 | C17: -0.0358 | D17: =SUM(C17*B16) -> -851383.88 | E17: =B17-(B16+D17) -> 2690660.1 | F17: =D17+E17 -> 1839276.2 | G17: 1
A18: =AUM!A11 -> 41547 | B18: 30750157 | C18: 0.0203 | D18: =SUM(C18*B17) -> 520105.26 | E18: =B18-(B17+D18) -> 4609103.1 | F18: =D18+E18 -> 5129208.4 | G18: 1
A19: =AUM!A12 -> 41578 | B19: 34983487 | C19: 0.0372 | D19: =SUM(C19*B18) -> 1143905.8 | E19: =B19-(B18+D19) -> 3089423.9 | F19: =D19+E19 -> 4233329.7 | G19: 1
A20: =AUM!A13 -> 41608 | B20: 38040703 | C20: 0.0183 | D20: =SUM(C20*B19) -> 640197.81 | E20: =B20-(B19+D20) -> 2417018 | F20: =D20+E20 -> 3057215.8 | G20: 1
A21: =AUM!A14 -> 41639 | B21: 40565492 | C21: 0.0201 | D21: =SUM(C21*B20) -> 764618.12 | E21: =B21-(B20+D21) -> 1760171.2 | F21: =D21+E21 -> 2524789.4 | G21: 1
A22: =AUM!A15 -> 41670 | B22: 44164273 | C22: -0.033 | D22: =SUM(C22*B21) -> -1338661.2 | E22: =B22-(B21+D22) -> 4937441.8 | F22: =D22+E22 -> 3598780.5 | G22: 1
... A33: =AUM!A26 -> 42004 | B33: 67662864 | C33: 0 | D33: =SUM(C33*B32) -> 0 | E33: =B33-(B32+D33) -> 164978.8 | F33: =D33+E33 -> 164978.8 | G33: 1
A34: =AUM!A27 -> 42035 | B34: 66896741 | C34: -0.0121 | D34: =SUM(C34*B33) -> -818720.65 | E34: =B34-(B33+D34) -> 52598.072 | F34: =D34+E34 -> -766122.58 | G34: 1 | H34: 13.84
A35: =AUM!A28 -> 42063 | B35: 69872904 | C35: 0.0303 | D35: =SUM(C35*B34) -> 2026971.3 | E35: =B35-(B34+D35) -> 949191.73 | F35: =D35+E35 -> 2976163 | G35: 1 | H35: 14.26
A36: =AUM!A29 -> 42094 | B36: 71575874 | C36: -0.007 | D36: =SUM(C36*B35) -> -489110.33 | E36: =B36-(B35+D36) -> 2192079.9 | F36: =D36+E36 -> 1702969.6 | G36: 1 | H36: 14.16
A37: =AUM!A30 -> 42124 | B37: 71483082 | C37: -0.0141 | D37: =SUM(C37*B36) -> -1009219.8 | E37: =B37-(B36+D37) -> 916428.2 | F37: =D37+E37 -> -92791.62 | G37: 1 | H37: 13.96
A38: =AUM!A31 -> 42155 | B38: 72089141 | C38: 0.01 | D38: =SUM(C38*B37) -> 714830.82 | E38: =B38-(B37+D38) -> -108772.02 | F38: =D38+E38 -> 606058.8 | G38: 1 | H38: 14.1
A39: 42185 | B39: 71051329 | C39: -0.0191 | D39: =SUM(C39*B38) -> -1376902.6 | E39: =B39-(B38+D39) -> 339090.27 | F39: =D39+E39 -> -1037812.3 | G39: 1 | H39: 13.83
A40: 42216 | B40: 75409202 | C40: 0.0463 | D40: =SUM(C40*B39) -> 3289676.5 | E40: =B40-(B39+D40) -> 1068196.6 | F40: =D40+E40 -> 4357873.2 | G40: 1 | H40: 14.47
A41: 42247 | B41: 72553876 | C41: -0.0477 | D41: =SUM(C41*B40) -> -3597018.9 | E41: =B41-(B40+D41) -> 741692.87 | F41: =D41+E41 -> -2855326.1 | G41: 1 | H41: 13.78
A42: 42277 | B42: 72933072 | C42: 0.0036 | D42: =SUM(C42*B41) -> 261193.95 | E42: =B42-(B41+D42) -> 118002.15 | F42: =D42+E42 -> 379196.1 | G42: 1 | H42: 13.83
A43: 42307 | B43: 81294138 | C43: 0.0578 | D43: =SUM(C43*B42) -> 4215531.6 | E43: =B43-(B42+D43) -> 4145534.5 | F43: =D43+E43 -> 8361066.1 | G43: 1 | H43: 14.63
A44: 42338 | B44: 80390280 | C44: -0.0055 | D44: =SUM(C44*B43) -> -447117.76 | E44: =B44-(B43+D44) -> -456740.43 | F44: =D44+E44 -> -903858.19 | G44: 1 | H44: 14.55
A45: 42369 | B45: 80182147 | C45: -0.0028 | D45: =SUM(C45*B44) -> -225092.78 | E45: =B45-(B44+D45) -> 16959.963 | F45: =D45+E45 -> -208132.82 | G45: 1 | H45: 13.58
A46: 42398 | B46: 79613453 | C46: -0.0251 | D46: =SUM(C46*B45) -> -2012571.9 | E46: =B46-(B45+D46) -> 1443878.4 | F46: =D46+E46 -> -568693.45 | G46: 1 | H46: 13.23
A47: 42429 | B47: 92880465 | C47: 0.0189 | D47: =SUM(C47*B46) -> 1504694.3 | E47: =B47-(B46+D47) -> 11762317 | F47: =D47+E47 -> 13267011 | G47: 1 | H47: 13.49
A48: 42460 | B48: 1.015352e+08 | C48: 0.0608 | D48: =SUM(C48*B47) -> 5647132.3 | E48: =B48-(B47+D48) -> 3007598.4 | F48: =D48+E48 -> 8654730.6 | G48: 1 | H48: 14.3
A49: 42489 | B49: =11507772.06+112941.2+90532889.13 -> 1.021536e+08 | C49: -0.014 | D49: =SUM(C49*B48) -> -1421492.7 | E49: =B49-(B48+D49) -> 2039899.7 | F49: =D49+E49 -> 618407 | G49: 1 | H49: 14.1
A50: 42521 | B50: =17765427.26+171062.43+92065880.89 -> 1.1000237e+08 | C50: 0.0191 | D50: =SUM(C50*B49) -> 1951133.8 | E50: =B50-(B49+D50) -> 5897634.4 | F50: =D50+E50 -> 7848768.2 | G50: 1 | H50: 14.37
A51: 42551 | B51: =18419778.67+200324.02+106300476.3 -> 1.2492058e+08 | C51: 0.0264 | D51: =SUM(C51*B50) -> 2904062.6 | E51: =B51-(B50+D51) -> 12014146 | F51: =D51+E51 -> 14918208 | G51: 1 | H51: 14.75
A52: 42582 | B52: =19357406.31+307272.58+107983525.24 -> 1.276482e+08 | C52: 0.0142 | D52: =SUM(C52*B51) -> 1773872.2 | E52: =B52-(B51+D52) -> 953752.92 | F52: =D52+E52 -> 2727625.1 | G52: 1 | H52: 14.96
A53: 42613 | B53: =108986438.14+372526.65+19278720.21 -> 128637685 | C53: -0.018 | D53: =SUM(C53*B52) -> -2297667.7 | E53: =B53-(B52+D53) -> 3287148.5 | F53: =D53+E53 -> 989480.87 | G53: 1 | H53: 14.69
A54: 42643 | B54: =99306955.45+499909.52+19059537.93 -> 1.188664e+08 | C54: -0.0136 | D54: =SUM(C54*B53) -> -1749472.5 | E54: =B54-(B53+D54) -> -8021809.6 | F54: =D54+E54 -> -9771282.1 | G54: 1 | H54: 14.49
A55: 42674 | B55: =18755802.01+621440.24+90623034.27 -> 1.1000028e+08 | C55: -0.0228 | D55: =SUM(C55*B54) -> -2710154 | E55: =B55-(B54+D55) -> -6155972.4 | F55: =D55+E55 -> -8866126.4 | G55: 1 | H55: 14.16
A56: 42704 | B56: =92751918.23+744014.52+19778568.4 -> 1.132745e+08 | C56: 0.0282 | D56: =SUM(C56*B55) -> 3102007.8 | E56: =B56-(B55+D56) -> 172216.83 | F56: =D56+E56 -> 3274224.6 | G56: 1 | H56: 14.56
A57: 42735 | B57: =95107430.97+792115.42+19931823.15 -> 1.1583137e+08 | C57: 0.0144 | D57: =SUM(C57*B56) -> 1631152.8 | E57: =B57-(B56+D57) -> 925715.57 | F57: =D57+E57 -> 2556868.4 | G57: 1 | H57: 14.4
A58: 42766 | B58: =95640194.61+825180.77+19993008.84 -> 1.1645838e+08 | C58: 0.0014 | D58: =SUM(C58*B57) -> 162163.92 | E58: =B58-(B57+D58) -> 464850.76 | F58: =D58+E58 -> 627014.68 | G58: 1 | H58: 14.42
A59: 42794 | B59: =91523293.61+1025415.21+20655551.16 -> 1.1320426e+08 | C59: 0.0381 | D59: =SUM(C59*B58) -> 4437064.4 | E59: =B59-(B58+D59) -> -7691188.7 | F59: =D59+E59 -> -3254124.2 | G59: 1 | H59: 14.97
A60: 42825 | B60: 1.1258416e+08 | C60: -0.0047 | D60: =SUM(C60*B59) -> -532060.02 | E60: =B60-(B59+D60) -> -88037.808 | F60: =D60+E60 -> -620097.83 | G60: 1 | H60: 14.9
A61: 42855 | B61: =20392828.75+1040284.02+90539676.37 -> 1.1197279e+08 | C61: 0.0067 | D61: =SUM(C61*B60) -> 754313.89 | E61: =B61-(B60+D61) -> -1365686.9 | F61: =D61+E61 -> -611373.01 | G61: 1 | H61: 14.9
A62: 42886 | B62: =20983034.45+1218781.55+91374112.79 -> 1.1357593e+08 | C62: 0.0133 | D62: =SUM(C62*B61) -> 1489238.1 | E62: =B62-(B61+D62) -> 113901.55 | F62: =D62+E62 -> 1603139.7 | G62: 1 | H62: 15.2
A63: 42916 | B63: 1.1428113e+08 | C63: 0.0007 | D63: =SUM(C63*B62) -> 79503.15 | E63: =B63-(B62+D63) -> 625702.72 | F63: =D63+E63 -> 705205.87 | G63: 1 | H63: 15.5
A64: 42947 | B64: =20983034.45+1218781.55+91374112.79 -> 1.1357593e+08 | C64: 0.0145 | D64: =SUM(C64*B63) -> 1657076.5 | E64: =B64-(B63+D64) -> -2362282.3 | F64: =D64+E64 -> -705205.87 | G64: 1 | H64: 15.8
A65: 42978 | B65: =22187245.55+1220421.17+92023612.14 -> 1.1543128e+08 | C65: 0 | D65: =SUM(C65*B64) -> 0 | E65: =B65-(B64+D65) -> 1855350.1 | F65: =D65+E65 -> 1855350.1 | G65: 1 | H65: 15.43
A66: 43008 | B66: =22710175.99+1288274.64+92746633.06 -> 1.1674508e+08 | C66: 0.013 | D66: =SUM(C66*B65) -> 1500606.6 | E66: =B66-(B65+D66) -> -186801.8 | F66: =D66+E66 -> 1313804.8 | G66: 1 | H66: 15.63
A67: 43039 | B67: =22914886.93+1275928.31+92250978.04 -> 1.1644179e+08 | C67: 0.007 | D67: =SUM(C67*B66) -> 817215.59 | E67: =B67-(B66+D67) -> -1120506 | F67: =D67+E67 -> -303290.41 | G67: 1 | H67: 15.74
A68: 43069 | B68: =9028244.41+1425101.41+94376722.62 -> 1.0483007e+08 | C68: 0.0496 | D68: =SUM(C68*B67) -> 5775512.9 | E68: =B68-(B67+D68) -> -17387238 | F68: =D68+E68 -> -11611725 | G68: 1 | H68: 16.52
A69: 43100 | B69: =9073270.06+1457971.43+92937116.72 -> 1.0346836e+08 | C69: 0.0147 | D69: =SUM(C69*B68) -> 1541002 | E69: =B69-(B68+D69) -> -2902712.2 | F69: =D69+E69 -> -1361710.2 | G69: 1 | H69: 15.62
A70: 43131 | B70: 1.0663257e+08 | C70: 0.0487 | D70: =SUM(C70*B69) -> 5038909 | E70: =B70-(B69+D70) -> -1874697.6 | F70: =D70+E70 -> 3164211.5 | G70: 1
A71: 43159 | B71: 1.0156336e+08 | C71: -0.0299 | D71: =SUM(C71*B70) -> -3188313.8 | E71: =B71-(B70+D71) -> -1880894.8 | F71: =D71+E71 -> -5069208.7 | G71: 1
A72: 43190 | B72: 1.3531654e+08 | C72: -0.0088 | D72: =SUM(C72*B71) -> -893757.58 | E72: =B72-(B71+D72) -> 34646932 | F72: =D72+E72 -> 33753175 | G72: 1 | H72: 15.75
A73: 43220 | B73: 2.4396862e+08 | C73: 0.0133 | D73: =SUM(C73*B72) -> 1799709.9 | E73: =B73-(B72+D73) -> 1.0685238e+08 | F73: =D73+E73 -> 1.0865209e+08 | G73: 1
A74: 43251 | B74: 3.8538892e+08 | C74: 0.0226 | D74: =SUM(C74*B73) -> 5513690.9 | E74: =B74-(B73+D74) -> 1.3590661e+08 | F74: =D74+E74 -> 1.414203e+08 | G74: 1
A75: 43281 | B75: 3.9804281e+08 | C75: 0.019 | D75: =SUM(C75*B74) -> 7322389.6 | E75: =B75-(B74+D75) -> 5331496 | F75: =D75+E75 -> 12653886 | G75: 1
A76: 43312 | B76: 4.1417588e+08 | C76: 0.0361 | D76: =SUM(C76*B75) -> 14369345 | E76: =B76-(B75+D76) -> 1763720.3 | F76: =D76+E76 -> 16133066 | G76: 1
A77: 43343 | B77: 4.4738347e+08 | C77: 0.0429 | D77: =SUM(C77*B76) -> 17768145 | E77: =B77-(B76+D77) -> 15439452 | F77: =D77+E77 -> 33207597 | G77: 1
A78: 43373 | B78: 4.5870091e+08 | C78: 0.0022 | D78: =SUM(C78*B77) -> 984243.64 | E78: =B78-(B77+D78) -> 10333195 | F78: =D78+E78 -> 11317439 | G78: 1
A79: 43404 | B79: 4.2727047e+08 | C79: -0.0738 | D79: =SUM(C79*B78) -> -33852127 | E79: =B79-(B78+D79) -> 2421682 | F79: =D79+E79 -> -31430445 | G79: 1
A80: 43434 | B80: 4.4745957e+08 | C80: 0.0156 | D80: =SUM(C80*B79) -> 6665419.3 | E80: =B80-(B79+D80) -> 13523685 | F80: =D80+E80 -> 20189104 | G80: 1
A81: 43465 | B81: 4.0023683e+08 | C81: -0.0762 | D81: =SUM(C81*B80) -> -34096419 | E81: =B81-(B80+D81) -> -13126322 | F81: =D81+E81 -> -47222742 | G81: 1
A82: 43496 | B82: 4.2858197e+08 | C82: 0.0713 | D82: =SUM(C82*B81) -> 28536886 | E82: =B82-(B81+D82) -> -191743.99 | F82: =D82+E82 -> 28345142 | G82: 1
A83: 43524 | B83: 4.4886731e+08 | C83: 0.0429 | D83: =SUM(C83*B82) -> 18386167 | E83: =B83-(B82+D83) -> 1899168.6 | F83: =D83+E83 -> 20285335 | G83: 1
A84: 43555 | B84: 4.6012176e+08 | C84: 0.0155 | D84: =SUM(C84*B83) -> 6957443.2 | E84: =B84-(B83+D84) -> 4297011.8 | F84: =D84+E84 -> 11254455 | G84: 1
... A104: 44165 | B104: 5.2607793e+08 | C104: 0.0703 | D104: =SUM(C104*B103) -> 37182923 | E104: =B104-(B103+D104) -> -40022818 | F104: =D104+E104 -> -2839894.3 | G104: 1
A105: 44196 | B105: 5.4053105e+08 | C105: 0.0376 | D105: =SUM(C105*B104) -> 19780530 | E105: =B105-(B104+D105) -> -5327417.4 | F105: =D105+E105 -> 14453113 | G105: 1 | H105: {=GEOMEAN(1+C94:C105)^12-1} -> 0.11476131
A106: 44227 | B106: 5.1512306e+08 | C106: -0.0311 | D106: =SUM(C106*B105) -> -16810516 | E106: =B106-(B105+D106) -> -8597467.1 | F106: =D106+E106 -> -25407983 | G106: 1
A107: 44255 | B107: 4.8725566e+08 | C107: 0.0015 | D107: =SUM(C107*B106) -> 772684.59 | E107: =B107-(B106+D107) -> -28640084 | F107: =D107+E107 -> -27867399 | G107: 1
A108: 44286 | B108: 4.9462568e+08 | C108: 0.0236 | D108: =SUM(C108*B107) -> 11499234 | E108: =B108-(B107+D108) -> -4129217.1 | F108: =D108+E108 -> 7370016.5 | G108: 1
A109: 44316 | B109: 5.1532155e+08 | C109: 0.0475 | D109: =SUM(C109*B108) -> 23494720 | E109: =B109-(B108+D109) -> -2798853.3 | F109: =D109+E109 -> 20695867 | G109: 1
A110: 44347 | B110: 5.0904428e+08 | C110: 0.0005 | D110: =SUM(C110*B109) -> 257660.77 | E110: =B110-(B109+D110) -> -6534928.8 | F110: =D110+E110 -> -6277268 | G110: 1
A111: 44377 | B111: 5.1673637e+08 | C111: 0.0322 | D111: =SUM(C111*B110) -> 16391226 | E111: =B111-(B110+D111) -> -8699137.6 | F111: =D111+E111 -> 7692088.2 | G111: 1
A112: 44408 | B112: 5.2845125e+08 | C112: 0.0281 | D112: =SUM(C112*B111) -> 14520292 | E112: =B112-(B111+D112) -> -2805410.2 | F112: =D112+E112 -> 11714882 | G112: 1
A113: 44439 | B113: 5.382333e+08 | C113: 0.022 | D113: =SUM(C113*B112) -> 11625927 | E113: =B113-(B112+D113) -> -1843875.3 | F113: =D113+E113 -> 9782052.2 | G113: 1
A114: 44469 | B114: 5.0679373e+08 | C114: -0.059 | D114: =SUM(C114*B113) -> -31755765 | E114: =B114-(B113+D114) -> 316190.26 | F114: =D114+E114 -> -31439574 | G114: 1
A115: 44500 | B115: 5.4601709e+08 | C115: 0.082 | D115: =SUM(C115*B114) -> 41557086 | E115: =B115-(B114+D115) -> -2333721.9 | F115: =D115+E115 -> 39223364 | G115: 1
A116: 44530 | B116: 5.3335247e+08 | C116: -0.0174 | D116: =SUM(C116*B115) -> -9500697.4 | E116: =B116-(B115+D116) -> -3163918.2 | F116: =D116+E116 -> -12664616 | G116: 1
A117: 44561 | B117: 5.5517039e+08 | C117: 0.04 | D117: =SUM(C117*B116) -> 21334099 | E117: =B117-(B116+D117) -> 483821.2 | F117: =D117+E117 -> 21817920 | G117: 1 | H117: {=GEOMEAN(1+C106:C117)^12-1} -> 0.17464979
A118: 44592 | B118: 5.1331478e+08 | C118: -0.0716 | D118: =SUM(C118*B117) -> -39750200 | E118: =B118-(B117+D118) -> -2105409.6 | F118: =D118+E118 -> -41855610 | G118: 1
A119: 44620 | B119: 4.7944561e+08 | C119: -0.0419 | D119: =SUM(C119*B118) -> -21507889 | E119: =B119-(B118+D119) -> -12361284 | F119: =D119+E119 -> -33869174 | G119: 1
A120: 44651 | B120: 4.9905729e+08 | C120: 0.0486 | D120: =SUM(C120*B119) -> 23301057 | E120: =B120-(B119+D120) -> -3689377.9 | F120: =D120+E120 -> 19611679 | G120: 1
A121: 44681 | B121: 4.7469747e+08 | C121: -0.0366 | D121: =SUM(C121*B120) -> -18265497 | E121: =B121-(B120+D121) -> -6094323.7 | F121: =D121+E121 -> -24359821 | G121: 1
A122: 44712 | B122: 4.5928923e+08 | C122: 0.0048 | D122: =SUM(C122*B121) -> 2278547.9 | E122: =B122-(B121+D122) -> -17686783 | F122: =D122+E122 -> -15408235 | G122: 1
A123: 44742 | B123: 4.2239625e+08 | C123: -0.0666 | D123: =SUM(C123*B122) -> -30588663 | E123: =B123-(B122+D123) -> -6304320.4 | F123: =D123+E123 -> -36892983 | G123: 1
A124: 44773 | B124: 4.3820323e+08 | C124: 0.0451 | D124: =SUM(C124*B123) -> 19050071 | E124: =B124-(B123+D124) -> -3243093.4 | F124: =D124+E124 -> 15806978 | G124: 1
A125: 44804 | B125: 4.219009e+08 | C125: -0.0257 | D125: =SUM(C125*B124) -> -11261823 | E125: =B125-(B124+D125) -> -5040505.4 | F125: =D125+E125 -> -16302328 | G125: 1
A126: 44834 | B126: 3.8585216e+08 | C126: -0.07787 | D126: =SUM(C126*B125) -> -32853423 | E126: =B126-(B125+D126) -> -3195313.6 | F126: =D126+E126 -> -36048737 | G126: 1
A127: 44865 | B127: 4.1857827e+08 | C127: 0.1045 | D127: =SUM(C127*B126) -> 40321551 | E127: =B127-(B126+D127) -> -7595447.2 | F127: =D127+E127 -> 32726104 | G127: 1
A128: 44895 | B128: 4.3652516e+08 | C128: 0.049 | D128: =SUM(C128*B127) -> 20510335 | E128: =B128-(B127+D128) -> -2563446 | F128: =D128+E128 -> 17946889 | G128: 1
A129: 44926 | B129: 4.0341206e+08 | C129: -0.0402 | D129: =SUM(C129*B128) -> -17548311 | E129: =B129-(B128+D129) -> -15564784 | F129: =D129+E129 -> -33113095 | G129: 1 | H129: {=GEOMEAN(1+C118:C129)^12-1} -> -0.12001647
...

Sheet SGLIX
A1: Date | B1: $$$ | C1: Ret % | D1: Ret $$ | E1: Contribution +/- | F1: Total | G1: Accts | H1: SGLIX NAV | J1: SGLIX | K1: Avg. Assets
J2: 2012 | K2: 0
A3: 42766 | B3: 26074095 | C3: 0.0489 | D3: =SUM(C3*B3) -> 1275023.3 | E3: =B3-(B2+D3) -> 24799072 | F3: =IF(E3>0,E3,E3+D3) -> 24799072 | G3: 1 | H3: 24.26 | J3: 2013 | K3: 0
A4: 42794 | B4: 24556813 | C4: 0.0367 | D4: =SUM(C4*B3) -> 956919.29 | E4: =B4-(B3+D4) -> -2474201.1 | F4: =IF(E4>0,E4,E4+D4) -> -1517281.8 | G4: 1 | H4: 25.15 | J4: 2014 | K4: 0
A5: 42825 | B5: 23502174 | C5: 0.0151 | D5: =SUM(C5*B4) -> 370807.88 | E5: =B5-(B4+D5) -> -1425447.7 | F5: =IF(E5>0,E5,E5+D5) -> -1054639.8 | G5: 1 | J5: 2015 | K5: 0
A6: 42855 | B6: 22855948 | C6: 0.0098 | D6: =SUM(C6*B5) -> 230321.3 | E6: =B6-(B5+D6) -> -876546.54 | F6: =IF(E6>0,E6,E6+D6) -> -646225.24 | G6: 1 | H6: 25.93 | J6: 2016 | K6: 0
A7: 42886 | B7: 22435710 | C7: 0.0275 | D7: =SUM(C7*B6) -> 628538.58 | E7: =B7-(B6+D7) -> -1048776.7 | F7: =IF(E7>0,E7,E7+D7) -> -420238.08 | G7: 1 | H7: 26.49 | J7: 2017 | K7: =AVERAGE(B3:B14) -> 23077221
A8: 42916 | B8: 22484295 | C8: -0.003 | D8: =SUM(C8*B7) -> -67307.131 | E8: =B8-(B7+D8) -> 115891.73 | F8: =IF(E8>0,E8,E8+D8) -> 115891.73 | G8: 1 | H8: 27.05 | J8: 2018
A9: 42947 | B9: 22532879 | C9: 0.011 | D9: =SUM(C9*B8) -> 247327.24 | E9: =B9-(B8+D9) -> -198742.64 | F9: =IF(E9>0,E9,E9+D9) -> 48584.6 | G9: 1 | H9: 27.61 | J9: 2019
A10: 42978 | B10: 22786318 | C10: 0.0191 | D10: =SUM(C10*B9) -> 430378 | E10: =B10-(B9+D10) -> -176938.97 | F10: =IF(E10>0,E10,E10+D10) -> 253439.03 | G10: 1 | H10: 27.21 | J10: 2020
A11: 43008 | B11: 22416582 | C11: 0.0129 | D11: =SUM(C11*B10) -> 293943.51 | E11: =B11-(B10+D11) -> -663679.78 | F11: =IF(E11>0,E11,E11+D11) -> -369736.27 | G11: 1 | H11: 27.56
A12: 43039 | B12: 22155044 | C12: 0.0134 | D12: =SUM(C12*B11) -> 300382.2 | E12: =B12-(B11+D12) -> -561920.47 | F12: =IF(E12>0,E12,E12+D12) -> -261538.27 | G12: 1 | H12: 27.93
A13: 43069 | B13: 22545615 | C13: 0.024 | D13: =SUM(C13*B12) -> 531721.05 | E13: =B13-(B12+D13) -> -141150.18 | F13: =IF(E13>0,E13,E13+D13) -> 390570.87 | G13: 1 | H13: 28.6
A14: 43100 | B14: =22581175.32 -> 22581175 | C14: 0.0077 | D14: =SUM(C14*B13) -> 173601.23 | E14: =B14-(B13+D14) -> -138040.66 | F14: =IF(E14>0,E14,E14+D14) -> 35560.57 | G14: 1 | H14: 29.27
A15: 43131 | B15: 22567923 | C15: 0.0399 | D15: =SUM(C15*B14) -> 900988.9 | E15: =B15-(B14+D15) -> -914241.34 | F15: =IF(E15>0,E15,E15+D15) -> -13252.44 | G15: 1
A16: 43159 | B16: 21278277 | C16: -0.0374 | D16: =SUM(C16*B15) -> -844040.32 | E16: =B16-(B15+D16) -> -445605.57 | F16: =IF(E16>0,E16,E16+D16) -> -1289645.9 | G16: 1
A17: 43190 | B17: 20822421 | C17: -0.0042 | D17: =SUM(C17*B16) -> -89368.763 | E17: =B17-(B16+D17) -> -366487.56 | F17: =IF(E17>0,E17,E17+D17) -> -455856.32 | G17: 1 | H17: 28.73
A18: 43220 | B18: 20159723 | C18: -0.009 | D18: =SUM(C18*B17) -> -187401.79 | E18: =B18-(B17+D18) -> -475295.93 | F18: =IF(E18>0,E18,E18+D18) -> -662697.72 | G18: 1
A19: 43251 | B19: 19672503 | C19: 0.0126 | D19: =SUM(C19*B18) -> 254012.51 | E19: =B19-(B18+D19) -> -741232.86 | F19: =IF(E19>0,E19,E19+D19) -> -487220.35 | G19: 1
A20: 43281 | B20: 19437260 | C20: -0.0007 | D20: =SUM(C20*B19) -> -13770.752 | E20: =B20-(B19+D20) -> -221471.8 | F20: =IF(E20>0,E20,E20+D20) -> -235242.55 | G20: 1
A21: 43312 | B21: 19910036 | C21: 0.0364 | D21: =SUM(C21*B20) -> 707516.27 | E21: =B21-(B20+D21) -> -234740.4 | F21: =IF(E21>0,E21,E21+D21) -> 472775.87 | G21: 1
A22: 43343 | B22: 19561940 | C22: 0.0147 | D22: =SUM(C22*B21) -> 292677.53 | E22: =B22-(B21+D22) -> -640773.67 | F22: =IF(E22>0,E22,E22+D22) -> -348096.14 | G22: 1
A23: 43373 | B23: 19452300 | C23: 0.0142 | D23: =SUM(C23*B22) -> 277779.54 | E23: =B23-(B22+D23) -> -387419.27 | F23: =IF(E23>0,E23,E23+D23) -> -109639.73 | G23: 1
A24: 43404 | B24: 18322540 | C24: -0.0576 | D24: =SUM(C24*B23) -> -1120452.5 | E24: =B24-(B23+D24) -> -9307.7671 | F24: =IF(E24>0,E24,E24+D24) -> -1129760.3 | G24: 1
A25: 43434 | B25: 19092665 | C25: 0.0383 | D25: =SUM(C25*B24) -> 701753.27 | E25: =B25-(B24+D25) -> 68371.976 | F25: =IF(E25>0,E25,E25+D25) -> 68371.976 | G25: 1
A26: 43465 | B26: 17632438 | C26: -0.0688 | D26: =SUM(C26*B25) -> -1313575.4 | E26: =B26-(B25+D26) -> -146651.86 | F26: =IF(E26>0,E26,E26+D26) -> -1460227.2 | G26: 1
A27: 43496 | B27: 18474074 | C27: 0.0554 | D27: =SUM(C27*B26) -> 976837.06 | E27: =B27-(B26+D27) -> -135200.39 | F27: =IF(E27>0,E27,E27+D27) -> 841636.67 | G27: 1
A28: 43524 | B28: 19109488 | C28: 0.0391 | D28: =SUM(C28*B27) -> 722336.31 | E28: =B28-(B27+D28) -> -86922.473 | F28: =IF(E28>0,E28,E28+D28) -> 635413.84 | G28: 1
A29: 43555 | B29: 19789283 | C29: 0.0175 | D29: =SUM(C29*B28) -> 334416.05 | E29: =B29-(B28+D29) -> 345378.84 | F29: =IF(E29>0,E29,E29+D29) -> 345378.84 | G29: 1
... A104: 45838 | B104: 95504246 | C104: 0.0105 | D104: =SUM(C104*B103) -> 998130.33 | E104: =B104-(B103+D104) -> -553916.15 | F104: =IF(E104>0,E104,E104+D104) -> 444214.18 | G104: 1
B106: =B104-B101 -> 2159767.9
B107: =B104-B98 -> -8389674.3

Sheet BOGIX
A1: Date | B1: $$$ | C1: Ret % | D1: Ret $$ | E1: Contribution +/- | F1: Total | G1: Accts
A2: 44286 | B2: 85117891 | C2: 0.0214 | G2: 1
A3: 44316 | B3: 86420239 | C3: 0.0244 | D3: =SUM(C3*B2) -> 2076876.5 | E3: =B3-(B2+D3) -> -774529.21 | F3: =IF(E3>0,E3,E3+D3) -> 1302347.3 | G3: 1
A4: 44347 | B4: 86603054 | C4: 0.0153 | D4: =SUM(C4*B3) -> 1322229.7 | E4: =B4-(B3+D4) -> -1139414.6 | F4: =IF(E4>0,E4,E4+D4) -> 182815.03 | G4: 1
A5: 44377 | B5: 86616881 | C5: 0.0107 | D5: =SUM(C5*B4) -> 926652.67 | E5: =B5-(B4+D5) -> -912825.76 | F5: =IF(E5>0,E5,E5+D5) -> 13826.91 | G5: 1
A6: 44408 | B6: 97188135 | C6: -0.0197 | D6: =SUM(C6*B5) -> -1706352.5 | E6: =B6-(B5+D6) -> 12277607 | F6: =IF(E6>0,E6,E6+D6) -> 12277607 | G6: 1
A7: 44439 | B7: 97514328 | C7: -0.0036 | D7: =SUM(C7*B6) -> -349877.29 | E7: =B7-(B6+D7) -> 676070.02 | F7: =IF(E7>0,E7,E7+D7) -> 676070.02 | G7: 1
A8: 44469 | B8: 95675494 | C8: -0.0264 | D8: =SUM(C8*B7) -> -2574378.3 | E8: =B8-(B7+D8) -> 735544.54 | F8: =IF(E8>0,E8,E8+D8) -> 735544.54 | G8: 1
A9: 44500 | B9: 97868978 | C9: 0.0303 | D9: =SUM(C9*B8) -> 2898967.5 | E9: =B9-(B8+D9) -> -705483.21 | F9: =IF(E9>0,E9,E9+D9) -> 2193484.3 | G9: 1
A10: 44530 | B10: 92770074 | C10: -0.0441 | D10: =SUM(C10*B9) -> -4316021.9 | E10: =B10-(B9+D10) -> -782882.57 | F10: =IF(E10>0,E10,E10+D10) -> -5098904.5 | G10: 1
A11: 44561 | B11: 98433397 | C11: 0.0516 | D11: =SUM(C11*B10) -> 4786935.8 | E11: =B11-(B10+D11) -> 876386.85 | F11: =IF(E11>0,E11,E11+D11) -> 876386.85 | G11: 1
A12: 44592 | B12: 91685412 | C12: -0.0703 | D12: =SUM(C12*B11) -> -6919867.8 | E12: =B12-(B11+D12) -> 171882.99 | F12: =IF(E12>0,E12,E12+D12) -> 171882.99 | G12: 1
A13: 44620 | B13: 92340241 | C13: 0.0079 | D13: =SUM(C13*B12) -> 724314.75 | E13: =B13-(B12+D13) -> -69485.213 | F13: =IF(E13>0,E13,E13+D13) -> 654829.54 | G13: 1
A14: 44651 | B14: 94464974 | C14: 0.0007 | D14: =SUM(C14*B13) -> 64638.169 | E14: =B14-(B13+D14) -> 2060094.9 | F14: =IF(E14>0,E14,E14+D14) -> 2060094.9 | G14: 1
... A53: 45838 | B53: 1.1195512e+08 | C53: 0.04 | D53: =SUM(C53*B52) -> 4309629.3 | E53: =B53-(B52+D53) -> -95239.332 | F53: =IF(E53>0,E53,E53+D53) -> 4214389.9 | G53: 1
B55: =B53-B50 -> 6889851.7
B56: =B53-B47 -> -10346092

Sheet FoF
B1: SGPKX | C1: SILVX | D1: SCLVX | E1: SGLIX | F1: BOGIX | G1: DYTA | H1: SGLC | I1: GINX | J1: USDX | K1: QXQ | L1: SGPGX | M1: SILVX | N1: SCLVX | O1: SGLIX | P1: BOGIX | Q1: DYTA | R1: SGLC | S1: GINX | T1: USDX | U1: SGCIX | V1: SILVX | W1: SCLVX | X1: SGLIX | Y1: BOGIX | Z1: DYTA | AA1: SGLC | AB1: Total FoF | AC1: Total SGI Funds | AD1: Total Net SGI Funds | AE1: Accts
A2: 44012 | B2: 5243507.9 | C2: 1362773.2 | D2: 1469657.7 | E2: 1449838.3 | L2: 3665913.1 | M2: 653372.63 | N2: 515529.78 | O2: 729663.35 | U2: 1185811.9 | V2: 77558.35 | W2: 31207.12 | AB2: =B2+L2+U2 -> 10095233 | AC2: =C2+D2+E2+M2+N2+O2+V2+W2 -> 6289600.5 | AD2: =AB2-AC2 -> 3805632.4 | AE2: =COUNT(B2,L2,U2) -> 3
A3: 44043 | B3: 6430391.7 | C3: 1694414.8 | D3: 1795688.9 | E3: 1783764.4 | L3: 5161737 | M3: 930729.03 | N3: 722132.57 | O3: 1029667 | U3: 1250974.7 | V3: 82631.649 | W3: 32718.909 | AB3: =B3+L3+U3 -> 12843103 | AC3: =C3+D3+E3+M3+N3+O3+V3+W3 -> 8071747.2 | AD3: =AB3-AC3 -> 4771356.2 | AE3: =COUNT(B3,L3,U3) -> 3
A4: 44074 | B4: 7260919.2 | C4: 1913578.6 | D4: 1988481 | E4: 2043807.3 | L4: 6401093.8 | M4: 1161698 | N4: 866569.2 | O4: 1306141 | U4: 640961.44 | V4: 42588.346 | W4: 16440.153 | AB4: =B4+L4+U4 -> 14302974 | AC4: =C4+D4+E4+M4+N4+O4+V4+W4 -> 9339303.6 | AD4: =AB4-AC4 -> 4963670.9 | AE4: =COUNT(B4,L4,U4) -> 3
A5: 44104 | B5: 7331031.6 | C5: 1924541 | D5: 2036376.6 | E5: 2030019.6 | L5: 7026846.9 | M5: 1256263.1 | N5: 973394.07 | O5: 1392519.8 | U5: 926236.68 | V5: 60172.49 | W5: 23853.49 | AB5: =B5+L5+U5 -> 15284115 | AC5: =C5+D5+E5+M5+N5+O5+V5+W5 -> 9697140.1 | AD5: =AB5-AC5 -> 5586975.1 | AE5: =COUNT(B5,L5,U5) -> 3
A6: 44135 | B6: 7304706.6 | C6: 1885078.8 | D6: 2063724.6 | E6: 1966067 | L6: 7138324.3 | M6: 1240070.7 | N6: 988286.21 | O6: 1386732.3 | U6: 1366741.2 | V6: 84400.66 | W6: 34307.53 | AB6: =B6+L6+U6 -> 15809772 | AC6: =C6+D6+E6+M6+N6+O6+V6+W6 -> 9648667.7 | AD6: =AB6-AC6 -> 6161104.4 | AE6: =COUNT(B6,L6,U6) -> 3
A7: 44165 | B7: 7204151.6 | C7: 1893515.8 | D7: 1935551.4 | E7: 2047175.6 | L7: 7805988.9 | M7: 1335349.9 | N7: 1030266.5 | O7: 1488754.2 | U7: 1418227.7 | V7: 90335.44 | W7: 35986.19 | AB7: =B7+L7+U7 -> 16428368 | AC7: =C7+D7+E7+M7+N7+O7+V7+W7 -> 9856935.1 | AD7: =AB7-AC7 -> 6571433 | AE7: =COUNT(B7,L7,U7) -> 3
A8: 44196 | B8: 8544130.6 | C8: 2206942.6 | D8: 2336271.7 | E8: 2362829.1 | L8: 8614549.3 | M8: 1534414.6 | N8: 1189503.2 | O8: 1726295.2 | U8: 1344354.6 | V8: 86831.25 | W8: 34332.83 | AB8: =B8+L8+U8 -> 18503035 | AC8: =C8+D8+E8+M8+N8+O8+V8+W8 -> 11477420 | AD8: =AB8-AC8 -> 7025614.1 | AE8: =COUNT(B8,L8,U8) -> 3
A9: 44227 | B9: 8619101 | C9: 2246121.9 | D9: 2410294.5 | E9: 2412384.5 | L9: 8111499.6 | M9: 1425043.1 | N9: 1126825.1 | O9: 1615473 | U9: 1584122.6 | V9: 100688.21 | W9: 40032.2 | AB9: =B9+L9+U9 -> 18314723 | AC9: =C9+D9+E9+M9+N9+O9+V9+W9 -> 11376863 | AD9: =AB9-AC9 -> 6937860.6 | AE9: =COUNT(B9,L9,U9) -> 3
A10: 44255 | B10: 9141695.2 | C10: 1353591.7 | D10: 989603.13 | E10: 2713415.9 | L10: 8473254.7 | M10: 1026227.9 | N10: 617619.86 | O10: 2037470.7 | U10: 1510702.9 | V10: 65514.62 | W10: 14651.07 | X10: 58602.48 | AB10: =B10+L10+U10 -> 19125653 | AC10: =C10+D10+E10+M10+N10+O10+V10+W10+X10 -> 8876697.4 | AD10: =AB10-AC10 -> 10248955 | AE10: =COUNT(B10,L10,U10) -> 3
A11: 44286 | B11: 10276972 | C11: 1539766 | D11: 1120731.1 | E11: 3065599.7 | F11: 1656309.7 | L11: 8696344.2 | M11: 1060929.9 | N11: 623642.75 | O11: 2080365.5 | P11: 522477.8 | U11: 1203612.8 | V11: 55159.95 | W11: 12105.49 | X11: 48266.96 | AB11: =B11+L11+U11 -> 20176929 | AC11: =C11+D11+E11+F11+M11+N11+O11+P11+V11+W11+X11 -> 11785355 | AD11: =AB11-AC11 -> 8391573.7 | AE11: =COUNT(B11,L11,U11) -> 3
A12: 44316 | B12: 11040922 | C12: 1654404.2 | D12: 1212905.3 | E12: 3314103 | F12: 1757284.9 | L12: 9373686.5 | M12: 1121181.7 | N12: 677462.21 | O12: 2222109 | P12: 556752.59 | U12: 1323153.7 | V12: 59129.874 | W12: 13165.306 | X12: 52653.756 | AB12: =B12+L12+U12 -> 21737762 | AC12: =C12+D12+E12+F12+M12+N12+O12+P12+V12+W12+X12 -> 12641152 | AD12: =AB12-AC12 -> 9096610 | AE12: =COUNT(B12,L12,U12) -> 3
A13: 44347 | B13: 10124497 | C13: 1825297.4 | D13: 1113878.5 | E13: 3044178.5 | F13: 1614484.7 | L13: 10519326 | M13: 1263361.4 | N13: 762523.67 | O13: 2501914.4 | P13: 628870.99 | U13: 1331510.5 | V13: 59864.574 | W13: 13108.851 | X13: 53235.907 | AB13: =B13+L13+U13 -> 21975334 | AC13: =C13+D13+E13+F13+M13+N13+O13+P13+V13+W13+X13 -> 12880719 | AD13: =AB13-AC13 -> 9094614.9 | AE13: =COUNT(B13,L13,U13) -> 3
A14: 44377 | B14: 10400682 | C14: 1893872.5 | D14: 1125890.6 | E14: 3096158.2 | F14: 1647734.6 | L14: 10798986 | M14: 1311288.7 | N14: 782327.21 | O14: 2565593 | P14: 655967.3 | U14: 1360338.8 | V14: 61794.85 | W14: 13131.39 | X14: 54145.03 | AB14: =B14+L14+U14 -> 22560006 | AC14: =C14+D14+E14+F14+M14+N14+O14+P14+V14+W14+X14 -> 13207903 | AD14: =AB14-AC14 -> 9352103 | AE14: =COUNT(B14,L14,U14) -> 3
A15: 44408 | B15: 11061990 | C15: 1993064.5 | D15: 675341.23 | E15: 3304396.9 | F15: 2335345.5 | L15: 10745081 | M15: 1294526 | N15: 433960.01 | O15: 2444869.4 | P15: 997235.38 | U15: 1282966.3 | V15: 58114.32 | W15: 0 | X15: 51333.92 | Y15: 12742.41 | AB15: =B15+L15+U15 -> 23090037 | AC15: =C15+D15+E15+F15+M15+N15+O15+P15+V15+W15+X15+Y15 -> 13600930 | AD15: =AB15-AC15 -> 9489107.2 | AE15: =COUNT(B15,L15,U15) -> 3
A16: 44439 | B16: 10960830 | C16: 1969949 | D16: 659773.57 | E16: 3286721.6 | F16: 2304649.1 | L16: 10826797 | M16: 1311872.4 | N16: 436894.65 | O16: 2459759.2 | P16: 1022574.5 | U16: 1408210.9 | V16: 64708.25 | W16: 0 | X16: 56913.15 | Y16: 14581.07 | AB16: =B16+L16+U16 -> 23195838 | AC16: =C16+D16+E16+F16+M16+N16+O16+P16+V16+W16+X16+Y16 -> 13588396 | AD16: =AB16-AC16 -> 9607441.5 | AE16: =COUNT(B16,L16,U16) -> 3
A17: 44469 | B17: 11087050 | C17: 1970257 | D17: 671477.41 | E17: 3313336 | F17: 2380178.4 | L17: 10626489 | M17: 1261188.9 | N17: 431235.67 | O17: 2411288.9 | P17: 1005570.9 | U17: 1311339.3 | V17: 57310.02 | W17: 0 | X17: 51654.5 | Y17: 13226.85 | AB17: =B17+L17+U17 -> 23024878 | AC17: =C17+D17+E17+F17+M17+N17+O17+P17+V17+W17+X17+Y17 -> 13566725 | AD17: =AB17-AC17 -> 9458152.8 | AE17: =COUNT(B17,L17,U17) -> 3
A18: 44500 | B18: 12180601 | C18: 2208110.4 | D18: 728146.89 | E18: 3669031.1 | F18: 2534513 | L18: 11307250 | M18: 1364183.2 | N18: 449535.42 | O18: 2576950.2 | P18: 1033323.6 | U18: 1344280.7 | V18: 62455.91 | W18: 0 | X18: 54423.79 | Y18: 13627.67 | AB18: =B18+L18+U18 -> 24832132 | AC18: =C18+D18+E18+F18+M18+N18+O18+P18+V18+W18+X18+Y18 -> 14694301 | AD18: =AB18-AC18 -> 10137831 | AE18: =COUNT(B18,L18,U18) -> 3
A19: 44530 | B19: 11478437 | C19: 2125484.5 | D19: 704409.88 | E19: 3553492.5 | F19: 2448169.2 | L19: 11377837 | M19: 1432655.2 | N19: 475071.64 | O19: 2723871.8 | P19: 1090552.7 | U19: 1345512.7 | V19: 58520.18 | W19: 0 | X19: 52082.54 | Y19: 13026.45 | AB19: =B19+L19+U19 -> 24201787 | AC19: =C19+D19+E19+F19+M19+N19+O19+P19+V19+W19+X19+Y19 -> 14677337 | AD19: =AB19-AC19 -> 9524450 | AE19: =COUNT(B19,L19,U19) -> 3
A20: 44561 | B20: 13159973 | C20: 2402335.1 | D20: 804201.74 | E20: 3995142.2 | F20: 2811758.6 | L20: 12634564 | M20: 1531414.2 | N20: 517972.09 | O20: 2893751.4 | P20: 1202690.7 | U20: 13237.54 | V20: 0 | W20: 0 | X20: 0 | Y20: 0 | AB20: =B20+L20+U20 -> 25807775 | AC20: =C20+D20+E20+F20+M20+N20+O20+P20+V20+W20+X20+Y20 -> 16159266 | AD20: =AB20-AC20 -> 9648508.5 | AE20: =COUNT(B20,L20,U20) -> 3
A21: 44592 | B21: 13344166 | C21: 2379704.6 | D21: 780220.14 | E21: 3990217 | F21: 2789655.5 | L21: 12153946 | M21: 1464276 | N21: 482683.47 | O21: 2791437.8 | P21: 1133521.8 | U21: 10770.46 | V21: 0 | W21: 0 | X21: 0 | Y21: 0 | AB21: =B21+L21+U21 -> 25508882 | AC21: =C21+D21+E21+F21+M21+N21+O21+P21+V21+W21+X21+Y21 -> 15811716 | AD21: =AB21-AC21 -> 9697165.8 | AE21: 3
A22: 44620 | B22: 13418856 | C22: 2329001.1 | D22: 797625.65 | E22: 3915980.8 | F22: 2833012.7 | L22: 11776685 | M22: 1368688.5 | N22: 468351.65 | O22: 2616612 | P22: 1098964.6 | U22: 9967.72 | V22: 0 | W22: 0 | X22: 0 | Y22: 0 | AB22: =B22+L22+U22 -> 25205508 | AC22: =C22+D22+E22+F22+M22+N22+O22+P22+V22+W22+X22+Y22 -> 15428237 | AD22: =AB22-AC22 -> 9777271.1 | AE22: 3
A23: 44651 | B23: 15491037 | C23: 2793083.4 | D23: 924767.19 | E23: 4624810 | F23: 3193182.5 | L23: 12634390 | M23: 1567822.3 | N23: 507659.7 | O23: 2915679.4 | P23: 1160162.8 | U23: 9875.42 | V23: 0 | W23: 0 | X23: 0 | Y23: 0 | AB23: =B23+L23+U23 -> 28135302 | AC23: =C23+D23+E23+F23+M23+N23+O23+P23+V23+W23+X23+Y23 -> 17687167 | AD23: =AB23-AC23 -> 10448135 | AE23: 3
A24: 44681 | B24: 13145978 | C24: 2363591.9 | D24: 785959.38 | E24: 3942227.9 | F24: 2782611.6 | L24: 12451107 | M24: 1489943.5 | N24: 498461.72 | O24: 2831739.3 | P24: 1160946.1 | U24: 6850.25 | V24: 0 | W24: 0 | X24: 0 | Y24: 0 | AB24: =B24+L24+U24 -> 25603935 | AC24: =C24+D24+E24+F24+M24+N24+O24+P24+V24+W24+X24+Y24 -> 15855481 | AD24: =AB24-AC24 -> 9748454.1 | AE24: 3
A25: 44712 | B25: 14102827 | C25: 2507634.5 | D25: 839762.75 | E25: 4200250.4 | F25: 3018715.5 | L25: 12913597 | M25: 1552895.4 | N25: 518478.03 | O25: 2959437.3 | P25: 1235562.3 | U25: 6843.86 | V25: 0 | W25: 0 | X25: 0 | Y25: 0 | AB25: =B25+L25+U25 -> 27023268 | AC25: =C25+D25+E25+F25+M25+N25+O25+P25+V25+W25+X25+Y25 -> 16832736 | AD25: =AB25-AC25 -> 10190532 | AE25: 3
A26: 44742 | B26: 13459718 | C26: 2441852.3 | D26: 827936.23 | E26: 4036386.8 | F26: 2860744.7 | L26: 13221560 | M26: 1582790.7 | N26: 536731.87 | O26: 2977229.4 | P26: 1226333.8 | U26: 0 | V26: 0 | W26: 0 | X26: 0 | Y26: 0 | AB26: =B26+L26+U26 -> 26681278 | AC26: =C26+D26+E26+F26+M26+N26+O26+P26+V26+W26+X26+Y26 -> 16490006 | AD26: =AB26-AC26 -> 10191272 | AE26: 2
A27: 44773 | B27: 14767675 | C27: 2742185.9 | D27: 909333.47 | E27: 4569269.6 | F27: 3211882.2 | L27: 14931989 | M27: 1824701.2 | N27: 602391.27 | O27: 3459367.3 | P27: 1424204.2 | U27: 0 | V27: 0 | W27: 0 | X27: 0 | Y27: 0 | AB27: =B27+L27+U27 -> 29699664 | AC27: =C27+D27+E27+F27+M27+N27+O27+P27+V27+W27+X27+Y27 -> 18743335 | AD27: =AB27-AC27 -> 10956328 | AE27: 2
A28: 44804 | B28: 12994591 | C28: 2345237.8 | D28: 777911.64 | E28: 3897027.2 | F28: 2705490.7 | L28: 15491379 | M28: 1805254.2 | N28: 598995.11 | O28: 3413463.3 | P28: 1386196.5 | U28: 0 | V28: 0 | W28: 0 | X28: 0 | Y28: 0 | AB28: =B28+L28+U28 -> 28485970 | AC28: =C28+D28+E28+F28+M28+N28+O28+P28+V28+W28+X28+Y28 -> 16929576 | AD28: =AB28-AC28 -> 11556394 | AE28: 2
A29: 44834 | B29: 12042264 | C29: 2162611.4 | D29: 723430.24 | E29: 3592645.4 | F29: 2450095.8 | L29: 15189762 | M29: 1762628.1 | N29: 598970.28 | O29: 3372240 | P29: 1364220.1 | U29: 0 | V29: 0 | W29: 0 | X29: 0 | Y29: 0 | AB29: =B29+L29+U29 -> 27232026 | AC29: =C29+D29+E29+F29+M29+N29+O29+P29+V29+W29+X29+Y29 -> 16026841 | AD29: =AB29-AC29 -> 11205185 | AE29: 2
A30: 44865 | B30: 13258536 | C30: 2413817.7 | D30: 797911.14 | E30: 3937638 | F30: 2783284 | L30: 16244597 | M30: 2003324.1 | N30: 660637.39 | O30: 3717999 | P30: 1526301.6 | U30: 0 | V30: 0 | W30: 0 | X30: 0 | Y30: 0 | AB30: =B30+L30+U30 -> 29503133 | AC30: =C30+D30+E30+F30+M30+N30+O30+P30+V30+W30+X30+Y30 -> 17840913 | AD30: =AB30-AC30 -> 11662220 | AE30: 2
A31: 44895 | B31: 13876594 | C31: 2531985.9 | D31: 822738.11 | E31: 4181178.4 | F31: 2868973.6 | L31: 17219167 | M31: 2101396.6 | N31: 681193.09 | O31: 3947954.9 | P31: 1573292.2 | U31: 0 | V31: 0 | W31: 0 | X31: 0 | Y31: 0 | AB31: =B31+L31+U31 -> 31095761 | AC31: =C31+D31+E31+F31+M31+N31+O31+P31+V31+W31+X31+Y31 -> 18708713 | AD31: =AB31-AC31 -> 12387048 | AE31: 2
A32: 44926 | B32: 13290036 | C32: 2430233.3 | D32: 775366.07 | E32: 3968905.4 | F32: 2689971.4 | L32: 17128175 | M32: 2016948 | N32: 666213.82 | O32: 3794085.4 | P32: 1544028.6 | U32: 0 | V32: 0 | W32: 0 | X32: 0 | Y32: 0 | AB32: =B32+L32+U32 -> 30418211 | AC32: =C32+D32+E32+F32+M32+N32+O32+P32+V32+W32+X32+Y32 -> 17885752 | AD32: =AB32-AC32 -> 12532459 | AE32: 2
... A35: 45016 | B35: 14832909 | C35: 2657788.5 | D35: 871628.58 | E35: 4445695.7 | F35: 3073202 | L35: 19427289 | M35: 2405967.4 | N35: 798984.61 | O35: 4529628.2 | P35: 1864862.1 | U35: 0 | V35: 0 | W35: 0 | X35: 0 | Y35: 0 | AB35: =B35+L35+U35 -> 34260198 | AC35: =C35+D35+E35+F35+M35+N35+O35+P35+V35+W35+X35+Y35 -> 20647757 | AD35: =AB35-AC35 -> 13612441 | AE35: 2
A36: 45046 | B36: 15416295 | C36: 2792491.6 | D36: 922287.69 | E36: 4654730.4 | F36: 3243409.6 | G36: 1547515.2 | H36: 1253266.7 | L36: 19749388 | M36: 2399907.3 | N36: 792617.05 | O36: 4550823.3 | P36: 1841793.2 | Q36: 3591364.8 | R36: 1918894.6 | U36: 0 | V36: 0 | W36: 0 | X36: 0 | Y36: 0 | Z36: 0 | AA36: 0 | AB36: =B36+L36+U36 -> 35165683 | AC36: =C36+D36+E36+F36+M36+N36+O36+P36+V36+W36+X36+Y36+G36+H36+Q36+R36+Z36+AA36 -> 29509102 | AD36: =AB36-AC36 -> 5656581.1 | AE36: 2
A37: 45077 | B37: 15670973 | C37: 2793160.7 | D37: 928090.07 | E37: 4620484.1 | F37: 3294819.1 | G37: 1578533.1 | H37: 1273395.2 | L37: 19961629 | M37: 2331029.9 | N37: 770599.91 | O37: 4426198.3 | P37: 1799112.3 | Q37: 3555225.3 | R37: 1913710.4 | U37: 0 | V37: 0 | W37: 0 | X37: 0 | Y37: 0 | Z37: 0 | AA37: 0 | AB37: =B37+L37+U37 -> 35632602 | AC37: =C37+D37+E37+F37+M37+N37+O37+P37+V37+W37+X37+Y37+G37+H37+Q37+R37+Z37+AA37 -> 29284358 | AD37: =AB37-AC37 -> 6348243.3 | AE37: 2
A38: 45107 | B38: 16617639 | C38: 2930715 | D38: 984545.32 | E38: 4820523.2 | F38: 3652519.6 | G38: 1628138.1 | H38: 1348631 | L38: 19270772 | M38: 2317478.7 | N38: 770109.03 | O38: 4350540.1 | P38: 1798579.9 | Q38: 3449533.1 | R38: 1827274.6 | U38: 0 | V38: 0 | W38: 0 | X38: 0 | Y38: 0 | Z38: 0 | AA38: 0 | AB38: =B38+L38+U38 -> 35888411 | AC38: =C38+D38+E38+F38+M38+N38+O38+P38+V38+W38+X38+Y38+G38+H38+Q38+R38+Z38+AA38 -> 29878588 | AD38: =AB38-AC38 -> 6009823.8 | AE38: 2
A39: 45138 | B39: 17218251 | C39: 2977645.2 | D39: 1017905.2 | E39: 4872281.6 | F39: 3814147.2 | G39: 1669168.4 | H39: 1410625.2 | L39: 20152638 | M39: 2354589 | N39: 796203.08 | O39: 4397252.2 | P39: 1878168.9 | Q39: 3536464 | R39: 1911271.2 | U39: 0 | V39: 0 | W39: 0 | X39: 0 | Y39: 0 | Z39: 0 | AA39: 0 | AB39: =B39+L39+U39 -> 37370888 | AC39: =C39+D39+E39+F39+M39+N39+O39+P39+V39+W39+X39+Y39+G39+H39+Q39+R39+Z39+AA39 -> 30635721 | AD39: =AB39-AC39 -> 6735167 | AE39: 2
A40: 45169 | B40: 19455075 | C40: 3464707 | D40: 1152578.5 | E40: 5766597.9 | F40: 4097896.7 | G40: 1954531.5 | H40: 1554840 | L40: 21252094 | M40: 2527556.9 | N40: 826725.48 | O40: 4819043.8 | P40: 1920591.9 | Q40: 3878584.5 | R40: 2040920 | U40: 0 | V40: 0 | W40: 0 | X40: 0 | Y40: 0 | Z40: 0 | AA40: 0 | AB40: =B40+L40+U40 -> 40707170 | AC40: =C40+D40+E40+F40+M40+N40+O40+P40+V40+W40+X40+Y40+G40+H40+Q40+R40+Z40+AA40 -> 34004574 | AD40: =AB40-AC40 -> 6702595.6 | AE40: 2
A41: 45199 | B41: 19478882 | C41: 3464635.7 | D41: 1162974.9 | E41: 5741541.3 | F41: 4074962.6 | G41: 1913045.4 | H41: 1541520.9 | L41: 20801980 | M41: 2502074.5 | N41: 839853.34 | O41: 4716402.4 | P41: 1944356.8 | Q41: 3730015.4 | R41: 1983191.1 | U41: 0 | V41: 0 | W41: 0 | X41: 0 | Y41: 0 | Z41: 0 | AA41: 0 | AB41: =B41+L41+U41 -> 40280862 | AC41: =C41+D41+E41+F41+M41+N41+O41+P41+V41+W41+X41+Y41+G41+H41+Q41+R41+Z41+AA41 -> 33614574 | AD41: =AB41-AC41 -> 6666288 | AE41: 2
A42: 45230 | B42: 19452749 | C42: 3510739.4 | D42: 1163993.9 | E42: 5821913.2 | F42: 4077299.5 | G42: 1948779.1 | H42: 1567961.7 | L42: 21175427 | M42: 2551804.6 | N42: 846054.81 | O42: 4813536.5 | P42: 1958059.8 | Q42: 3824439.2 | R42: 2029872.6 | U42: 0 | V42: 0 | W42: 0 | X42: 0 | Y42: 0 | Z42: 0 | AA42: 0 | AB42: =B42+L42+U42 -> 40628176 | AC42: =C42+D42+E42+F42+M42+N42+O42+P42+V42+W42+X42+Y42+G42+H42+Q42+R42+Z42+AA42 -> 34114454 | AD42: =AB42-AC42 -> 6513721.2 | AE42: 2
A43: 45260 | B43: 21363704 | C43: 3835828.5 | D43: 1255753.7 | E43: 6352072.7 | F43: 4428335.3 | G43: 2113039.8 | H43: 1708633 | L43: 22590124 | M43: 2742983.4 | N43: 897963.32 | O43: 5166692.2 | P43: 2124430.9 | Q43: 4079520.9 | R43: 2211984.7 | U43: 0 | V43: 0 | W43: 0 | X43: 0 | Y43: 0 | Z43: 0 | AA43: 0 | AB43: =B43+L43+U43 -> 43953829 | AC43: =C43+D43+E43+F43+M43+N43+O43+P43+V43+W43+X43+Y43+G43+H43+Q43+R43+Z43+AA43 -> 36917238 | AD43: =AB43-AC43 -> 7036590.2 | AE43: 2
A44: 45291 | B44: 22803909 | C44: 4046870.6 | D44: 0 | E44: 6845538.7 | F44: 6113908.6 | G44: 2237019.2 | H44: 1784273.4 | L44: 23576376 | M44: 2839114.8 | N44: 0 | O44: 5419486.1 | P44: 3132917.3 | Q44: 4252580.8 | R44: 2279575.4 | U44: 0 | V44: 0 | W44: 0 | X44: 0 | Y44: 0 | Z44: 0 | AA44: 0 | AB44: =B44+L44+U44 -> 46380285 | AC44: =C44+D44+E44+F44+M44+N44+O44+P44+V44+W44+X44+Y44+G44+H44+Q44+R44+Z44+AA44 -> 38951285 | AD44: =AB44-AC44 -> 7429000.4 | AE44: 2
A45: 45322 | B45: 21635103 | C45: 3930353.3 | D45: 0 | E45: 6530850.6 | F45: 5855499.8 | G45: 2173226.3 | H45: 1742196.8 | L45: 23508692 | M45: 2808892.5 | N45: 0 | O45: 5269896.5 | P45: 3082555.6 | Q45: 4105467.1 | R45: 2172912 | U45: 0 | V45: 0 | W45: 0 | X45: 0 | Y45: 0 | Z45: 0 | AA45: 0 | AB45: =B45+L45+U45 -> 45143795 | AC45: =C45+D45+E45+F45+M45+N45+O45+P45+V45+W45+X45+Y45+G45+H45+Q45+R45+Z45+AA45 -> 37671850 | AD45: =AB45-AC45 -> 7471945 | AE45: 2
A46: 45351 | B46: 23794486 | C46: 4198411.8 | D46: 0 | E46: 6975188.6 | F46: 6341152.2 | G46: 2356824 | H46: 1895627.3 | L46: 24640203 | M46: 2961683 | N46: 0 | O46: 5597121 | P46: 3292402.3 | Q46: 4489229 | R46: 2381953.5 | U46: 0 | V46: 0 | W46: 0 | X46: 0 | Y46: 0 | Z46: 0 | AA46: 0 | AB46: =B46+L46+U46 -> 48434689 | AC46: =C46+D46+E46+F46+M46+N46+O46+P46+V46+W46+X46+Y46+G46+H46+Q46+R46+Z46+AA46 -> 40489593 | AD46: =AB46-AC46 -> 7945096.8 | AE46: 2
A47: 45382 | B47: 24706809 | C47: 7132292.5 | D47: 0 | E47: 3449717.6 | F47: 4375591.5 | G47: 2474559.4 | H47: 3225468.1 | I47: 3675785 | J47: 242537.49 | L47: 25094937 | M47: 7544770.2 | N47: 0 | O47: 2275085.1 | P47: 2110626 | Q47: 1267331.5 | R47: 2286923.1 | S47: 2259043.5 | T47: 2235769.3 | U47: 0 | V47: 0 | W47: 0 | X47: 0 | Y47: 0 | Z47: 0 | AA47: 0 | AB47: =B47+L47+U47 -> 49801746 | AC47: =C47+D47+E47+F47+M47+N47+O47+P47+V47+W47+X47+Y47+G47+H47+Q47+R47+Z47+AA47+I47+J47+S47+T47 -> 44555500 | AD47: =AB47-AC47 -> 5246246 | AE47: 2
A48: 45412 | B48: 23928711 | C48: 6887592.7 | D48: 0 | E48: 3372478.4 | F48: 4070091.6 | G48: 2393419.9 | H48: 3093697.7 | I48: 3598893.1 | J48: 243986.34 | L48: 23847955 | M48: 7177856.8 | N48: 0 | O48: 2161312 | P48: 1918767.1 | Q48: 1201782.3 | R48: 2155179.2 | S48: 2168527.5 | T48: 2155663.1 | U48: 0 | V48: 0 | W48: 0 | X48: 0 | Y48: 0 | Z48: 0 | AA48: 0 | AB48: =B48+L48+U48 -> 47776666 | AC48: =C48+D48+E48+F48+M48+N48+O48+P48+V48+W48+X48+Y48+G48+H48+Q48+R48+Z48+AA48+I48+J48+S48+T48 -> 42599248 | AD48: =AB48-AC48 -> 5177417.8 | AE48: 2
A49: 45443 | B49: 26054832 | C49: 7487510.3 | D49: 0 | E49: 3653492.7 | F49: 4397555.7 | G49: 2605576.4 | H49: 3408656.2 | I49: 3856047.8 | J49: 262846.85 | L49: 26184183 | M49: 7815804.9 | N49: 0 | O49: 2345015.5 | P49: 2080977.9 | Q49: 1309952 | R49: 2375011.2 | S49: 2326585.9 | T49: 2378089.7 | U49: 0 | V49: 0 | W49: 0 | X49: 0 | Y49: 0 | Z49: 0 | AA49: 0 | AB49: =B49+L49+U49 -> 52239015 | AC49: =C49+D49+E49+F49+M49+N49+O49+P49+V49+W49+X49+Y49+G49+H49+Q49+R49+Z49+AA49+I49+J49+S49+T49 -> 46303123 | AD49: =AB49-AC49 -> 5935891.9 | AE49: 2
A50: 45473 | B50: 26307728 | C50: 7631355.3 | D50: 0 | E50: 3719754.4 | F50: 4498612.8 | G50: 2675973.3 | H50: 3510242 | I50: 3879870.7 | J50: 264344.7 | L50: 25170712 | M50: 7672854.1 | N50: 0 | O50: 2293249.2 | P50: 2029478.6 | Q50: 1264563.3 | R50: 2283856 | S50: 2267169.1 | T50: 2278277.7 | U50: 0 | V50: 0 | W50: 0 | X50: 0 | Y50: 0 | Z50: 0 | AA50: 0 | AB50: =B50+L50+U50 -> 51478440 | AC50: =C50+D50+E50+F50+M50+N50+O50+P50+V50+W50+X50+Y50+G50+H50+Q50+R50+Z50+AA50+I50+J50+S50+T50 -> 46269601 | AD50: =AB50-AC50 -> 5208838.8 | AE50: 2
A51: 45504 | B51: 27909356 | C51: 8018458.3 | D51: 0 | E51: 3879748.5 | F51: 4941714.9 | G51: 2707161.8 | H51: 3555436.5 | I51: 4107653.8 | J51: 275146.25 | L51: 26837771 | M51: 8018812.3 | N51: 0 | O51: 2393247.5 | P51: 2229377.2 | Q51: 1320314.8 | R51: 2361744 | S51: 2385021.2 | T51: 2392364.6 | U51: 0 | V51: 0 | W51: 0 | X51: 0 | Y51: 0 | Z51: 0 | AA51: 0 | AB51: =B51+L51+U51 -> 54747127 | AC51: =C51+D51+E51+F51+M51+N51+O51+P51+V51+W51+X51+Y51+G51+H51+Q51+R51+Z51+AA51+I51+J51+S51+T51 -> 48586202 | AD51: =AB51-AC51 -> 6160925 | AE51: 2
A52: 45535 | B52: 28048906 | C52: 8257602.5 | D52: 0 | E52: 3955071.1 | F52: 4848588.4 | G52: 2720528.3 | H52: 3615463.4 | I52: 4158920.7 | J52: 277350 | L52: 26969310 | M52: 8162943.9 | N52: 0 | O52: 2403963.6 | P52: 2166131.8 | Q52: 1326833.8 | R52: 2401617.6 | S52: 2414788.2 | T52: 2286138 | U52: 0 | V52: 0 | W52: 0 | X52: 0 | Y52: 0 | Z52: 0 | AA52: 0 | AB52: =B52+L52+U52 -> 55018216 | AC52: =C52+D52+E52+F52+M52+N52+O52+P52+V52+W52+X52+Y52+G52+H52+Q52+R52+Z52+AA52+I52+J52+S52+T52 -> 48995941 | AD52: =AB52-AC52 -> 6022274.7 | AE52: 2
A53: 45565 | B53: 27926050 | C53: 8025936.6 | D53: 0 | E53: 3896963.9 | F53: 4908670 | G53: 2762410 | H53: 3590480.1 | I53: 4139168.8 | J53: 279715 | L53: 28025252 | M53: 8513759.2 | N53: 0 | O53: 2542109.3 | P53: 2347955.8 | Q53: 1410190 | R53: 2539677.1 | S53: 2538553.6 | T53: 2510669.8 | U53: 0 | V53: 0 | W53: 0 | X53: 0 | Y53: 0 | Z53: 0 | AA53: 0 | AB53: =B53+L53+U53 -> 55951302 | AC53: =C53+D53+E53+F53+M53+N53+O53+P53+V53+W53+X53+Y53+G53+H53+Q53+R53+Z53+AA53+I53+J53+S53+T53 -> 50006259 | AD53: =AB53-AC53 -> 5945042.5 | AE53: 2
A54: 45596 | B54: 27277336 | C54: 7790420.8 | D54: 0 | E54: 3761719.7 | F54: 4761470 | G54: 2713862.9 | H54: 3517730.1 | I54: 4033233.1 | J54: 280682.5 | L54: 26317074 | M54: 7778991.7 | N54: 0 | O54: 2374294.1 | P54: 2071630.7 | Q54: 1354038.2 | R54: 2359529.5 | S54: 2364562.7 | T54: 2433190.9 | U54: 0 | V54: 0 | W54: 0 | X54: 0 | Y54: 0 | Z54: 0 | AA54: 0 | AB54: =B54+L54+U54 -> 53594410 | AC54: =C54+D54+E54+F54+M54+N54+O54+P54+V54+W54+X54+Y54+G54+H54+Q54+R54+Z54+AA54+I54+J54+S54+T54 -> 47595357 | AD54: =AB54-AC54 -> 5999052.9 | AE54: 2
A55: 45626 | B55: 29218960 | C55: 8342411 | D55: 0 | E55: 4022246.8 | F55: 5183543.5 | G55: 2887064 | H55: 3737319.3 | I55: 4292415 | J55: 282510 | L55: 28578374 | M55: 8442663.9 | N55: 0 | O55: 2548791.4 | P55: 2277285.5 | Q55: 1424943 | R55: 2527543.6 | S55: 2560516.5 | T55: 2523142.8 | U55: 0 | V55: 0 | W55: 0 | X55: 0 | Y55: 0 | Z55: 0 | AA55: 0 | AB55: =B55+L55+U55 -> 57797334 | AC55: =C55+D55+E55+F55+M55+N55+O55+P55+V55+W55+X55+Y55+G55+H55+Q55+R55+Z55+AA55+I55+J55+S55+T55 -> 51052396 | AD55: =AB55-AC55 -> 6744937.3 | AE55: 2
A56: 45657 | B56: 29068294 | C56: 8283158.1 | D56: 0 | E56: 4049213.5 | F56: 4899702.2 | G56: 2911590.4 | H56: 3765865.9 | I56: 4367715 | J56: 289594.8 | L56: 28472742 | M56: 8511779.8 | N56: 0 | O56: 2558548.2 | P56: 2282587 | Q56: 1438319 | R56: 2581556.7 | S56: 2594055 | T56: 2581048.8 | U56: 0 | V56: 0 | W56: 0 | X56: 0 | Y56: 0 | Z56: 0 | AA56: 0 | AB56: =B56+L56+U56 -> 57541036 | AC56: =C56+D56+E56+F56+M56+N56+O56+P56+V56+W56+X56+Y56+G56+H56+Q56+R56+Z56+AA56+I56+J56+S56+T56 -> 51114734 | AD56: =AB56-AC56 -> 6426301.3 | AE56: 2
A57: 45688 | B57: 41398631 | C57: 0 | D57: 0 | E57: 0 | F57: 4157817.9 | G57: 3822792 | H57: 8277155 | I57: 6170889.6 | J57: 415150.9 | K57: 8321225.5 | L57: 38815781 | M57: 11683705 | N57: 0 | O57: 3508332.7 | P57: 3124065.4 | Q57: 1927188 | R57: 3501836.8 | S57: 3471724.8 | T57: 3503699.5 | U57: 0 | V57: 0 | W57: 0 | X57: 0 | Y57: 0 | Z57: 0 | AA57: 0 | AB57: =B57+L57+U57 -> 80214413 | AC57: =C57+D57+E57+F57+M57+N57+O57+P57+V57+W57+X57+Y57+G57+H57+Q57+R57+Z57+AA57+I57+J57+S57+T57+K57 -> 61885583 | AD57: =AB57-AC57 -> 18328830 | AE57: 2
A58: 45716 | B58: 42382128 | C58: 0 | D58: 0 | E58: 0 | F58: 4049211.9 | G58: 3974619 | H58: 8354370.9 | I58: 6548335.2 | J58: 415880.8 | K58: 8379680.8 | L58: 39644442 | M58: 11426157 | N58: 0 | O58: 4289577.1 | P58: 3125777.3 | Q58: 1939489.2 | R58: 1523652.8 | S58: 3979185.6 | T58: 5836946 | U58: 0 | V58: 0 | W58: 0 | X58: 0 | Y58: 0 | Z58: 0 | AA58: 0 | AB58: =B58+L58+U58 -> 82026570 | AC58: =C58+D58+E58+F58+M58+N58+O58+P58+V58+W58+X58+Y58+G58+H58+Q58+R58+Z58+AA58+I58+J58+S58+T58+K58 -> 63842884 | AD58: =AB58-AC58 -> 18183686 | AE58: 2
A59: 45747 | B59: 41414969 | C59: 0 | D59: 0 | E59: 0 | F59: 4902613 | G59: 4081875.2 | H59: 8257405 | I59: 0 | J59: 4065614.6 | K59: 7860234.8 | L59: 43193645 | M59: 12458823 | N59: 0 | O59: 4713060.8 | P59: 3392365.9 | Q59: 2139888.8 | R59: 1722962.2 | S59: 4276885.2 | T59: 6383102.2 | U59: 0 | V59: 0 | W59: 0 | X59: 0 | Y59: 0 | Z59: 0 | AA59: 0 | AB59: =B59+L59+U59 -> 84608614 | AC59: =C59+D59+E59+F59+M59+N59+O59+P59+V59+W59+X59+Y59+G59+H59+Q59+R59+Z59+AA59+I59+J59+S59+T59+K59 -> 64254831 | AD59: =AB59-AC59 -> 20353783 | AE59: 2
A60: 45777 | B60: 42790826 | C60: 0 | D60: 0 | E60: 0 | F60: 5068370.5 | G60: 4248571 | H60: 8493655.1 | I60: 0 | J60: 4233052.7 | K60: 8057971 | L60: 43441459 | M60: 12581159 | N60: 0 | O60: 4762043.1 | P60: 3407905.8 | Q60: 2146962.8 | R60: 1701322.9 | S60: 4262312.5 | T60: 6420905.4 | U60: 0 | V60: 0 | W60: 0 | X60: 0 | Y60: 0 | Z60: 0 | AA60: 0 | AB60: =B60+L60+U60 -> 86232285 | AC60: =C60+D60+E60+F60+M60+N60+O60+P60+V60+W60+X60+Y60+G60+H60+Q60+R60+Z60+AA60+I60+J60+S60+T60+K60 -> 65384232 | AD60: =AB60-AC60 -> 20848053 | AE60: 2
A61: 45808 | B61: 46244829 | C61: 0 | D61: 0 | E61: 0 | F61: 5330371.8 | G61: 4551715 | H61: 9071751.5 | I61: 0 | J61: 4553151.2 | K61: 8823297.1 | L61: 47337054 | M61: 13325078 | N61: 0 | O61: 5111447.3 | P61: 3584072 | Q61: 2312658.6 | R61: 1835357.5 | S61: 4583918.9 | T61: 6926902.4 | U61: 0 | V61: 0 | W61: 0 | X61: 0 | Y61: 0 | Z61: 0 | AA61: 0 | AB61: =B61+L61+U61 -> 93581883 | AC61: =C61+D61+E61+F61+M61+N61+O61+P61+V61+W61+X61+Y61+G61+H61+Q61+R61+Z61+AA61+I61+J61+S61+T61+K61 -> 70009721 | AD61: =AB61-AC61 -> 23572161 | AE61: 2
A62: 45838 | B62: 48904002 | C62: 0 | D62: 0 | E62: 0 | F62: 5753785.2 | G62: 4836900 | H62: 9684745.6 | I62: 0 | J62: 4837906.8 | K62: 9338948 | L62: 48792587 | M62: 14087269 | N62: 0 | O62: 5358698.7 | P62: 3912749.9 | Q62: 2391251.2 | R62: 1952748 | S62: 4796320.9 | T62: 7218122 | U62: 0 | V62: 0 | W62: 0 | X62: 0 | Y62: 0 | Z62: 0 | AA62: 0 | AB62: =B62+L62+U62 -> 97696589 | AC62: =C62+D62+E62+F62+M62+N62+O62+P62+V62+W62+X62+Y62+G62+H62+Q62+R62+Z62+AA62+I62+J62+S62+T62+K62 -> 74169445 | AD62: =AB62-AC62 -> 23527144 | AE62: 2
B64: =B62-B59 -> 7489033 | L64: =L62-L59 -> 5598942
B65: =B62-B56 -> 19835708 | L65: =L62-L56 -> 20319845

Sheet DYTA
A1: Date | B1: $$$ | C1: Ret % | D1: Ret $$ | E1: Contribution +/- | F1: Total | G1: SGLC | H1: QXQ | I1: USDX | J1: Total Net SGI Funds | K1: Accts
A2: 45016 | B2: 12672900 | G2: 0 | J2: =B2-G2 -> 12672900 | K2: 1
A3: 45046 | B3: 70190908 | C3: 0.0016 | D3: =SUM(C3*B2) -> 20276.64 | E3: =B3-(B2+D3) -> 57497731 | F3: =IF(E3>0,E3,E3+D3) -> 57497731 | G3: 7050681 | J3: =B3-G3 -> 63140226 | K3: 1
A4: 45077 | B4: 87531195 | C4: -0.0083 | D4: =SUM(C4*B3) -> -582584.53 | E4: =B4-(B3+D4) -> 17922872 | F4: =IF(E4>0,E4,E4+D4) -> 17922872 | G4: 8829553.8 | J4: =B4-G4 -> 78701641 | K4: 1
A5: 45107 | B5: 94108810 | C5: 0.03076 | D5: =SUM(C5*B4) -> 2692459.5 | E5: =B5-(B4+D5) -> 3885155.5 | F5: =IF(E5>0,E5,E5+D5) -> 3885155.5 | G5: 9753519.2 | J5: =B5-G5 -> 84355290 | K5: 1
A6: 45138 | B6: 1.0260867e+08 | C6: 0.0233 | D6: =SUM(C6*B5) -> 2192735.3 | E6: =B6-(B5+D6) -> 6307122.8 | F6: =IF(E6>0,E6,E6+D6) -> 6307122.8 | G6: 11169272 | J6: =B6-G6 -> 91439396 | K6: 1
A7: 45169 | B7: 1.1038916e+08 | C7: -0.0218 | D7: =SUM(C7*B6) -> -2236869 | E7: =B7-(B6+D7) -> 10017365 | F7: =IF(E7>0,E7,E7+D7) -> 10017365 | G7: 23216088 | J7: =B7-G7 -> 87173076 | K7: 1
A8: 45199 | B8: 1.0776051e+08 | C8: -0.0402 | D8: =SUM(C8*B7) -> -4437644.4 | E8: =B8-(B7+D8) -> 1808994.8 | F8: =IF(E8>0,E8,E8+D8) -> 1808994.8 | G8: 22832241 | J8: =B8-G8 -> 84928273 | K8: 1
A9: 45230 | B9: 1.0297663e+08 | C9: -0.0196 | D9: =SUM(C9*B8) -> -2112106.1 | E9: =B9-(B8+D9) -> -2671776.9 | F9: =IF(E9>0,E9,E9+D9) -> -4783883 | G9: 30543112 | J9: =B9-G9 -> 72433519 | K9: 1
A10: 45260 | B10: 1.0646769e+08 | C10: 0.0617 | D10: =SUM(C10*B9) -> 6353658.1 | E10: =B10-(B9+D10) -> -2862597.3 | F10: =IF(E10>0,E10,E10+D10) -> 3491060.9 | G10: 31864321 | J10: =B10-G10 -> 74603371 | K10: 1
A11: 45291 | B11: 1.0637306e+08 | C11: 0.0521 | D11: =SUM(C11*B10) -> 5546966.8 | E11: =B11-(B10+D11) -> -5641595.8 | F11: =IF(E11>0,E11,E11+D11) -> -94629.09 | G11: 31351576 | J11: =B11-G11 -> 75021487 | K11: 1
A12: 45322 | B12: 103661400 | C12: 0.0075 | D12: =SUM(C12*B11) -> 797797.97 | E12: =B12-(B11+D12) -> -3509461 | F12: =IF(E12>0,E12,E12+D12) -> -2711663 | G12: 36204502 | J12: =B12-G12 -> 67456898 | K12: 1
A13: 45351 | B13: 99875980 | C13: 0.0402 | D13: =SUM(C13*B12) -> 4167188.3 | E13: =B13-(B12+D13) -> -7952608.7 | F13: =IF(E13>0,E13,E13+D13) -> -3785420.4 | G13: 35427250 | J13: =B13-G13 -> 64448730 | K13: 1
A14: 45382 | B14: 60328964 | C14: 0.0272 | D14: =SUM(C14*B13) -> 2716626.6 | E14: =B14-(B13+D14) -> -42263642 | F14: =IF(E14>0,E14,E14+D14) -> -39547016 | G14: 21603312 | J14: =B14-G14 -> 38725651 | K14: 1
... A16: 45443 | B16: 57410548 | C16: 0.0482 | D16: =SUM(C16*B15) -> 2747666.1 | E16: =B16-(B15+D16) -> -2342639.2 | F16: =IF(E16>0,E16,E16+D16) -> 405026.88 | G16: 20769453 | J16: =B16-G16 -> 36641095 | K16: 1
A17: 45473 | B17: 58001184 | C17: 0.0274 | D17: =SUM(C17*B16) -> 1573049 | E17: =B17-(B16+D17) -> -982413.15 | F17: =IF(E17>0,E17,E17+D17) -> 590635.86 | G17: 21061347 | H17: 4230644.2 | J17: =B17-G17-H17 -> 32709192 | K17: 1
A18: 45504 | B18: 59524319 | C18: 0.0092 | D18: =SUM(C18*B17) -> 533610.89 | E18: =B18-(B17+D18) -> 989524.12 | F18: =IF(E18>0,E18,E18+D18) -> 989524.12 | G18: 21233970 | H18: 5299120 | J18: =B18-G18-H18 -> 32991228 | K18: 1
A19: 45535 | B19: 59655724 | C19: 0.0073 | D19: =SUM(C19*B18) -> 434527.53 | E19: =B19-(B18+D19) -> -303122.46 | F19: =IF(E19>0,E19,E19+D19) -> 131405.07 | G19: 21093080 | H19: 5263151.3 | J19: =B19-G19-H19 -> 33299492 | K19: 1
A20: 45565 | B20: 60511803 | C20: 0.0122 | D20: =SUM(C20*B19) -> 727799.83 | E20: =B20-(B19+D20) -> 128278.8 | F20: =IF(E20>0,E20,E20+D20) -> 128278.8 | G20: 21073427 | H20: 6034728.1 | J20: =B20-G20-H20 -> 33403647 | K20: 1
A21: 45596 | B21: 59540692 | C21: -0.01652425 | D21: =SUM(C21*B20) -> -999912.15 | E21: =B21-(B20+D21) -> 28801.183 | F21: =IF(E21>0,E21,E21+D21) -> 28801.183 | G21: 20646439 | H21: 6015529.7 | J21: =B21-G21-H21 -> 32878723 | K21: 1
A22: 45626 | B22: 62620446 | C22: 0.05446402 | D22: =SUM(C22*B21) -> 3242825.4 | E22: =B22-(B21+D22) -> -163070.6 | F22: =IF(E22>0,E22,E22+D22) -> 3079754.8 | G22: 21652329 | H22: 9220377.8 | J22: =B22-G22-H22 -> 31747740 | K22: 1
A23: 45657 | B23: 58941096 | C23: -0.04493827 | D23: =SUM(C23*B22) -> -2814054.5 | E23: =B23-(B22+D23) -> -865295.54 | F23: =IF(E23>0,E23,E23+D23) -> -3679350.1 | G23: 19683903 | H23: 9297598 | J23: =B23-G23-H23 -> 29959596 | K23: 1
A24: 45688 | B24: 63469387 | C24: 0.02604878 | D24: =SUM(C24*B23) -> 1535343.7 | E24: =B24-(B23+D24) -> 2992946.6 | F24: =IF(E24>0,E24,E24+D24) -> 2992946.6 | G24: 19107609 | H24: 3156057.4 | I24: 12489925 | J24: =B24-G24-H24-I24 -> 28715796 | K24: 1
A25: 45716 | B25: 68213638 | C25: -0.00114885 | D25: =SUM(C25*B24) -> -72916.805 | E25: =B25-(B24+D25) -> 4817168.3 | F25: =IF(E25>0,E25,E25+D25) -> 4817168.3 | G25: 20082824 | H25: 3311351.6 | I25: 13461641 | J25: =B25-G25-H25-I25 -> 31357822 | K25: 1
A26: 45747 | B26: 62572936 | C26: -0.02437234 | D26: =SUM(C26*B25) -> -1662526 | E26: =B26-(B25+D26) -> -3978175.7 | F26: =IF(E26>0,E26,E26+D26) -> -5640701.7 | G26: 11479562 | H26: 0 | I26: 15807971 | J26: =B26-G26-H26-I26 -> 35285403 | K26: 1
A27: 45777 | B27: 61059803 | C27: -0.0128 | D27: =SUM(C27*B26) -> -800933.59 | E27: =B27-(B26+D27) -> -712199.66 | F27: =IF(E27>0,E27,E27+D27) -> -1513133.2 | G27: 11479562 | H27: 0 | I27: 15807971 | J27: =B27-G27-H27-I27 -> 33772270 | K27: 1
A28: 45808 | B28: 62801622 | C28: 0.0127 | D28: =SUM(C28*B27) -> 775459.5 | E28: =B28-(B27+D28) -> 966359.66 | F28: =IF(E28>0,E28,E28+D28) -> 966359.66 | G28: 12059668 | H28: 0 | I28: 18327164 | J28: =B28-G28-H28-I28 -> 32414790 | K28: 1
A29: 45838 | B29: 63631276 | C29: 0.0138 | D29: =SUM(C29*B28) -> 866662.39 | E29: =B29-(B28+D29) -> -37008.349 | F29: =IF(E29>0,E29,E29+D29) -> 829654.04 | G29: 12585121 | H29: 0 | I29: 18337457 | J29: =B29-G29-H29-I29 -> 32708698 | K29: 1
B31: =B29-B26 -> 1058340
B32: =B29-B23 -> 4690180.1

Sheet SGLC
A1: Date | B1: $$$ | C1: Ret % | D1: Ret $$ | E1: Contribution +/- | F1: Total | G1: Accts
A2: 45016 | B2: 5698563.5 | G2: 1
A3: 45046 | B3: 47363506 | C3: 0.0199 | D3: =SUM(C3*B2) -> 113401.41 | E3: =B3-(B2+D3) -> 41551541 | F3: =IF(E3>0,E3,E3+D3) -> 41551541 | G3: 1
A4: 45077 | B4: 55640095 | C4: 0.0001 | D4: =SUM(C4*B3) -> 4736.3506 | E4: =B4-(B3+D4) -> 8271852.7 | F4: =IF(E4>0,E4,E4+D4) -> 8271852.7 | G4: 1
A5: 45107 | B5: 69018468 | C5: 0.058 | D5: =SUM(C5*B4) -> 3227125.5 | E5: =B5-(B4+D5) -> 10151248 | F5: =IF(E5>0,E5,E5+D5) -> 10151248 | G5: 1
A6: 45138 | B6: 82138554 | C6: 0.0475 | D6: =SUM(C6*B5) -> 3278377.3 | E6: =B6-(B5+D6) -> 9841707.8 | F6: =IF(E6>0,E6,E6+D6) -> 9841707.8 | G6: 1
A7: 45169 | B7: 97874099 | C7: -0.0218 | D7: =SUM(C7*B6) -> -1790620.5 | E7: =B7-(B6+D7) -> 17526166 | F7: =IF(E7>0,E7,E7+D7) -> 17526166 | G7: 1
A8: 45199 | B8: 94408790 | C8: -0.0364 | D8: =SUM(C8*B7) -> -3562617.2 | E8: =B8-(B7+D8) -> 97308.063 | F8: =IF(E8>0,E8,E8+D8) -> 97308.063 | G8: 1
A9: 45230 | B9: 97936020 | C9: -0.022 | D9: =SUM(C9*B8) -> -2076993.4 | E9: =B9-(B8+D9) -> 5604223.6 | F9: =IF(E9>0,E9,E9+D9) -> 5604223.6 | G9: 1
A10: 45260 | B10: 1.0230182e+08 | C10: 0.0908 | D10: =SUM(C10*B9) -> 8892590.6 | E10: =B10-(B9+D10) -> -4526794.3 | F10: =IF(E10>0,E10,E10+D10) -> 4365796.3 | G10: 1
A11: 45291 | B11: 1.0163629e+08 | C11: 0.0464 | D11: =SUM(C11*B10) -> 4746804.3 | E11: =B11-(B10+D11) -> -5412329.4 | F11: =IF(E11>0,E11,E11+D11) -> -665525.16 | G11: 1
A12: 45322 | B12: 1.0411578e+08 | C12: 0.0275 | D12: =SUM(C12*B11) -> 2794998 | E12: =B12-(B11+D12) -> -315504.05 | F12: =IF(E12>0,E12,E12+D12) -> 2479493.9 | G12: 1
A13: 45351 | B13: 96960236 | C13: 0.0537 | D13: =SUM(C13*B12) -> 5591017.6 | E13: =B13-(B12+D13) -> -12746567 | F13: =IF(E13>0,E13,E13+D13) -> -7155549.1 | G13: 1
A14: 45382 | B14: 79820678 | C14: 0.0397 | D14: =SUM(C14*B13) -> 3849321.4 | E14: =B14-(B13+D14) -> -20988879 | F14: =IF(E14>0,E14,E14+D14) -> -17139558 | G14: 1
... A29: 45838 | B29: 88990314 | C29: 0.0466 | D29: =SUM(C29*B28) -> 3907680.2 | E29: =B29-(B28+D29) -> 1226835.9 | F29: =IF(E29>0,E29,E29+D29) -> 1226835.9 | G29: 1
B31: =B29-B26 -> 9154002.8
B32: =B29-B23 -> -7371320.3

Sheet GINX
A1: Date | B1: $$$ | C1: Ret % | D1: Ret $$ | E1: Contribution +/- | F1: Total | G1: Accts
A2: 45351 | B2: 500718.36 | G2: 1
A3: 45382 | B3: =50914376.13+18431.08 -> 50932807 | C3: 0.0332 | D3: =SUM(C3*B2) -> 16623.85 | E3: =B3-(B2+D3) -> 50415465 | F3: =IF(E3>0,E3,E3+D3) -> 50415465 | G3: 1
A4: 45412 | B4: 52718518 | C4: -0.0337 | D4: =SUM(C4*B3) -> -1716435.6 | E4: =B4-(B3+D4) -> 3502146.8 | F4: =IF(E4>0,E4,E4+D4) -> 3502146.8 | G4: 1
A5: 45443 | B5: 56751982 | C5: 0.0361 | D5: =SUM(C5*B4) -> 1903138.5 | E5: =B5-(B4+D5) -> 2130324.7 | F5: =IF(E5>0,E5,E5+D5) -> 2130324.7 | G5: 1
A6: 45473 | B6: 60301102 | C6: 0.0062 | D6: =SUM(C6*B5) -> 351862.29 | E6: =B6-(B5+D6) -> 3197258.5 | F6: =IF(E6>0,E6,E6+D6) -> 3197258.5 | G6: 1
A7: 45504 | B7: 65974476 | C7: 0.018 | D7: =SUM(C7*B6) -> 1085419.8 | E7: =B7-(B6+D7) -> 4587953.7 | F7: =IF(E7>0,E7,E7+D7) -> 4587953.7 | G7: 1
A8: 45535 | B8: 68064875 | C8: 0.0177 | D8: =SUM(C8*B7) -> 1167748.2 | E8: =B8-(B7+D8) -> 922650.53 | F8: =IF(E8>0,E8,E8+D8) -> 922650.53 | G8: 1
A9: 45565 | B9: 70351254 | C9: 0.0067 | D9: =SUM(C9*B8) -> 456034.66 | E9: =B9-(B8+D9) -> 1830345.1 | F9: =IF(E9>0,E9,E9+D9) -> 1830345.1 | G9: 1
A10: 45596 | B10: 69154544 | C10: -0.02633001 | D10: =SUM(C10*B9) -> -1852349.2 | E10: =B10-(B9+D10) -> 655639.24 | F10: =IF(E10>0,E10,E10+D10) -> 655639.24 | G10: 1
A11: 45626 | B11: 72806721 | C11: 0.03404873 | D11: =SUM(C11*B10) -> 2354624.4 | E11: =B11-(B10+D11) -> 1297552.5 | F11: =IF(E11>0,E11,E11+D11) -> 1297552.5 | G11: 1
A12: 45657 | B12: 73276330 | C12: -0.03289058 | D12: =SUM(C12*B11) -> -2394655.3 | E12: =B12-(B11+D12) -> 2864263.7 | F12: =IF(E12>0,E12,E12+D12) -> 2864263.7 | G12: 1
A13: 45688 | B13: 81064825 | C13: 0.03691509 | D13: =SUM(C13*B12) -> 2705002.3 | E13: =B13-(B12+D13) -> 5083492.9 | F13: =IF(E13>0,E13,E13+D13) -> 5083492.9 | G13: 1
A14: 45716 | B14: 83210582 | C14: 0.02701688 | D14: =SUM(C14*B13) -> 2190118.6 | E14: =B14-(B13+D14) -> -44362.018 | F14: =IF(E14>0,E14,E14+D14) -> 2145756.6 | G14: 1
A15: 45747 | B15: 77606548 | C15: 0.0008735686 | D15: =SUM(C15*B14) -> 72690.151 | E15: =B15-(B14+D15) -> -5676723.5 | F15: =IF(E15>0,E15,E15+D15) -> -5604033.4 | G15: 1
... A18: 45838 | B18: 80061333 | C18: 0.0301 | D18: =SUM(C18*B17) -> 2381124.4 | E18: =B18-(B17+D18) -> -1426913.9 | F18: =IF(E18>0,E18,E18+D18) -> 954210.52 | G18: 1
B20: =B18-B15 -> 2454784.7
B21: =B18-B12 -> 6785003.1

Sheet USDX
A1: Date | B1: $$$ | C1: Ret % | D1: Ret $$ | E1: Contribution +/- | F1: Total | G1: Accts
A2: 45351 | B2: 500000 | G2: 1
A3: 45382 | B3: =45130607.33+42037.74 -> 45172645 | C3: 0.004 | D3: =B2*C3 -> 2000 | E3: =B3-(B2+D3) -> 44670645 | F3: =D3+E3 -> 44672645 | G3: 1
A4: 45412 | B4: 78616273 | C4: 0.0054 | D4: =B3*C4 -> 243932.28 | E4: =B4-(B3+D4) -> 33199695 | F4: =D4+E4 -> 33443628 | G4: 1
A5: 45443 | B5: 90769839 | C5: 0.0079 | D5: =B4*C5 -> 621068.55 | E5: =B5-(B4+D5) -> 11532498 | F5: =D5+E5 -> 12153567 | G5: 1
A6: 45473 | B6: 96980283 | C6: 0.0064 | D6: =B5*C6 -> 580926.97 | E6: =B6-(B5+D6) -> 5629517 | F6: =D6+E6 -> 6210444 | G6: 1
A7: 45504 | B7: 1.1615852e+08 | C7: 0.0084 | D7: =B6*C7 -> 814634.38 | E7: =B7-(B6+D7) -> 18363599 | F7: =D7+E7 -> 19178234 | G7: 1
A8: 45535 | B8: 1.2885027e+08 | C8: 0.0081 | D8: =B7*C8 -> 940883.99 | E8: =B8-(B7+D8) -> 11750865 | F8: =D8+E8 -> 12691749 | G8: 1
A9: 45565 | B9: 1.3685536e+08 | C9: 0.007 | D9: =B8*C9 -> 901951.86 | E9: =B9-(B8+D9) -> 7103146.3 | F9: =D9+E9 -> 8005098.2 | G9: 1
A10: 45596 | B10: 1.5207899e+08 | C10: 0.007749162 | D10: =B9*C10 -> 1060514.4 | E10: =B10-(B9+D10) -> 14163107 | F10: =D10+E10 -> 15223622 | G10: 1
A11: 45626 | B11: 1.6539627e+08 | C11: 0.006641017 | D11: =B10*C11 -> 1009959.1 | E11: =B11-(B10+D11) -> 12307330 | F11: =D11+E11 -> 13317289 | G11: 1
