Workbook
Name XTOT_CURRENCY_CHOICES: '[1]Total Return Settings'!$N$7:$N$18
Name XTOT_DIVIDEND_TYPE: '[1]Total Return Settings'!$T$15:$T$16
Name XTOT_DIVIDEND_TYPE_TABLE: '[1]Total Return Settings'!$T$15:$U$16
Name XTOT_END_DATE_CHOICES: '[1]Total Return Settings'!$I$7
Name XTOT_OVERRIDE_FIELDS: #REF!
Name XTOT_OVERRIDE_FIELDS: #REF!
Name XTOT_OVERRIDE_FIELDS: #REF!
Name XTOT_OVERRIDE_FIELDS: #REF!
Name XTOT_OVERRIDE_FIELDS: #REF!
Name XTOT_OVERRIDE_FIELDS: #REF!
Name XTOT_OVERRIDE_FIELDS: #REF!
Name XTOT_OVERRIDE_FIELDS: #REF!
Name XTOT_RETURN_PERIODS_LIST: '[1]Total Return Settings'!$T$7:$T$8
Name XTOT_RETURN_PERIODS_TABLE: '[1]Total Return Settings'!$T$7:$U$8
Name XTOT_START_DATE_CHOICES: '[1]Total Return Settings'!$D$7:$D$18
Name XTOT_START_DATE_TABLE: '[1]Total Return Settings'!$D$7:$E$18
Name XTOT_TICKER: '[1]Total Return Settings'!$U$4

Sheet ChartAdvisorTempSheet

Sheet Returns
A1: Summit Global Investments' Low Volatility Portfolios | H1: Summit Global Investments' Low Volatility Portfolios
A2: ="Performance ending "&MONTH(MAX('LC (Gross)'!A:A))&"/"&DAY(MAX('LC (Gross)'!A:A))&"/"&YEAR(MAX('LC (Gross)'!A:A)) -> Performance ending 12/31/2025 | H2: ="Performance ending "&MONTH(MAX('LC (Gross)'!A:A))&"/"&DAY(MAX('LC (Gross)'!A:A))&"/"&YEAR(MAX('LC (Gross)'!A:A)) -> Performance ending 12/31/2025
A4: =MAX('LC (Gross)'!A:A) -> 46022 | B4: SGI | C4: Bench | D4: Rel | E4: Capture | H4: ="Performance on "&MONTH($A$4)&"/"&DAY($A$4)&"/"&YEAR($A$4) -> Performance on 12/31/2025 | I4: MTD | J4: QTD | K4: YTD | L4: 1 Year | M4: 3 Year | N4: 5 Year | O4: Inception*
A5: US LV (SPX) | B5: =VLOOKUP($A$4,'LC (Gross)'!A:D,4,0) -> -0.050948327 | C5: =VLOOKUP($A$4,'LC (Gross)'!J:K,2,0) -> 0.05917608 | D5: =B5-C5 -> -0.11012441 | E5: =B5/C5 -> -0.8609615 | H5: SGI US Low Volatility Equity | I5: =B5 -> -0.050948327 | J5: =B13 -> 3.6945085 | K5: =B21 -> 9.8795519 | L5: =B29 -> 9.8795519 | M5: =B37 -> 13.639609 | N5: =B45 -> 9.084744 | O5: =B53 -> 12.725923
A6: US LV (RusDef) | B6: =VLOOKUP($A$4,'LC (Gross)'!A:D,4,0) -> -0.050948327 | C6: =VLOOKUP($A$4,'LC (Gross)'!P:Q,2,0) -> -0.8506307 | D6: =B6-C6 -> 0.79968237 | E6: =B6/C6 -> 0.059894766 | H6: S&P 500 Index | I6: =C5 -> 0.05917608 | J6: =C13 -> 2.6529335 | K6: =C21 -> 17.859984 | L6: =C29 -> 17.859984 | M6: =C37 -> 22.982389 | N6: =C45 -> 14.400236 | O6: =C53 -> 13.954857
A7: GLV (ACWI) | B7: =VLOOKUP($A$4,'Global (Gross)'!A:D,4,0) -> 0.357371 | C7: =VLOOKUP($A$4,'Global (Gross)'!J:K,2,0) -> 1.0703 | D7: =B7-C7 -> -0.712929 | E7: =B7/C7 -> 0.33389797 | H7: Value Added | I7: =I5-I6 -> -0.11012441 | J7: =J5-J6 -> 1.041575 | K7: =K5-K6 -> -7.980432 | L7: =L5-L6 -> -7.980432 | M7: =M5-M6 -> -9.3427795 | N7: =N5-N6 -> -5.3154916 | O7: =O5-O6 -> -1.2289342
A8: SCLV (R2000) | B8: =VLOOKUP($A$4,'SC (Gross)'!A:D,4,0) -> #N/A | C8: =VLOOKUP($A$4,'SC (Gross)'!J:K,2,0) -> #N/A | D8: =B8-C8 -> #N/A | E8: =B8/C8 -> #N/A | H8: *Inception date for the SGI Low Volatility Equity composite was February 1, 2011
A9: ITL LV (ACWIxUS) | B9: =VLOOKUP($A$4,ITL!A:D,4,0) -> #N/A | C9: =VLOOKUP($A$4,ITL!J:K,2,0) -> #N/A | D9: =B9-C9 -> #N/A | E9: =B9/C9 -> #N/A
H10: ="Performance on "&MONTH($A$4)&"/"&DAY($A$4)&"/"&YEAR($A$4) -> Performance on 12/31/2025 | I10: MTD | J10: QTD | K10: YTD | L10: 1 Year | M10: 3 Year | N10: 5 Year | O10: Inception*
H11: SGI Global Low Volatility Equity | I11: =B7 -> 0.357371 | J11: =B15 -> 1.486825 | K11: =B23 -> 12.65947 | L11: =B31 -> 12.65947 | M11: =B39 -> 12.376696 | N11: =B47 -> 7.7968755 | O11: =B55 -> 10.047428
A12: QTD | B12: SGI | C12: Bench | D12: Rel | E12: Capture | H12: MSCI ACWI | I12: =C7 -> 1.0703 | J12: =C15 -> 3.3691709 | K12: =C23 -> 22.892597 | L12: =C31 -> 22.892597 | M12: =C39 -> 21.21063 | N12: =C47 -> 11.708136 | O12: =C55 -> 11.033473
A13: US LV (SPX) | B13: =VLOOKUP($A$4,'LC (Gross)'!A:H,7,0) -> 3.6945085 | C13: =VLOOKUP($A$4,'LC (Gross)'!J:N,5,0) -> 2.6529335 | D13: =B13-C13 -> 1.041575 | E13: =B13/C13 -> 1.3926126 | H13: Value Added | I13: =I11-I12 -> -0.712929 | J13: =J11-J12 -> -1.8823459 | K13: =K11-K12 -> -10.233127 | L13: =L11-L12 -> -10.233127 | M13: =M11-M12 -> -8.8339343 | N13: =N11-N12 -> -3.9112605 | O13: =O11-O12 -> -0.98604571
A14: US LV (RusDef) | B14: =VLOOKUP($A$4,'LC (Gross)'!A:H,7,0) -> 3.6945085 | C14: =VLOOKUP($A$4,'LC (Gross)'!P:T,5,0) -> 2.3658665 | D14: =B14-C14 -> 1.3286421 | E14: =B14/C14 -> 1.5615879 | H14: *Inception date for the SGI Global Low Volatility Equity composite was March 1, 2012
A15: GLV (ACWI) | B15: =VLOOKUP($A$4,'Global (Gross)'!A:H,7,0) -> 1.486825 | C15: =VLOOKUP($A$4,'Global (Gross)'!J:N,5,0) -> 3.3691709 | D15: =B15-C15 -> -1.8823459 | E15: =B15/C15 -> 0.44130293
A16: SCLV (R2000) | B16: =VLOOKUP($A$4,'SC (Gross)'!A:H,7,0) -> #N/A | C16: =VLOOKUP($A$4,'SC (Gross)'!J:N,5,0) -> #N/A | D16: =B16-C16 -> #N/A | E16: =B16/C16 -> #N/A | H16: ="Performance on "&MONTH($A$4)&"/"&DAY($A$4)&"/"&YEAR($A$4) -> Performance on 12/31/2025 | I16: MTD | J16: QTD | K16: YTD | L16: 1 Year | M16: 3 Year | N16: 5 Year | O16: Inception*
A17: ITL LV (ACWIxUS) | B17: =VLOOKUP($A$4,ITL!A:H,7,0) -> #N/A | C17: =VLOOKUP($A$4,ITL!J:N,5,0) -> #N/A | D17: =B17-C17 -> #N/A | E17: =B17/C17 -> #N/A | H17: SGI Small Cap Low Volatility Equity | I17: =B8 -> #N/A | J17: =B16 -> #N/A | K17: =B24 -> N/A | L17: =B32 -> 0 | M17: =B40 -> 0.40159714 | N17: =B48 -> 1.530695 | O17: =B56 -> 7.3796506
H18: Russell 2000 | I18: =C8 -> #N/A | J18: =C16 -> #N/A | K18: =C24 -> N/A | L18: =C32 -> 11.526909 | M18: =C40 -> 1.212514 | N18: =C48 -> 7.3756287 | O18: =C56 -> 7.8616628
H19: Value Added | I19: =I17-I18 -> #N/A | J19: =J17-J18 -> #N/A | K19: =K17-K18 -> #VALUE! | L19: =L17-L18 -> -11.526909 | M19: =M17-M18 -> -0.81091681 | N19: =N17-N18 -> -5.8449336 | O19: =O17-O18 -> -0.48201228
A20: YTD | B20: SGI | C20: Bench | D20: Rel | E20: Capture | H20: *Inception date for the SGI Small Cap Low Volatility Equity composite was February 1, 2014
A21: US LV (SPX) | B21: ='LC (Gross)'!D$5 -> 9.8795519 | C21: ='LC (Gross)'!K$5 -> 17.859984 | D21: =B21-C21 -> -7.980432 | E21: =B21/C21 -> 0.5531669
A22: US LV (RusDef) | B22: ='LC (Gross)'!D$5 -> 9.8795519 | C22: ='LC (Gross)'!Q$5 -> 12.246788 | D22: =B22-C22 -> -2.3672359 | E22: =B22/C22 -> 0.80670557 | H22: ="Performance on "&MONTH($A$4)&"/"&DAY($A$4)&"/"&YEAR($A$4) -> Performance on 12/31/2025 | I22: MTD | J22: QTD | K22: YTD | L22: 1 Year | M22: 3 Year | N22: 5 Year | O22: Inception*
A23: GLV (ACWI) | B23: ='Global (Gross)'!D$5 -> 12.65947 | C23: ='Global (Gross)'!K$5 -> 22.892597 | D23: =B23-C23 -> -10.233127 | E23: =B23/C23 -> 0.55299407 | H23: SGI International Low Volatility Equity | I23: =B9 -> #N/A | J23: =B17 -> #N/A | K23: =B25 -> N/A | L23: =B33 -> 0 | M23: =B41 -> 0.32472839 | N23: =B49 -> 3.1715374 | O23: =B57 -> 2.3495971
A24: SCLV (R2000) | B24: ='SC (Gross)'!D$5 -> N/A | C24: ='SC (Gross)'!K$5 -> N/A | D24: =B24-C24 -> #VALUE! | E24: =B24/C24 -> #VALUE! | H24: MSCI ACWIxUS | I24: =C9 -> #N/A | J24: =C17 -> #N/A | K24: =C25 -> N/A | L24: =C33 -> 8.8385128 | M24: =C41 -> 11.230079 | N24: =C49 -> 9.5274798 | O24: =C57 -> 6.5002383
A25: ITL LV (ACWIxUS) | B25: =ITL!D$5 -> N/A | C25: =ITL!K$5 -> N/A | D25: =B25-C25 -> #VALUE! | E25: =B25/C25 -> #VALUE! | H25: Value Added | I25: =I23-I24 -> #N/A | J25: =J23-J24 -> #N/A | K25: =K23-K24 -> #VALUE! | L25: =L23-L24 -> -8.8385128 | M25: =M23-M24 -> -10.905351 | N25: =N23-N24 -> -6.3559424 | O25: =O23-O24 -> -4.1506412
H26: *Inception date for the SGI International Low Volatility Equity composite was March 1, 2015
A28: 1 Year | B28: SGI | C28: Bench | D28: Rel | E28: Capture | H28: Live Data Linked with Model Data
A29: US LV (SPX) | B29: ='LC (Gross)'!D$6 -> 9.8795519 | C29: ='LC (Gross)'!K$6 -> 17.859984 | D29: =B29-C29 -> -7.980432 | E29: =B29/C29 -> 0.5531669
A30: US LV (RusDef) | B30: ='LC (Gross)'!D$6 -> 9.8795519 | C30: ='LC (Gross)'!Q$6 -> 12.246788 | D30: =B30-C30 -> -2.3672359 | E30: =B30/C30 -> 0.80670557
A31: GLV (ACWI) | B31: ='Global (Gross)'!D$6 -> 12.65947 | C31: ='Global (Gross)'!K$6 -> 22.892597 | D31: =B31-C31 -> -10.233127 | E31: =B31/C31 -> 0.55299407
A32: SCLV (R2000) | B32: ='SC (Gross)'!D$6 -> 0 | C32: ='SC (Gross)'!K$6 -> 11.526909 | D32: =B32-C32 -> -11.526909 | E32: =B32/C32 -> 0
A33: ITL LV (ACWIxUS) | B33: =ITL!D$6 -> 0 | C33: =ITL!K$6 -> 8.8385128 | D33: =B33-C33 -> -8.8385128 | E33: =B33/C33 -> 0
A36: 3 Year | B36: SGI | C36: Bench | D36: Rel | E36: Capture
A37: US LV (SPX) | B37: ='LC (Gross)'!D$8 -> 13.639609 | C37: ='LC (Gross)'!K$8 -> 22.982389 | D37: =B37-C37 -> -9.3427795 | E37: =B37/C37 -> 0.59348092
A38: US LV (RusDef) | B38: ='LC (Gross)'!D$8 -> 13.639609 | C38: ='LC (Gross)'!Q$8 -> 16.938916 | D38: =B38-C38 -> -3.2993063 | E38: =B38/C38 -> 0.80522329
A39: GLV (ACWI) | B39: ='Global (Gross)'!D$8 -> 12.376696 | C39: ='Global (Gross)'!K$8 -> 21.21063 | D39: =B39-C39 -> -8.8339343 | E39: =B39/C39 -> 0.58351383
A40: SCLV (R2000) | B40: ='SC (Gross)'!D$8 -> 0.40159714 | C40: ='SC (Gross)'!K$8 -> 1.212514 | D40: =B40-C40 -> -0.81091681 | E40: =B40/C40 -> 0.33121033
A41: ITL LV (ACWIxUS) | B41: =ITL!D$8 -> 0.32472839 | C41: =ITL!K$8 -> 11.230079 | D41: =B41-C41 -> -10.905351 | E41: =B41/C41 -> 0.028915948
A44: 5 Year | B44: SGI | C44: Bench | D44: Rel | E44: Capture
A45: US LV (SPX) | B45: ='LC (Gross)'!D$10 -> 9.084744 | C45: ='LC (Gross)'!K$10 -> 14.400236 | D45: =B45-C45 -> -5.3154916 | E45: =B45/C45 -> 0.63087468
A46: US LV (RusDef) | B46: ='LC (Gross)'!D$10 -> 9.084744 | C46: ='LC (Gross)'!Q$10 -> 11.138063 | D46: =B46-C46 -> -2.0533193 | E46: =B46/C46 -> 0.81564845
A47: GLV (ACWI) | B47: ='Global (Gross)'!D$10 -> 7.7968755 | C47: ='Global (Gross)'!K$10 -> 11.708136 | D47: =B47-C47 -> -3.9112605 | E47: =B47/C47 -> 0.66593653
A48: SCLV (R2000) | B48: ='SC (Gross)'!D$10 -> 1.530695 | C48: ='SC (Gross)'!K$10 -> 7.3756287 | D48: =B48-C48 -> -5.8449336 | E48: =B48/C48 -> 0.20753418
A49: ITL LV (ACWIxUS) | B49: =ITL!D$10 -> 3.1715374 | C49: =ITL!K$10 -> 9.5274798 | D49: =B49-C49 -> -6.3559424 | E49: =B49/C49 -> 0.33288314
A52: Live Record Only | B52: SGI | C52: Bench | D52: Rel | E52: Capture
A53: US LV (SPX) Jan 2011 | B53: ='LC (Gross)'!D$13 -> 12.725923 | C53: ='LC (Gross)'!K$13 -> 13.954857 | D53: =B53-C53 -> -1.2289342 | E53: =B53/C53 -> 0.91193502
A54: US LV (RusDef) Jan 2011 | B54: ='LC (Gross)'!D$13 -> 12.725923 | C54: ='LC (Gross)'!Q$13 -> 12.932305 | D54: =B54-C54 -> -0.20638199 | E54: =B54/C54 -> 0.98404136
A55: GLV (ACWI) Mar 2012 | B55: ='Global (Gross)'!D$13 -> 10.047428 | C55: ='Global (Gross)'!K$13 -> 11.033473 | D55: =B55-C55 -> -0.98604571 | E55: =B55/C55 -> 0.91063143
A56: SCLV (R2000) Feb 2014 | B56: ='SC (Gross)'!D$13 -> 7.3796506 | C56: ='SC (Gross)'!K$13 -> 7.8616628 | D56: =B56-C56 -> -0.48201228 | E56: =B56/C56 -> 0.93868825
A57: ITL LV (ACWIxUS) Mar 2015 | B57: =ITL!D$13 -> 2.3495971 | C57: =ITL!K$13 -> 6.5002383 | D57: =B57-C57 -> -4.1506412 | E57: =B57/C57 -> 0.36146323

Sheet LC (Gross)
C1: Large Cap (Gross) | J1: S&P 500® Index | P1: Russell Defensive® Index | W1: S&P 500 Low Volatility Total Return Index
D4: Return | E4: Relative Return | F4: Beta | G4: Alpha | H4: stdevp | K4: Return | L4: Beta | M4: stdevp | Q4: Return | R4: Relative Return | S4: Beta | T4: Alpha | U4: stdevp | X4: Return | Y4: Relative Return | Z4: Beta | AA4: stdevp
B5: 12 | C5: YTD | D5: {=IFERROR((GEOMEAN(1+OFFSET(D$16,MAX($B$16:$B$506)-$B$5+1,0,$B$5,1)/100)^$B$5-1)*100,"N/A")} -> 9.8795519 | E5: =IFERROR(D5-$K5,"N/A") -> -7.980432 | F5: =IFERROR(SLOPE(OFFSET(D$16,MAX($B$16:$B$506)-$B$5+1,0,$B$5,1),OFFSET($K$16,MAX($B$16:$B$506)-$B$5+1,0,$B$5,1)),"N/A") -> 0.30043818 | G5: {=IFERROR(INTERCEPT(OFFSET(D$16,MAX($B$16:$B$506)-$B$5+1,0,$B$5,1),OFFSET($K$16,MAX($B$16:$B$506)-$B$5+1,0,$B$5,1))*12,"N/A")} -> 4.5432835 | H5: =IFERROR(STDEVP(OFFSET(D$16,MAX($B$16:$B$506)-$B$5+1,0,$B$5,1))*SQRT(12),"N/A") -> 6.7090947 | J5: YTD | K5: {=IFERROR((GEOMEAN(1+OFFSET(K$16,MAX($B$16:$B$506)-$B$5+1,0,$B$5,1)/100)^$B$5-1)*100,"N/A")} -> 17.859984 | L5: =IFERROR(SLOPE(OFFSET(K$16,MAX($B$16:$B$506)-$B$5+1,0,$B$5,1),OFFSET($K$16,MAX($B$16:$B$506)-$B$5+1,0,$B$5,1)),"N/A") -> 1 | M5: =IFERROR(STDEVP(OFFSET(K$16,MAX($B$16:$B$506)-$B$5+1,0,$B$5,1))*SQRT(12),"N/A") -> 10.521019 | P5: YTD | Q5: {=IFERROR((GEOMEAN(1+OFFSET(Q$16,MAX($B$16:$B$506)-$B$5+1,0,$B$5,1)/100)^$B$5-1)*100,"N/A")} -> 12.246788 | R5: =IFERROR(Q5-$K5,"N/A") -> -5.6131961 | S5: =IFERROR(SLOPE(OFFSET(Q$16,MAX($B$16:$B$506)-$B$5+1,0,$B$5,1),OFFSET($K$16,MAX($B$16:$B$506)-$B$5+1,0,$B$5,1)),"N/A") -> 0.57084148 | T5: {=IFERROR(INTERCEPT(OFFSET(Q$16,MAX($B$16:$B$506)-$B$5+1,0,$B$5,1),OFFSET($K$16,MAX($B$16:$B$506)-$B$5+1,0,$B$5,1))*12,"N/A")} -> 2.1012202 | U5: =IFERROR(STDEVP(OFFSET(Q$16,MAX($B$16:$B$506)-$B$5+1,0,$B$5,1))*SQRT(12),"N/A") -> 7.1053408 | W5: YTD | X5: {=IFERROR((GEOMEAN(1+OFFSET(X$16,MAX($B$16:$B$506)-$B$5+1,0,$B$5,1)/100)^$B$5-1)*100,"N/A")} -> 4.3575279 | Y5: =IFERROR(X5-$K6,"N/A") -> -13.502456 | Z5: =IFERROR(SLOPE(OFFSET(X$16,MAX($B$16:$B$506)-$B$5+1,0,$B$5,1),OFFSET($K$16,MAX($B$16:$B$506)-$B$5+1,0,$B$5,1)),"N/A") -> -0.080393747 | AA5: =IFERROR(STDEVP(OFFSET(X$16,MAX($B$16:$B$506)-$B$5+1,0,$B$5,1))*SQRT(12),"N/A") -> 8.2295016
C6: One Year | D6: {=IFERROR((GEOMEAN(1+OFFSET(D$16,MAX($B$16:$B$506)-11,0,12,1)/100)^12-1)*100,"N/A")} -> 9.8795519 | E6: =IFERROR(D6-$K6,"N/A") -> -7.980432 | F6: =IFERROR(SLOPE(OFFSET(D$16,MAX($B$16:$B$506)-11,0,12,1),OFFSET($K$16,MAX($B$16:$B$506)-11,0,12,1)),"N/A") -> 0.30043818 | G6: =IFERROR(INTERCEPT(OFFSET(D$16,MAX($B$16:$B$506)-11,0,12,1),OFFSET($K$16,MAX($B$16:$B$506)-11,0,12,1))*12,"N/A") -> 4.5432835 | H6: =IFERROR(STDEVP(OFFSET(D$16,MAX($B$16:$B$506)-11,0,12,1))*SQRT(12),"N/A") -> 6.7090947 | J6: One Year | K6: {=IFERROR((GEOMEAN(1+OFFSET(K$16,MAX($B$16:$B$506)-11,0,12,1)/100)^12-1)*100,"N/A")} -> 17.859984 | L6: =IFERROR(SLOPE(OFFSET(K$16,MAX($B$16:$B$506)-11,0,12,1),OFFSET($K$16,MAX($B$16:$B$506)-11,0,12,1)),"N/A") -> 1 | M6: =IFERROR(STDEVP(OFFSET(K$16,MAX($B$16:$B$506)-11,0,12,1))*SQRT(12),"N/A") -> 10.521019 | P6: One Year | Q6: {=IFERROR((GEOMEAN(1+OFFSET(Q$16,MAX($B$16:$B$506)-11,0,12,1)/100)^12-1)*100,"N/A")} -> 12.246788 | R6: =IFERROR(Q6-$K6,"N/A") -> -5.6131961 | S6: =IFERROR(SLOPE(OFFSET(Q$16,MAX($B$16:$B$506)-11,0,12,1),OFFSET($K$16,MAX($B$16:$B$506)-11,0,12,1)),"N/A") -> 0.57084148 | T6: =IFERROR(INTERCEPT(OFFSET(Q$16,MAX($B$16:$B$506)-11,0,12,1),OFFSET($K$16,MAX($B$16:$B$506)-11,0,12,1))*12,"N/A") -> 2.1012202 | U6: =IFERROR(STDEVP(OFFSET(Q$16,MAX($B$16:$B$506)-11,0,12,1))*SQRT(12),"N/A") -> 7.1053408 | W6: One Year | X6: {=IFERROR((GEOMEAN(1+OFFSET(X$16,MAX($B$16:$B$506)-11,0,12,1)/100)^12-1)*100,"N/A")} -> 4.3575279 | Y6: =IFERROR(X6-$K7,"N/A") -> -17.018744 | Z6: =IFERROR(SLOPE(OFFSET(X$16,MAX($B$16:$B$506)-11,0,12,1),OFFSET($K$16,MAX($B$16:$B$506)-11,0,12,1)),"N/A") -> -0.080393747 | AA6: =IFERROR(STDEVP(OFFSET(X$16,MAX($B$16:$B$506)-11,0,12,1))*SQRT(12),"N/A") -> 8.2295016
C7: Two Year | D7: {=IFERROR((GEOMEAN(1+OFFSET(D$16,MAX($B$16:$B$506)-23,0,24,1)/100)^12-1)*100,"N/A")} -> 14.743645 | E7: =IFERROR(D7-$K7,"N/A") -> -6.6326273 | F7: =IFERROR(SLOPE(OFFSET(D$16,MAX($B$16:$B$506)-23,0,24,1),OFFSET($K$16,MAX($B$16:$B$506)-23,0,24,1)),"N/A") -> 0.67719662 | G7: =IFERROR(INTERCEPT(OFFSET(D$16,MAX($B$16:$B$506)-23,0,24,1),OFFSET($K$16,MAX($B$16:$B$506)-23,0,24,1))*12,"N/A") -> 0.7309049 | H7: =IFERROR(STDEVP(OFFSET(D$16,MAX($B$16:$B$506)-23,0,24,1))*SQRT(12),"N/A") -> 9.9331019 | J7: Two Year | K7: {=IFERROR((GEOMEAN(1+OFFSET(K$16,MAX($B$16:$B$506)-23,0,24,1)/100)^12-1)*100,"N/A")} -> 21.376272 | L7: =IFERROR(SLOPE(OFFSET(K$16,MAX($B$16:$B$506)-23,0,24,1),OFFSET($K$16,MAX($B$16:$B$506)-23,0,24,1)),"N/A") -> 1 | M7: =IFERROR(STDEVP(OFFSET(K$16,MAX($B$16:$B$506)-23,0,24,1))*SQRT(12),"N/A") -> 10.408855 | P7: Two Year | Q7: {=IFERROR((GEOMEAN(1+OFFSET(Q$16,MAX($B$16:$B$506)-23,0,24,1)/100)^12-1)*100,"N/A")} -> 15.342648 | R7: =IFERROR(Q7-$K7,"N/A") -> -6.0336236 | S7: =IFERROR(SLOPE(OFFSET(Q$16,MAX($B$16:$B$506)-23,0,24,1),OFFSET($K$16,MAX($B$16:$B$506)-23,0,24,1)),"N/A") -> 0.70297198 | T7: =IFERROR(INTERCEPT(OFFSET(Q$16,MAX($B$16:$B$506)-23,0,24,1),OFFSET($K$16,MAX($B$16:$B$506)-23,0,24,1))*12,"N/A") -> 0.58014032 | U7: =IFERROR(STDEVP(OFFSET(Q$16,MAX($B$16:$B$506)-23,0,24,1))*SQRT(12),"N/A") -> 8.1174348 | W7: Two Year | X7: {=IFERROR((GEOMEAN(1+OFFSET(X$16,MAX($B$16:$B$506)-23,0,24,1)/100)^12-1)*100,"N/A")} -> 9.1946034 | Y7: =IFERROR(X7-$K8,"N/A") -> -13.787786 | Z7: =IFERROR(SLOPE(OFFSET(X$16,MAX($B$16:$B$506)-23,0,24,1),OFFSET($K$16,MAX($B$16:$B$506)-23,0,24,1)),"N/A") -> 0.36734111 | AA7: =IFERROR(STDEVP(OFFSET(X$16,MAX($B$16:$B$506)-23,0,24,1))*SQRT(12),"N/A") -> 10.053997
C8: Three Year | D8: {=IFERROR((GEOMEAN(1+OFFSET(D$16,MAX($B$16:$B$506)-35,0,36,1)/100)^12-1)*100,"N/A")} -> 13.639609 | E8: =IFERROR(D8-$K8,"N/A") -> -9.3427795 | F8: =IFERROR(SLOPE(OFFSET(D$16,MAX($B$16:$B$506)-35,0,36,1),OFFSET($K$16,MAX($B$16:$B$506)-35,0,36,1)),"N/A") -> 0.68543853 | G8: =IFERROR(INTERCEPT(OFFSET(D$16,MAX($B$16:$B$506)-35,0,36,1),OFFSET($K$16,MAX($B$16:$B$506)-35,0,36,1))*12,"N/A") -> -1.4054295 | H8: =IFERROR(STDEVP(OFFSET(D$16,MAX($B$16:$B$506)-35,0,36,1))*SQRT(12),"N/A") -> 10.184179 | J8: Three Year | K8: {=IFERROR((GEOMEAN(1+OFFSET(K$16,MAX($B$16:$B$506)-35,0,36,1)/100)^12-1)*100,"N/A")} -> 22.982389 | L8: =IFERROR(SLOPE(OFFSET(K$16,MAX($B$16:$B$506)-35,0,36,1),OFFSET($K$16,MAX($B$16:$B$506)-35,0,36,1)),"N/A") -> 1 | M8: =IFERROR(STDEVP(OFFSET(K$16,MAX($B$16:$B$506)-35,0,36,1))*SQRT(12),"N/A") -> 11.787719 | P8: Three Year | Q8: {=IFERROR((GEOMEAN(1+OFFSET(Q$16,MAX($B$16:$B$506)-35,0,36,1)/100)^12-1)*100,"N/A")} -> 16.938916 | R8: =IFERROR(Q8-$K8,"N/A") -> -6.0434732 | S8: =IFERROR(SLOPE(OFFSET(Q$16,MAX($B$16:$B$506)-35,0,36,1),OFFSET($K$16,MAX($B$16:$B$506)-35,0,36,1)),"N/A") -> 0.74561056 | T8: =IFERROR(INTERCEPT(OFFSET(Q$16,MAX($B$16:$B$506)-35,0,36,1),OFFSET($K$16,MAX($B$16:$B$506)-35,0,36,1))*12,"N/A") -> 0.12908565 | U8: =IFERROR(STDEVP(OFFSET(Q$16,MAX($B$16:$B$506)-35,0,36,1))*SQRT(12),"N/A") -> 9.5089491 | W8: Three Year | X8: {=IFERROR((GEOMEAN(1+OFFSET(X$16,MAX($B$16:$B$506)-35,0,36,1)/100)^12-1)*100,"N/A")} -> 6.2917988 | Y8: =IFERROR(X8-$K9,"N/A") -> -4.7936672 | Z8: =IFERROR(SLOPE(OFFSET(X$16,MAX($B$16:$B$506)-35,0,36,1),OFFSET($K$16,MAX($B$16:$B$506)-35,0,36,1)),"N/A") -> 0.48989091 | AA8: =IFERROR(STDEVP(OFFSET(X$16,MAX($B$16:$B$506)-35,0,36,1))*SQRT(12),"N/A") -> 10.468154
C9: Four Year | D9: {=IFERROR((GEOMEAN(1+OFFSET(D$16,MAX($B$16:$B$506)-47,0,48,1)/100)^12-1)*100,"N/A")} -> 6.8430999 | E9: =IFERROR(D9-$K9,"N/A") -> -4.2423661 | F9: =IFERROR(SLOPE(OFFSET(D$16,MAX($B$16:$B$506)-47,0,48,1),OFFSET($K$16,MAX($B$16:$B$506)-47,0,48,1)),"N/A") -> 0.74040922 | G9: =IFERROR(INTERCEPT(OFFSET(D$16,MAX($B$16:$B$506)-47,0,48,1),OFFSET($K$16,MAX($B$16:$B$506)-47,0,48,1))*12,"N/A") -> -1.2109496 | H9: =IFERROR(STDEVP(OFFSET(D$16,MAX($B$16:$B$506)-47,0,48,1))*SQRT(12),"N/A") -> 13.413597 | J9: Four Year | K9: {=IFERROR((GEOMEAN(1+OFFSET(K$16,MAX($B$16:$B$506)-47,0,48,1)/100)^12-1)*100,"N/A")} -> 11.085466 | L9: =IFERROR(SLOPE(OFFSET(K$16,MAX($B$16:$B$506)-47,0,48,1),OFFSET($K$16,MAX($B$16:$B$506)-47,0,48,1)),"N/A") -> 1 | M9: =IFERROR(STDEVP(OFFSET(K$16,MAX($B$16:$B$506)-47,0,48,1))*SQRT(12),"N/A") -> 15.787972 | P9: Four Year | Q9: {=IFERROR((GEOMEAN(1+OFFSET(Q$16,MAX($B$16:$B$506)-47,0,48,1)/100)^12-1)*100,"N/A")} -> 7.5142335 | R9: =IFERROR(Q9-$K9,"N/A") -> -3.5712325 | S9: =IFERROR(SLOPE(OFFSET(Q$16,MAX($B$16:$B$506)-47,0,48,1),OFFSET($K$16,MAX($B$16:$B$506)-47,0,48,1)),"N/A") -> 0.81284932 | T9: =IFERROR(INTERCEPT(OFFSET(Q$16,MAX($B$16:$B$506)-47,0,48,1),OFFSET($K$16,MAX($B$16:$B$506)-47,0,48,1))*12,"N/A") -> -1.4322126 | U9: =IFERROR(STDEVP(OFFSET(Q$16,MAX($B$16:$B$506)-47,0,48,1))*SQRT(12),"N/A") -> 13.386429 | W9: Four Year | X9: {=IFERROR((GEOMEAN(1+OFFSET(X$16,MAX($B$16:$B$506)-47,0,48,1)/100)^12-1)*100,"N/A")} -> 3.4615128 | Y9: =IFERROR(X9-$K10,"N/A") -> -10.938723 | Z9: =IFERROR(SLOPE(OFFSET(X$16,MAX($B$16:$B$506)-47,0,48,1),OFFSET($K$16,MAX($B$16:$B$506)-47,0,48,1)),"N/A") -> 0.55345764 | AA9: =IFERROR(STDEVP(OFFSET(X$16,MAX($B$16:$B$506)-47,0,48,1))*SQRT(12),"N/A") -> 12.138203
C10: Five Year | D10: {=IFERROR((GEOMEAN(1+OFFSET(D$16,MAX($B$16:$B$506)-59,0,60,1)/100)^12-1)*100,"N/A")} -> 9.084744 | E10: =IFERROR(D10-$K10,"N/A") -> -5.3154916 | F10: =IFERROR(SLOPE(OFFSET(D$16,MAX($B$16:$B$506)-59,0,60,1),OFFSET($K$16,MAX($B$16:$B$506)-59,0,60,1)),"N/A") -> 0.779603 | G10: =IFERROR(INTERCEPT(OFFSET(D$16,MAX($B$16:$B$506)-59,0,60,1),OFFSET($K$16,MAX($B$16:$B$506)-59,0,60,1))*12,"N/A") -> -1.8182154 | H10: =IFERROR(STDEVP(OFFSET(D$16,MAX($B$16:$B$506)-59,0,60,1))*SQRT(12),"N/A") -> 13.297042 | J10: Five Year | K10: {=IFERROR((GEOMEAN(1+OFFSET(K$16,MAX($B$16:$B$506)-59,0,60,1)/100)^12-1)*100,"N/A")} -> 14.400236 | L10: =IFERROR(SLOPE(OFFSET(K$16,MAX($B$16:$B$506)-59,0,60,1),OFFSET($K$16,MAX($B$16:$B$506)-59,0,60,1)),"N/A") -> 1 | M10: =IFERROR(STDEVP(OFFSET(K$16,MAX($B$16:$B$506)-59,0,60,1))*SQRT(12),"N/A") -> 14.98254 | P10: Five Year | Q10: {=IFERROR((GEOMEAN(1+OFFSET(Q$16,MAX($B$16:$B$506)-59,0,60,1)/100)^12-1)*100,"N/A")} -> 11.138063 | R10: =IFERROR(Q10-$K10,"N/A") -> -3.2621723 | S10: =IFERROR(SLOPE(OFFSET(Q$16,MAX($B$16:$B$506)-59,0,60,1),OFFSET($K$16,MAX($B$16:$B$506)-59,0,60,1)),"N/A") -> 0.84847872 | T10: =IFERROR(INTERCEPT(OFFSET(Q$16,MAX($B$16:$B$506)-59,0,60,1),OFFSET($K$16,MAX($B$16:$B$506)-59,0,60,1))*12,"N/A") -> -0.93936988 | U10: =IFERROR(STDEVP(OFFSET(Q$16,MAX($B$16:$B$506)-59,0,60,1))*SQRT(12),"N/A") -> 13.30768 | W10: Five Year | X10: {=IFERROR((GEOMEAN(1+OFFSET(X$16,MAX($B$16:$B$506)-59,0,60,1)/100)^12-1)*100,"N/A")} -> 7.349583 | Y10: =IFERROR(X10-$K11,"N/A") -> -7.4537143 | Z10: =IFERROR(SLOPE(OFFSET(X$16,MAX($B$16:$B$506)-59,0,60,1),OFFSET($K$16,MAX($B$16:$B$506)-59,0,60,1)),"N/A") -> 0.61101938 | AA10: =IFERROR(STDEVP(OFFSET(X$16,MAX($B$16:$B$506)-59,0,60,1))*SQRT(12),"N/A") -> 12.625094
C11: Ten Year | D11: {=IFERROR((GEOMEAN(1+OFFSET(D$16,MAX($B$16:$B$506)-119,0,120,1)/100)^12-1)*100,"N/A")} -> 11.300724 | E11: =IFERROR(D11-$K11,"N/A") -> -3.5025738 | F11: =IFERROR(SLOPE(OFFSET(D$16,MAX($B$16:$B$506)-119,0,120,1),OFFSET($K$16,MAX($B$16:$B$506)-119,0,120,1)),"N/A") -> 0.79918135 | G11: =IFERROR(INTERCEPT(OFFSET(D$16,MAX($B$16:$B$506)-119,0,120,1),OFFSET($K$16,MAX($B$16:$B$506)-119,0,120,1))*12,"N/A") -> -0.37666802 | H11: =IFERROR(STDEVP(OFFSET(D$16,MAX($B$16:$B$506)-119,0,120,1))*SQRT(12),"N/A") -> 13.193883 | J11: Ten Year | K11: {=IFERROR((GEOMEAN(1+OFFSET(K$16,MAX($B$16:$B$506)-119,0,120,1)/100)^12-1)*100,"N/A")} -> 14.803297 | L11: =IFERROR(SLOPE(OFFSET(K$16,MAX($B$16:$B$506)-119,0,120,1),OFFSET($K$16,MAX($B$16:$B$506)-119,0,120,1)),"N/A") -> 1 | M11: =IFERROR(STDEVP(OFFSET(K$16,MAX($B$16:$B$506)-119,0,120,1))*SQRT(12),"N/A") -> 15.056111 | P11: Ten Year | Q11: {=IFERROR((GEOMEAN(1+OFFSET(Q$16,MAX($B$16:$B$506)-119,0,120,1)/100)^12-1)*100,"N/A")} -> 12.825832 | R11: =IFERROR(Q11-$K11,"N/A") -> -1.9774654 | S11: =IFERROR(SLOPE(OFFSET(Q$16,MAX($B$16:$B$506)-119,0,120,1),OFFSET($K$16,MAX($B$16:$B$506)-119,0,120,1)),"N/A") -> 0.85660272 | T11: =IFERROR(INTERCEPT(OFFSET(Q$16,MAX($B$16:$B$506)-119,0,120,1),OFFSET($K$16,MAX($B$16:$B$506)-119,0,120,1))*12,"N/A") -> 0.15423806 | U11: =IFERROR(STDEVP(OFFSET(Q$16,MAX($B$16:$B$506)-119,0,120,1))*SQRT(12),"N/A") -> 13.350051 | W11: Ten Year | X11: {=IFERROR((GEOMEAN(1+OFFSET(X$16,MAX($B$16:$B$506)-119,0,120,1)/100)^12-1)*100,"N/A")} -> 8.9173184 | Y11: =IFERROR(X11-$K12,"N/A") -> 0.85041593 | Z11: =IF(P12="N/A","N/A",IFERROR(SLOPE(OFFSET(X$16,MAX($B$16:$B$506)-119,0,120,1),OFFSET($K$16,MAX($B$16:$B$506)-119,0,120,1)),"N/A")) -> 0.6470853 | AA11: =IFERROR(STDEVP(OFFSET(X$16,MAX($B$16:$B$506)-119,0,120,1))*SQRT(12),"N/A") -> 12.473098
C12: Model Incep. | D12: {=IFERROR((GEOMEAN(1+OFFSET(D$16,1,0,MAX($B$16:$B$506),1)/100)^12-1)*100,"N/A")} -> 11.898457 | E12: =IFERROR(D12-$K12,"N/A") -> 3.8315542 | F12: =IFERROR(SLOPE(OFFSET(D$16,1,0,MAX($B$16:$B$506),1),OFFSET($K$16,1,0,MAX($B$16:$B$506),1)),"N/A") -> 0.65366306 | G12: =IFERROR(INTERCEPT(OFFSET(D$16,1,0,MAX($B$16:$B$506),1),OFFSET($K$16,1,0,MAX($B$16:$B$506),1))*12,"N/A") -> 6.1814839 | H12: =IFERROR(STDEVP(OFFSET(D$16,1,0,MAX($B$16:$B$506),1))*SQRT(12),"N/A") -> 12.037363 | J12: Inception | K12: {=IFERROR((GEOMEAN(1+OFFSET(K$16,1,0,MAX($B$16:$B$506),1)/100)^12-1)*100,"N/A")} -> 8.0669024 | L12: =IFERROR(SLOPE(OFFSET(K$16,1,0,MAX($B$16:$B$506),1),OFFSET($K$16,1,0,MAX($B$16:$B$506),1)),"N/A") -> 1 | M12: =IFERROR(STDEVP(OFFSET(K$16,1,0,MAX($B$16:$B$506),1))*SQRT(12),"N/A") -> 15.141943 | P12: Model Incep. | Q12: {=IFERROR((GEOMEAN(1+OFFSET(Q$16,1,0,MAX($B$16:$B$506),1)/100)^12-1)*100,"N/A")} -> 7.1818795 | R12: =IFERROR(Q12-$K12,"N/A") -> -0.88502295 | S12: =IFERROR(SLOPE(OFFSET(Q$16,1,0,MAX($B$16:$B$506),1),OFFSET($K$16,1,0,MAX($B$16:$B$506),1)),"N/A") -> 0.80660002 | T12: =IFERROR(INTERCEPT(OFFSET(Q$16,1,0,MAX($B$16:$B$506),1),OFFSET($K$16,1,0,MAX($B$16:$B$506),1))*12,"N/A") -> 0.56007074 | U12: =IFERROR(STDEVP(OFFSET(Q$16,1,0,MAX($B$16:$B$506),1))*SQRT(12),"N/A") -> 12.724272 | W12: Model Incep. | X12: {=IFERROR((GEOMEAN(1+OFFSET(X$16,1,0,MAX($B$16:$B$506),1)/100)^12-1)*100,"N/A")} -> 9.3867894 | Y12: =IFERROR(X12-$K13,"N/A") -> -4.5680677 | Z12: =IFERROR(SLOPE(OFFSET(X$16,1,0,MAX($B$16:$B$506),1),OFFSET($K$16,1,0,MAX($B$16:$B$506),1)),"N/A") -> 0.58320267 | AA12: =IFERROR(STDEVP(OFFSET(X$16,1,0,MAX($B$16:$B$506),1))*SQRT(12),"N/A") -> 11.687065
C13: Feb'11 Incep. | D13: {=IFERROR((GEOMEAN(1+OFFSET(D$149,1,0,MAX($B$16:$B$506)-133,1)/100)^(MIN(COUNTA(OFFSET(D$149,1,0,MAX($B$16:$B$506)-133,1)),12))-1)*100,"N/A")} -> 12.725923 | E13: =IFERROR(D13-$K13,"N/A") -> -1.2289342 | F13: =IFERROR(SLOPE(OFFSET(D$149,1,0,MAX($B$16:$B$506)-133,1),OFFSET($K$149,1,0,MAX($B$16:$B$506)-133,1)),"N/A") -> 0.72821754 | G13: =IFERROR(INTERCEPT(OFFSET(D$149,1,0,MAX($B$16:$B$506)-133,1),OFFSET($K$149,1,0,MAX($B$16:$B$506)-133,1))*12,"N/A") -> 2.4433103 | H13: =IFERROR(STDEVP(OFFSET(D$149,1,0,MAX($B$16:$B$506)-133,1))*SQRT(12),"N/A") -> 11.705171 | J13: Feb'11 Incep. | K13: {=IFERROR((GEOMEAN(1+OFFSET(K$149,1,0,MAX($B$16:$B$506)-133,1)/100)^(MIN(COUNTA(OFFSET(K$149,1,0,MAX($B$16:$B$506)-133,1)),12))-1)*100,"N/A")} -> 13.954857 | L13: =IFERROR(SLOPE(OFFSET(K$149,1,0,MAX($B$16:$B$506)-133,1),OFFSET($K$149,1,0,MAX($B$16:$B$506)-133,1)),"N/A") -> 1 | M13: =IFERROR(STDEVP(OFFSET(K$149,1,0,MAX($B$16:$B$506)-133,1))*SQRT(12),"N/A") -> 14.03842 | P13: Feb'11 Incep. | Q13: {=IFERROR((GEOMEAN(1+OFFSET(Q$149,1,0,MAX($B$16:$B$506)-133,1)/100)^(MIN(COUNTA(OFFSET(Q$149,1,0,MAX($B$16:$B$506)-133,1)),12))-1)*100,"N/A")} -> 12.932305 | R13: =IFERROR(Q13-$K13,"N/A") -> -1.0225522 | S13: =IFERROR(SLOPE(OFFSET(Q$149,1,0,MAX($B$16:$B$506)-133,1),OFFSET($K$149,1,0,MAX($B$16:$B$506)-133,1)),"N/A") -> 0.84675574 | T13: =IFERROR(INTERCEPT(OFFSET(Q$149,1,0,MAX($B$16:$B$506)-133,1),OFFSET($K$149,1,0,MAX($B$16:$B$506)-133,1))*12,"N/A") -> 1.0242804 | U13: =IFERROR(STDEVP(OFFSET(Q$149,1,0,MAX($B$16:$B$506)-133,1))*SQRT(12),"N/A") -> 12.304197 | W13: Feb'11 Incep. | X13: {=IFERROR((GEOMEAN(1+OFFSET(X$149,1,0,MAX($B$16:$B$506)-133,1)/100)^(MIN(COUNTA(OFFSET(X$149,1,0,MAX($B$16:$B$506)-133,1)),12))-1)*100,"N/A")} -> 10.642852 | Y13: =IFERROR(X13-$K14,"N/A") -> 10.642852 | Z13: =IFERROR(SLOPE(OFFSET(X$102,1,0,MAX($B$16:$B$506)-86,1),OFFSET($K$102,1,0,MAX($B$16:$B$506)-86,1)),"N/A") -> 0.63650071 | AA13: =IFERROR(STDEVP(OFFSET(X$102,1,0,MAX($B$16:$B$506)-86,1))*SQRT(12),"N/A") -> 12.022481 | AC13: Composite Performance
AC14: SILVX | AE14: UNC LC | AG14: Asbestos | AI14: BHI Senior Living (26761461) | AK14: Cynthia Simon-Skjodt (32056582) | AM14: Sisters of St Benedict (42547037) | AO14: French Capital Investors (46872499) | AQ14: St Paul Hermitage (57304051) | AS14: Tony Cercy (79114916) | AU14: Leonardo Locascio (44175471) | AW14: Walter Miller (66237513) | AY14: Composite
A15: Date | B15: # | C15: Porfolio | D15: Gross Return | E15: Growth | F15: Annual | G15: Quarterly | J15: Date | K15: Return | L15: Growth | M15: Annual | N15: Quarterly | P15: Date | Q15: Return | R15: Growth | S15: Annual | T15: Quarterly | AC15: Return | AD15: AUM | AE15: Return | AF15: AUM | AG15: Return | AH15: AUM | AI15: Return | AJ15: AUM | AK15: Return | AL15: AUM | AM15: Return | AN15: AUM | AO15: Return | AP15: AUM | AQ15: Return | AR15: AUM | AS15: Return | AT15: AUM | AU15: Return | AV15: AUM | AW15: Return | AX15: AUM | AY15: Return | AZ15: AUM
A16: 36525 | B16: 0 | E16: 1000000 | J16: =$A16 -> 36525 | L16: 1000000 | P16: =$A16 -> 36525 | R16: 1000000 | W16: =$A16 -> 36525 | Y16: 1000000
A17: 36556 | B17: =IF(A17>A16,1+B16,"-") -> 1 | C17: Model | D17: -4.22 | E17: =E16*D17/100+E16 -> 957800 | J17: =$A17 -> 36556 | K17: -5.0242437 | L17: =L16*K17/100+L16 -> 949757.56 | P17: =$A17 -> 36556 | Q17: -3.7996474 | R17: =R16*Q17/100+R16 -> 962003.53 | W17: =$A17 -> 36556 | X17: -3.5109291 | Y17: =Y16*X17/100+Y16 -> 964890.71
A18: 36585 | B18: =IF(A18>A17,1+B17,"-") -> 2 | C18: Model | D18: -7.58 | E18: =E17*D18/100+E17 -> 885198.76 | J18: =$A18 -> 36585 | K18: -1.8937944 | L18: =L17*K18/100+L17 -> 931771.11 | P18: =$A18 -> 36585 | Q18: -6.7517383 | R18: =R17*Q18/100+R17 -> 897051.57 | W18: =$A18 -> 36585 | X18: -10.51414 | Y18: =Y17*X18/100+Y17 -> 863440.75
A19: 36616 | B19: =IF(A19>A18,1+B18,"-") -> 3 | C19: Model | D19: 13.21 | E19: =E18*D19/100+E18 -> 1002133.5 | G19: =(E19/E16-1)*100 -> 0.21335162 | J19: =$A19 -> 36616 | K19: 9.7830709 | L19: =L18*K19/100+L18 -> 1022926.9 | N19: =(L19/L16-1)*100 -> 2.2926936 | P19: =$A19 -> 36616 | Q19: 10.20982 | R19: =R18*Q19/100+R18 -> 988638.92 | T19: =(R19/R16-1)*100 -> -1.1361085 | W19: =$A19 -> 36616 | X19: 9.3534453 | Y19: =Y18*X19/100+Y18 -> 944202.21 | AA19: =(Y19/Y16-1)*100 -> -5.5797794
A20: 36646 | B20: =IF(A20>A19,1+B19,"-") -> 4 | C20: Model | D20: 3.05 | E20: =E19*D20/100+E19 -> 1032698.6 | J20: =$A20 -> 36646 | K20: -3.0091713 | L20: =L19*K20/100+L19 -> 992145.31 | P20: =$A20 -> 36646 | Q20: -1.0985094 | R20: =R19*Q20/100+R19 -> 977778.62 | W20: =$A20 -> 36646 | X20: 4.7344924 | Y20: =Y19*X20/100+Y19 -> 988905.39
A21: 36677 | B21: =IF(A21>A20,1+B20,"-") -> 5 | C21: Model | D21: 0.28 | E21: =E20*D21/100+E20 -> 1035590.1 | J21: =$A21 -> 36677 | K21: -2.0522676 | L21: =L20*K21/100+L20 -> 971783.84 | P21: =$A21 -> 36677 | Q21: 1.2422987 | R21: =R20*Q21/100+R20 -> 989925.55 | W21: =$A21 -> 36677 | X21: 4.9107001 | Y21: =Y20*X21/100+Y20 -> 1037467.6
A22: 36707 | B22: =IF(A22>A21,1+B21,"-") -> 6 | C22: Model | D22: -0.53 | E22: =E21*D22/100+E21 -> 1030101.5 | G22: =(E22/E19-1)*100 -> 2.7908457 | J22: =$A22 -> 36707 | K22: 2.4652586 | L22: =L21*K22/100+L21 -> 995740.82 | N22: =(L22/L19-1)*100 -> -2.6576791 | P22: =$A22 -> 36707 | Q22: 1.7420177 | R22: =R21*Q22/100+R21 -> 1007170.2 | T22: =(R22/R19-1)*100 -> 1.8744273 | W22: =$A22 -> 36707 | X22: -4.1760746 | Y22: =Y21*X22/100+Y21 -> 994142.15 | AA22: =(Y22/Y19-1)*100 -> 5.2891149
A23: 36738 | B23: =IF(A23>A22,1+B22,"-") -> 7 | C23: Model | D23: -0.47 | E23: =E22*D23/100+E22 -> 1025260 | J23: =$A23 -> 36738 | K23: -1.5573152 | L23: =L22*K23/100+L22 -> 980234 | P23: =$A23 -> 36738 | Q23: -1.0405934 | R23: =R22*Q23/100+R22 -> 996689.69 | W23: =$A23 -> 36738 | X23: 1.3630468 | Y23: =Y22*X23/100+Y22 -> 1007692.8
A24: 36769 | B24: =IF(A24>A23,1+B23,"-") -> 8 | C24: Model | D24: 0.2 | E24: =E23*D24/100+E23 -> 1027310.6 | J24: =$A24 -> 36769 | K24: 6.2114813 | L24: =L23*K24/100+L23 -> 1041121 | P24: =$A24 -> 36769 | Q24: 4.1027128 | R24: =R23*Q24/100+R23 -> 1037581 | W24: =$A24 -> 36769 | X24: 7.4544539 | Y24: =Y23*X24/100+Y23 -> 1082810.8
A25: 36799 | B25: =IF(A25>A24,1+B24,"-") -> 9 | C25: Model | D25: 4.74 | E25: =E24*D25/100+E24 -> 1076005.1 | G25: =(E25/E22-1)*100 -> 4.4562174 | J25: =$A25 -> 36799 | K25: -5.2795736 | L25: =L24*K25/100+L24 -> 986154.3 | N25: =(L25/L22-1)*100 -> -0.96275291 | P25: =$A25 -> 36799 | Q25: -2.4192023 | R25: =R24*Q25/100+R24 -> 1012479.8 | T25: =(R25/R22-1)*100 -> 0.52717843 | W25: =$A25 -> 36799 | X25: 3.158566 | Y25: =Y24*X25/100+Y24 -> 1117012.1 | AA25: =(Y25/Y22-1)*100 -> 12.35939
A26: 36830 | B26: =IF(A26>A25,1+B25,"-") -> 10 | C26: Model | D26: 1.04 | E26: =E25*D26/100+E25 -> 1087195.5 | J26: =$A26 -> 36830 | K26: -0.42330523 | L26: =L25*K26/100+L25 -> 981979.85 | P26: =$A26 -> 36830 | Q26: 2.9561552 | R26: =R25*Q26/100+R25 -> 1042410.3 | W26: =$A26 -> 36830 | X26: 2.3517126 | Y26: =Y25*X26/100+Y25 -> 1143281
A27: 36860 | B27: =IF(A27>A26,1+B26,"-") -> 11 | C27: Model | D27: 0.83 | E27: =E26*D27/100+E26 -> 1096219.3 | J27: =$A27 -> 36860 | K27: -7.8835014 | L27: =L26*K27/100+L26 -> 904565.46 | P27: =$A27 -> 36860 | Q27: -3.6785295 | R27: =R26*Q27/100+R26 -> 1004064.9 | W27: =$A27 -> 36860 | X27: 1.7025759 | Y27: =Y26*X27/100+Y26 -> 1162746.2
A28: 36891 | B28: =IF(A28>A27,1+B27,"-") -> 12 | C28: Model | D28: 6.43 | E28: =E27*D28/100+E27 -> 1166706.2 | F28: =(E28-E16)/E16*100 -> 16.670615 | G28: =(E28/E25-1)*100 -> 8.429428 | J28: =$A28 -> 36891 | K28: 0.48873135 | L28: =L27*K28/100+L27 -> 908986.35 | M28: =(L28-L16)/L16*100 -> -9.1013646 | N28: =(L28/L25-1)*100 -> -7.8251388 | P28: =$A28 -> 36891 | Q28: -0.62846487 | R28: =R27*Q28/100+R27 -> 997754.73 | S28: =(R28-R16)/R16*100 -> -0.22452737 | T28: =(R28/R25-1)*100 -> -1.4543589 | W28: =$A28 -> 36891 | X28: 7.5325175 | Y28: =Y27*X28/100+Y27 -> 1250330.3 | AA28: =(Y28/Y25-1)*100 -> 11.935252
A29: 36922 | B29: =IF(A29>A28,1+B28,"-") -> 13 | C29: Model | D29: -0.62 | E29: =E28*D29/100+E28 -> 1159472.6 | J29: =$A29 -> 36922 | K29: 3.5478697 | L29: =L28*K29/100+L28 -> 941236 | P29: =$A29 -> 36922 | Q29: -0.34175608 | R29: =R28*Q29/100+R28 -> 994344.84 | W29: =$A29 -> 36922 | X29: -4.3133685 | Y29: =Y28*X29/100+Y28 -> 1196398.9
A30: 36950 | B30: =IF(A30>A29,1+B29,"-") -> 14 | C30: Model | D30: 2.02 | E30: =E29*D30/100+E29 -> 1182893.9 | J30: =$A30 -> 36950 | K30: -9.1189455 | L30: =L29*K30/100+L29 -> 855405.21 | P30: =$A30 -> 36950 | Q30: -4.5916623 | R30: =R29*Q30/100+R29 -> 948687.88 | W30: =$A30 -> 36950 | X30: 2.8779234 | Y30: =Y29*X30/100+Y29 -> 1230830.3
A31: 36981 | B31: =IF(A31>A30,1+B30,"-") -> 15 | C31: Model | D31: -2.11 | E31: =E30*D31/100+E30 -> 1157934.9 | G31: =(E31/E28-1)*100 -> -0.75179974 | J31: =$A31 -> 36981 | K31: -6.334973 | L31: =L30*K31/100+L30 -> 801215.52 | N31: =(L31/L28-1)*100 -> -11.856155 | P31: =$A31 -> 36981 | Q31: -5.3831855 | R31: =R30*Q31/100+R30 -> 897618.25 | T31: =(R31/R28-1)*100 -> -10.036181 | W31: =$A31 -> 36981 | X31: -1.2489882 | Y31: =Y30*X31/100+Y30 -> 1215457.4 | AA31: =(Y31/Y28-1)*100 -> -2.7890897
A32: 37011 | B32: =IF(A32>A31,1+B31,"-") -> 16 | C32: Model | D32: 6.72 | E32: =E31*D32/100+E31 -> 1235748.1 | J32: =$A32 -> 37011 | K32: 7.7701831 | L32: =L31*K32/100+L31 -> 863471.43 | P32: =$A32 -> 37011 | Q32: 6.6005994 | R32: =R31*Q32/100+R31 -> 956866.44 | W32: =$A32 -> 37011 | X32: 5.2440859 | Y32: =Y31*X32/100+Y31 -> 1279197.1
A33: 37042 | B33: =IF(A33>A32,1+B32,"-") -> 17 | C33: Model | D33: 3.17 | E33: =E32*D33/100+E32 -> 1274921.3 | J33: =$A33 -> 37042 | K33: 0.66989034 | L33: =L32*K33/100+L32 -> 869255.74 | P33: =$A33 -> 37042 | Q33: 0.99856242 | R33: =R32*Q33/100+R32 -> 966421.35 | W33: =$A33 -> 37042 | X33: 3.6247619 | Y33: =Y32*X33/100+Y32 -> 1325564.9
A34: 37072 | B34: =IF(A34>A33,1+B33,"-") -> 18 | C34: Model | D34: 0.07 | E34: =E33*D34/100+E33 -> 1275813.7 | G34: =(E34/E31-1)*100 -> 10.180096 | J34: =$A34 -> 37072 | K34: -2.4345302 | L34: =L33*K34/100+L33 -> 848093.45 | N34: =(L34/L31-1)*100 -> 5.8508516 | P34: =$A34 -> 37072 | Q34: -2.5146445 | R34: =R33*Q34/100+R33 -> 942119.28 | T34: =(R34/R31-1)*100 -> 4.957679 | W34: =$A34 -> 37072 | X34: -2.4726242 | Y34: =Y33*X34/100+Y33 -> 1292788.7 | AA34: =(Y34/Y31-1)*100 -> 6.3623158
A35: 37103 | B35: =IF(A35>A34,1+B34,"-") -> 19 | C35: Model | D35: -1.65 | E35: =E34*D35/100+E34 -> 1254762.8 | J35: =$A35 -> 37103 | K35: -0.98539293 | L35: =L34*K35/100+L34 -> 839736.4 | P35: =$A35 -> 37103 | Q35: -0.10469571 | R35: =R34*Q35/100+R34 -> 941132.93 | W35: =$A35 -> 37103 | X35: -0.39044209 | Y35: =Y34*X35/100+Y34 -> 1287741.1
A36: 37134 | B36: =IF(A36>A35,1+B35,"-") -> 20 | C36: Model | D36: -0.23 | E36: =E35*D36/100+E35 -> 1251876.9 | J36: =$A36 -> 37134 | K36: -6.259903 | L36: =L35*K36/100+L35 -> 787169.71 | P36: =$A36 -> 37134 | Q36: -4.1201586 | R36: =R35*Q36/100+R35 -> 902356.76 | W36: =$A36 -> 37134 | X36: 0.053862557 | Y36: =Y35*X36/100+Y35 -> 1288434.7
A37: 37164 | B37: =IF(A37>A36,1+B36,"-") -> 21 | C37: Model | D37: -3.34 | E37: =E36*D37/100+E36 -> 1210064.2 | G37: =(E37/E34-1)*100 -> -5.1535398 | J37: =$A37 -> 37164 | K37: -8.0765443 | L37: =L36*K37/100+L36 -> 723593.6 | N37: =(L37/L34-1)*100 -> -14.679968 | P37: =$A37 -> 37164 | Q37: -3.6734538 | R37: =R36*Q37/100+R36 -> 869209.1 | T37: =(R37/R34-1)*100 -> -7.738955 | W37: =$A37 -> 37164 | X37: -4.6035036 | Y37: =Y36*X37/100+Y36 -> 1229121.5 | AA37: =(Y37/Y34-1)*100 -> -4.9247893
A38: 37195 | B38: =IF(A38>A37,1+B37,"-") -> 22 | C38: Model | D38: -0.02 | E38: =E37*D38/100+E37 -> 1209822.2 | J38: =$A38 -> 37195 | K38: 1.9053654 | L38: =L37*K38/100+L37 -> 737380.7 | P38: =$A38 -> 37195 | Q38: -0.19510438 | R38: =R37*Q38/100+R37 -> 867513.23 | W38: =$A38 -> 37195 | X38: -0.78952634 | Y38: =Y37*X38/100+Y37 -> 1219417.3
A39: 37225 | B39: =IF(A39>A38,1+B38,"-") -> 23 | C39: Model | D39: 4.74 | E39: =E38*D39/100+E38 -> 1267167.7 | J39: =$A39 -> 37225 | K39: 7.6715489 | L39: =L38*K39/100+L38 -> 793949.23 | P39: =$A39 -> 37225 | Q39: 4.7526157 | R39: =R38*Q39/100+R38 -> 908742.8 | W39: =$A39 -> 37225 | X39: 3.395764 | Y39: =Y38*X39/100+Y38 -> 1260825.8
A40: 37256 | B40: =IF(A40>A39,1+B39,"-") -> 24 | C40: Model | D40: 4.02 | E40: =E39*D40/100+E39 -> 1318107.9 | F40: =(E40-E28)/E28*100 -> 12.976851 | G40: =(E40/E37-1)*100 -> 8.9287579 | J40: =$A40 -> 37256 | K40: 0.87621202 | L40: =L39*K40/100+L39 -> 800905.9 | M40: =(L40-L28)/L28*100 -> -11.890217 | N40: =(L40/L37-1)*100 -> 10.684492 | P40: =$A40 -> 37256 | Q40: 1.2979157 | R40: =R39*Q40/100+R39 -> 920537.52 | S40: =(R40-R28)/R28*100 -> -7.7390972 | T40: =(R40/R37-1)*100 -> 5.9051868 | W40: =$A40 -> 37256 | X40: 3.5005376 | Y40: =Y39*X40/100+Y39 -> 1304961.5 | AA40: =(Y40/Y37-1)*100 -> 6.1702586
A41: 37287 | B41: =IF(A41>A40,1+B40,"-") -> 25 | C41: Model | D41: -1.85 | E41: =E40*D41/100+E40 -> 1293722.9 | J41: =$A41 -> 37287 | K41: -1.4591355 | L41: =L40*K41/100+L40 -> 789219.6 | P41: =$A41 -> 37287 | Q41: -0.83238713 | R41: =R40*Q41/100+R40 -> 912875.08 | W41: =$A41 -> 37287 | X41: -0.24498138 | Y41: =Y40*X41/100+Y40 -> 1301764.6
A42: 37315 | B42: =IF(A42>A41,1+B41,"-") -> 26 | C42: Model | D42: 1.34 | E42: =E41*D42/100+E41 -> 1311058.8 | J42: =$A42 -> 37315 | K42: -1.9299633 | L42: =L41*K42/100+L41 -> 773987.95 | P42: =$A42 -> 37315 | Q42: 1.1064504 | R42: =R41*Q42/100+R41 -> 922975.59 | W42: =$A42 -> 37315 | X42: 2.6350525 | Y42: =Y41*X42/100+Y41 -> 1336066.8
A43: 37346 | B43: =IF(A43>A42,1+B42,"-") -> 27 | C43: Model | D43: 7.41 | E43: =E42*D43/100+E42 -> 1408208.2 | G43: =(E43/E40-1)*100 -> 6.8355821 | J43: =$A43 -> 37346 | K43: 3.7602607 | L43: =L42*K43/100+L42 -> 803091.92 | N43: =(L43/L40-1)*100 -> 0.27294258 | P43: =$A43 -> 37346 | Q43: 1.901526 | R43: =R42*Q43/100+R42 -> 940526.21 | T43: =(R43/R40-1)*100 -> 2.1714156 | W43: =$A43 -> 37346 | X43: 4.6300513 | Y43: =Y42*X43/100+Y42 -> 1397927.4 | AA43: =(Y43/Y40-1)*100 -> 7.1240297
A44: 37376 | B44: =IF(A44>A43,1+B43,"-") -> 28 | C44: Model | D44: -0.84 | E44: =E43*D44/100+E43 -> 1396379.3 | J44: =$A44 -> 37376 | K44: -6.0635566 | L44: =L43*K44/100+L43 -> 754395.98 | P44: =$A44 -> 37376 | Q44: -5.2617955 | R44: =R43*Q44/100+R43 -> 891037.65 | W44: =$A44 -> 37376 | X44: -0.19598733 | Y44: =Y43*X44/100+Y43 -> 1395187.6
A45: 37407 | B45: =IF(A45>A44,1+B44,"-") -> 29 | C45: Model | D45: 0.33 | E45: =E44*D45/100+E44 -> 1400987.3 | J45: =$A45 -> 37407 | K45: -0.73730849 | L45: =L44*K45/100+L44 -> 748833.76 | P45: =$A45 -> 37407 | Q45: -0.5778654 | R45: =R44*Q45/100+R44 -> 885888.65 | W45: =$A45 -> 37407 | X45: -0.40652887 | Y45: =Y44*X45/100+Y44 -> 1389515.8
A46: 37437 | B46: =IF(A46>A45,1+B45,"-") -> 30 | C46: Model | D46: -3.09 | E46: =E45*D46/100+E45 -> 1357696.8 | G46: =(E46/E43-1)*100 -> -3.5869273 | J46: =$A46 -> 37437 | K46: -7.1145149 | L46: =L45*K46/100+L45 -> 695557.87 | N46: =(L46/L43-1)*100 -> -13.390005 | P46: =$A46 -> 37437 | Q46: -5.3806288 | R46: =R45*Q46/100+R45 -> 838222.27 | T46: =(R46/R43-1)*100 -> -10.877309 | W46: =$A46 -> 37437 | X46: -3.234875 | Y46: =Y45*X46/100+Y45 -> 1344566.7 | AA46: =(Y46/Y43-1)*100 -> -3.8171296
A47: 37468 | B47: =IF(A47>A46,1+B46,"-") -> 31 | C47: Model | D47: -5.38 | E47: =E46*D47/100+E46 -> 1284652.7 | J47: =$A47 -> 37468 | K47: -7.795149 | L47: =L46*K47/100+L46 -> 641338.1 | P47: =$A47 -> 37468 | Q47: -5.8181354 | R47: =R46*Q47/100+R46 -> 789453.36 | W47: =$A47 -> 37468 | X47: -6.0299528 | Y47: =Y46*X47/100+Y46 -> 1263489.9
A48: 37499 | B48: =IF(A48>A47,1+B47,"-") -> 32 | C48: Model | D48: -0.42 | E48: =E47*D48/100+E47 -> 1279257.2 | J48: =$A48 -> 37499 | K48: 0.65484365 | L48: =L47*K48/100+L47 -> 645537.86 | P48: =$A48 -> 37499 | Q48: 0.72354799 | R48: =R47*Q48/100+R47 -> 795165.44 | W48: =$A48 -> 37499 | X48: 1.1959926 | Y48: =Y47*X48/100+Y47 -> 1278601.2
A49: 37529 | B49: =IF(A49>A48,1+B48,"-") -> 33 | C49: Model | D49: -5.43 | E49: =E48*D49/100+E48 -> 1209793.5 | G49: =(E49/E46-1)*100 -> -10.893691 | J49: =$A49 -> 37529 | K49: -10.867942 | L49: =L48*K49/100+L48 -> 575381.18 | N49: =(L49/L46-1)*100 -> -17.277741 | P49: =$A49 -> 37529 | Q49: -9.9631231 | R49: =R48*Q49/100+R48 -> 715942.13 | T49: =(R49/R46-1)*100 -> -14.588033 | W49: =$A49 -> 37529 | X49: -7.7098149 | Y49: =Y48*X49/100+Y48 -> 1180023.4 | AA49: =(Y49/Y46-1)*100 -> -12.237643
A50: 37560 | B50: =IF(A50>A49,1+B49,"-") -> 34 | C50: Model | D50: 2.85 | E50: =E49*D50/100+E49 -> 1244272.6 | J50: =$A50 -> 37560 | K50: 8.8015692 | L50: =L49*K50/100+L49 -> 626023.75 | P50: =$A50 -> 37560 | Q50: 7.3309994 | R50: =R49*Q50/100+R49 -> 768427.84 | W50: =$A50 -> 37560 | X50: 3.0159158 | Y50: =Y49*X50/100+Y49 -> 1215611.9
A51: 37590 | B51: =IF(A51>A50,1+B50,"-") -> 35 | C51: Model | D51: 2.84 | E51: =E50*D51/100+E50 -> 1279610 | J51: =$A51 -> 37590 | K51: 5.8859708 | L51: =L50*K51/100+L50 -> 662871.33 | P51: =$A51 -> 37590 | Q51: 1.7565989 | R51: =R50*Q51/100+R50 -> 781926.03 | W51: =$A51 -> 37590 | X51: -0.12864105 | Y51: =Y50*X51/100+Y50 -> 1214048.1
A52: 37621 | B52: =IF(A52>A51,1+B51,"-") -> 36 | C52: Model | D52: -0.24 | E52: =E51*D52/100+E51 -> 1276538.9 | F52: =(E52-E40)/E40*100 -> -3.1536843 | G52: =(E52/E49-1)*100 -> 5.5170897 | J52: =$A52 -> 37621 | K52: -5.8756759 | L52: =L51*K52/100+L51 -> 623923.16 | M52: =(L52-L40)/L40*100 -> -22.09782 | N52: =(L52/L49-1)*100 -> 8.4364902 | P52: =$A52 -> 37621 | Q52: -3.3318864 | R52: =R51*Q52/100+R51 -> 755873.15 | S52: =(R52-R40)/R40*100 -> -17.88785 | T52: =(R52/R49-1)*100 -> 5.5774091 | W52: =$A52 -> 37621 | X52: -0.21294664 | Y52: =Y51*X52/100+Y51 -> 1211462.9 | AA52: =(Y52/Y49-1)*100 -> 2.6643084
A53: 37652 | B53: =IF(A53>A52,1+B52,"-") -> 37 | C53: Model | D53: -3.6 | E53: =E52*D53/100+E52 -> 1230583.5 | J53: =$A53 -> 37652 | K53: -2.6196491 | L53: =L52*K53/100+L52 -> 607578.56 | P53: =$A53 -> 37652 | Q53: -3.2514793 | R53: =R52*Q53/100+R52 -> 731296.09 | W53: =$A53 -> 37652 | X53: -2.0018061 | Y53: =Y52*X53/100+Y52 -> 1187211.7
A54: 37680 | B54: =IF(A54>A53,1+B53,"-") -> 38 | C54: Model | D54: -0.42 | E54: =E53*D54/100+E53 -> 1225415.1 | J54: =$A54 -> 37680 | K54: -1.500384 | L54: =L53*K54/100+L53 -> 598462.55 | P54: =$A54 -> 37680 | Q54: -2.2920472 | R54: =R53*Q54/100+R53 -> 714534.44 | W54: =$A54 -> 37680 | X54: -1.3235571 | Y54: =Y53*X54/100+Y53 -> 1171498.3
A55: 37711 | B55: =IF(A55>A54,1+B54,"-") -> 39 | C55: Model | D55: 1.81 | E55: =E54*D55/100+E54 -> 1247595.1 | G55: =(E55/E52-1)*100 -> -2.2673683 | J55: =$A55 -> 37711 | K55: 0.96986083 | L55: =L54*K55/100+L54 -> 604266.8 | N55: =(L55/L52-1)*100 -> -3.1504449 | P55: =$A55 -> 37711 | Q55: 1.719119 | R55: =R54*Q55/100+R54 -> 726818.13 | T55: =(R55/R52-1)*100 -> -3.8439007 | W55: =$A55 -> 37711 | X55: 0.58507389 | Y55: =Y54*X55/100+Y54 -> 1178352.4 | AA55: =(Y55/Y52-1)*100 -> -2.7330951
A56: 37741 | B56: =IF(A56>A55,1+B55,"-") -> 40 | C56: Model | D56: 5.52 | E56: =E55*D56/100+E55 -> 1316462.3 | J56: =$A56 -> 37741 | K56: 8.2347753 | L56: =L55*K56/100+L55 -> 654026.82 | P56: =$A56 -> 37741 | Q56: 5.7619831 | R56: =R55*Q56/100+R55 -> 768697.27 | W56: =$A56 -> 37741 | X56: 5.3792498 | Y56: =Y55*X56/100+Y55 -> 1241738.9
A57: 37772 | B57: =IF(A57>A56,1+B56,"-") -> 41 | C57: Model | D57: 5.62 | E57: =E56*D57/100+E56 -> 1390447.5 | J57: =$A57 -> 37772 | K57: 5.2682982 | L57: =L56*K57/100+L56 -> 688482.9 | P57: =$A57 -> 37772 | Q57: 3.5828549 | R57: =R56*Q57/100+R56 -> 796238.58 | W57: =$A57 -> 37772 | X57: 6.2604099 | Y57: =Y56*X57/100+Y56 -> 1319476.9
A58: 37802 | B58: =IF(A58>A57,1+B57,"-") -> 42 | C58: Model | D58: 3.92 | E58: =E57*D58/100+E57 -> 1444953 | G58: =(E58/E55-1)*100 -> 15.819073 | J58: =$A58 -> 37802 | K58: 1.2751871 | L58: =L57*K58/100+L57 -> 697262.34 | N58: =(L58/L55-1)*100 -> 15.389815 | P58: =$A58 -> 37802 | Q58: 0.88071285 | R58: =R57*Q58/100+R57 -> 803251.16 | T58: =(R58/R55-1)*100 -> 10.516114 | W58: =$A58 -> 37802 | X58: -0.62865431 | Y58: =Y57*X58/100+Y57 -> 1311181.9 | AA58: =(Y58/Y55-1)*100 -> 11.272478
A59: 37833 | B59: =IF(A59>A58,1+B58,"-") -> 43 | C59: Model | D59: 1.97 | E59: =E58*D59/100+E58 -> 1473418.6 | J59: =$A59 -> 37833 | K59: 1.7595249 | L59: =L58*K59/100+L58 -> 709530.85 | P59: =$A59 -> 37833 | Q59: 0.3761046 | R59: =R58*Q59/100+R58 -> 806272.22 | W59: =$A59 -> 37833 | X59: 0.35346565 | Y59: =Y58*X59/100+Y58 -> 1315816.5
A60: 37864 | B60: =IF(A60>A59,1+B59,"-") -> 44 | C60: Model | D60: 1.26 | E60: =E59*D60/100+E59 -> 1491983.7 | J60: =$A60 -> 37864 | K60: 1.9495851 | L60: =L59*K60/100+L59 -> 723363.76 | P60: =$A60 -> 37864 | Q60: 0.58757201 | R60: =R59*Q60/100+R59 -> 811009.65 | W60: =$A60 -> 37864 | X60: 1.0315034 | Y60: =Y59*X60/100+Y59 -> 1329389.2
A61: 37894 | B61: =IF(A61>A60,1+B60,"-") -> 45 | C61: Model | D61: 0.93 | E61: =E60*D61/100+E60 -> 1505859.1 | G61: =(E61/E58-1)*100 -> 4.2150918 | J61: =$A61 -> 37894 | K61: -1.0626342 | L61: =L60*K61/100+L60 -> 715677.05 | N61: =(L61/L58-1)*100 -> 2.6410004 | P61: =$A61 -> 37894 | Q61: -0.32234876 | R61: =R60*Q61/100+R60 -> 808395.37 | T61: =(R61/R58-1)*100 -> 0.64042421 | W61: =$A61 -> 37894 | X61: 0.92539671 | Y61: =Y60*X61/100+Y60 -> 1341691.3 | AA61: =(Y61/Y58-1)*100 -> 2.3268619
A62: 37925 | B62: =IF(A62>A61,1+B61,"-") -> 46 | C62: Model | D62: 4.71 | E62: =E61*D62/100+E61 -> 1576785.1 | J62: =$A62 -> 37925 | K62: 5.6532876 | L62: =L61*K62/100+L61 -> 756136.33 | P62: =$A62 -> 37925 | Q62: 3.6363759 | R62: =R61*Q62/100+R61 -> 837791.67 | W62: =$A62 -> 37925 | X62: 4.7509276 | Y62: =Y61*X62/100+Y61 -> 1405434.1
A63: 37955 | B63: =IF(A63>A62,1+B62,"-") -> 47 | C63: Model | D63: 2.69 | E63: =E62*D63/100+E62 -> 1619200.6 | J63: =$A63 -> 37955 | K63: 0.87824574 | L63: =L62*K63/100+L62 -> 762777.06 | P63: =$A63 -> 37955 | Q63: 0.81258477 | R63: =R62*Q63/100+R62 -> 844599.43 | W63: =$A63 -> 37955 | X63: 1.1537159 | Y63: =Y62*X63/100+Y62 -> 1421648.8
A64: 37986 | B64: =IF(A64>A63,1+B63,"-") -> 48 | C64: Model | D64: 5.07 | E64: =E63*D64/100+E63 -> 1701294.1 | F64: =(E64-E52)/E52*100 -> 33.273971 | G64: =(E64/E61-1)*100 -> 12.978303 | J64: =$A64 -> 37986 | K64: 5.2430503 | L64: =L63*K64/100+L63 -> 802769.85 | M64: =(L64-L52)/L52*100 -> 28.664859 | N64: =(L64/L61-1)*100 -> 12.169288 | P64: =$A64 -> 37986 | Q64: 4.7449351 | R64: =R63*Q64/100+R63 -> 884675.13 | S64: =(R64-R52)/R52*100 -> 17.040158 | T64: =(R64/R61-1)*100 -> 9.4359468 | W64: =$A64 -> 37986 | X64: 4.6021467 | Y64: =Y63*X64/100+Y63 -> 1487075.2 | AA64: =(Y64/Y61-1)*100 -> 10.835865
A65: 38017 | B65: =IF(A65>A64,1+B64,"-") -> 49 | C65: Model | D65: 2.39 | E65: =E64*D65/100+E64 -> 1741955 | J65: =$A65 -> 38017 | K65: 1.8354691 | L65: =L64*K65/100+L64 -> 817504.44 | P65: =$A65 -> 38017 | Q65: 1.2549239 | R65: =R64*Q65/100+R64 -> 895777.13 | W65: =$A65 -> 38017 | X65: 1.2911515 | Y65: =Y64*X65/100+Y64 -> 1506275.6
A66: 38046 | B66: =IF(A66>A65,1+B65,"-") -> 50 | C66: Model | D66: 2.25 | E66: =E65*D66/100+E65 -> 1781149 | J66: =$A66 -> 38046 | K66: 1.3894051 | L66: =L65*K66/100+L65 -> 828862.89 | P66: =$A66 -> 38046 | Q66: 1.5268347 | R66: =R65*Q66/100+R65 -> 909454.16 | W66: =$A66 -> 38046 | X66: 3.0044248 | Y66: =Y65*X66/100+Y65 -> 1551530.5
A67: 38077 | B67: =IF(A67>A66,1+B66,"-") -> 51 | C67: Model | D67: 1.81 | E67: =E66*D67/100+E66 -> 1813387.8 | G67: =(E67/E64-1)*100 -> 6.5887323 | J67: =$A67 -> 38077 | K67: -1.5087779 | L67: =L66*K67/100+L66 -> 816357.19 | N67: =(L67/L64-1)*100 -> 1.6925574 | P67: =$A67 -> 38077 | Q67: -1.3835666 | R67: =R66*Q67/100+R66 -> 896871.26 | T67: =(R67/R64-1)*100 -> 1.3786 | W67: =$A67 -> 38077 | X67: 0.49398922 | Y67: =Y66*X67/100+Y66 -> 1559194.9 | AA67: =(Y67/Y64-1)*100 -> 4.8497685
A68: 38107 | B68: =IF(A68>A67,1+B67,"-") -> 52 | C68: Model | D68: -2.23 | E68: =E67*D68/100+E67 -> 1772949.3 | J68: =$A68 -> 38107 | K68: -1.569817 | L68: =L67*K68/100+L67 -> 803541.88 | P68: =$A68 -> 38107 | Q68: 0.29481951 | R68: =R67*Q68/100+R67 -> 899515.41 | W68: =$A68 -> 38107 | X68: -1.0898863 | Y68: =Y67*X68/100+Y67 -> 1542201.5
A69: 38138 | B69: =IF(A69>A68,1+B68,"-") -> 53 | C69: Model | D69: 0.09 | E69: =E68*D69/100+E68 -> 1774544.9 | J69: =$A69 -> 38138 | K69: 1.3714253 | L69: =L68*K69/100+L68 -> 814561.85 | P69: =$A69 -> 38138 | Q69: 1.1161332 | R69: =R68*Q69/100+R68 -> 909555.2 | W69: =$A69 -> 38138 | X69: 1.9537694 | Y69: =Y68*X69/100+Y68 -> 1572332.5
A70: 38168 | B70: =IF(A70>A69,1+B69,"-") -> 54 | C70: Model | D70: 5.27 | E70: =E69*D70/100+E69 -> 1868063.4 | G70: =(E70/E67-1)*100 -> 3.0151092 | J70: =$A70 -> 38168 | K70: 1.9445436 | L70: =L69*K70/100+L69 -> 830401.36 | N70: =(L70/L67-1)*100 -> 1.7203465 | P70: =$A70 -> 38168 | Q70: 1.3143367 | R70: =R69*Q70/100+R69 -> 921509.82 | T70: =(R70/R67-1)*100 -> 2.7471679 | W70: =$A70 -> 38168 | X70: 1.313378 | Y70: =Y69*X70/100+Y69 -> 1592983.2 | AA70: =(Y70/Y67-1)*100 -> 2.1670337
A71: 38199 | B71: =IF(A71>A70,1+B70,"-") -> 55 | C71: Model | D71: -1.78 | E71: =E70*D71/100+E70 -> 1834811.9 | J71: =$A71 -> 38199 | K71: -3.3097521 | L71: =L70*K71/100+L70 -> 802917.13 | P71: =$A71 -> 38199 | Q71: -1.9831654 | R71: =R70*Q71/100+R70 -> 903234.76 | W71: =$A71 -> 38199 | X71: -1.476258 | Y71: =Y70*X71/100+Y70 -> 1569466.6
A72: 38230 | B72: =IF(A72>A71,1+B71,"-") -> 56 | C72: Model | D72: 0.78 | E72: =E71*D72/100+E71 -> 1849123.4 | J72: =$A72 -> 38230 | K72: 0.403387 | L72: =L71*K72/100+L71 -> 806156 | P72: =$A72 -> 38230 | Q72: 1.3836257 | R72: =R71*Q72/100+R71 -> 915732.14 | W72: =$A72 -> 38230 | X72: 2.542361 | Y72: =Y71*X72/100+Y71 -> 1609368.2
A73: 38260 | B73: =IF(A73>A72,1+B72,"-") -> 57 | C73: Model | D73: 2.01 | E73: =E72*D73/100+E72 -> 1886290.8 | G73: =(E73/E70-1)*100 -> 0.97573693 | J73: =$A73 -> 38260 | K73: 1.0830983 | L73: =L72*K73/100+L72 -> 814887.46 | N73: =(L73/L70-1)*100 -> -1.8682414 | P73: =$A73 -> 38260 | Q73: 0.37522432 | R73: =R72*Q73/100+R72 -> 919168.19 | T73: =(R73/R70-1)*100 -> -0.25410746 | W73: =$A73 -> 38260 | X73: 0.46291489 | Y73: =Y72*X73/100+Y72 -> 1616818.2 | AA73: =(Y73/Y70-1)*100 -> 1.4962475
A74: 38291 | B74: =IF(A74>A73,1+B73,"-") -> 58 | C74: Model | D74: 0.82 | E74: =E73*D74/100+E73 -> 1901758.4 | J74: =$A74 -> 38291 | K74: 1.5277379 | L74: =L73*K74/100+L73 -> 827336.8 | P74: =$A74 -> 38291 | Q74: 0.80763871 | R74: =R73*Q74/100+R73 -> 926591.75 | W74: =$A74 -> 38291 | X74: 1.9375068 | Y74: =Y73*X74/100+Y73 -> 1648144.1
A75: 38321 | B75: =IF(A75>A74,1+B74,"-") -> 59 | C75: Model | D75: 4.61 | E75: =E74*D75/100+E74 -> 1989429.5 | J75: =$A75 -> 38321 | K75: 4.0461445 | L75: =L74*K75/100+L74 -> 860812.05 | P75: =$A75 -> 38321 | Q75: 3.2235838 | R75: =R74*Q75/100+R74 -> 956461.21 | W75: =$A75 -> 38321 | X75: 3.3659806 | Y75: =Y74*X75/100+Y74 -> 1703620.3
A76: 38352 | B76: =IF(A76>A75,1+B75,"-") -> 60 | C76: Model | D76: 5.23 | E76: =E75*D76/100+E75 -> 2093476.6 | F76: =(E76-E64)/E64*100 -> 23.052013 | G76: =(E76/E73-1)*100 -> 10.983768 | J76: =$A76 -> 38352 | K76: 3.3996651 | L76: =L75*K76/100+L75 -> 890076.77 | M76: =(L76-L64)/L64*100 -> 10.875711 | N76: =(L76/L73-1)*100 -> 9.2269569 | P76: =$A76 -> 38352 | Q76: 2.9684397 | R76: =R75*Q76/100+R75 -> 984853.19 | S76: =(R76-R64)/R64*100 -> 11.323712 | T76: =(R76/R73-1)*100 -> 7.1461343 | W76: =$A76 -> 38352 | X76: 2.727091 | Y76: =Y75*X76/100+Y75 -> 1750079.6 | AA76: =(Y76/Y73-1)*100 -> 8.242204
A77: 38383 | B77: =IF(A77>A76,1+B76,"-") -> 61 | C77: Model | D77: -0.64 | E77: =E76*D77/100+E76 -> 2080078.4 | J77: =$A77 -> 38383 | K77: -2.4374624 | L77: =L76*K77/100+L76 -> 868381.49 | P77: =$A77 -> 38383 | Q77: -1.3978776 | R77: =R76*Q77/100+R76 -> 971086.15 | W77: =$A77 -> 38383 | X77: -1.4774128 | Y77: =Y76*X77/100+Y76 -> 1724223.7
A78: 38411 | B78: =IF(A78>A77,1+B77,"-") -> 62 | C78: Model | D78: 0.84 | E78: =E77*D78/100+E77 -> 2097551 | J78: =$A78 -> 38411 | K78: 2.1043923 | L78: =L77*K78/100+L77 -> 886655.64 | P78: =$A78 -> 38411 | Q78: 2.214273 | R78: =R77*Q78/100+R77 -> 992588.64 | W78: =$A78 -> 38411 | X78: 0.80546215 | Y78: =Y77*X78/100+Y77 -> 1738111.7
A79: 38442 | B79: =IF(A79>A78,1+B78,"-") -> 63 | C79: Model | D79: -0.53 | E79: =E78*D79/100+E78 -> 2086434 | G79: =(E79/E76-1)*100 -> -0.33640751 | J79: =$A79 -> 38442 | K79: -1.7707812 | L79: =L78*K79/100+L78 -> 870954.91 | N79: =(L79/L76-1)*100 -> -2.1483388 | P79: =$A79 -> 38442 | Q79: -1.8409354 | R79: =R78*Q79/100+R78 -> 974315.73 | T79: =(R79/R76-1)*100 -> -1.0699524 | W79: =$A79 -> 38442 | X79: -0.46381617 | Y79: =Y78*X79/100+Y78 -> 1730050 | AA79: =(Y79/Y76-1)*100 -> -1.144495
A80: 38472 | B80: =IF(A80>A79,1+B79,"-") -> 64 | C80: Model | D80: -1.66 | E80: =E79*D80/100+E79 -> 2051799.2 | J80: =$A80 -> 38472 | K80: -1.8965257 | L80: =L79*K80/100+L79 -> 854437.03 | P80: =$A80 -> 38472 | Q80: -1.5651005 | R80: =R79*Q80/100+R79 -> 959066.71 | W80: =$A80 -> 38472 | X80: -0.060502352 | Y80: =Y79*X80/100+Y79 -> 1729003.3
A81: 38503 | B81: =IF(A81>A80,1+B80,"-") -> 65 | C81: Model | D81: 3.46 | E81: =E80*D81/100+E80 -> 2122791.5 | J81: =$A81 -> 38503 | K81: 3.1818293 | L81: =L80*K81/100+L80 -> 881623.75 | P81: =$A81 -> 38503 | Q81: 2.1340678 | R81: =R80*Q81/100+R80 -> 979533.84 | W81: =$A81 -> 38503 | X81: 1.5034454 | Y81: =Y80*X81/100+Y80 -> 1754997.9
A82: 38533 | B82: =IF(A82>A81,1+B81,"-") -> 66 | C82: Model | D82: 3.38 | E82: =E81*D82/100+E81 -> 2194541.8 | G82: =(E82/E79-1)*100 -> 5.1814627 | J82: =$A82 -> 38533 | K82: 0.14197974 | L82: =L81*K82/100+L81 -> 882875.48 | N82: =(L82/L79-1)*100 -> 1.3686784 | P82: =$A82 -> 38533 | Q82: -0.65988047 | R82: =R81*Q82/100+R81 -> 973070.09 | T82: =(R82/R79-1)*100 -> -0.12784755 | W82: =$A82 -> 38533 | X82: -0.003592909 | Y82: =Y81*X82/100+Y81 -> 1754934.9 | AA82: =(Y82/Y79-1)*100 -> 1.4383887
A83: 38564 | B83: =IF(A83>A82,1+B82,"-") -> 67 | C83: Model | D83: 2.62 | E83: =E82*D83/100+E82 -> 2252038.8 | J83: =$A83 -> 38564 | K83: 3.7187488 | L83: =L82*K83/100+L82 -> 915707.4 | P83: =$A83 -> 38564 | Q83: 2.5037729 | R83: =R82*Q83/100+R82 -> 997433.55 | W83: =$A83 -> 38564 | X83: 2.4015867 | Y83: =Y82*X83/100+Y82 -> 1797081.2
A84: 38595 | B84: =IF(A84>A83,1+B83,"-") -> 68 | C84: Model | D84: -1.69 | E84: =E83*D84/100+E83 -> 2213979.4 | J84: =$A84 -> 38595 | K84: -0.91215042 | L84: =L83*K84/100+L83 -> 907354.77 | P84: =$A84 -> 38595 | Q84: -1.1860102 | R84: =R83*Q84/100+R83 -> 985603.89 | W84: =$A84 -> 38595 | X84: -1.0084211 | Y84: =Y83*X84/100+Y83 -> 1778959
A85: 38625 | B85: =IF(A85>A84,1+B84,"-") -> 69 | C85: Model | D85: 1.24 | E85: =E84*D85/100+E84 -> 2241432.7 | G85: =(E85/E82-1)*100 -> 2.136705 | J85: =$A85 -> 38625 | K85: 0.8099054 | L85: =L84*K85/100+L84 -> 914703.49 | N85: =(L85/L82-1)*100 -> 3.6050392 | P85: =$A85 -> 38625 | Q85: 0.22018032 | R85: =R84*Q85/100+R84 -> 987774 | T85: =(R85/R82-1)*100 -> 1.5110841 | W85: =$A85 -> 38625 | X85: -0.050509347 | Y85: =Y84*X85/100+Y84 -> 1778060.5 | AA85: =(Y85/Y82-1)*100 -> 1.3177467
A86: 38656 | B86: =IF(A86>A85,1+B85,"-") -> 70 | C86: Model | D86: -2.95 | E86: =E85*D86/100+E85 -> 2175310.4 | J86: =$A86 -> 38656 | K86: -1.6670311 | L86: =L85*K86/100+L85 -> 899455.1 | P86: =$A86 -> 38656 | Q86: -1.9101744 | R86: =R85*Q86/100+R85 -> 968905.79 | W86: =$A86 -> 38656 | X86: -1.6633952 | Y86: =Y85*X86/100+Y85 -> 1748484.3
A87: 38686 | B87: =IF(A87>A86,1+B86,"-") -> 71 | C87: Model | D87: 0.33 | E87: =E86*D87/100+E86 -> 2182489 | J87: =$A87 -> 38686 | K87: 3.7821852 | L87: =L86*K87/100+L86 -> 933474.15 | P87: =$A87 -> 38686 | Q87: 2.7450377 | R87: =R86*Q87/100+R86 -> 995502.62 | W87: =$A87 -> 38686 | X87: 2.053063 | Y87: =Y86*X87/100+Y86 -> 1784381.8
A88: 38717 | B88: =IF(A88>A87,1+B87,"-") -> 72 | C88: Model | D88: 3.32 | E88: =E87*D88/100+E87 -> 2254947.6 | F88: =(E88-E76)/E76*100 -> 7.7130531 | G88: =(E88/E85-1)*100 -> 0.6029578 | J88: =$A88 -> 38717 | K88: 0.030360766 | L88: =L87*K88/100+L87 -> 933757.56 | M88: =(L88-L76)/L76*100 -> 4.9075305 | N88: =(L88/L85-1)*100 -> 2.0830876 | P88: =$A88 -> 38717 | Q88: -0.49207319 | R88: =R87*Q88/100+R87 -> 990604.02 | S88: =(R88-R76)/R76*100 -> 0.58392757 | T88: =(R88/R85-1)*100 -> 0.28650492 | W88: =$A88 -> 38717 | X88: 0.23393383 | Y88: =Y87*X88/100+Y87 -> 1788556.1 | AA88: =(Y88/Y85-1)*100 -> 0.59028276
A89: 38748 | B89: =IF(A89>A88,1+B88,"-") -> 73 | C89: Model | D89: 1 | E89: =E88*D89/100+E88 -> 2277497.1 | J89: =$A89 -> 38748 | K89: 2.6477865 | L89: =L88*K89/100+L88 -> 958481.47 | P89: =$A89 -> 38748 | Q89: 1.3903931 | R89: =R88*Q89/100+R88 -> 1004377.3 | W89: =$A89 -> 38748 | X89: 0.80187415 | Y89: =Y88*X89/100+Y88 -> 1802898
A90: 38776 | B90: =IF(A90>A89,1+B89,"-") -> 74 | C90: Model | D90: 1.72 | E90: =E89*D90/100+E89 -> 2316670 | J90: =$A90 -> 38776 | K90: 0.27106004 | L90: =L89*K90/100+L89 -> 961079.53 | P90: =$A90 -> 38776 | Q90: 0.41842509 | R90: =R89*Q90/100+R89 -> 1008579.9 | W90: =$A90 -> 38776 | X90: 2.3525606 | Y90: =Y89*X90/100+Y89 -> 1845312.3
A91: 38807 | B91: =IF(A91>A90,1+B90,"-") -> 75 | C91: Model | D91: 1.47 | E91: =E90*D91/100+E90 -> 2350725.1 | G91: =(E91/E88-1)*100 -> 4.2474368 | J91: =$A91 -> 38807 | K91: 1.2433129 | L91: =L90*K91/100+L90 -> 973028.76 | N91: =(L91/L88-1)*100 -> 4.2057162 | P91: =$A91 -> 38807 | Q91: 0.80868169 | R91: =R90*Q91/100+R90 -> 1016736.1 | T91: =(R91/R88-1)*100 -> 2.6379923 | W91: =$A91 -> 38807 | X91: 0.65214643 | Y91: =Y90*X91/100+Y90 -> 1857346.4 | AA91: =(Y91/Y88-1)*100 -> 3.8461403
A92: 38837 | B92: =IF(A92>A91,1+B91,"-") -> 76 | C92: Model | D92: -0.42 | E92: =E91*D92/100+E91 -> 2340852 | J92: =$A92 -> 38837 | K92: 1.3427741 | L92: =L91*K92/100+L91 -> 986094.33 | P92: =$A92 -> 38837 | Q92: 0.86556353 | R92: =R91*Q92/100+R91 -> 1025536.6 | W92: =$A92 -> 38837 | X92: 2.1635844 | Y92: =Y91*X92/100+Y91 -> 1897531.7
A93: 38868 | B93: =IF(A93>A92,1+B92,"-") -> 77 | C93: Model | D93: -0.86 | E93: =E92*D93/100+E92 -> 2320720.7 | J93: =$A93 -> 38868 | K93: -2.8781302 | L93: =L92*K93/100+L92 -> 957713.26 | P93: =$A93 -> 38868 | Q93: -2.1535735 | R93: =R92*Q93/100+R92 -> 1003450.9 | W93: =$A93 -> 38868 | X93: -0.76811756 | Y93: =Y92*X93/100+Y92 -> 1882956.4
A94: 38898 | B94: =IF(A94>A93,1+B93,"-") -> 78 | C94: Model | D94: 1.49 | E94: =E93*D94/100+E93 -> 2355299.4 | G94: =(E94/E91-1)*100 -> 0.19459382 | J94: =$A94 -> 38898 | K94: 0.13289554 | L94: =L93*K94/100+L93 -> 958986.01 | N94: =(L94/L91-1)*100 -> -1.4431992 | P94: =$A94 -> 38898 | Q94: 0.13473955 | R94: =R93*Q94/100+R93 -> 1004802.9 | T94: =(R94/R91-1)*100 -> -1.1736715 | W94: =$A94 -> 38898 | X94: 0.43667684 | Y94: =Y93*X94/100+Y93 -> 1891178.9 | AA94: =(Y94/Y91-1)*100 -> 1.8215459
A95: 38929 | B95: =IF(A95>A94,1+B94,"-") -> 79 | C95: Model | D95: 0.18 | E95: =E94*D95/100+E94 -> 2359539 | J95: =$A95 -> 38929 | K95: 0.61685312 | L95: =L94*K95/100+L94 -> 964901.55 | P95: =$A95 -> 38929 | Q95: 1.5581554 | R95: =R94*Q95/100+R94 -> 1020459.3 | W95: =$A95 -> 38929 | X95: 2.1868946 | Y95: =Y94*X95/100+Y94 -> 1932536.9
A96: 38960 | B96: =IF(A96>A95,1+B95,"-") -> 80 | C96: Model | D96: 2.6 | E96: =E95*D96/100+E95 -> 2420887 | J96: =$A96 -> 38960 | K96: 2.3793072 | L96: =L95*K96/100+L95 -> 987859.52 | P96: =$A96 -> 38960 | Q96: 2.1797859 | R96: =R95*Q96/100+R95 -> 1042703.2 | W96: =$A96 -> 38960 | X96: 2.1864253 | Y96: =Y95*X96/100+Y95 -> 1974790.4
A97: 38990 | B97: =IF(A97>A96,1+B96,"-") -> 81 | C97: Model | D97: 2.72 | E97: =E96*D97/100+E96 -> 2486735.1 | G97: =(E97/E94-1)*100 -> 5.5804233 | J97: =$A97 -> 38990 | K97: 2.5744988 | L97: =L96*K97/100+L96 -> 1013292 | N97: =(L97/L94-1)*100 -> 5.6628499 | P97: =$A97 -> 38990 | Q97: 1.9453843 | R97: =R96*Q97/100+R96 -> 1062987.7 | T97: =(R97/R94-1)*100 -> 5.7906682 | W97: =$A97 -> 38990 | X97: 2.0467267 | Y97: =Y96*X97/100+Y96 -> 2015209 | AA97: =(Y97/Y94-1)*100 -> 6.55835
A98: 39021 | B98: =IF(A98>A97,1+B97,"-") -> 82 | C98: Model | D98: 2.75 | E98: =E97*D98/100+E97 -> 2555120.3 | J98: =$A98 -> 39021 | K98: 3.2586431 | L98: =L97*K98/100+L97 -> 1046311.5 | P98: =$A98 -> 39021 | Q98: 2.5310934 | R98: =R97*Q98/100+R97 -> 1089892.9 | W98: =$A98 -> 39021 | X98: 2.8015319 | Y98: =Y97*X98/100+Y97 -> 2071665.7
A99: 39051 | B99: =IF(A99>A98,1+B98,"-") -> 83 | C99: Model | D99: 1.75 | E99: =E98*D99/100+E98 -> 2599834.9 | J99: =$A99 -> 39051 | K99: 1.9018103 | L99: =L98*K99/100+L98 -> 1066210.4 | P99: =$A99 -> 39051 | Q99: 1.3980821 | R99: =R98*Q99/100+R98 -> 1105130.5 | W99: =$A99 -> 39051 | X99: 1.0108158 | Y99: =Y98*X99/100+Y98 -> 2092606.4
A100: 39082 | B100: =IF(A100>A99,1+B99,"-") -> 84 | C100: Model | D100: 2.85 | E100: =E99*D100/100+E99 -> 2673930.2 | F100: =(E100-E88)/E88*100 -> 18.580593 | G100: =(E100/E97-1)*100 -> 7.5277466 | J100: =$A100 -> 39082 | K100: 1.3938645 | L100: =L99*K100/100+L99 -> 1081071.9 | M100: =(L100-L88)/L88*100 -> 15.776509 | N100: =(L100/L97-1)*100 -> 6.6890846 | P100: =$A100 -> 39082 | Q100: 1.7874384 | R100: =R99*Q100/100+R99 -> 1124884.1 | S100: =(R100-R88)/R88*100 -> 13.555372 | T100: =(R100/R97-1)*100 -> 5.8228648 | W100: =$A100 -> 39082 | X100: 2.298809 | Y100: =Y99*X100/100+Y99 -> 2140711.5 | AA100: =(Y100/Y97-1)*100 -> 6.2277647
A101: 39113 | B101: =IF(A101>A100,1+B100,"-") -> 85 | C101: Model | D101: 2.34 | E101: =E100*D101/100+E100 -> 2736500.2 | J101: =$A101 -> 39113 | K101: 1.512291 | L101: =L100*K101/100+L100 -> 1097420.9 | P101: =$A101 -> 39113 | Q101: 0.72498355 | R101: =R100*Q101/100+R100 -> 1133039.3 | W101: =$A101 -> 39113 | X101: 1.0263729 | Y101: =Y100*X101/100+Y100 -> 2162683.1
A102: 39141 | B102: =IF(A102>A101,1+B101,"-") -> 86 | C102: Model | D102: -1.73 | E102: =E101*D102/100+E101 -> 2689158.7 | J102: =$A102 -> 39141 | K102: -1.9557481 | L102: =L101*K102/100+L101 -> 1075958.1 | P102: =$A102 -> 39141 | Q102: -2.5164217 | R102: =R101*Q102/100+R101 -> 1104527.3 | W102: =$A102 -> 39141 | X102: 0.063414591 | Y102: =Y101*X102/100+Y101 -> 2164054.6
...

Sheet LC (Net)
C1: Large Cap (Net) | J1: S&P 500® Index | P1: Russell Defensive® Index | W1: S&P 500 Low Volatility Total Return Index
D4: Return | E4: Relative Return | F4: Beta | G4: Alpha | H4: stdevp | K4: Return | L4: Beta | M4: stdevp | Q4: Return | R4: Relative Return | S4: Beta | T4: Alpha | U4: stdevp | X4: Return | Y4: Relative Return | Z4: Beta | AA4: stdevp
B5: 12 | C5: YTD | D5: {=IFERROR((GEOMEAN(1+OFFSET(D$16,MAX($B$16:$B$506)-$B$5+1,0,$B$5,1)/100)^$B$5-1)*100,"N/A")} -> 9.0771338 | E5: =IFERROR(D5-$K5,"N/A") -> -8.7828501 | F5: =IFERROR(SLOPE(OFFSET(D$16,MAX($B$16:$B$506)-$B$5+1,0,$B$5,1),OFFSET($K$16,MAX($B$16:$B$506)-$B$5+1,0,$B$5,1)),"N/A") -> 0.30071459 | G5: {=IFERROR(INTERCEPT(OFFSET(D$16,MAX($B$16:$B$506)-$B$5+1,0,$B$5,1),OFFSET($K$16,MAX($B$16:$B$506)-$B$5+1,0,$B$5,1))*12,"N/A")} -> 3.8005156 | H5: =IFERROR(STDEVP(OFFSET(D$16,MAX($B$16:$B$506)-$B$5+1,0,$B$5,1))*SQRT(12),"N/A") -> 6.7137267 | J5: YTD | K5: {=IFERROR((GEOMEAN(1+OFFSET(K$16,MAX($B$16:$B$506)-$B$5+1,0,$B$5,1)/100)^$B$5-1)*100,"N/A")} -> 17.859984 | L5: =IFERROR(SLOPE(OFFSET(K$16,MAX($B$16:$B$506)-$B$5+1,0,$B$5,1),OFFSET($K$16,MAX($B$16:$B$506)-$B$5+1,0,$B$5,1)),"N/A") -> 1 | M5: =IFERROR(STDEVP(OFFSET(K$16,MAX($B$16:$B$506)-$B$5+1,0,$B$5,1))*SQRT(12),"N/A") -> 10.521019 | P5: YTD | Q5: {=IFERROR((GEOMEAN(1+OFFSET(Q$16,MAX($B$16:$B$506)-$B$5+1,0,$B$5,1)/100)^$B$5-1)*100,"N/A")} -> 12.246788 | R5: =IFERROR(Q5-$K5,"N/A") -> -5.6131961 | S5: =IFERROR(SLOPE(OFFSET(Q$16,MAX($B$16:$B$506)-$B$5+1,0,$B$5,1),OFFSET($K$16,MAX($B$16:$B$506)-$B$5+1,0,$B$5,1)),"N/A") -> 0.57084148 | T5: {=IFERROR(INTERCEPT(OFFSET(Q$16,MAX($B$16:$B$506)-$B$5+1,0,$B$5,1),OFFSET($K$16,MAX($B$16:$B$506)-$B$5+1,0,$B$5,1))*12,"N/A")} -> 2.1012202 | U5: =IFERROR(STDEVP(OFFSET(Q$16,MAX($B$16:$B$506)-$B$5+1,0,$B$5,1))*SQRT(12),"N/A") -> 7.1053408 | W5: YTD | X5: {=IFERROR((GEOMEAN(1+OFFSET(X$16,MAX($B$16:$B$506)-$B$5+1,0,$B$5,1)/100)^$B$5-1)*100,"N/A")} -> 4.3575279 | Y5: =IFERROR(X5-$K6,"N/A") -> -13.502456 | Z5: =IFERROR(SLOPE(OFFSET(X$16,MAX($B$16:$B$506)-$B$5+1,0,$B$5,1),OFFSET($K$16,MAX($B$16:$B$506)-$B$5+1,0,$B$5,1)),"N/A") -> -0.080393747 | AA5: =IFERROR(STDEVP(OFFSET(X$16,MAX($B$16:$B$506)-$B$5+1,0,$B$5,1))*SQRT(12),"N/A") -> 8.2295016
C6: One Year | D6: {=IFERROR((GEOMEAN(1+OFFSET(D$16,MAX($B$16:$B$506)-11,0,12,1)/100)^12-1)*100,"N/A")} -> 9.0771338 | E6: =IFERROR(D6-$K6,"N/A") -> -8.7828501 | F6: =IFERROR(SLOPE(OFFSET(D$16,MAX($B$16:$B$506)-11,0,12,1),OFFSET($K$16,MAX($B$16:$B$506)-11,0,12,1)),"N/A") -> 0.30071459 | G6: =IFERROR(INTERCEPT(OFFSET(D$16,MAX($B$16:$B$506)-11,0,12,1),OFFSET($K$16,MAX($B$16:$B$506)-11,0,12,1))*12,"N/A") -> 3.8005156 | H6: =IFERROR(STDEVP(OFFSET(D$16,MAX($B$16:$B$506)-11,0,12,1))*SQRT(12),"N/A") -> 6.7137267 | J6: One Year | K6: {=IFERROR((GEOMEAN(1+OFFSET(K$16,MAX($B$16:$B$506)-11,0,12,1)/100)^12-1)*100,"N/A")} -> 17.859984 | L6: =IFERROR(SLOPE(OFFSET(K$16,MAX($B$16:$B$506)-11,0,12,1),OFFSET($K$16,MAX($B$16:$B$506)-11,0,12,1)),"N/A") -> 1 | M6: =IFERROR(STDEVP(OFFSET(K$16,MAX($B$16:$B$506)-11,0,12,1))*SQRT(12),"N/A") -> 10.521019 | P6: One Year | Q6: {=IFERROR((GEOMEAN(1+OFFSET(Q$16,MAX($B$16:$B$506)-11,0,12,1)/100)^12-1)*100,"N/A")} -> 12.246788 | R6: =IFERROR(Q6-$K6,"N/A") -> -5.6131961 | S6: =IFERROR(SLOPE(OFFSET(Q$16,MAX($B$16:$B$506)-11,0,12,1),OFFSET($K$16,MAX($B$16:$B$506)-11,0,12,1)),"N/A") -> 0.57084148 | T6: =IFERROR(INTERCEPT(OFFSET(Q$16,MAX($B$16:$B$506)-11,0,12,1),OFFSET($K$16,MAX($B$16:$B$506)-11,0,12,1))*12,"N/A") -> 2.1012202 | U6: =IFERROR(STDEVP(OFFSET(Q$16,MAX($B$16:$B$506)-11,0,12,1))*SQRT(12),"N/A") -> 7.1053408 | W6: One Year | X6: {=IFERROR((GEOMEAN(1+OFFSET(X$16,MAX($B$16:$B$506)-11,0,12,1)/100)^12-1)*100,"N/A")} -> 4.3575279 | Y6: =IFERROR(X6-$K7,"N/A") -> -17.018744 | Z6: =IFERROR(SLOPE(OFFSET(X$16,MAX($B$16:$B$506)-11,0,12,1),OFFSET($K$16,MAX($B$16:$B$506)-11,0,12,1)),"N/A") -> -0.080393747 | AA6: =IFERROR(STDEVP(OFFSET(X$16,MAX($B$16:$B$506)-11,0,12,1))*SQRT(12),"N/A") -> 8.2295016
C7: Two Year | D7: {=IFERROR((GEOMEAN(1+OFFSET(D$16,MAX($B$16:$B$506)-23,0,24,1)/100)^12-1)*100,"N/A")} -> 13.990405 | E7: =IFERROR(D7-$K7,"N/A") -> -7.3858675 | F7: =IFERROR(SLOPE(OFFSET(D$16,MAX($B$16:$B$506)-23,0,24,1),OFFSET($K$16,MAX($B$16:$B$506)-23,0,24,1)),"N/A") -> 0.67863175 | G7: =IFERROR(INTERCEPT(OFFSET(D$16,MAX($B$16:$B$506)-23,0,24,1),OFFSET($K$16,MAX($B$16:$B$506)-23,0,24,1))*12,"N/A") -> 0.037018484 | H7: =IFERROR(STDEVP(OFFSET(D$16,MAX($B$16:$B$506)-23,0,24,1))*SQRT(12),"N/A") -> 9.9401748 | J7: Two Year | K7: {=IFERROR((GEOMEAN(1+OFFSET(K$16,MAX($B$16:$B$506)-23,0,24,1)/100)^12-1)*100,"N/A")} -> 21.376272 | L7: =IFERROR(SLOPE(OFFSET(K$16,MAX($B$16:$B$506)-23,0,24,1),OFFSET($K$16,MAX($B$16:$B$506)-23,0,24,1)),"N/A") -> 1 | M7: =IFERROR(STDEVP(OFFSET(K$16,MAX($B$16:$B$506)-23,0,24,1))*SQRT(12),"N/A") -> 10.408855 | P7: Two Year | Q7: {=IFERROR((GEOMEAN(1+OFFSET(Q$16,MAX($B$16:$B$506)-23,0,24,1)/100)^12-1)*100,"N/A")} -> 15.342648 | R7: =IFERROR(Q7-$K7,"N/A") -> -6.0336236 | S7: =IFERROR(SLOPE(OFFSET(Q$16,MAX($B$16:$B$506)-23,0,24,1),OFFSET($K$16,MAX($B$16:$B$506)-23,0,24,1)),"N/A") -> 0.70297198 | T7: =IFERROR(INTERCEPT(OFFSET(Q$16,MAX($B$16:$B$506)-23,0,24,1),OFFSET($K$16,MAX($B$16:$B$506)-23,0,24,1))*12,"N/A") -> 0.58014032 | U7: =IFERROR(STDEVP(OFFSET(Q$16,MAX($B$16:$B$506)-23,0,24,1))*SQRT(12),"N/A") -> 8.1174348 | W7: Two Year | X7: {=IFERROR((GEOMEAN(1+OFFSET(X$16,MAX($B$16:$B$506)-23,0,24,1)/100)^12-1)*100,"N/A")} -> 9.1946034 | Y7: =IFERROR(X7-$K8,"N/A") -> -13.787786 | Z7: =IFERROR(SLOPE(OFFSET(X$16,MAX($B$16:$B$506)-23,0,24,1),OFFSET($K$16,MAX($B$16:$B$506)-23,0,24,1)),"N/A") -> 0.36734111 | AA7: =IFERROR(STDEVP(OFFSET(X$16,MAX($B$16:$B$506)-23,0,24,1))*SQRT(12),"N/A") -> 10.053997
C8: Three Year | D8: {=IFERROR((GEOMEAN(1+OFFSET(D$16,MAX($B$16:$B$506)-35,0,36,1)/100)^12-1)*100,"N/A")} -> 12.883268 | E8: =IFERROR(D8-$K8,"N/A") -> -10.099121 | F8: =IFERROR(SLOPE(OFFSET(D$16,MAX($B$16:$B$506)-35,0,36,1),OFFSET($K$16,MAX($B$16:$B$506)-35,0,36,1)),"N/A") -> 0.68622583 | G8: =IFERROR(INTERCEPT(OFFSET(D$16,MAX($B$16:$B$506)-35,0,36,1),OFFSET($K$16,MAX($B$16:$B$506)-35,0,36,1))*12,"N/A") -> -2.0963514 | H8: =IFERROR(STDEVP(OFFSET(D$16,MAX($B$16:$B$506)-35,0,36,1))*SQRT(12),"N/A") -> 10.189435 | J8: Three Year | K8: {=IFERROR((GEOMEAN(1+OFFSET(K$16,MAX($B$16:$B$506)-35,0,36,1)/100)^12-1)*100,"N/A")} -> 22.982389 | L8: =IFERROR(SLOPE(OFFSET(K$16,MAX($B$16:$B$506)-35,0,36,1),OFFSET($K$16,MAX($B$16:$B$506)-35,0,36,1)),"N/A") -> 1 | M8: =IFERROR(STDEVP(OFFSET(K$16,MAX($B$16:$B$506)-35,0,36,1))*SQRT(12),"N/A") -> 11.787719 | P8: Three Year | Q8: {=IFERROR((GEOMEAN(1+OFFSET(Q$16,MAX($B$16:$B$506)-35,0,36,1)/100)^12-1)*100,"N/A")} -> 16.938916 | R8: =IFERROR(Q8-$K8,"N/A") -> -6.0434732 | S8: =IFERROR(SLOPE(OFFSET(Q$16,MAX($B$16:$B$506)-35,0,36,1),OFFSET($K$16,MAX($B$16:$B$506)-35,0,36,1)),"N/A") -> 0.74561056 | T8: =IFERROR(INTERCEPT(OFFSET(Q$16,MAX($B$16:$B$506)-35,0,36,1),OFFSET($K$16,MAX($B$16:$B$506)-35,0,36,1))*12,"N/A") -> 0.12908565 | U8: =IFERROR(STDEVP(OFFSET(Q$16,MAX($B$16:$B$506)-35,0,36,1))*SQRT(12),"N/A") -> 9.5089491 | W8: Three Year | X8: {=IFERROR((GEOMEAN(1+OFFSET(X$16,MAX($B$16:$B$506)-35,0,36,1)/100)^12-1)*100,"N/A")} -> 6.2917988 | Y8: =IFERROR(X8-$K9,"N/A") -> -4.7936672 | Z8: =IFERROR(SLOPE(OFFSET(X$16,MAX($B$16:$B$506)-35,0,36,1),OFFSET($K$16,MAX($B$16:$B$506)-35,0,36,1)),"N/A") -> 0.48989091 | AA8: =IFERROR(STDEVP(OFFSET(X$16,MAX($B$16:$B$506)-35,0,36,1))*SQRT(12),"N/A") -> 10.468154
C9: Four Year | D9: {=IFERROR((GEOMEAN(1+OFFSET(D$16,MAX($B$16:$B$506)-47,0,48,1)/100)^12-1)*100,"N/A")} -> 6.1061404 | E9: =IFERROR(D9-$K9,"N/A") -> -4.9793256 | F9: =IFERROR(SLOPE(OFFSET(D$16,MAX($B$16:$B$506)-47,0,48,1),OFFSET($K$16,MAX($B$16:$B$506)-47,0,48,1)),"N/A") -> 0.74087069 | G9: =IFERROR(INTERCEPT(OFFSET(D$16,MAX($B$16:$B$506)-47,0,48,1),OFFSET($K$16,MAX($B$16:$B$506)-47,0,48,1))*12,"N/A") -> -1.9109021 | H9: =IFERROR(STDEVP(OFFSET(D$16,MAX($B$16:$B$506)-47,0,48,1))*SQRT(12),"N/A") -> 13.419106 | J9: Four Year | K9: {=IFERROR((GEOMEAN(1+OFFSET(K$16,MAX($B$16:$B$506)-47,0,48,1)/100)^12-1)*100,"N/A")} -> 11.085466 | L9: =IFERROR(SLOPE(OFFSET(K$16,MAX($B$16:$B$506)-47,0,48,1),OFFSET($K$16,MAX($B$16:$B$506)-47,0,48,1)),"N/A") -> 1 | M9: =IFERROR(STDEVP(OFFSET(K$16,MAX($B$16:$B$506)-47,0,48,1))*SQRT(12),"N/A") -> 15.787972 | P9: Four Year | Q9: {=IFERROR((GEOMEAN(1+OFFSET(Q$16,MAX($B$16:$B$506)-47,0,48,1)/100)^12-1)*100,"N/A")} -> 7.5142335 | R9: =IFERROR(Q9-$K9,"N/A") -> -3.5712325 | S9: =IFERROR(SLOPE(OFFSET(Q$16,MAX($B$16:$B$506)-47,0,48,1),OFFSET($K$16,MAX($B$16:$B$506)-47,0,48,1)),"N/A") -> 0.81284932 | T9: =IFERROR(INTERCEPT(OFFSET(Q$16,MAX($B$16:$B$506)-47,0,48,1),OFFSET($K$16,MAX($B$16:$B$506)-47,0,48,1))*12,"N/A") -> -1.4322126 | U9: =IFERROR(STDEVP(OFFSET(Q$16,MAX($B$16:$B$506)-47,0,48,1))*SQRT(12),"N/A") -> 13.386429 | W9: Four Year | X9: {=IFERROR((GEOMEAN(1+OFFSET(X$16,MAX($B$16:$B$506)-47,0,48,1)/100)^12-1)*100,"N/A")} -> 3.4615128 | Y9: =IFERROR(X9-$K10,"N/A") -> -10.938723 | Z9: =IFERROR(SLOPE(OFFSET(X$16,MAX($B$16:$B$506)-47,0,48,1),OFFSET($K$16,MAX($B$16:$B$506)-47,0,48,1)),"N/A") -> 0.55345764 | AA9: =IFERROR(STDEVP(OFFSET(X$16,MAX($B$16:$B$506)-47,0,48,1))*SQRT(12),"N/A") -> 12.138203
C10: Five Year | D10: {=IFERROR((GEOMEAN(1+OFFSET(D$16,MAX($B$16:$B$506)-59,0,60,1)/100)^12-1)*100,"N/A")} -> 8.3141643 | E10: =IFERROR(D10-$K10,"N/A") -> -6.0860714 | F10: =IFERROR(SLOPE(OFFSET(D$16,MAX($B$16:$B$506)-59,0,60,1),OFFSET($K$16,MAX($B$16:$B$506)-59,0,60,1)),"N/A") -> 0.77985611 | G10: =IFERROR(INTERCEPT(OFFSET(D$16,MAX($B$16:$B$506)-59,0,60,1),OFFSET($K$16,MAX($B$16:$B$506)-59,0,60,1))*12,"N/A") -> -2.5350069 | H10: =IFERROR(STDEVP(OFFSET(D$16,MAX($B$16:$B$506)-59,0,60,1))*SQRT(12),"N/A") -> 13.298803 | J10: Five Year | K10: {=IFERROR((GEOMEAN(1+OFFSET(K$16,MAX($B$16:$B$506)-59,0,60,1)/100)^12-1)*100,"N/A")} -> 14.400236 | L10: =IFERROR(SLOPE(OFFSET(K$16,MAX($B$16:$B$506)-59,0,60,1),OFFSET($K$16,MAX($B$16:$B$506)-59,0,60,1)),"N/A") -> 1 | M10: =IFERROR(STDEVP(OFFSET(K$16,MAX($B$16:$B$506)-59,0,60,1))*SQRT(12),"N/A") -> 14.98254 | P10: Five Year | Q10: {=IFERROR((GEOMEAN(1+OFFSET(Q$16,MAX($B$16:$B$506)-59,0,60,1)/100)^12-1)*100,"N/A")} -> 11.138063 | R10: =IFERROR(Q10-$K10,"N/A") -> -3.2621723 | S10: =IFERROR(SLOPE(OFFSET(Q$16,MAX($B$16:$B$506)-59,0,60,1),OFFSET($K$16,MAX($B$16:$B$506)-59,0,60,1)),"N/A") -> 0.84847872 | T10: =IFERROR(INTERCEPT(OFFSET(Q$16,MAX($B$16:$B$506)-59,0,60,1),OFFSET($K$16,MAX($B$16:$B$506)-59,0,60,1))*12,"N/A") -> -0.93936988 | U10: =IFERROR(STDEVP(OFFSET(Q$16,MAX($B$16:$B$506)-59,0,60,1))*SQRT(12),"N/A") -> 13.30768 | W10: Five Year | X10: {=IFERROR((GEOMEAN(1+OFFSET(X$16,MAX($B$16:$B$506)-59,0,60,1)/100)^12-1)*100,"N/A")} -> 7.349583 | Y10: =IFERROR(X10-$K11,"N/A") -> -7.4537143 | Z10: =IFERROR(SLOPE(OFFSET(X$16,MAX($B$16:$B$506)-59,0,60,1),OFFSET($K$16,MAX($B$16:$B$506)-59,0,60,1)),"N/A") -> 0.61101938 | AA10: =IFERROR(STDEVP(OFFSET(X$16,MAX($B$16:$B$506)-59,0,60,1))*SQRT(12),"N/A") -> 12.625094 | AD10: =AD209/AZ209 -> 0.56806967 | AE10: =AF209/AZ209 -> 0.43193033
C11: Ten Year | D11: {=IFERROR((GEOMEAN(1+OFFSET(D$16,MAX($B$16:$B$506)-119,0,120,1)/100)^12-1)*100,"N/A")} -> 10.503037 | E11: =IFERROR(D11-$K11,"N/A") -> -4.3002605 | F11: =IFERROR(SLOPE(OFFSET(D$16,MAX($B$16:$B$506)-119,0,120,1),OFFSET($K$16,MAX($B$16:$B$506)-119,0,120,1)),"N/A") -> 0.79929338 | G11: =IFERROR(INTERCEPT(OFFSET(D$16,MAX($B$16:$B$506)-119,0,120,1),OFFSET($K$16,MAX($B$16:$B$506)-119,0,120,1))*12,"N/A") -> -1.1033388 | H11: =IFERROR(STDEVP(OFFSET(D$16,MAX($B$16:$B$506)-119,0,120,1))*SQRT(12),"N/A") -> 13.193272 | J11: Ten Year | K11: {=IFERROR((GEOMEAN(1+OFFSET(K$16,MAX($B$16:$B$506)-119,0,120,1)/100)^12-1)*100,"N/A")} -> 14.803297 | L11: =IFERROR(SLOPE(OFFSET(K$16,MAX($B$16:$B$506)-119,0,120,1),OFFSET($K$16,MAX($B$16:$B$506)-119,0,120,1)),"N/A") -> 1 | M11: =IFERROR(STDEVP(OFFSET(K$16,MAX($B$16:$B$506)-119,0,120,1))*SQRT(12),"N/A") -> 15.056111 | P11: Ten Year | Q11: {=IFERROR((GEOMEAN(1+OFFSET(Q$16,MAX($B$16:$B$506)-119,0,120,1)/100)^12-1)*100,"N/A")} -> 12.825832 | R11: =IFERROR(Q11-$K11,"N/A") -> -1.9774654 | S11: =IFERROR(SLOPE(OFFSET(Q$16,MAX($B$16:$B$506)-119,0,120,1),OFFSET($K$16,MAX($B$16:$B$506)-119,0,120,1)),"N/A") -> 0.85660272 | T11: =IFERROR(INTERCEPT(OFFSET(Q$16,MAX($B$16:$B$506)-119,0,120,1),OFFSET($K$16,MAX($B$16:$B$506)-119,0,120,1))*12,"N/A") -> 0.15423806 | U11: =IFERROR(STDEVP(OFFSET(Q$16,MAX($B$16:$B$506)-119,0,120,1))*SQRT(12),"N/A") -> 13.350051 | W11: Ten Year | X11: {=IFERROR((GEOMEAN(1+OFFSET(X$16,MAX($B$16:$B$506)-119,0,120,1)/100)^12-1)*100,"N/A")} -> 8.9173184 | Y11: =IFERROR(X11-$K12,"N/A") -> 0.85041593 | Z11: =IF(P12="N/A","N/A",IFERROR(SLOPE(OFFSET(X$16,MAX($B$16:$B$506)-119,0,120,1),OFFSET($K$16,MAX($B$16:$B$506)-119,0,120,1)),"N/A")) -> 0.6470853 | AA11: =IFERROR(STDEVP(OFFSET(X$16,MAX($B$16:$B$506)-119,0,120,1))*SQRT(12),"N/A") -> 12.473098 | AD11: =AD10*AC210 -> 1.0734499 | AE11: =AE10*AE210 -> 0.95327024 | AF11: =AD11+AE11 -> 2.0267201
C12: Model Incep. | D12: {=IFERROR((GEOMEAN(1+OFFSET(D$16,1,0,MAX($B$16:$B$506),1)/100)^12-1)*100,"N/A")} -> 11.383945 | E12: =IFERROR(D12-$K12,"N/A") -> 3.3170424 | F12: =IFERROR(SLOPE(OFFSET(D$16,1,0,MAX($B$16:$B$506),1),OFFSET($K$16,1,0,MAX($B$16:$B$506),1)),"N/A") -> 0.65286552 | G12: =IFERROR(INTERCEPT(OFFSET(D$16,1,0,MAX($B$16:$B$506),1),OFFSET($K$16,1,0,MAX($B$16:$B$506),1))*12,"N/A") -> 5.7234274 | H12: =IFERROR(STDEVP(OFFSET(D$16,1,0,MAX($B$16:$B$506),1))*SQRT(12),"N/A") -> 12.034673 | J12: Inception | K12: {=IFERROR((GEOMEAN(1+OFFSET(K$16,1,0,MAX($B$16:$B$506),1)/100)^12-1)*100,"N/A")} -> 8.0669024 | L12: =IFERROR(SLOPE(OFFSET(K$16,1,0,MAX($B$16:$B$506),1),OFFSET($K$16,1,0,MAX($B$16:$B$506),1)),"N/A") -> 1 | M12: =IFERROR(STDEVP(OFFSET(K$16,1,0,MAX($B$16:$B$506),1))*SQRT(12),"N/A") -> 15.141943 | P12: Model Incep. | Q12: {=IFERROR((GEOMEAN(1+OFFSET(Q$16,1,0,MAX($B$16:$B$506),1)/100)^12-1)*100,"N/A")} -> 7.1818795 | R12: =IFERROR(Q12-$K12,"N/A") -> -0.88502295 | S12: =IFERROR(SLOPE(OFFSET(Q$16,1,0,MAX($B$16:$B$506),1),OFFSET($K$16,1,0,MAX($B$16:$B$506),1)),"N/A") -> 0.80660002 | T12: =IFERROR(INTERCEPT(OFFSET(Q$16,1,0,MAX($B$16:$B$506),1),OFFSET($K$16,1,0,MAX($B$16:$B$506),1))*12,"N/A") -> 0.56007074 | U12: =IFERROR(STDEVP(OFFSET(Q$16,1,0,MAX($B$16:$B$506),1))*SQRT(12),"N/A") -> 12.724272 | W12: Model Incep. | X12: {=IFERROR((GEOMEAN(1+OFFSET(X$16,1,0,MAX($B$16:$B$506),1)/100)^12-1)*100,"N/A")} -> 9.3867894 | Y12: =IFERROR(X12-$K13,"N/A") -> -4.5680677 | Z12: =IFERROR(SLOPE(OFFSET(X$16,1,0,MAX($B$16:$B$506),1),OFFSET($K$16,1,0,MAX($B$16:$B$506),1)),"N/A") -> 0.58320267 | AA12: =IFERROR(STDEVP(OFFSET(X$16,1,0,MAX($B$16:$B$506),1))*SQRT(12),"N/A") -> 11.687065
C13: Feb'11 Incep. | D13: {=IFERROR((GEOMEAN(1+OFFSET(D$149,1,0,MAX($B$16:$B$506)-133,1)/100)^(MIN(COUNTA(OFFSET(D$149,1,0,MAX($B$16:$B$506)-133,1)),12))-1)*100,"N/A")} -> 11.824032 | E13: =IFERROR(D13-$K13,"N/A") -> -2.1308247 | F13: =IFERROR(SLOPE(OFFSET(D$149,1,0,MAX($B$16:$B$506)-133,1),OFFSET($K$149,1,0,MAX($B$16:$B$506)-133,1)),"N/A") -> 0.72837623 | G13: =IFERROR(INTERCEPT(OFFSET(D$149,1,0,MAX($B$16:$B$506)-133,1),OFFSET($K$149,1,0,MAX($B$16:$B$506)-133,1))*12,"N/A") -> 1.6302397 | H13: =IFERROR(STDEVP(OFFSET(D$149,1,0,MAX($B$16:$B$506)-133,1))*SQRT(12),"N/A") -> 11.703397 | J13: Feb'11 Incep. | K13: {=IFERROR((GEOMEAN(1+OFFSET(K$149,1,0,MAX($B$16:$B$506)-133,1)/100)^(MIN(COUNTA(OFFSET(K$149,1,0,MAX($B$16:$B$506)-133,1)),12))-1)*100,"N/A")} -> 13.954857 | L13: =IFERROR(SLOPE(OFFSET(K$149,1,0,MAX($B$16:$B$506)-133,1),OFFSET($K$149,1,0,MAX($B$16:$B$506)-133,1)),"N/A") -> 1 | M13: =IFERROR(STDEVP(OFFSET(K$149,1,0,MAX($B$16:$B$506)-133,1))*SQRT(12),"N/A") -> 14.03842 | P13: Feb'11 Incep. | Q13: {=IFERROR((GEOMEAN(1+OFFSET(Q$149,1,0,MAX($B$16:$B$506)-133,1)/100)^(MIN(COUNTA(OFFSET(Q$149,1,0,MAX($B$16:$B$506)-133,1)),12))-1)*100,"N/A")} -> 12.932305 | R13: =IFERROR(Q13-$K13,"N/A") -> -1.0225522 | S13: =IFERROR(SLOPE(OFFSET(Q$149,1,0,MAX($B$16:$B$506)-133,1),OFFSET($K$149,1,0,MAX($B$16:$B$506)-133,1)),"N/A") -> 0.84675574 | T13: =IFERROR(INTERCEPT(OFFSET(Q$149,1,0,MAX($B$16:$B$506)-133,1),OFFSET($K$149,1,0,MAX($B$16:$B$506)-133,1))*12,"N/A") -> 1.0242804 | U13: =IFERROR(STDEVP(OFFSET(Q$149,1,0,MAX($B$16:$B$506)-133,1))*SQRT(12),"N/A") -> 12.304197 | W13: Feb'11 Incep. | X13: {=IFERROR((GEOMEAN(1+OFFSET(X$149,1,0,MAX($B$16:$B$506)-133,1)/100)^(MIN(COUNTA(OFFSET(X$149,1,0,MAX($B$16:$B$506)-133,1)),12))-1)*100,"N/A")} -> 10.642852 | Y13: =IFERROR(X13-$K14,"N/A") -> 10.642852 | Z13: =IFERROR(SLOPE(OFFSET(X$102,1,0,MAX($B$16:$B$506)-86,1),OFFSET($K$102,1,0,MAX($B$16:$B$506)-86,1)),"N/A") -> 0.63650071 | AA13: =IFERROR(STDEVP(OFFSET(X$102,1,0,MAX($B$16:$B$506)-86,1))*SQRT(12),"N/A") -> 12.022481 | AC13: Composite Performance
AC14: SILVX | AE14: UNC LC | AG14: Asbestos | AI14: BHI Senior Living | AK14: Cynthia Simon-Skjodt | AM14: Sisters of St Benedict | AO14: French Capital Investors | AQ14: St Paul Hermitage | AS14: Tony Cercy | AU14: Leonardo Locascio | AW14: Walter Miller | AY14: Composite
A15: Date | B15: # | C15: Porfolio | D15: Net Return | E15: Growth | F15: Annual | G15: Quarterly | J15: Date | K15: Return | L15: Growth | M15: Annual | N15: Quarterly | P15: Date | Q15: Return | R15: Growth | S15: Annual | T15: Quarterly | AC15: Return | AD15: AUM | AE15: Return | AF15: AUM | AG15: Return | AH15: AUM | AI15: Return | AJ15: AUM | AK15: Return | AL15: AUM | AM15: Return | AN15: AUM | AO15: Return | AP15: AUM | AQ15: Return | AR15: AUM | AS15: Return | AT15: AUM | AU15: Return | AV15: AUM | AW15: Return | AX15: AUM | AY15: Return | AZ15: AUM
A16: 36525 | B16: 0 | E16: 1000000 | J16: =$A16 -> 36525 | L16: 1000000 | P16: =$A16 -> 36525 | R16: 1000000 | W16: =$A16 -> 36525 | Y16: 1000000
A17: 36556 | B17: =IF(A17>A16,1+B16,"-") -> 1 | C17: Model | D17: -4.22 | E17: =E16*D17/100+E16 -> 957800 | J17: =$A17 -> 36556 | K17: ='LC (Gross)'!K17 -> -5.0242437 | L17: =L16*K17/100+L16 -> 949757.56 | P17: =$A17 -> 36556 | Q17: ='LC (Gross)'!Q17 -> -3.7996474 | R17: =R16*Q17/100+R16 -> 962003.53 | W17: =$A17 -> 36556 | X17: ='LC (Gross)'!X17 -> -3.5109291 | Y17: =Y16*X17/100+Y16 -> 964890.71
A18: 36585 | B18: =IF(A18>A17,1+B17,"-") -> 2 | C18: Model | D18: -7.58 | E18: =E17*D18/100+E17 -> 885198.76 | J18: =$A18 -> 36585 | K18: ='LC (Gross)'!K18 -> -1.8937944 | L18: =L17*K18/100+L17 -> 931771.11 | P18: =$A18 -> 36585 | Q18: ='LC (Gross)'!Q18 -> -6.7517383 | R18: =R17*Q18/100+R17 -> 897051.57 | W18: =$A18 -> 36585 | X18: ='LC (Gross)'!X18 -> -10.51414 | Y18: =Y17*X18/100+Y17 -> 863440.75
A19: 36616 | B19: =IF(A19>A18,1+B18,"-") -> 3 | C19: Model | D19: 13.21 | E19: =E18*D19/100+E18 -> 1002133.5 | G19: =(E19/E16-1)*100 -> 0.21335162 | J19: =$A19 -> 36616 | K19: ='LC (Gross)'!K19 -> 9.7830709 | L19: =L18*K19/100+L18 -> 1022926.9 | N19: =(L19/L16-1)*100 -> 2.2926936 | P19: =$A19 -> 36616 | Q19: ='LC (Gross)'!Q19 -> 10.20982 | R19: =R18*Q19/100+R18 -> 988638.92 | T19: =(R19/R16-1)*100 -> -1.1361085 | W19: =$A19 -> 36616 | X19: ='LC (Gross)'!X19 -> 9.3534453 | Y19: =Y18*X19/100+Y18 -> 944202.21
A20: 36646 | B20: =IF(A20>A19,1+B19,"-") -> 4 | C20: Model | D20: 3.05 | E20: =E19*D20/100+E19 -> 1032698.6 | J20: =$A20 -> 36646 | K20: ='LC (Gross)'!K20 -> -3.0091713 | L20: =L19*K20/100+L19 -> 992145.31 | P20: =$A20 -> 36646 | Q20: ='LC (Gross)'!Q20 -> -1.0985094 | R20: =R19*Q20/100+R19 -> 977778.62 | W20: =$A20 -> 36646 | X20: ='LC (Gross)'!X20 -> 4.7344924 | Y20: =Y19*X20/100+Y19 -> 988905.39
A21: 36677 | B21: =IF(A21>A20,1+B20,"-") -> 5 | C21: Model | D21: 0.28 | E21: =E20*D21/100+E20 -> 1035590.1 | J21: =$A21 -> 36677 | K21: ='LC (Gross)'!K21 -> -2.0522676 | L21: =L20*K21/100+L20 -> 971783.84 | P21: =$A21 -> 36677 | Q21: ='LC (Gross)'!Q21 -> 1.2422987 | R21: =R20*Q21/100+R20 -> 989925.55 | W21: =$A21 -> 36677 | X21: ='LC (Gross)'!X21 -> 4.9107001 | Y21: =Y20*X21/100+Y20 -> 1037467.6
A22: 36707 | B22: =IF(A22>A21,1+B21,"-") -> 6 | C22: Model | D22: -0.53 | E22: =E21*D22/100+E21 -> 1030101.5 | G22: =(E22/E19-1)*100 -> 2.7908457 | J22: =$A22 -> 36707 | K22: ='LC (Gross)'!K22 -> 2.4652586 | L22: =L21*K22/100+L21 -> 995740.82 | N22: =(L22/L19-1)*100 -> -2.6576791 | P22: =$A22 -> 36707 | Q22: ='LC (Gross)'!Q22 -> 1.7420177 | R22: =R21*Q22/100+R21 -> 1007170.2 | T22: =(R22/R19-1)*100 -> 1.8744273 | W22: =$A22 -> 36707 | X22: ='LC (Gross)'!X22 -> -4.1760746 | Y22: =Y21*X22/100+Y21 -> 994142.15
A23: 36738 | B23: =IF(A23>A22,1+B22,"-") -> 7 | C23: Model | D23: -0.47 | E23: =E22*D23/100+E22 -> 1025260 | J23: =$A23 -> 36738 | K23: ='LC (Gross)'!K23 -> -1.5573152 | L23: =L22*K23/100+L22 -> 980234 | P23: =$A23 -> 36738 | Q23: ='LC (Gross)'!Q23 -> -1.0405934 | R23: =R22*Q23/100+R22 -> 996689.69 | W23: =$A23 -> 36738 | X23: ='LC (Gross)'!X23 -> 1.3630468 | Y23: =Y22*X23/100+Y22 -> 1007692.8
A24: 36769 | B24: =IF(A24>A23,1+B23,"-") -> 8 | C24: Model | D24: 0.2 | E24: =E23*D24/100+E23 -> 1027310.6 | J24: =$A24 -> 36769 | K24: ='LC (Gross)'!K24 -> 6.2114813 | L24: =L23*K24/100+L23 -> 1041121 | P24: =$A24 -> 36769 | Q24: ='LC (Gross)'!Q24 -> 4.1027128 | R24: =R23*Q24/100+R23 -> 1037581 | W24: =$A24 -> 36769 | X24: ='LC (Gross)'!X24 -> 7.4544539 | Y24: =Y23*X24/100+Y23 -> 1082810.8
A25: 36799 | B25: =IF(A25>A24,1+B24,"-") -> 9 | C25: Model | D25: 4.74 | E25: =E24*D25/100+E24 -> 1076005.1 | G25: =(E25/E22-1)*100 -> 4.4562174 | J25: =$A25 -> 36799 | K25: ='LC (Gross)'!K25 -> -5.2795736 | L25: =L24*K25/100+L24 -> 986154.3 | N25: =(L25/L22-1)*100 -> -0.96275291 | P25: =$A25 -> 36799 | Q25: ='LC (Gross)'!Q25 -> -2.4192023 | R25: =R24*Q25/100+R24 -> 1012479.8 | T25: =(R25/R22-1)*100 -> 0.52717843 | W25: =$A25 -> 36799 | X25: ='LC (Gross)'!X25 -> 3.158566 | Y25: =Y24*X25/100+Y24 -> 1117012.1
A26: 36830 | B26: =IF(A26>A25,1+B25,"-") -> 10 | C26: Model | D26: 1.04 | E26: =E25*D26/100+E25 -> 1087195.5 | J26: =$A26 -> 36830 | K26: ='LC (Gross)'!K26 -> -0.42330523 | L26: =L25*K26/100+L25 -> 981979.85 | P26: =$A26 -> 36830 | Q26: ='LC (Gross)'!Q26 -> 2.9561552 | R26: =R25*Q26/100+R25 -> 1042410.3 | W26: =$A26 -> 36830 | X26: ='LC (Gross)'!X26 -> 2.3517126 | Y26: =Y25*X26/100+Y25 -> 1143281
A27: 36860 | B27: =IF(A27>A26,1+B26,"-") -> 11 | C27: Model | D27: 0.83 | E27: =E26*D27/100+E26 -> 1096219.3 | J27: =$A27 -> 36860 | K27: ='LC (Gross)'!K27 -> -7.8835014 | L27: =L26*K27/100+L26 -> 904565.46 | P27: =$A27 -> 36860 | Q27: ='LC (Gross)'!Q27 -> -3.6785295 | R27: =R26*Q27/100+R26 -> 1004064.9 | W27: =$A27 -> 36860 | X27: ='LC (Gross)'!X27 -> 1.7025759 | Y27: =Y26*X27/100+Y26 -> 1162746.2
A28: 36891 | B28: =IF(A28>A27,1+B27,"-") -> 12 | C28: Model | D28: 6.43 | E28: =E27*D28/100+E27 -> 1166706.2 | F28: =(E28-E16)/E16*100 -> 16.670615 | G28: =(E28/E25-1)*100 -> 8.429428 | J28: =$A28 -> 36891 | K28: ='LC (Gross)'!K28 -> 0.48873135 | L28: =L27*K28/100+L27 -> 908986.35 | M28: =(L28-L16)/L16*100 -> -9.1013646 | N28: =(L28/L25-1)*100 -> -7.8251388 | P28: =$A28 -> 36891 | Q28: ='LC (Gross)'!Q28 -> -0.62846487 | R28: =R27*Q28/100+R27 -> 997754.73 | S28: =(R28-R16)/R16*100 -> -0.22452737 | T28: =(R28/R25-1)*100 -> -1.4543589 | W28: =$A28 -> 36891 | X28: ='LC (Gross)'!X28 -> 7.5325175 | Y28: =Y27*X28/100+Y27 -> 1250330.3
A29: 36922 | B29: =IF(A29>A28,1+B28,"-") -> 13 | C29: Model | D29: -0.62 | E29: =E28*D29/100+E28 -> 1159472.6 | J29: =$A29 -> 36922 | K29: ='LC (Gross)'!K29 -> 3.5478697 | L29: =L28*K29/100+L28 -> 941236 | P29: =$A29 -> 36922 | Q29: ='LC (Gross)'!Q29 -> -0.34175608 | R29: =R28*Q29/100+R28 -> 994344.84 | W29: =$A29 -> 36922 | X29: ='LC (Gross)'!X29 -> -4.3133685 | Y29: =Y28*X29/100+Y28 -> 1196398.9
A30: 36950 | B30: =IF(A30>A29,1+B29,"-") -> 14 | C30: Model | D30: 2.02 | E30: =E29*D30/100+E29 -> 1182893.9 | J30: =$A30 -> 36950 | K30: ='LC (Gross)'!K30 -> -9.1189455 | L30: =L29*K30/100+L29 -> 855405.21 | P30: =$A30 -> 36950 | Q30: ='LC (Gross)'!Q30 -> -4.5916623 | R30: =R29*Q30/100+R29 -> 948687.88 | W30: =$A30 -> 36950 | X30: ='LC (Gross)'!X30 -> 2.8779234 | Y30: =Y29*X30/100+Y29 -> 1230830.3
A31: 36981 | B31: =IF(A31>A30,1+B30,"-") -> 15 | C31: Model | D31: -2.11 | E31: =E30*D31/100+E30 -> 1157934.9 | G31: =(E31/E28-1)*100 -> -0.75179974 | J31: =$A31 -> 36981 | K31: ='LC (Gross)'!K31 -> -6.334973 | L31: =L30*K31/100+L30 -> 801215.52 | N31: =(L31/L28-1)*100 -> -11.856155 | P31: =$A31 -> 36981 | Q31: ='LC (Gross)'!Q31 -> -5.3831855 | R31: =R30*Q31/100+R30 -> 897618.25 | T31: =(R31/R28-1)*100 -> -10.036181 | W31: =$A31 -> 36981 | X31: ='LC (Gross)'!X31 -> -1.2489882 | Y31: =Y30*X31/100+Y30 -> 1215457.4
A32: 37011 | B32: =IF(A32>A31,1+B31,"-") -> 16 | C32: Model | D32: 6.72 | E32: =E31*D32/100+E31 -> 1235748.1 | J32: =$A32 -> 37011 | K32: ='LC (Gross)'!K32 -> 7.7701831 | L32: =L31*K32/100+L31 -> 863471.43 | P32: =$A32 -> 37011 | Q32: ='LC (Gross)'!Q32 -> 6.6005994 | R32: =R31*Q32/100+R31 -> 956866.44 | W32: =$A32 -> 37011 | X32: ='LC (Gross)'!X32 -> 5.2440859 | Y32: =Y31*X32/100+Y31 -> 1279197.1
A33: 37042 | B33: =IF(A33>A32,1+B32,"-") -> 17 | C33: Model | D33: 3.17 | E33: =E32*D33/100+E32 -> 1274921.3 | J33: =$A33 -> 37042 | K33: ='LC (Gross)'!K33 -> 0.66989034 | L33: =L32*K33/100+L32 -> 869255.74 | P33: =$A33 -> 37042 | Q33: ='LC (Gross)'!Q33 -> 0.99856242 | R33: =R32*Q33/100+R32 -> 966421.35 | W33: =$A33 -> 37042 | X33: ='LC (Gross)'!X33 -> 3.6247619 | Y33: =Y32*X33/100+Y32 -> 1325564.9
A34: 37072 | B34: =IF(A34>A33,1+B33,"-") -> 18 | C34: Model | D34: 0.07 | E34: =E33*D34/100+E33 -> 1275813.7 | G34: =(E34/E31-1)*100 -> 10.180096 | J34: =$A34 -> 37072 | K34: ='LC (Gross)'!K34 -> -2.4345302 | L34: =L33*K34/100+L33 -> 848093.45 | N34: =(L34/L31-1)*100 -> 5.8508516 | P34: =$A34 -> 37072 | Q34: ='LC (Gross)'!Q34 -> -2.5146445 | R34: =R33*Q34/100+R33 -> 942119.28 | T34: =(R34/R31-1)*100 -> 4.957679 | W34: =$A34 -> 37072 | X34: ='LC (Gross)'!X34 -> -2.4726242 | Y34: =Y33*X34/100+Y33 -> 1292788.7
A35: 37103 | B35: =IF(A35>A34,1+B34,"-") -> 19 | C35: Model | D35: -1.65 | E35: =E34*D35/100+E34 -> 1254762.8 | J35: =$A35 -> 37103 | K35: ='LC (Gross)'!K35 -> -0.98539293 | L35: =L34*K35/100+L34 -> 839736.4 | P35: =$A35 -> 37103 | Q35: ='LC (Gross)'!Q35 -> -0.10469571 | R35: =R34*Q35/100+R34 -> 941132.93 | W35: =$A35 -> 37103 | X35: ='LC (Gross)'!X35 -> -0.39044209 | Y35: =Y34*X35/100+Y34 -> 1287741.1
A36: 37134 | B36: =IF(A36>A35,1+B35,"-") -> 20 | C36: Model | D36: -0.23 | E36: =E35*D36/100+E35 -> 1251876.9 | J36: =$A36 -> 37134 | K36: ='LC (Gross)'!K36 -> -6.259903 | L36: =L35*K36/100+L35 -> 787169.71 | P36: =$A36 -> 37134 | Q36: ='LC (Gross)'!Q36 -> -4.1201586 | R36: =R35*Q36/100+R35 -> 902356.76 | W36: =$A36 -> 37134 | X36: ='LC (Gross)'!X36 -> 0.053862557 | Y36: =Y35*X36/100+Y35 -> 1288434.7
A37: 37164 | B37: =IF(A37>A36,1+B36,"-") -> 21 | C37: Model | D37: -3.34 | E37: =E36*D37/100+E36 -> 1210064.2 | G37: =(E37/E34-1)*100 -> -5.1535398 | J37: =$A37 -> 37164 | K37: ='LC (Gross)'!K37 -> -8.0765443 | L37: =L36*K37/100+L36 -> 723593.6 | N37: =(L37/L34-1)*100 -> -14.679968 | P37: =$A37 -> 37164 | Q37: ='LC (Gross)'!Q37 -> -3.6734538 | R37: =R36*Q37/100+R36 -> 869209.1 | T37: =(R37/R34-1)*100 -> -7.738955 | W37: =$A37 -> 37164 | X37: ='LC (Gross)'!X37 -> -4.6035036 | Y37: =Y36*X37/100+Y36 -> 1229121.5
A38: 37195 | B38: =IF(A38>A37,1+B37,"-") -> 22 | C38: Model | D38: -0.02 | E38: =E37*D38/100+E37 -> 1209822.2 | J38: =$A38 -> 37195 | K38: ='LC (Gross)'!K38 -> 1.9053654 | L38: =L37*K38/100+L37 -> 737380.7 | P38: =$A38 -> 37195 | Q38: ='LC (Gross)'!Q38 -> -0.19510438 | R38: =R37*Q38/100+R37 -> 867513.23 | W38: =$A38 -> 37195 | X38: ='LC (Gross)'!X38 -> -0.78952634 | Y38: =Y37*X38/100+Y37 -> 1219417.3
A39: 37225 | B39: =IF(A39>A38,1+B38,"-") -> 23 | C39: Model | D39: 4.74 | E39: =E38*D39/100+E38 -> 1267167.7 | J39: =$A39 -> 37225 | K39: ='LC (Gross)'!K39 -> 7.6715489 | L39: =L38*K39/100+L38 -> 793949.23 | P39: =$A39 -> 37225 | Q39: ='LC (Gross)'!Q39 -> 4.7526157 | R39: =R38*Q39/100+R38 -> 908742.8 | W39: =$A39 -> 37225 | X39: ='LC (Gross)'!X39 -> 3.395764 | Y39: =Y38*X39/100+Y38 -> 1260825.8
A40: 37256 | B40: =IF(A40>A39,1+B39,"-") -> 24 | C40: Model | D40: 4.02 | E40: =E39*D40/100+E39 -> 1318107.9 | F40: =(E40-E28)/E28*100 -> 12.976851 | G40: =(E40/E37-1)*100 -> 8.9287579 | J40: =$A40 -> 37256 | K40: ='LC (Gross)'!K40 -> 0.87621202 | L40: =L39*K40/100+L39 -> 800905.9 | M40: =(L40-L28)/L28*100 -> -11.890217 | N40: =(L40/L37-1)*100 -> 10.684492 | P40: =$A40 -> 37256 | Q40: ='LC (Gross)'!Q40 -> 1.2979157 | R40: =R39*Q40/100+R39 -> 920537.52 | S40: =(R40-R28)/R28*100 -> -7.7390972 | T40: =(R40/R37-1)*100 -> 5.9051868 | W40: =$A40 -> 37256 | X40: ='LC (Gross)'!X40 -> 3.5005376 | Y40: =Y39*X40/100+Y39 -> 1304961.5
A41: 37287 | B41: =IF(A41>A40,1+B40,"-") -> 25 | C41: Model | D41: -1.85 | E41: =E40*D41/100+E40 -> 1293722.9 | J41: =$A41 -> 37287 | K41: ='LC (Gross)'!K41 -> -1.4591355 | L41: =L40*K41/100+L40 -> 789219.6 | P41: =$A41 -> 37287 | Q41: ='LC (Gross)'!Q41 -> -0.83238713 | R41: =R40*Q41/100+R40 -> 912875.08 | W41: =$A41 -> 37287 | X41: ='LC (Gross)'!X41 -> -0.24498138 | Y41: =Y40*X41/100+Y40 -> 1301764.6
A42: 37315 | B42: =IF(A42>A41,1+B41,"-") -> 26 | C42: Model | D42: 1.34 | E42: =E41*D42/100+E41 -> 1311058.8 | J42: =$A42 -> 37315 | K42: ='LC (Gross)'!K42 -> -1.9299633 | L42: =L41*K42/100+L41 -> 773987.95 | P42: =$A42 -> 37315 | Q42: ='LC (Gross)'!Q42 -> 1.1064504 | R42: =R41*Q42/100+R41 -> 922975.59 | W42: =$A42 -> 37315 | X42: ='LC (Gross)'!X42 -> 2.6350525 | Y42: =Y41*X42/100+Y41 -> 1336066.8
A43: 37346 | B43: =IF(A43>A42,1+B42,"-") -> 27 | C43: Model | D43: 7.41 | E43: =E42*D43/100+E42 -> 1408208.2 | G43: =(E43/E40-1)*100 -> 6.8355821 | J43: =$A43 -> 37346 | K43: ='LC (Gross)'!K43 -> 3.7602607 | L43: =L42*K43/100+L42 -> 803091.92 | N43: =(L43/L40-1)*100 -> 0.27294258 | P43: =$A43 -> 37346 | Q43: ='LC (Gross)'!Q43 -> 1.901526 | R43: =R42*Q43/100+R42 -> 940526.21 | T43: =(R43/R40-1)*100 -> 2.1714156 | W43: =$A43 -> 37346 | X43: ='LC (Gross)'!X43 -> 4.6300513 | Y43: =Y42*X43/100+Y42 -> 1397927.4
A44: 37376 | B44: =IF(A44>A43,1+B43,"-") -> 28 | C44: Model | D44: -0.84 | E44: =E43*D44/100+E43 -> 1396379.3 | J44: =$A44 -> 37376 | K44: ='LC (Gross)'!K44 -> -6.0635566 | L44: =L43*K44/100+L43 -> 754395.98 | P44: =$A44 -> 37376 | Q44: ='LC (Gross)'!Q44 -> -5.2617955 | R44: =R43*Q44/100+R43 -> 891037.65 | W44: =$A44 -> 37376 | X44: ='LC (Gross)'!X44 -> -0.19598733 | Y44: =Y43*X44/100+Y43 -> 1395187.6
A45: 37407 | B45: =IF(A45>A44,1+B44,"-") -> 29 | C45: Model | D45: 0.33 | E45: =E44*D45/100+E44 -> 1400987.3 | J45: =$A45 -> 37407 | K45: ='LC (Gross)'!K45 -> -0.73730849 | L45: =L44*K45/100+L44 -> 748833.76 | P45: =$A45 -> 37407 | Q45: ='LC (Gross)'!Q45 -> -0.5778654 | R45: =R44*Q45/100+R44 -> 885888.65 | W45: =$A45 -> 37407 | X45: ='LC (Gross)'!X45 -> -0.40652887 | Y45: =Y44*X45/100+Y44 -> 1389515.8
A46: 37437 | B46: =IF(A46>A45,1+B45,"-") -> 30 | C46: Model | D46: -3.09 | E46: =E45*D46/100+E45 -> 1357696.8 | G46: =(E46/E43-1)*100 -> -3.5869273 | J46: =$A46 -> 37437 | K46: ='LC (Gross)'!K46 -> -7.1145149 | L46: =L45*K46/100+L45 -> 695557.87 | N46: =(L46/L43-1)*100 -> -13.390005 | P46: =$A46 -> 37437 | Q46: ='LC (Gross)'!Q46 -> -5.3806288 | R46: =R45*Q46/100+R45 -> 838222.27 | T46: =(R46/R43-1)*100 -> -10.877309 | W46: =$A46 -> 37437 | X46: ='LC (Gross)'!X46 -> -3.234875 | Y46: =Y45*X46/100+Y45 -> 1344566.7
A47: 37468 | B47: =IF(A47>A46,1+B46,"-") -> 31 | C47: Model | D47: -5.38 | E47: =E46*D47/100+E46 -> 1284652.7 | J47: =$A47 -> 37468 | K47: ='LC (Gross)'!K47 -> -7.795149 | L47: =L46*K47/100+L46 -> 641338.1 | P47: =$A47 -> 37468 | Q47: ='LC (Gross)'!Q47 -> -5.8181354 | R47: =R46*Q47/100+R46 -> 789453.36 | W47: =$A47 -> 37468 | X47: ='LC (Gross)'!X47 -> -6.0299528 | Y47: =Y46*X47/100+Y46 -> 1263489.9
A48: 37499 | B48: =IF(A48>A47,1+B47,"-") -> 32 | C48: Model | D48: -0.42 | E48: =E47*D48/100+E47 -> 1279257.2 | J48: =$A48 -> 37499 | K48: ='LC (Gross)'!K48 -> 0.65484365 | L48: =L47*K48/100+L47 -> 645537.86 | P48: =$A48 -> 37499 | Q48: ='LC (Gross)'!Q48 -> 0.72354799 | R48: =R47*Q48/100+R47 -> 795165.44 | W48: =$A48 -> 37499 | X48: ='LC (Gross)'!X48 -> 1.1959926 | Y48: =Y47*X48/100+Y47 -> 1278601.2
A49: 37529 | B49: =IF(A49>A48,1+B48,"-") -> 33 | C49: Model | D49: -5.43 | E49: =E48*D49/100+E48 -> 1209793.5 | G49: =(E49/E46-1)*100 -> -10.893691 | J49: =$A49 -> 37529 | K49: ='LC (Gross)'!K49 -> -10.867942 | L49: =L48*K49/100+L48 -> 575381.18 | N49: =(L49/L46-1)*100 -> -17.277741 | P49: =$A49 -> 37529 | Q49: ='LC (Gross)'!Q49 -> -9.9631231 | R49: =R48*Q49/100+R48 -> 715942.13 | T49: =(R49/R46-1)*100 -> -14.588033 | W49: =$A49 -> 37529 | X49: ='LC (Gross)'!X49 -> -7.7098149 | Y49: =Y48*X49/100+Y48 -> 1180023.4
A50: 37560 | B50: =IF(A50>A49,1+B49,"-") -> 34 | C50: Model | D50: 2.85 | E50: =E49*D50/100+E49 -> 1244272.6 | J50: =$A50 -> 37560 | K50: ='LC (Gross)'!K50 -> 8.8015692 | L50: =L49*K50/100+L49 -> 626023.75 | P50: =$A50 -> 37560 | Q50: ='LC (Gross)'!Q50 -> 7.3309994 | R50: =R49*Q50/100+R49 -> 768427.84 | W50: =$A50 -> 37560 | X50: ='LC (Gross)'!X50 -> 3.0159158 | Y50: =Y49*X50/100+Y49 -> 1215611.9
A51: 37590 | B51: =IF(A51>A50,1+B50,"-") -> 35 | C51: Model | D51: 2.84 | E51: =E50*D51/100+E50 -> 1279610 | J51: =$A51 -> 37590 | K51: ='LC (Gross)'!K51 -> 5.8859708 | L51: =L50*K51/100+L50 -> 662871.33 | P51: =$A51 -> 37590 | Q51: ='LC (Gross)'!Q51 -> 1.7565989 | R51: =R50*Q51/100+R50 -> 781926.03 | W51: =$A51 -> 37590 | X51: ='LC (Gross)'!X51 -> -0.12864105 | Y51: =Y50*X51/100+Y50 -> 1214048.1
A52: 37621 | B52: =IF(A52>A51,1+B51,"-") -> 36 | C52: Model | D52: -0.24 | E52: =E51*D52/100+E51 -> 1276538.9 | F52: =(E52-E40)/E40*100 -> -3.1536843 | G52: =(E52/E49-1)*100 -> 5.5170897 | J52: =$A52 -> 37621 | K52: ='LC (Gross)'!K52 -> -5.8756759 | L52: =L51*K52/100+L51 -> 623923.16 | M52: =(L52-L40)/L40*100 -> -22.09782 | N52: =(L52/L49-1)*100 -> 8.4364902 | P52: =$A52 -> 37621 | Q52: ='LC (Gross)'!Q52 -> -3.3318864 | R52: =R51*Q52/100+R51 -> 755873.15 | S52: =(R52-R40)/R40*100 -> -17.88785 | T52: =(R52/R49-1)*100 -> 5.5774091 | W52: =$A52 -> 37621 | X52: ='LC (Gross)'!X52 -> -0.21294664 | Y52: =Y51*X52/100+Y51 -> 1211462.9
A53: 37652 | B53: =IF(A53>A52,1+B52,"-") -> 37 | C53: Model | D53: -3.6 | E53: =E52*D53/100+E52 -> 1230583.5 | J53: =$A53 -> 37652 | K53: ='LC (Gross)'!K53 -> -2.6196491 | L53: =L52*K53/100+L52 -> 607578.56 | P53: =$A53 -> 37652 | Q53: ='LC (Gross)'!Q53 -> -3.2514793 | R53: =R52*Q53/100+R52 -> 731296.09 | W53: =$A53 -> 37652 | X53: ='LC (Gross)'!X53 -> -2.0018061 | Y53: =Y52*X53/100+Y52 -> 1187211.7
A54: 37680 | B54: =IF(A54>A53,1+B53,"-") -> 38 | C54: Model | D54: -0.42 | E54: =E53*D54/100+E53 -> 1225415.1 | J54: =$A54 -> 37680 | K54: ='LC (Gross)'!K54 -> -1.500384 | L54: =L53*K54/100+L53 -> 598462.55 | P54: =$A54 -> 37680 | Q54: ='LC (Gross)'!Q54 -> -2.2920472 | R54: =R53*Q54/100+R53 -> 714534.44 | W54: =$A54 -> 37680 | X54: ='LC (Gross)'!X54 -> -1.3235571 | Y54: =Y53*X54/100+Y53 -> 1171498.3
A55: 37711 | B55: =IF(A55>A54,1+B54,"-") -> 39 | C55: Model | D55: 1.81 | E55: =E54*D55/100+E54 -> 1247595.1 | G55: =(E55/E52-1)*100 -> -2.2673683 | J55: =$A55 -> 37711 | K55: ='LC (Gross)'!K55 -> 0.96986083 | L55: =L54*K55/100+L54 -> 604266.8 | N55: =(L55/L52-1)*100 -> -3.1504449 | P55: =$A55 -> 37711 | Q55: ='LC (Gross)'!Q55 -> 1.719119 | R55: =R54*Q55/100+R54 -> 726818.13 | T55: =(R55/R52-1)*100 -> -3.8439007 | W55: =$A55 -> 37711 | X55: ='LC (Gross)'!X55 -> 0.58507389 | Y55: =Y54*X55/100+Y54 -> 1178352.4
A56: 37741 | B56: =IF(A56>A55,1+B55,"-") -> 40 | C56: Model | D56: 5.52 | E56: =E55*D56/100+E55 -> 1316462.3 | J56: =$A56 -> 37741 | K56: ='LC (Gross)'!K56 -> 8.2347753 | L56: =L55*K56/100+L55 -> 654026.82 | P56: =$A56 -> 37741 | Q56: ='LC (Gross)'!Q56 -> 5.7619831 | R56: =R55*Q56/100+R55 -> 768697.27 | W56: =$A56 -> 37741 | X56: ='LC (Gross)'!X56 -> 5.3792498 | Y56: =Y55*X56/100+Y55 -> 1241738.9
A57: 37772 | B57: =IF(A57>A56,1+B56,"-") -> 41 | C57: Model | D57: 5.62 | E57: =E56*D57/100+E56 -> 1390447.5 | J57: =$A57 -> 37772 | K57: ='LC (Gross)'!K57 -> 5.2682982 | L57: =L56*K57/100+L56 -> 688482.9 | P57: =$A57 -> 37772 | Q57: ='LC (Gross)'!Q57 -> 3.5828549 | R57: =R56*Q57/100+R56 -> 796238.58 | W57: =$A57 -> 37772 | X57: ='LC (Gross)'!X57 -> 6.2604099 | Y57: =Y56*X57/100+Y56 -> 1319476.9
A58: 37802 | B58: =IF(A58>A57,1+B57,"-") -> 42 | C58: Model | D58: 3.92 | E58: =E57*D58/100+E57 -> 1444953 | G58: =(E58/E55-1)*100 -> 15.819073 | J58: =$A58 -> 37802 | K58: ='LC (Gross)'!K58 -> 1.2751871 | L58: =L57*K58/100+L57 -> 697262.34 | N58: =(L58/L55-1)*100 -> 15.389815 | P58: =$A58 -> 37802 | Q58: ='LC (Gross)'!Q58 -> 0.88071285 | R58: =R57*Q58/100+R57 -> 803251.16 | T58: =(R58/R55-1)*100 -> 10.516114 | W58: =$A58 -> 37802 | X58: ='LC (Gross)'!X58 -> -0.62865431 | Y58: =Y57*X58/100+Y57 -> 1311181.9
A59: 37833 | B59: =IF(A59>A58,1+B58,"-") -> 43 | C59: Model | D59: 1.97 | E59: =E58*D59/100+E58 -> 1473418.6 | J59: =$A59 -> 37833 | K59: ='LC (Gross)'!K59 -> 1.7595249 | L59: =L58*K59/100+L58 -> 709530.85 | P59: =$A59 -> 37833 | Q59: ='LC (Gross)'!Q59 -> 0.3761046 | R59: =R58*Q59/100+R58 -> 806272.22 | W59: =$A59 -> 37833 | X59: ='LC (Gross)'!X59 -> 0.35346565 | Y59: =Y58*X59/100+Y58 -> 1315816.5
A60: 37864 | B60: =IF(A60>A59,1+B59,"-") -> 44 | C60: Model | D60: 1.26 | E60: =E59*D60/100+E59 -> 1491983.7 | J60: =$A60 -> 37864 | K60: ='LC (Gross)'!K60 -> 1.9495851 | L60: =L59*K60/100+L59 -> 723363.76 | P60: =$A60 -> 37864 | Q60: ='LC (Gross)'!Q60 -> 0.58757201 | R60: =R59*Q60/100+R59 -> 811009.65 | W60: =$A60 -> 37864 | X60: ='LC (Gross)'!X60 -> 1.0315034 | Y60: =Y59*X60/100+Y59 -> 1329389.2
A61: 37894 | B61: =IF(A61>A60,1+B60,"-") -> 45 | C61: Model | D61: 0.93 | E61: =E60*D61/100+E60 -> 1505859.1 | G61: =(E61/E58-1)*100 -> 4.2150918 | J61: =$A61 -> 37894 | K61: ='LC (Gross)'!K61 -> -1.0626342 | L61: =L60*K61/100+L60 -> 715677.05 | N61: =(L61/L58-1)*100 -> 2.6410004 | P61: =$A61 -> 37894 | Q61: ='LC (Gross)'!Q61 -> -0.32234876 | R61: =R60*Q61/100+R60 -> 808395.37 | T61: =(R61/R58-1)*100 -> 0.64042421 | W61: =$A61 -> 37894 | X61: ='LC (Gross)'!X61 -> 0.92539671 | Y61: =Y60*X61/100+Y60 -> 1341691.3
A62: 37925 | B62: =IF(A62>A61,1+B61,"-") -> 46 | C62: Model | D62: 4.71 | E62: =E61*D62/100+E61 -> 1576785.1 | J62: =$A62 -> 37925 | K62: ='LC (Gross)'!K62 -> 5.6532876 | L62: =L61*K62/100+L61 -> 756136.33 | P62: =$A62 -> 37925 | Q62: ='LC (Gross)'!Q62 -> 3.6363759 | R62: =R61*Q62/100+R61 -> 837791.67 | W62: =$A62 -> 37925 | X62: ='LC (Gross)'!X62 -> 4.7509276 | Y62: =Y61*X62/100+Y61 -> 1405434.1
A63: 37955 | B63: =IF(A63>A62,1+B62,"-") -> 47 | C63: Model | D63: 2.69 | E63: =E62*D63/100+E62 -> 1619200.6 | J63: =$A63 -> 37955 | K63: ='LC (Gross)'!K63 -> 0.87824574 | L63: =L62*K63/100+L62 -> 762777.06 | P63: =$A63 -> 37955 | Q63: ='LC (Gross)'!Q63 -> 0.81258477 | R63: =R62*Q63/100+R62 -> 844599.43 | W63: =$A63 -> 37955 | X63: ='LC (Gross)'!X63 -> 1.1537159 | Y63: =Y62*X63/100+Y62 -> 1421648.8
A64: 37986 | B64: =IF(A64>A63,1+B63,"-") -> 48 | C64: Model | D64: 5.07 | E64: =E63*D64/100+E63 -> 1701294.1 | F64: =(E64-E52)/E52*100 -> 33.273971 | G64: =(E64/E61-1)*100 -> 12.978303 | J64: =$A64 -> 37986 | K64: ='LC (Gross)'!K64 -> 5.2430503 | L64: =L63*K64/100+L63 -> 802769.85 | M64: =(L64-L52)/L52*100 -> 28.664859 | N64: =(L64/L61-1)*100 -> 12.169288 | P64: =$A64 -> 37986 | Q64: ='LC (Gross)'!Q64 -> 4.7449351 | R64: =R63*Q64/100+R63 -> 884675.13 | S64: =(R64-R52)/R52*100 -> 17.040158 | T64: =(R64/R61-1)*100 -> 9.4359468 | W64: =$A64 -> 37986 | X64: ='LC (Gross)'!X64 -> 4.6021467 | Y64: =Y63*X64/100+Y63 -> 1487075.2
A65: 38017 | B65: =IF(A65>A64,1+B64,"-") -> 49 | C65: Model | D65: 2.39 | E65: =E64*D65/100+E64 -> 1741955 | J65: =$A65 -> 38017 | K65: ='LC (Gross)'!K65 -> 1.8354691 | L65: =L64*K65/100+L64 -> 817504.44 | P65: =$A65 -> 38017 | Q65: ='LC (Gross)'!Q65 -> 1.2549239 | R65: =R64*Q65/100+R64 -> 895777.13 | W65: =$A65 -> 38017 | X65: ='LC (Gross)'!X65 -> 1.2911515 | Y65: =Y64*X65/100+Y64 -> 1506275.6
A66: 38046 | B66: =IF(A66>A65,1+B65,"-") -> 50 | C66: Model | D66: 2.25 | E66: =E65*D66/100+E65 -> 1781149 | J66: =$A66 -> 38046 | K66: ='LC (Gross)'!K66 -> 1.3894051 | L66: =L65*K66/100+L65 -> 828862.89 | P66: =$A66 -> 38046 | Q66: ='LC (Gross)'!Q66 -> 1.5268347 | R66: =R65*Q66/100+R65 -> 909454.16 | W66: =$A66 -> 38046 | X66: ='LC (Gross)'!X66 -> 3.0044248 | Y66: =Y65*X66/100+Y65 -> 1551530.5
A67: 38077 | B67: =IF(A67>A66,1+B66,"-") -> 51 | C67: Model | D67: 1.81 | E67: =E66*D67/100+E66 -> 1813387.8 | G67: =(E67/E64-1)*100 -> 6.5887323 | J67: =$A67 -> 38077 | K67: ='LC (Gross)'!K67 -> -1.5087779 | L67: =L66*K67/100+L66 -> 816357.19 | N67: =(L67/L64-1)*100 -> 1.6925574 | P67: =$A67 -> 38077 | Q67: ='LC (Gross)'!Q67 -> -1.3835666 | R67: =R66*Q67/100+R66 -> 896871.26 | T67: =(R67/R64-1)*100 -> 1.3786 | W67: =$A67 -> 38077 | X67: ='LC (Gross)'!X67 -> 0.49398922 | Y67: =Y66*X67/100+Y66 -> 1559194.9
A68: 38107 | B68: =IF(A68>A67,1+B67,"-") -> 52 | C68: Model | D68: -2.23 | E68: =E67*D68/100+E67 -> 1772949.3 | J68: =$A68 -> 38107 | K68: ='LC (Gross)'!K68 -> -1.569817 | L68: =L67*K68/100+L67 -> 803541.88 | P68: =$A68 -> 38107 | Q68: ='LC (Gross)'!Q68 -> 0.29481951 | R68: =R67*Q68/100+R67 -> 899515.41 | W68: =$A68 -> 38107 | X68: ='LC (Gross)'!X68 -> -1.0898863 | Y68: =Y67*X68/100+Y67 -> 1542201.5
A69: 38138 | B69: =IF(A69>A68,1+B68,"-") -> 53 | C69: Model | D69: 0.09 | E69: =E68*D69/100+E68 -> 1774544.9 | J69: =$A69 -> 38138 | K69: ='LC (Gross)'!K69 -> 1.3714253 | L69: =L68*K69/100+L68 -> 814561.85 | P69: =$A69 -> 38138 | Q69: ='LC (Gross)'!Q69 -> 1.1161332 | R69: =R68*Q69/100+R68 -> 909555.2 | W69: =$A69 -> 38138 | X69: ='LC (Gross)'!X69 -> 1.9537694 | Y69: =Y68*X69/100+Y68 -> 1572332.5
A70: 38168 | B70: =IF(A70>A69,1+B69,"-") -> 54 | C70: Model | D70: 5.27 | E70: =E69*D70/100+E69 -> 1868063.4 | G70: =(E70/E67-1)*100 -> 3.0151092 | J70: =$A70 -> 38168 | K70: ='LC (Gross)'!K70 -> 1.9445436 | L70: =L69*K70/100+L69 -> 830401.36 | N70: =(L70/L67-1)*100 -> 1.7203465 | P70: =$A70 -> 38168 | Q70: ='LC (Gross)'!Q70 -> 1.3143367 | R70: =R69*Q70/100+R69 -> 921509.82 | T70: =(R70/R67-1)*100 -> 2.7471679 | W70: =$A70 -> 38168 | X70: ='LC (Gross)'!X70 -> 1.313378 | Y70: =Y69*X70/100+Y69 -> 1592983.2
A71: 38199 | B71: =IF(A71>A70,1+B70,"-") -> 55 | C71: Model | D71: -1.78 | E71: =E70*D71/100+E70 -> 1834811.9 | J71: =$A71 -> 38199 | K71: ='LC (Gross)'!K71 -> -3.3097521 | L71: =L70*K71/100+L70 -> 802917.13 | P71: =$A71 -> 38199 | Q71: ='LC (Gross)'!Q71 -> -1.9831654 | R71: =R70*Q71/100+R70 -> 903234.76 | W71: =$A71 -> 38199 | X71: ='LC (Gross)'!X71 -> -1.476258 | Y71: =Y70*X71/100+Y70 -> 1569466.6
A72: 38230 | B72: =IF(A72>A71,1+B71,"-") -> 56 | C72: Model | D72: 0.78 | E72: =E71*D72/100+E71 -> 1849123.4 | J72: =$A72 -> 38230 | K72: ='LC (Gross)'!K72 -> 0.403387 | L72: =L71*K72/100+L71 -> 806156 | P72: =$A72 -> 38230 | Q72: ='LC (Gross)'!Q72 -> 1.3836257 | R72: =R71*Q72/100+R71 -> 915732.14 | W72: =$A72 -> 38230 | X72: ='LC (Gross)'!X72 -> 2.542361 | Y72: =Y71*X72/100+Y71 -> 1609368.2
A73: 38260 | B73: =IF(A73>A72,1+B72,"-") -> 57 | C73: Model | D73: 2.01 | E73: =E72*D73/100+E72 -> 1886290.8 | G73: =(E73/E70-1)*100 -> 0.97573693 | J73: =$A73 -> 38260 | K73: ='LC (Gross)'!K73 -> 1.0830983 | L73: =L72*K73/100+L72 -> 814887.46 | N73: =(L73/L70-1)*100 -> -1.8682414 | P73: =$A73 -> 38260 | Q73: ='LC (Gross)'!Q73 -> 0.37522432 | R73: =R72*Q73/100+R72 -> 919168.19 | T73: =(R73/R70-1)*100 -> -0.25410746 | W73: =$A73 -> 38260 | X73: ='LC (Gross)'!X73 -> 0.46291489 | Y73: =Y72*X73/100+Y72 -> 1616818.2
A74: 38291 | B74: =IF(A74>A73,1+B73,"-") -> 58 | C74: Model | D74: 0.82 | E74: =E73*D74/100+E73 -> 1901758.4 | J74: =$A74 -> 38291 | K74: ='LC (Gross)'!K74 -> 1.5277379 | L74: =L73*K74/100+L73 -> 827336.8 | P74: =$A74 -> 38291 | Q74: ='LC (Gross)'!Q74 -> 0.80763871 | R74: =R73*Q74/100+R73 -> 926591.75 | W74: =$A74 -> 38291 | X74: ='LC (Gross)'!X74 -> 1.9375068 | Y74: =Y73*X74/100+Y73 -> 1648144.1
A75: 38321 | B75: =IF(A75>A74,1+B74,"-") -> 59 | C75: Model | D75: 4.61 | E75: =E74*D75/100+E74 -> 1989429.5 | J75: =$A75 -> 38321 | K75: ='LC (Gross)'!K75 -> 4.0461445 | L75: =L74*K75/100+L74 -> 860812.05 | P75: =$A75 -> 38321 | Q75: ='LC (Gross)'!Q75 -> 3.2235838 | R75: =R74*Q75/100+R74 -> 956461.21 | W75: =$A75 -> 38321 | X75: ='LC (Gross)'!X75 -> 3.3659806 | Y75: =Y74*X75/100+Y74 -> 1703620.3
A76: 38352 | B76: =IF(A76>A75,1+B75,"-") -> 60 | C76: Model | D76: 5.23 | E76: =E75*D76/100+E75 -> 2093476.6 | F76: =(E76-E64)/E64*100 -> 23.052013 | G76: =(E76/E73-1)*100 -> 10.983768 | J76: =$A76 -> 38352 | K76: ='LC (Gross)'!K76 -> 3.3996651 | L76: =L75*K76/100+L75 -> 890076.77 | M76: =(L76-L64)/L64*100 -> 10.875711 | N76: =(L76/L73-1)*100 -> 9.2269569 | P76: =$A76 -> 38352 | Q76: ='LC (Gross)'!Q76 -> 2.9684397 | R76: =R75*Q76/100+R75 -> 984853.19 | S76: =(R76-R64)/R64*100 -> 11.323712 | T76: =(R76/R73-1)*100 -> 7.1461343 | W76: =$A76 -> 38352 | X76: ='LC (Gross)'!X76 -> 2.727091 | Y76: =Y75*X76/100+Y75 -> 1750079.6
A77: 38383 | B77: =IF(A77>A76,1+B76,"-") -> 61 | C77: Model | D77: -0.64 | E77: =E76*D77/100+E76 -> 2080078.4 | J77: =$A77 -> 38383 | K77: ='LC (Gross)'!K77 -> -2.4374624 | L77: =L76*K77/100+L76 -> 868381.49 | P77: =$A77 -> 38383 | Q77: ='LC (Gross)'!Q77 -> -1.3978776 | R77: =R76*Q77/100+R76 -> 971086.15 | W77: =$A77 -> 38383 | X77: ='LC (Gross)'!X77 -> -1.4774128 | Y77: =Y76*X77/100+Y76 -> 1724223.7
A78: 38411 | B78: =IF(A78>A77,1+B77,"-") -> 62 | C78: Model | D78: 0.84 | E78: =E77*D78/100+E77 -> 2097551 | J78: =$A78 -> 38411 | K78: ='LC (Gross)'!K78 -> 2.1043923 | L78: =L77*K78/100+L77 -> 886655.64 | P78: =$A78 -> 38411 | Q78: ='LC (Gross)'!Q78 -> 2.214273 | R78: =R77*Q78/100+R77 -> 992588.64 | W78: =$A78 -> 38411 | X78: ='LC (Gross)'!X78 -> 0.80546215 | Y78: =Y77*X78/100+Y77 -> 1738111.7
A79: 38442 | B79: =IF(A79>A78,1+B78,"-") -> 63 | C79: Model | D79: -0.53 | E79: =E78*D79/100+E78 -> 2086434 | G79: =(E79/E76-1)*100 -> -0.33640751 | J79: =$A79 -> 38442 | K79: ='LC (Gross)'!K79 -> -1.7707812 | L79: =L78*K79/100+L78 -> 870954.91 | N79: =(L79/L76-1)*100 -> -2.1483388 | P79: =$A79 -> 38442 | Q79: ='LC (Gross)'!Q79 -> -1.8409354 | R79: =R78*Q79/100+R78 -> 974315.73 | T79: =(R79/R76-1)*100 -> -1.0699524 | W79: =$A79 -> 38442 | X79: ='LC (Gross)'!X79 -> -0.46381617 | Y79: =Y78*X79/100+Y78 -> 1730050
A80: 38472 | B80: =IF(A80>A79,1+B79,"-") -> 64 | C80: Model | D80: -1.66 | E80: =E79*D80/100+E79 -> 2051799.2 | J80: =$A80 -> 38472 | K80: ='LC (Gross)'!K80 -> -1.8965257 | L80: =L79*K80/100+L79 -> 854437.03 | P80: =$A80 -> 38472 | Q80: ='LC (Gross)'!Q80 -> -1.5651005 | R80: =R79*Q80/100+R79 -> 959066.71 | W80: =$A80 -> 38472 | X80: ='LC (Gross)'!X80 -> -0.060502352 | Y80: =Y79*X80/100+Y79 -> 1729003.3
A81: 38503 | B81: =IF(A81>A80,1+B80,"-") -> 65 | C81: Model | D81: 3.46 | E81: =E80*D81/100+E80 -> 2122791.5 | J81: =$A81 -> 38503 | K81: ='LC (Gross)'!K81 -> 3.1818293 | L81: =L80*K81/100+L80 -> 881623.75 | P81: =$A81 -> 38503 | Q81: ='LC (Gross)'!Q81 -> 2.1340678 | R81: =R80*Q81/100+R80 -> 979533.84 | W81: =$A81 -> 38503 | X81: ='LC (Gross)'!X81 -> 1.5034454 | Y81: =Y80*X81/100+Y80 -> 1754997.9
A82: 38533 | B82: =IF(A82>A81,1+B81,"-") -> 66 | C82: Model | D82: 3.38 | E82: =E81*D82/100+E81 -> 2194541.8 | G82: =(E82/E79-1)*100 -> 5.1814627 | J82: =$A82 -> 38533 | K82: ='LC (Gross)'!K82 -> 0.14197974 | L82: =L81*K82/100+L81 -> 882875.48 | N82: =(L82/L79-1)*100 -> 1.3686784 | P82: =$A82 -> 38533 | Q82: ='LC (Gross)'!Q82 -> -0.65988047 | R82: =R81*Q82/100+R81 -> 973070.09 | T82: =(R82/R79-1)*100 -> -0.12784755 | W82: =$A82 -> 38533 | X82: ='LC (Gross)'!X82 -> -0.003592909 | Y82: =Y81*X82/100+Y81 -> 1754934.9
A83: 38564 | B83: =IF(A83>A82,1+B82,"-") -> 67 | C83: Model | D83: 2.62 | E83: =E82*D83/100+E82 -> 2252038.8 | J83: =$A83 -> 38564 | K83: ='LC (Gross)'!K83 -> 3.7187488 | L83: =L82*K83/100+L82 -> 915707.4 | P83: =$A83 -> 38564 | Q83: ='LC (Gross)'!Q83 -> 2.5037729 | R83: =R82*Q83/100+R82 -> 997433.55 | W83: =$A83 -> 38564 | X83: ='LC (Gross)'!X83 -> 2.4015867 | Y83: =Y82*X83/100+Y82 -> 1797081.2
A84: 38595 | B84: =IF(A84>A83,1+B83,"-") -> 68 | C84: Model | D84: -1.69 | E84: =E83*D84/100+E83 -> 2213979.4 | J84: =$A84 -> 38595 | K84: ='LC (Gross)'!K84 -> -0.91215042 | L84: =L83*K84/100+L83 -> 907354.77 | P84: =$A84 -> 38595 | Q84: ='LC (Gross)'!Q84 -> -1.1860102 | R84: =R83*Q84/100+R83 -> 985603.89 | W84: =$A84 -> 38595 | X84: ='LC (Gross)'!X84 -> -1.0084211 | Y84: =Y83*X84/100+Y83 -> 1778959
A85: 38625 | B85: =IF(A85>A84,1+B84,"-") -> 69 | C85: Model | D85: 1.24 | E85: =E84*D85/100+E84 -> 2241432.7 | G85: =(E85/E82-1)*100 -> 2.136705 | J85: =$A85 -> 38625 | K85: ='LC (Gross)'!K85 -> 0.8099054 | L85: =L84*K85/100+L84 -> 914703.49 | N85: =(L85/L82-1)*100 -> 3.6050392 | P85: =$A85 -> 38625 | Q85: ='LC (Gross)'!Q85 -> 0.22018032 | R85: =R84*Q85/100+R84 -> 987774 | T85: =(R85/R82-1)*100 -> 1.5110841 | W85: =$A85 -> 38625 | X85: ='LC (Gross)'!X85 -> -0.050509347 | Y85: =Y84*X85/100+Y84 -> 1778060.5
A86: 38656 | B86: =IF(A86>A85,1+B85,"-") -> 70 | C86: Model | D86: -2.95 | E86: =E85*D86/100+E85 -> 2175310.4 | J86: =$A86 -> 38656 | K86: ='LC (Gross)'!K86 -> -1.6670311 | L86: =L85*K86/100+L85 -> 899455.1 | P86: =$A86 -> 38656 | Q86: ='LC (Gross)'!Q86 -> -1.9101744 | R86: =R85*Q86/100+R85 -> 968905.79 | W86: =$A86 -> 38656 | X86: ='LC (Gross)'!X86 -> -1.6633952 | Y86: =Y85*X86/100+Y85 -> 1748484.3
A87: 38686 | B87: =IF(A87>A86,1+B86,"-") -> 71 | C87: Model | D87: 0.33 | E87: =E86*D87/100+E86 -> 2182489 | J87: =$A87 -> 38686 | K87: ='LC (Gross)'!K87 -> 3.7821852 | L87: =L86*K87/100+L86 -> 933474.15 | P87: =$A87 -> 38686 | Q87: ='LC (Gross)'!Q87 -> 2.7450377 | R87: =R86*Q87/100+R86 -> 995502.62 | W87: =$A87 -> 38686 | X87: ='LC (Gross)'!X87 -> 2.053063 | Y87: =Y86*X87/100+Y86 -> 1784381.8
A88: 38717 | B88: =IF(A88>A87,1+B87,"-") -> 72 | C88: Model | D88: 3.32 | E88: =E87*D88/100+E87 -> 2254947.6 | F88: =(E88-E76)/E76*100 -> 7.7130531 | G88: =(E88/E85-1)*100 -> 0.6029578 | J88: =$A88 -> 38717 | K88: ='LC (Gross)'!K88 -> 0.030360766 | L88: =L87*K88/100+L87 -> 933757.56 | M88: =(L88-L76)/L76*100 -> 4.9075305 | N88: =(L88/L85-1)*100 -> 2.0830876 | P88: =$A88 -> 38717 | Q88: ='LC (Gross)'!Q88 -> -0.49207319 | R88: =R87*Q88/100+R87 -> 990604.02 | S88: =(R88-R76)/R76*100 -> 0.58392757 | T88: =(R88/R85-1)*100 -> 0.28650492 | W88: =$A88 -> 38717 | X88: ='LC (Gross)'!X88 -> 0.23393383 | Y88: =Y87*X88/100+Y87 -> 1788556.1
A89: 38748 | B89: =IF(A89>A88,1+B88,"-") -> 73 | C89: Model | D89: 1 | E89: =E88*D89/100+E88 -> 2277497.1 | J89: =$A89 -> 38748 | K89: ='LC (Gross)'!K89 -> 2.6477865 | L89: =L88*K89/100+L88 -> 958481.47 | P89: =$A89 -> 38748 | Q89: ='LC (Gross)'!Q89 -> 1.3903931 | R89: =R88*Q89/100+R88 -> 1004377.3 | W89: =$A89 -> 38748 | X89: ='LC (Gross)'!X89 -> 0.80187415 | Y89: =Y88*X89/100+Y88 -> 1802898
A90: 38776 | B90: =IF(A90>A89,1+B89,"-") -> 74 | C90: Model | D90: 1.72 | E90: =E89*D90/100+E89 -> 2316670 | J90: =$A90 -> 38776 | K90: ='LC (Gross)'!K90 -> 0.27106004 | L90: =L89*K90/100+L89 -> 961079.53 | P90: =$A90 -> 38776 | Q90: ='LC (Gross)'!Q90 -> 0.41842509 | R90: =R89*Q90/100+R89 -> 1008579.9 | W90: =$A90 -> 38776 | X90: ='LC (Gross)'!X90 -> 2.3525606 | Y90: =Y89*X90/100+Y89 -> 1845312.3
A91: 38807 | B91: =IF(A91>A90,1+B90,"-") -> 75 | C91: Model | D91: 1.47 | E91: =E90*D91/100+E90 -> 2350725.1 | G91: =(E91/E88-1)*100 -> 4.2474368 | J91: =$A91 -> 38807 | K91: ='LC (Gross)'!K91 -> 1.2433129 | L91: =L90*K91/100+L90 -> 973028.76 | N91: =(L91/L88-1)*100 -> 4.2057162 | P91: =$A91 -> 38807 | Q91: ='LC (Gross)'!Q91 -> 0.80868169 | R91: =R90*Q91/100+R90 -> 1016736.1 | T91: =(R91/R88-1)*100 -> 2.6379923 | W91: =$A91 -> 38807 | X91: ='LC (Gross)'!X91 -> 0.65214643 | Y91: =Y90*X91/100+Y90 -> 1857346.4
A92: 38837 | B92: =IF(A92>A91,1+B91,"-") -> 76 | C92: Model | D92: -0.42 | E92: =E91*D92/100+E91 -> 2340852 | J92: =$A92 -> 38837 | K92: ='LC (Gross)'!K92 -> 1.3427741 | L92: =L91*K92/100+L91 -> 986094.33 | P92: =$A92 -> 38837 | Q92: ='LC (Gross)'!Q92 -> 0.86556353 | R92: =R91*Q92/100+R91 -> 1025536.6 | W92: =$A92 -> 38837 | X92: ='LC (Gross)'!X92 -> 2.1635844 | Y92: =Y91*X92/100+Y91 -> 1897531.7
A93: 38868 | B93: =IF(A93>A92,1+B92,"-") -> 77 | C93: Model | D93: -0.86 | E93: =E92*D93/100+E92 -> 2320720.7 | J93: =$A93 -> 38868 | K93: ='LC (Gross)'!K93 -> -2.8781302 | L93: =L92*K93/100+L92 -> 957713.26 | P93: =$A93 -> 38868 | Q93: ='LC (Gross)'!Q93 -> -2.1535735 | R93: =R92*Q93/100+R92 -> 1003450.9 | W93: =$A93 -> 38868 | X93: ='LC (Gross)'!X93 -> -0.76811756 | Y93: =Y92*X93/100+Y92 -> 1882956.4
A94: 38898 | B94: =IF(A94>A93,1+B93,"-") -> 78 | C94: Model | D94: 1.49 | E94: =E93*D94/100+E93 -> 2355299.4 | G94: =(E94/E91-1)*100 -> 0.19459382 | J94: =$A94 -> 38898 | K94: ='LC (Gross)'!K94 -> 0.13289554 | L94: =L93*K94/100+L93 -> 958986.01 | N94: =(L94/L91-1)*100 -> -1.4431992 | P94: =$A94 -> 38898 | Q94: ='LC (Gross)'!Q94 -> 0.13473955 | R94: =R93*Q94/100+R93 -> 1004802.9 | T94: =(R94/R91-1)*100 -> -1.1736715 | W94: =$A94 -> 38898 | X94: ='LC (Gross)'!X94 -> 0.43667684 | Y94: =Y93*X94/100+Y93 -> 1891178.9
A95: 38929 | B95: =IF(A95>A94,1+B94,"-") -> 79 | C95: Model | D95: 0.18 | E95: =E94*D95/100+E94 -> 2359539 | J95: =$A95 -> 38929 | K95: ='LC (Gross)'!K95 -> 0.61685312 | L95: =L94*K95/100+L94 -> 964901.55 | P95: =$A95 -> 38929 | Q95: ='LC (Gross)'!Q95 -> 1.5581554 | R95: =R94*Q95/100+R94 -> 1020459.3 | W95: =$A95 -> 38929 | X95: ='LC (Gross)'!X95 -> 2.1868946 | Y95: =Y94*X95/100+Y94 -> 1932536.9
A96: 38960 | B96: =IF(A96>A95,1+B95,"-") -> 80 | C96: Model | D96: 2.6 | E96: =E95*D96/100+E95 -> 2420887 | J96: =$A96 -> 38960 | K96: ='LC (Gross)'!K96 -> 2.3793072 | L96: =L95*K96/100+L95 -> 987859.52 | P96: =$A96 -> 38960 | Q96: ='LC (Gross)'!Q96 -> 2.1797859 | R96: =R95*Q96/100+R95 -> 1042703.2 | W96: =$A96 -> 38960 | X96: ='LC (Gross)'!X96 -> 2.1864253 | Y96: =Y95*X96/100+Y95 -> 1974790.4
A97: 38990 | B97: =IF(A97>A96,1+B96,"-") -> 81 | C97: Model | D97: 2.72 | E97: =E96*D97/100+E96 -> 2486735.1 | G97: =(E97/E94-1)*100 -> 5.5804233 | J97: =$A97 -> 38990 | K97: ='LC (Gross)'!K97 -> 2.5744988 | L97: =L96*K97/100+L96 -> 1013292 | N97: =(L97/L94-1)*100 -> 5.6628499 | P97: =$A97 -> 38990 | Q97: ='LC (Gross)'!Q97 -> 1.9453843 | R97: =R96*Q97/100+R96 -> 1062987.7 | T97: =(R97/R94-1)*100 -> 5.7906682 | W97: =$A97 -> 38990 | X97: ='LC (Gross)'!X97 -> 2.0467267 | Y97: =Y96*X97/100+Y96 -> 2015209
A98: 39021 | B98: =IF(A98>A97,1+B97,"-") -> 82 | C98: Model | D98: 2.75 | E98: =E97*D98/100+E97 -> 2555120.3 | J98: =$A98 -> 39021 | K98: ='LC (Gross)'!K98 -> 3.2586431 | L98: =L97*K98/100+L97 -> 1046311.5 | P98: =$A98 -> 39021 | Q98: ='LC (Gross)'!Q98 -> 2.5310934 | R98: =R97*Q98/100+R97 -> 1089892.9 | W98: =$A98 -> 39021 | X98: ='LC (Gross)'!X98 -> 2.8015319 | Y98: =Y97*X98/100+Y97 -> 2071665.7
A99: 39051 | B99: =IF(A99>A98,1+B98,"-") -> 83 | C99: Model | D99: 1.75 | E99: =E98*D99/100+E98 -> 2599834.9 | J99: =$A99 -> 39051 | K99: ='LC (Gross)'!K99 -> 1.9018103 | L99: =L98*K99/100+L98 -> 1066210.4 | P99: =$A99 -> 39051 | Q99: ='LC (Gross)'!Q99 -> 1.3980821 | R99: =R98*Q99/100+R98 -> 1105130.5 | W99: =$A99 -> 39051 | X99: ='LC (Gross)'!X99 -> 1.0108158 | Y99: =Y98*X99/100+Y98 -> 2092606.4
A100: 39082 | B100: =IF(A100>A99,1+B99,"-") -> 84 | C100: Model | D100: 2.85 | E100: =E99*D100/100+E99 -> 2673930.2 | F100: =(E100-E88)/E88*100 -> 18.580593 | G100: =(E100/E97-1)*100 -> 7.5277466 | J100: =$A100 -> 39082 | K100: ='LC (Gross)'!K100 -> 1.3938645 | L100: =L99*K100/100+L99 -> 1081071.9 | M100: =(L100-L88)/L88*100 -> 15.776509 | N100: =(L100/L97-1)*100 -> 6.6890846 | P100: =$A100 -> 39082 | Q100: ='LC (Gross)'!Q100 -> 1.7874384 | R100: =R99*Q100/100+R99 -> 1124884.1 | S100: =(R100-R88)/R88*100 -> 13.555372 | T100: =(R100/R97-1)*100 -> 5.8228648 | W100: =$A100 -> 39082 | X100: ='LC (Gross)'!X100 -> 2.298809 | Y100: =Y99*X100/100+Y99 -> 2140711.5
A101: 39113 | B101: =IF(A101>A100,1+B100,"-") -> 85 | C101: Model | D101: 2.34 | E101: =E100*D101/100+E100 -> 2736500.2 | J101: =$A101 -> 39113 | K101: ='LC (Gross)'!K101 -> 1.512291 | L101: =L100*K101/100+L100 -> 1097420.9 | P101: =$A101 -> 39113 | Q101: ='LC (Gross)'!Q101 -> 0.72498355 | R101: =R100*Q101/100+R100 -> 1133039.3 | W101: =$A101 -> 39113 | X101: ='LC (Gross)'!X101 -> 1.0263729 | Y101: =Y100*X101/100+Y100 -> 2162683.1
A102: 39141 | B102: =IF(A102>A101,1+B101,"-") -> 86 | C102: Model | D102: -1.73 | E102: =E101*D102/100+E101 -> 2689158.7 | J102: =$A102 -> 39141 | K102: ='LC (Gross)'!K102 -> -1.9557481 | L102: =L101*K102/100+L101 -> 1075958.1 | P102: =$A102 -> 39141 | Q102: ='LC (Gross)'!Q102 -> -2.5164217 | R102: =R101*Q102/100+R101 -> 1104527.3 | W102: =$A102 -> 39141 | X102: ='LC (Gross)'!X102 -> 0.063414591 | Y102: =Y101*X102/100+Y101 -> 2164054.6
...

Sheet Global (Gross)
C1: Global (Gross) | J1: MSCI ACWI® Index | P1: MSCI ACWI® Minimum Volatility Index
D4: Return | E4: Relative Return | F4: Beta | G4: Alpha | H4: stdevp | K4: Return | L4: Beta | M4: stdevp | Q4: Return | R4: Relative Return | S4: Beta | T4: stdevp
B5: 12 | C5: YTD | D5: {=IFERROR((GEOMEAN(1+OFFSET(D$16,MAX($B$16:$B$506)-$B$5+1,0,$B$5,1)/100)^$B$5-1)*100,"N/A")} -> 12.65947 | E5: =IFERROR(D5-$K5,"N/A") -> -10.233127 | F5: =IFERROR(SLOPE(OFFSET(D$16,MAX($B$16:$B$506)-$B$5+1,0,$B$5,1),OFFSET($K$16,MAX($B$16:$B$506)-$B$5+1,0,$B$5,1)),"N/A") -> 0.16337531 | G5: {=IFERROR(INTERCEPT(OFFSET(D$16,MAX($B$16:$B$506)-$B$5+1,0,$B$5,1),OFFSET($K$16,MAX($B$16:$B$506)-$B$5+1,0,$B$5,1))*12,"N/A")} -> 8.7151895 | H5: =IFERROR(STDEVP(OFFSET(D$16,MAX($B$16:$B$506)-$B$5+1,0,$B$5,1))*SQRT(12),"N/A") -> 6.2003629 | J5: YTD | K5: {=IFERROR((GEOMEAN(1+OFFSET(K$16,MAX($B$16:$B$506)-$B$5+1,0,$B$5,1)/100)^$B$5-1)*100,"N/A")} -> 22.892597 | L5: =IFERROR(SLOPE(OFFSET(K$16,MAX($B$16:$B$506)-$B$5+1,0,$B$5,1),OFFSET($K$16,MAX($B$16:$B$506)-$B$5+1,0,$B$5,1)),"N/A") -> 1 | M5: =IFERROR(STDEVP(OFFSET(K$16,MAX($B$16:$B$506)-$B$5+1,0,$B$5,1))*SQRT(12),"N/A") -> 8.5348447 | P5: YTD | Q5: {=IFERROR((GEOMEAN(1+OFFSET(Q$16,MAX($B$16:$B$506)-$B$5+1,0,$B$5,1)/100)^$B$5-1)*100,"N/A")} -> 11.218931 | R5: =IFERROR(Q5-$K5,"N/A") -> -11.673665 | S5: =IFERROR(SLOPE(OFFSET(Q$16,MAX($B$16:$B$506)-$B$5+1,0,$B$5,1),OFFSET($K$16,MAX($B$16:$B$506)-$B$5+1,0,$B$5,1)),"N/A") -> -0.014363083 | T5: =IFERROR(STDEVP(OFFSET(Q$16,MAX($B$16:$B$506)-$B$5+1,0,$B$5,1))*SQRT(12),"N/A") -> 4.9459417
C6: One Year | D6: {=IFERROR((GEOMEAN(1+OFFSET(D$16,MAX($B$16:$B$506)-11,0,12,1)/100)^12-1)*100,"N/A")} -> 12.65947 | E6: =IFERROR(D6-$K6,"N/A") -> -10.233127 | F6: =IFERROR(SLOPE(OFFSET(D$16,MAX($B$16:$B$506)-11,0,12,1),OFFSET(K$16,MAX($B$16:$B$506)-11,0,12,1)),"N/A") -> 0.16337531 | G6: =IFERROR(INTERCEPT(OFFSET($D$16,MAX($B$16:$B$506)-11,0,12,1),OFFSET($K$16,MAX($B$16:$B$506)-11,0,12,1))*12,"N/A") -> 8.7151895 | H6: =IFERROR(STDEVP(OFFSET(D$16,MAX($B$16:$B$506)-11,0,12,1))*SQRT(12),"N/A") -> 6.2003629 | J6: One Year | K6: {=IFERROR((GEOMEAN(1+OFFSET(K$16,MAX($B$16:$B$506)-11,0,12,1)/100)^12-1)*100,"N/A")} -> 22.892597 | L6: =IFERROR(SLOPE(OFFSET(K$16,MAX($B$16:$B$506)-11,0,12,1),OFFSET(K$16,MAX($B$16:$B$506)-11,0,12,1)),"N/A") -> 1 | M6: =IFERROR(STDEVP(OFFSET(K$16,MAX($B$16:$B$506)-11,0,12,1))*SQRT(12),"N/A") -> 8.5348447 | P6: One Year | Q6: {=IFERROR((GEOMEAN(1+OFFSET(Q$16,MAX($B$16:$B$506)-11,0,12,1)/100)^12-1)*100,"N/A")} -> 11.218931 | R6: =IFERROR(Q6-$K6,"N/A") -> -11.673665 | S6: =IFERROR(SLOPE(OFFSET(Q$16,MAX($B$16:$B$506)-11,0,12,1),OFFSET($K$16,MAX($B$16:$B$506)-11,0,12,1)),"N/A") -> -0.014363083 | T6: =IFERROR(STDEVP(OFFSET(Q$16,MAX($B$16:$B$506)-11,0,12,1))*SQRT(12),"N/A") -> 4.9459417
C7: Two Year | D7: {=IFERROR((GEOMEAN(1+OFFSET(D$16,MAX($B$16:$B$506)-23,0,24,1)/100)^12-1)*100,"N/A")} -> 11.390894 | E7: =IFERROR(D7-$K7,"N/A") -> -9.0458764 | F7: =IFERROR(SLOPE(OFFSET(D$16,MAX($B$16:$B$506)-23,0,24,1),OFFSET($K$16,MAX($B$16:$B$506)-23,0,24,1)),"N/A") -> 0.56190465 | G7: =IFERROR(INTERCEPT(OFFSET(D$16,MAX($B$16:$B$506)-23,0,24,1),OFFSET($K$16,MAX($B$16:$B$506)-23,0,24,1))*12,"N/A") -> 0.40564386 | H7: =IFERROR(STDEVP(OFFSET(D$16,MAX($B$16:$B$506)-23,0,24,1))*SQRT(12),"N/A") -> 7.8771072 | J7: Two Year | K7: {=IFERROR((GEOMEAN(1+OFFSET(K$16,MAX($B$16:$B$506)-23,0,24,1)/100)^12-1)*100,"N/A")} -> 20.436771 | L7: =IFERROR(SLOPE(OFFSET(K$16,MAX($B$16:$B$506)-23,0,24,1),OFFSET($K$16,MAX($B$16:$B$506)-23,0,24,1)),"N/A") -> 1 | M7: =IFERROR(STDEVP(OFFSET(K$16,MAX($B$16:$B$506)-23,0,24,1))*SQRT(12),"N/A") -> 8.6852357 | P7: Two Year | Q7: {=IFERROR((GEOMEAN(1+OFFSET(Q$16,MAX($B$16:$B$506)-23,0,24,1)/100)^12-1)*100,"N/A")} -> 11.573775 | R7: =IFERROR(Q7-$K7,"N/A") -> -8.8629954 | S7: =IFERROR(SLOPE(OFFSET(Q$16,MAX($B$16:$B$506)-23,0,24,1),OFFSET($K$16,MAX($B$16:$B$506)-23,0,24,1)),"N/A") -> 0.40552781 | T7: =IFERROR(STDEVP(OFFSET(Q$16,MAX($B$16:$B$506)-23,0,24,1))*SQRT(12),"N/A") -> 7.0941341
C8: Three Year | D8: {=IFERROR((GEOMEAN(1+OFFSET(D$16,MAX($B$16:$B$506)-35,0,36,1)/100)^12-1)*100,"N/A")} -> 12.376696 | E8: =IFERROR(D8-$K8,"N/A") -> -8.8339343 | F8: =IFERROR(SLOPE(OFFSET(D$16,MAX($B$16:$B$506)-35,0,36,1),OFFSET(K$16,MAX($B$16:$B$506)-35,0,36,1)),"N/A") -> 0.66526204 | G8: =IFERROR(INTERCEPT(OFFSET($D$16,MAX($B$16:$B$506)-35,0,36,1),OFFSET($K$16,MAX($B$16:$B$506)-35,0,36,1))*12,"N/A") -> -1.1598505 | H8: =IFERROR(STDEVP(OFFSET(D$16,MAX($B$16:$B$506)-35,0,36,1))*SQRT(12),"N/A") -> 9.2530616 | J8: Three Year | K8: {=IFERROR((GEOMEAN(1+OFFSET(K$16,MAX($B$16:$B$506)-35,0,36,1)/100)^12-1)*100,"N/A")} -> 21.21063 | L8: =IFERROR(SLOPE(OFFSET(K$16,MAX($B$16:$B$506)-35,0,36,1),OFFSET(K$16,MAX($B$16:$B$506)-35,0,36,1)),"N/A") -> 1 | M8: =IFERROR(STDEVP(OFFSET(K$16,MAX($B$16:$B$506)-35,0,36,1))*SQRT(12),"N/A") -> 11.184857 | P8: Three Year | Q8: {=IFERROR((GEOMEAN(1+OFFSET(Q$16,MAX($B$16:$B$506)-35,0,36,1)/100)^12-1)*100,"N/A")} -> 10.470772 | R8: =IFERROR(Q8-$K8,"N/A") -> -10.739858 | S8: =IFERROR(SLOPE(OFFSET(Q$16,MAX($B$16:$B$506)-35,0,36,1),OFFSET($K$16,MAX($B$16:$B$506)-35,0,36,1)),"N/A") -> 0.50975685 | T8: =IFERROR(STDEVP(OFFSET(Q$16,MAX($B$16:$B$506)-35,0,36,1))*SQRT(12),"N/A") -> 8.1967833
C9: Four Year | D9: {=IFERROR((GEOMEAN(1+OFFSET(D$16,MAX($B$16:$B$506)-47,0,48,1)/100)^12-1)*100,"N/A")} -> 5.6189203 | E9: =IFERROR(D9-$K9,"N/A") -> -4.3269809 | F9: =IFERROR(SLOPE(OFFSET(D$16,MAX($B$16:$B$506)-47,0,48,1),OFFSET($K$16,MAX($B$16:$B$506)-47,0,48,1)),"N/A") -> 0.7377533 | G9: =IFERROR(INTERCEPT(OFFSET(D$16,MAX($B$16:$B$506)-47,0,48,1),OFFSET($K$16,MAX($B$16:$B$506)-47,0,48,1))*12,"N/A") -> -1.6175528 | H9: =IFERROR(STDEVP(OFFSET(D$16,MAX($B$16:$B$506)-47,0,48,1))*SQRT(12),"N/A") -> 12.114279 | J9: Four Year | K9: {=IFERROR((GEOMEAN(1+OFFSET(K$16,MAX($B$16:$B$506)-47,0,48,1)/100)^12-1)*100,"N/A")} -> 9.9459012 | L9: =IFERROR(SLOPE(OFFSET(K$16,MAX($B$16:$B$506)-47,0,48,1),OFFSET($K$16,MAX($B$16:$B$506)-47,0,48,1)),"N/A") -> 1 | M9: =IFERROR(STDEVP(OFFSET(K$16,MAX($B$16:$B$506)-47,0,48,1))*SQRT(12),"N/A") -> 14.775176 | P9: Four Year | Q9: {=IFERROR((GEOMEAN(1+OFFSET(Q$16,MAX($B$16:$B$506)-47,0,48,1)/100)^12-1)*100,"N/A")} -> 5.0067674 | R9: =IFERROR(Q9-$K9,"N/A") -> -4.9391338 | S9: =IFERROR(SLOPE(OFFSET(Q$16,MAX($B$16:$B$506)-47,0,48,1),OFFSET($K$16,MAX($B$16:$B$506)-47,0,48,1)),"N/A") -> 0.57609941 | T9: =IFERROR(STDEVP(OFFSET(Q$16,MAX($B$16:$B$506)-47,0,48,1))*SQRT(12),"N/A") -> 10.175138
C10: Five Year | D10: {=IFERROR((GEOMEAN(1+OFFSET(D$16,MAX($B$16:$B$506)-59,0,60,1)/100)^12-1)*100,"N/A")} -> 7.7968755 | E10: =IFERROR(D10-$K10,"N/A") -> -3.9112605 | F10: =IFERROR(SLOPE(OFFSET(D$16,MAX($B$16:$B$506)-59,0,60,1),OFFSET(K$16,MAX($B$16:$B$506)-59,0,60,1)),"N/A") -> 0.76146475 | G10: =IFERROR(INTERCEPT(OFFSET($D$16,MAX($B$16:$B$506)-59,0,60,1),OFFSET($K$16,MAX($B$16:$B$506)-59,0,60,1))*12,"N/A") -> -0.9892025 | H10: =IFERROR(STDEVP(OFFSET(D$16,MAX($B$16:$B$506)-59,0,60,1))*SQRT(12),"N/A") -> 11.679647 | J10: Five Year | K10: {=IFERROR((GEOMEAN(1+OFFSET(K$16,MAX($B$16:$B$506)-59,0,60,1)/100)^12-1)*100,"N/A")} -> 11.708136 | L10: =IFERROR(SLOPE(OFFSET(K$16,MAX($B$16:$B$506)-59,0,60,1),OFFSET(K$16,MAX($B$16:$B$506)-59,0,60,1)),"N/A") -> 1 | M10: =IFERROR(STDEVP(OFFSET(K$16,MAX($B$16:$B$506)-59,0,60,1))*SQRT(12),"N/A") -> 13.847692 | P10: Five Year | Q10: {=IFERROR((GEOMEAN(1+OFFSET(Q$16,MAX($B$16:$B$506)-59,0,60,1)/100)^12-1)*100,"N/A")} -> 6.8376476 | R10: =IFERROR(Q10-$K10,"N/A") -> -4.8704884 | S10: =IFERROR(SLOPE(OFFSET(Q$16,MAX($B$16:$B$506)-59,0,60,1),OFFSET($K$16,MAX($B$16:$B$506)-59,0,60,1)),"N/A") -> 0.59992683 | T10: =IFERROR(STDEVP(OFFSET(Q$16,MAX($B$16:$B$506)-59,0,60,1))*SQRT(12),"N/A") -> 10.034055
C11: Ten Year | D11: {=IFERROR((GEOMEAN(1+OFFSET(D$16,MAX($B$16:$B$506)-119,0,120,1)/100)^12-1)*100,"N/A")} -> 9.6898793 | E11: =IFERROR(D11-$K11,"N/A") -> -2.6030971 | F11: =IF(D11="N/A","N/A",IFERROR(SLOPE(OFFSET(D$16,MAX($B$16:$B$506)-119,0,120,1),OFFSET(K$16,MAX($B$16:$B$506)-119,0,120,1)),"N/A")) -> 0.75549575 | G11: =IF(D11="N/A","N/A",IFERROR(INTERCEPT(OFFSET($D$16,MAX($B$16:$B$506)-119,0,120,1),OFFSET($K$16,MAX($B$16:$B$506)-119,0,120,1))*12,"N/A")) -> 0.42434691 | H11: =IFERROR(STDEVP(OFFSET(D$16,MAX($B$16:$B$506)-119,0,120,1))*SQRT(12),"N/A") -> 12.01116 | J11: Ten Year | K11: {=IFERROR((GEOMEAN(1+OFFSET(K$16,MAX($B$16:$B$506)-119,0,120,1)/100)^12-1)*100,"N/A")} -> 12.292976 | L11: =IF(D11="N/A","N/A",IFERROR(SLOPE(OFFSET(K$16,MAX($B$16:$B$506)-119,0,120,1),OFFSET(K$16,MAX($B$16:$B$506)-119,0,120,1)),"N/A")) -> 1 | M11: =IFERROR(STDEVP(OFFSET(K$16,MAX($B$16:$B$506)-119,0,120,1))*SQRT(12),"N/A") -> 14.412409 | P11: Ten Year | Q11: {=IFERROR((GEOMEAN(1+OFFSET(Q$16,MAX($B$16:$B$506)-119,0,120,1)/100)^12-1)*100,"N/A")} -> 8.3313349 | R11: =IFERROR(Q11-$K11,"N/A") -> -3.9616415 | S11: =IF(D11="N/A","N/A",IFERROR(SLOPE(OFFSET(Q$16,MAX($B$16:$B$506)-119,0,120,1),OFFSET($K$16,MAX($B$16:$B$506)-119,0,120,1)),"N/A")) -> 0.61355756 | T11: =IFERROR(STDEVP(OFFSET(Q$16,MAX($B$16:$B$506)-119,0,120,1))*SQRT(12),"N/A") -> 10.300705
C12: Model Incep. | D12: {=IFERROR((GEOMEAN(1+OFFSET(D$16,1,0,MAX($B$16:$B$506),1)/100)^12-1)*100,"N/A")} -> 9.1793453 | E12: =IFERROR(D12-$K12,"N/A") -> 0.2846 | F12: =IFERROR(SLOPE(OFFSET(D$16,1,0,MAX($B$16:$B$506),1),OFFSET(K$16,1,0,MAX($B$16:$B$506),1)),"N/A") -> 0.63783714 | G12: =IFERROR(INTERCEPT(OFFSET($D$16,1,0,MAX($B$16:$B$506),1),OFFSET($K$16,1,0,MAX($B$16:$B$506),1))*12,"N/A") -> 3.2226505 | H12: =IFERROR(STDEVP(OFFSET(D$16,1,0,MAX($B$16:$B$506),1))*SQRT(12),"N/A") -> 11.174588 | J12: Model Incep. | K12: {=IFERROR((GEOMEAN(1+OFFSET(K$16,1,0,MAX($B$16:$B$506),1)/100)^12-1)*100,"N/A")} -> 8.8947453 | L12: =IFERROR(SLOPE(OFFSET(K$16,1,0,MAX($B$16:$B$506),1),OFFSET(K$16,1,0,MAX($B$16:$B$506),1)),"N/A") -> 1 | M12: =IFERROR(STDEVP(OFFSET(K$16,1,0,MAX($B$16:$B$506),1))*SQRT(12),"N/A") -> 15.404455 | P12: Model Incep. | Q12: {=IFERROR((GEOMEAN(1+OFFSET(Q$16,1,0,MAX($B$16:$B$506),1)/100)^12-1)*100,"N/A")} -> 7.1129851 | R12: =IFERROR(Q12-$K12,"N/A") -> -1.7817601 | S12: =IFERROR(SLOPE(OFFSET(Q$16,1,0,MAX($B$16:$B$506),1),OFFSET($K$16,1,0,MAX($B$16:$B$506),1)),"N/A") -> 0.61427714 | T12: =IFERROR(STDEVP(OFFSET(Q$16,1,0,MAX($B$16:$B$506),1))*SQRT(12),"N/A") -> 10.59435
C13: Mar'12 Incep. | D13: {=IFERROR((GEOMEAN(1+OFFSET(D$102,1,0,MAX($B$16:$B$506)-86,1)/100)^(MIN(COUNTA(OFFSET(D$102,1,0,MAX($B$16:$B$506)-86,1)),12))-1)*100,"N/A")} -> 10.047428 | E13: =IFERROR(D13-$K13,"N/A") -> -0.98604571 | F13: =IFERROR(SLOPE(OFFSET(D$102,1,0,MAX($B$16:$B$506)-86,1),OFFSET($K$102,1,0,MAX($B$16:$B$506)-86,1)),"N/A") -> 0.7255591 | G13: =IFERROR(INTERCEPT(OFFSET(D$102,1,0,MAX($B$16:$B$506)-86,1),OFFSET($K$102,1,0,MAX($B$16:$B$506)-86,1))*12,"N/A") -> 1.9328869 | H13: =IFERROR(STDEVP(OFFSET(D$102,1,0,MAX($B$16:$B$506)-86,1))*SQRT(12),"N/A") -> 11.095262 | J13: Mar'12 Incep. | K13: {=IFERROR((GEOMEAN(1+OFFSET(K$102,1,0,MAX($B$16:$B$506)-86,1)/100)^(MIN(COUNTA(OFFSET(K$102,1,0,MAX($B$16:$B$506)-86,1)),12))-1)*100,"N/A")} -> 11.033473 | L13: =IFERROR(SLOPE(OFFSET(K$102,1,0,MAX($B$16:$B$506)-86,1),OFFSET($K$102,1,0,MAX($B$16:$B$506)-86,1)),"N/A") -> 1 | M13: =IFERROR(STDEVP(OFFSET(K$102,1,0,MAX($B$16:$B$506)-86,1))*SQRT(12),"N/A") -> 13.597562 | P13: Mar'12 Incep. | Q13: {=IFERROR((GEOMEAN(1+OFFSET(Q$102,1,0,MAX($B$16:$B$506)-86,1)/100)^(MIN(COUNTA(OFFSET(Q$102,1,0,MAX($B$16:$B$506)-86,1)),12))-1)*100,"N/A")} -> 8.6484819 | R13: =IFERROR(Q13-$K13,"N/A") -> -2.3849915 | S13: =IFERROR(SLOPE(OFFSET(Q$102,1,0,MAX($B$16:$B$506)-86,1),OFFSET($K$102,1,0,MAX($B$16:$B$506)-86,1)),"N/A") -> 0.61877706 | T13: =IFERROR(STDEVP(OFFSET(Q$102,1,0,MAX($B$16:$B$506)-86,1))*SQRT(12),"N/A") -> 9.8596387
A15: Date | B15: # | C15: Porfolio | D15: Gross Return | E15: Growth | F15: Annual | G15: Quarterly | J15: Date | K15: Return | L15: Growth | M15: Annual | N15: Quarterly | P15: Date | Q15: Return | R15: Net Growth | S15: Annual | T15: Quarterly | X15: SGLIX | Z15: Cline | AA15: Jolene GLV | AB15: NC State | AC15: Jolene GLV
A16: 38352 | B16: 0 | E16: 1000000 | J16: =A16 -> 38352 | L16: 1000000 | P16: =$A16 -> 38352 | R16: 1000000
A17: 38383 | B17: =IF(A17>A16,1+B16,"-") -> 1 | C17: Model | D17: -0.26113428 | E17: =E16*D17/100+E16 -> 997388.66 | J17: =A17 -> 38383 | K17: -2.1081822 | L17: =L16*K17/100+L16 -> 978918.18 | P17: =$A17 -> 38383 | Q17: -1.81061 | R17: =R16*Q17/100+R16 -> 981893.9
A18: 38411 | B18: =IF(A18>A17,1+B17,"-") -> 2 | C18: Model | D18: 4.33 | E18: =E17*D18/100+E17 -> 1040575.6 | J18: =A18 -> 38411 | K18: 3.5050398 | L18: =L17*K18/100+L17 -> 1013229.6 | P18: =$A18 -> 38411 | Q18: 3.115247 | R18: =R17*Q18/100+R17 -> 1012482.3
A19: 38442 | B19: =IF(A19>A18,1+B18,"-") -> 3 | C19: Model | D19: -1.05 | E19: =E18*D19/100+E18 -> 1029649.5 | G19: =(E19/E16-1)*100 -> 2.9649542 | J19: =A19 -> 38442 | K19: -2.1526681 | L19: =L18*K19/100+L18 -> 991418.18 | N19: =(L19/L16-1)*100 -> -0.8581822 | P19: =$A19 -> 38442 | Q19: -1.781636 | R19: =R18*Q19/100+R18 -> 994443.57 | T19: =(R19/R16-1)*100 -> -0.55564286
A20: 38472 | B20: =IF(A20>A19,1+B19,"-") -> 4 | C20: Model | D20: 0.38 | E20: =E19*D20/100+E19 -> 1033562.2 | J20: =A20 -> 38472 | K20: -2.1392996 | L20: =L19*K20/100+L19 -> 970208.77 | P20: =$A20 -> 38472 | Q20: -0.24720344 | R20: =R19*Q20/100+R19 -> 991985.27
A21: 38503 | B21: =IF(A21>A20,1+B20,"-") -> 5 | C21: Model | D21: 1.64 | E21: =E20*D21/100+E20 -> 1050512.6 | J21: =A21 -> 38503 | K21: 1.9416122 | L21: =L20*K21/100+L20 -> 989046.46 | P21: =$A21 -> 38503 | Q21: 0.035078984 | R21: =R20*Q21/100+R20 -> 992333.25
A22: 38533 | B22: =IF(A22>A21,1+B21,"-") -> 6 | C22: Model | D22: 1.12 | E22: =E21*D22/100+E21 -> 1062278.4 | G22: =(E22/E19-1)*100 -> 3.1689258 | J22: =A22 -> 38533 | K22: 1.0632775 | L22: =L21*K22/100+L21 -> 999562.77 | N22: =(L22/L19-1)*100 -> 0.82150949 | P22: =$A22 -> 38533 | Q22: 1.1526758 | R22: =R21*Q22/100+R21 -> 1003771.6 | T22: =(R22/R19-1)*100 -> 0.93801853
A23: 38564 | B23: =IF(A23>A22,1+B22,"-") -> 7 | C23: Model | D23: 3.05 | E23: =E22*D23/100+E22 -> 1094677.9 | J23: =A23 -> 38564 | K23: 3.7250928 | L23: =L22*K23/100+L22 -> 1036797.4 | P23: =$A23 -> 38564 | Q23: 2.4300508 | R23: =R22*Q23/100+R22 -> 1028163.8
A24: 38595 | B24: =IF(A24>A23,1+B23,"-") -> 8 | C24: Model | D24: 0.98 | E24: =E23*D24/100+E23 -> 1105405.7 | J24: =A24 -> 38595 | K24: 0.8137914 | L24: =L23*K24/100+L23 -> 1045234.8 | P24: =$A24 -> 38595 | Q24: 0.63322234 | R24: =R23*Q24/100+R23 -> 1034674.4
A25: 38625 | B25: =IF(A25>A24,1+B24,"-") -> 9 | C25: Model | D25: 0.65 | E25: =E24*D25/100+E24 -> 1112590.8 | G25: =(E25/E22-1)*100 -> 4.7362793 | J25: =A25 -> 38625 | K25: 3.0411897 | L25: =L24*K25/100+L24 -> 1077022.4 | N25: =(L25/L22-1)*100 -> 7.7493463 | P25: =$A25 -> 38625 | Q25: 2.3129916 | R25: =R24*Q25/100+R24 -> 1058606.3 | T25: =(R25/R22-1)*100 -> 5.4628615
A26: 38656 | B26: =IF(A26>A25,1+B25,"-") -> 10 | C26: Model | D26: -3.13 | E26: =E25*D26/100+E25 -> 1077766.7 | J26: =A26 -> 38656 | K26: -2.675385 | L26: =L25*K26/100+L25 -> 1048207.9 | P26: =$A26 -> 38656 | Q26: -3.5660131 | R26: =R25*Q26/100+R25 -> 1020856.3
A27: 38686 | B27: =IF(A27>A26,1+B26,"-") -> 11 | C27: Model | D27: 1.32 | E27: =E26*D27/100+E26 -> 1091993.3 | J27: =A27 -> 38686 | K27: 3.701061 | L27: =L26*K27/100+L26 -> 1087002.7 | P27: =$A27 -> 38686 | Q27: 2.1221851 | R27: =R26*Q27/100+R26 -> 1042520.7
A28: 38717 | B28: =IF(A28>A27,1+B27,"-") -> 12 | C28: Model | D28: 1.87 | E28: =E27*D28/100+E27 -> 1112413.5 | F28: =(E28-E16)/E16*100 -> 11.241354 | G28: =(E28/E25-1)*100 -> -0.015935609 | J28: =A28 -> 38717 | K28: 2.5029585 | L28: =L27*K28/100+L27 -> 1114209.9 | M28: =(L28-L16)/L16*100 -> 11.42099 | N28: =(L28/L25-1)*100 -> 3.4528108 | P28: =$A28 -> 38717 | Q28: 2.1426879 | R28: =R27*Q28/100+R27 -> 1064858.7 | S28: =(R28-R16)/R16*100 -> 6.4858676 | T28: =(R28/R25-1)*100 -> 0.59062424
A29: 38748 | B29: =IF(A29>A28,1+B28,"-") -> 13 | C29: Model | D29: 3.26 | E29: =E28*D29/100+E28 -> 1148678.2 | J29: =A29 -> 38748 | K29: 4.9319748 | L29: =L28*K29/100+L28 -> 1169162.4 | P29: =$A29 -> 38748 | Q29: 4.0626581 | R29: =R28*Q29/100+R28 -> 1108120.2
A30: 38776 | B30: =IF(A30>A29,1+B29,"-") -> 14 | C30: Model | D30: -0.33 | E30: =E29*D30/100+E29 -> 1144887.6 | J30: =A30 -> 38776 | K30: -0.10753041 | L30: =L29*K30/100+L29 -> 1167905.2 | P30: =$A30 -> 38776 | Q30: 0.37784396 | R30: =R29*Q30/100+R29 -> 1112307.2
A31: 38807 | B31: =IF(A31>A30,1+B30,"-") -> 15 | C31: Model | D31: 0.47 | E31: =E30*D31/100+E30 -> 1150268.6 | G31: =(E31/E28-1)*100 -> 3.4029624 | J31: =A31 -> 38807 | K31: 2.1593332 | L31: =L30*K31/100+L30 -> 1193124.2 | N31: =(L31/L28-1)*100 -> 7.0825355 | P31: =$A31 -> 38807 | Q31: 1.2634851 | R31: =R30*Q31/100+R30 -> 1126361 | T31: =(R31/R28-1)*100 -> 5.7756367
A32: 38837 | B32: =IF(A32>A31,1+B31,"-") -> 16 | C32: Model | D32: 2.56 | E32: =E31*D32/100+E31 -> 1179715.4 | J32: =A32 -> 38837 | K32: 3.3753138 | L32: =L31*K32/100+L31 -> 1233395.9 | P32: =$A32 -> 38837 | Q32: 3.0515332 | R32: =R31*Q32/100+R31 -> 1160732.3
A33: 38868 | B33: =IF(A33>A32,1+B32,"-") -> 17 | C33: Model | D33: -0.84 | E33: =E32*D33/100+E32 -> 1169805.8 | J33: =A33 -> 38868 | K33: -3.8580235 | L33: =L32*K33/100+L32 -> 1185811.2 | P33: =$A33 -> 38868 | Q33: -2.9369953 | R33: =R32*Q33/100+R32 -> 1126641.7
A34: 38898 | B34: =IF(A34>A33,1+B33,"-") -> 18 | C34: Model | D34: 0 | E34: =E33*D34/100+E33 -> 1169805.8 | G34: =(E34/E31-1)*100 -> 1.698496 | J34: =A34 -> 38898 | K34: 0.0020154896 | L34: =L33*K34/100+L33 -> 1185835.1 | N34: =(L34/L31-1)*100 -> -0.61092705 | P34: =$A34 -> 38898 | Q34: 0.2022557 | R34: =R33*Q34/100+R33 -> 1128920.4 | T34: =(R34/R31-1)*100 -> 0.22722063
A35: 38929 | B35: =IF(A35>A34,1+B34,"-") -> 19 | C35: Model | D35: 3.18 | E35: =E34*D35/100+E34 -> 1207005.7 | J35: =A35 -> 38929 | K35: 0.70265073 | L35: =L34*K35/100+L34 -> 1194167.4 | P35: =$A35 -> 38929 | Q35: 1.9130763 | R35: =R34*Q35/100+R34 -> 1150517.5
A36: 38960 | B36: =IF(A36>A35,1+B35,"-") -> 20 | C36: Model | D36: 2.69 | E36: =E35*D36/100+E35 -> 1239474.1 | J36: =A36 -> 38960 | K36: 2.6488347 | L36: =L35*K36/100+L35 -> 1225798.9 | P36: =$A36 -> 38960 | Q36: 2.2235231 | R36: =R35*Q36/100+R35 -> 1176099.5
A37: 38990 | B37: =IF(A37>A36,1+B36,"-") -> 21 | C37: Model | D37: 0 | E37: =E36*D37/100+E36 -> 1239474.1 | G37: =(E37/E34-1)*100 -> 5.955542 | J37: =A37 -> 38990 | K37: 1.2016998 | L37: =L36*K37/100+L36 -> 1240529.3 | N37: =(L37/L34-1)*100 -> 4.6122958 | P37: =$A37 -> 38990 | Q37: 1.2646267 | R37: =R36*Q37/100+R36 -> 1190972.8 | T37: =(R37/R34-1)*100 -> 5.4966143
A38: 39021 | B38: =IF(A38>A37,1+B37,"-") -> 22 | C38: Model | D38: 3.17 | E38: =E37*D38/100+E37 -> 1278765.4 | J38: =A38 -> 39021 | K38: 3.7716947 | L38: =L37*K38/100+L37 -> 1287318.3 | P38: =$A38 -> 39021 | Q38: 3.4882515 | R38: =R37*Q38/100+R37 -> 1232516.9
A39: 39051 | B39: =IF(A39>A38,1+B38,"-") -> 23 | C39: Model | D39: 2.44 | E39: =E38*D39/100+E38 -> 1309967.3 | J39: =A39 -> 39051 | K39: 2.8775939 | L39: =L38*K39/100+L38 -> 1324362.1 | P39: =$A39 -> 39051 | Q39: 2.9881603 | R39: =R38*Q39/100+R38 -> 1269346.5
A40: 39082 | B40: =IF(A40>A39,1+B39,"-") -> 24 | C40: Model | D40: 1.01 | E40: =E39*D40/100+E39 -> 1323198 | F40: =(E40-E28)/E28*100 -> 18.948388 | G40: =(E40/E37-1)*100 -> 6.7547902 | J40: =A40 -> 39082 | K40: 2.2787232 | L40: =L39*K40/100+L39 -> 1354540.6 | M40: =(L40-L28)/L28*100 -> 21.56961 | N40: =(L40/L37-1)*100 -> 9.190538 | P40: =$A40 -> 39082 | Q40: 2.5203173 | R40: =R39*Q40/100+R39 -> 1301338 | S40: =(R40-R28)/R28*100 -> 22.207581 | T40: =(R40/R37-1)*100 -> 9.2668168
A41: 39113 | B41: =IF(A41>A40,1+B40,"-") -> 25 | C41: Model | D41: 1.53 | E41: =E40*D41/100+E40 -> 1343442.9 | J41: =A41 -> 39113 | K41: 1.0069957 | L41: =L40*K41/100+L40 -> 1368180.8 | P41: =$A41 -> 39113 | Q41: 1.2162407 | R41: =R40*Q41/100+R40 -> 1317165.4
A42: 39141 | B42: =IF(A42>A41,1+B41,"-") -> 26 | C42: Model | D42: -0.32 | E42: =E41*D42/100+E41 -> 1339143.9 | J42: =A42 -> 39141 | K42: -0.48449065 | L42: =L41*K42/100+L41 -> 1361552.1 | P42: =$A42 -> 39141 | Q42: 0.019600992 | R42: =R41*Q42/100+R41 -> 1317423.6
A43: 39172 | B43: =IF(A43>A42,1+B42,"-") -> 27 | C43: Model | D43: 2.09 | E43: =E42*D43/100+E42 -> 1367132 | G43: =(E43/E40-1)*100 -> 3.3202907 | J43: =A43 -> 39172 | K43: 2.0520986 | L43: =L42*K43/100+L42 -> 1389492.5 | N43: =(L43/L40-1)*100 -> 2.580347 | P43: =$A43 -> 39172 | Q43: 1.2695545 | R43: =R42*Q43/100+R42 -> 1334149 | T43: =(R43/R40-1)*100 -> 2.5213273
A44: 39202 | B44: =IF(A44>A43,1+B43,"-") -> 28 | C44: Model | D44: 3.72 | E44: =E43*D44/100+E43 -> 1417989.3 | J44: =A44 -> 39202 | K44: 4.4809459 | L44: =L43*K44/100+L43 -> 1451754.9 | P44: =$A44 -> 39202 | Q44: 2.5459808 | R44: =R43*Q44/100+R43 -> 1368116.2
A45: 39233 | B45: =IF(A45>A44,1+B44,"-") -> 29 | C45: Model | D45: 2.74 | E45: =E44*D45/100+E44 -> 1456842.2 | J45: =A45 -> 39233 | K45: 3.07585 | L45: =L44*K45/100+L44 -> 1496408.7 | P45: =$A45 -> 39233 | Q45: 1.2011815 | R45: =R44*Q45/100+R44 -> 1384549.8
A46: 39263 | B46: =IF(A46>A45,1+B45,"-") -> 30 | C46: Model | D46: -1.35 | E46: =E45*D46/100+E45 -> 1437174.8 | G46: =(E46/E43-1)*100 -> 5.123342 | J46: =A46 -> 39263 | K46: -0.25641315 | L46: =L45*K46/100+L45 -> 1492571.7 | N46: =(L46/L43-1)*100 -> 7.41848 | P46: =$A46 -> 39263 | Q46: -2.1030614 | R46: =R45*Q46/100+R45 -> 1355431.8 | T46: =(R46/R43-1)*100 -> 1.5952345
A47: 39294 | B47: =IF(A47>A46,1+B46,"-") -> 31 | C47: Model | D47: -2.55 | E47: =E46*D47/100+E46 -> 1400526.9 | J47: =A47 -> 39294 | K47: -1.5107855 | L47: =L46*K47/100+L46 -> 1470022.1 | P47: =$A47 -> 39294 | Q47: -2.2277433 | R47: =R46*Q47/100+R46 -> 1325236.3
A48: 39325 | B48: =IF(A48>A47,1+B47,"-") -> 32 | C48: Model | D48: 1.21 | E48: =E47*D48/100+E47 -> 1417473.3 | J48: =A48 -> 39325 | K48: -0.22543895 | L48: =L47*K48/100+L47 -> 1466708.1 | P48: =$A48 -> 39325 | Q48: 0.91478909 | R48: =R47*Q48/100+R47 -> 1337359.4
A49: 39355 | B49: =IF(A49>A48,1+B48,"-") -> 33 | C49: Model | D49: 3.24 | E49: =E48*D49/100+E48 -> 1463399.4 | G49: =(E49/E46-1)*100 -> 1.8247293 | J49: =A49 -> 39355 | K49: 5.4063212 | L49: =L48*K49/100+L48 -> 1546003.1 | N49: =(L49/L46-1)*100 -> 3.5798209 | P49: =$A49 -> 39355 | Q49: 3.5538022 | R49: =R48*Q49/100+R48 -> 1384886.5 | T49: =(R49/R46-1)*100 -> 2.1730849
A50: 39386 | B50: =IF(A50>A49,1+B49,"-") -> 34 | C50: Model | D50: 2.37 | E50: =E49*D50/100+E49 -> 1498082 | J50: =A50 -> 39386 | K50: 3.9223514 | L50: =L49*K50/100+L49 -> 1606642.8 | P50: =$A50 -> 39386 | Q50: 2.4697262 | R50: =R49*Q50/100+R49 -> 1419089.4
A51: 39416 | B51: =IF(A51>A50,1+B50,"-") -> 35 | C51: Model | D51: -1.2 | E51: =E50*D51/100+E50 -> 1480105 | J51: =A51 -> 39416 | K51: -4.3203565 | L51: =L50*K51/100+L50 -> 1537230.1 | P51: =$A51 -> 39416 | Q51: -2.5604923 | R51: =R50*Q51/100+R50 -> 1382753.7
A52: 39447 | B52: =IF(A52>A51,1+B51,"-") -> 36 | C52: Model | D52: -1.35 | E52: =E51*D52/100+E51 -> 1460123.6 | F52: =(E52-E40)/E40*100 -> 10.34808 | G52: =(E52/E49-1)*100 -> -0.22385106 | J52: =A52 -> 39447 | K52: -1.0547755 | L52: =L51*K52/100+L51 -> 1521015.7 | M52: =(L52-L40)/L40*100 -> 12.290153 | N52: =(L52/L49-1)*100 -> -1.6162547 | P52: =$A52 -> 39447 | Q52: -1.4587933 | R52: =R51*Q52/100+R51 -> 1362582.2 | S52: =(R52-R40)/R40*100 -> 4.7062477 | T52: =(R52/R49-1)*100 -> -1.61055
A53: 39478 | B53: =IF(A53>A52,1+B52,"-") -> 37 | C53: Model | D53: -3.29 | E53: =E52*D53/100+E52 -> 1412085.5 | J53: =A53 -> 39478 | K53: -8.1778004 | L53: =L52*K53/100+L52 -> 1396630.1 | P53: =$A53 -> 39478 | Q53: -5.1035119 | R53: =R52*Q53/100+R52 -> 1293042.7
A54: 39507 | B54: =IF(A54>A53,1+B53,"-") -> 38 | C54: Model | D54: -2.1 | E54: =E53*D54/100+E53 -> 1382431.7 | J54: =A54 -> 39507 | K54: 0.32632121 | L54: =L53*K54/100+L53 -> 1401187.6 | P54: =$A54 -> 39507 | Q54: -0.11372318 | R54: =R53*Q54/100+R53 -> 1291572.2
A55: 39538 | B55: =IF(A55>A54,1+B54,"-") -> 39 | C55: Model | D55: 0.33 | E55: =E54*D55/100+E54 -> 1386993.7 | G55: =(E55/E52-1)*100 -> -5.008469 | J55: =A55 -> 39538 | K55: -1.4119843 | L55: =L54*K55/100+L54 -> 1381403.1 | N55: =(L55/L52-1)*100 -> -9.178911 | P55: =$A55 -> 39538 | Q55: -0.85519855 | R55: =R54*Q55/100+R54 -> 1280526.7 | T55: =(R55/R52-1)*100 -> -6.0220617
A56: 39568 | B56: =IF(A56>A55,1+B55,"-") -> 40 | C56: Model | D56: 2.74 | E56: =E55*D56/100+E55 -> 1424997.4 | J56: =A56 -> 39568 | K56: 5.6487331 | L56: =L55*K56/100+L55 -> 1459434.8 | P56: =$A56 -> 39568 | Q56: 2.1248806 | R56: =R55*Q56/100+R55 -> 1307736.3
A57: 39599 | B57: =IF(A57>A56,1+B56,"-") -> 41 | C57: Model | D57: 1.05 | E57: =E56*D57/100+E56 -> 1439959.8 | J57: =A57 -> 39599 | K57: 1.6884277 | L57: =L56*K57/100+L56 -> 1484076.3 | P57: =$A57 -> 39599 | Q57: 1.1261706 | R57: =R56*Q57/100+R56 -> 1322463.7
A58: 39629 | B58: =IF(A58>A57,1+B57,"-") -> 42 | C58: Model | D58: -7.49 | E58: =E57*D58/100+E57 -> 1332106.8 | G58: =(E58/E55-1)*100 -> -3.9572559 | J58: =A58 -> 39629 | K58: -8.1762106 | L58: =L57*K58/100+L57 -> 1362735.1 | N58: =(L58/L55-1)*100 -> -1.3513747 | P58: =$A58 -> 39629 | Q58: -5.9356777 | R58: =R57*Q58/100+R57 -> 1243966.5 | T58: =(R58/R55-1)*100 -> -2.8550891
A59: 39660 | B59: =IF(A59>A58,1+B58,"-") -> 43 | C59: Model | D59: 2.69 | E59: =E58*D59/100+E58 -> 1367940.5 | J59: =A59 -> 39660 | K59: -2.5668682 | L59: =L58*K59/100+L58 -> 1327755.5 | P59: =$A59 -> 39660 | Q59: -0.37267641 | R59: =R58*Q59/100+R58 -> 1239330.5
A60: 39691 | B60: =IF(A60>A59,1+B59,"-") -> 44 | C60: Model | D60: 1.96 | E60: =E59*D60/100+E59 -> 1394752.1 | J60: =A60 -> 39691 | K60: -2.1051266 | L60: =L59*K60/100+L59 -> 1299804.6 | P60: =$A60 -> 39691 | Q60: -0.34961551 | R60: =R59*Q60/100+R59 -> 1234997.6
A61: 39721 | B61: =IF(A61>A60,1+B60,"-") -> 45 | C61: Model | D61: -3.51 | E61: =E60*D61/100+E60 -> 1345796.3 | G61: =(E61/E58-1)*100 -> 1.0276584 | J61: =A61 -> 39721 | K61: -12.454153 | L61: =L60*K61/100+L60 -> 1137924.9 | N61: =(L61/L58-1)*100 -> -16.496985 | P61: =$A61 -> 39721 | Q61: -6.2524427 | R61: =R60*Q61/100+R60 -> 1157780.1 | T61: =(R61/R58-1)*100 -> -6.9283523
A62: 39752 | B62: =IF(A62>A61,1+B61,"-") -> 46 | C62: Model | D62: -10.61 | E62: =E61*D62/100+E61 -> 1203007.3 | J62: =A62 -> 39752 | K62: -19.791427 | L62: =L61*K62/100+L61 -> 912713.34 | P62: =$A62 -> 39752 | Q62: -14.402474 | R62: =R61*Q62/100+R61 -> 991031.14
A63: 39782 | B63: =IF(A63>A62,1+B62,"-") -> 47 | C63: Model | D63: -5.26 | E63: =E62*D63/100+E62 -> 1139729.2 | J63: =A63 -> 39782 | K63: -6.4962886 | L63: =L62*K63/100+L62 -> 853420.85 | P63: =$A63 -> 39782 | Q63: -2.8328066 | R63: =R62*Q63/100+R62 -> 962957.14
A64: 39813 | B64: =IF(A64>A63,1+B63,"-") -> 48 | C64: Model | D64: -0.42 | E64: =E63*D64/100+E63 -> 1134942.3 | F64: =(E64-E52)/E52*100 -> -22.270804 | G64: =(E64/E61-1)*100 -> -15.667604 | J64: =A64 -> 39813 | K64: 3.6902535 | L64: =L63*K64/100+L63 -> 884914.24 | M64: =(L64-L52)/L52*100 -> -41.820836 | N64: =(L64/L61-1)*100 -> -22.234392 | P64: =$A64 -> 39813 | Q64: 2.6775931 | R64: =R63*Q64/100+R63 -> 988741.22 | S64: =(R64-R52)/R52*100 -> -27.436216 | T64: =(R64/R61-1)*100 -> -14.60026
A65: 39844 | B65: =IF(A65>A64,1+B64,"-") -> 49 | C65: Model | D65: -3.78 | E65: =E64*D65/100+E64 -> 1092041.5 | J65: =A65 -> 39844 | K65: -8.5254818 | L65: =L64*K65/100+L64 -> 809471.04 | P65: =$A65 -> 39844 | Q65: -6.8866864 | R65: =R64*Q65/100+R64 -> 920649.71
A66: 39872 | B66: =IF(A66>A65,1+B65,"-") -> 50 | C66: Model | D66: -10.13 | E66: =E65*D66/100+E65 -> 981417.68 | J66: =A66 -> 39872 | K66: -9.7234301 | L66: =L65*K66/100+L65 -> 730762.69 | P66: =$A66 -> 39872 | Q66: -9.1919968 | R66: =R65*Q66/100+R65 -> 836023.62
A67: 39903 | B67: =IF(A67>A66,1+B66,"-") -> 51 | C67: Model | D67: 3.32 | E67: =E66*D67/100+E66 -> 1014000.7 | G67: =(E67/E64-1)*100 -> -10.656185 | J67: =A67 -> 39903 | K67: 8.3095818 | L67: =L66*K67/100+L66 -> 791486.01 | N67: =(L67/L64-1)*100 -> -10.557885 | P67: =$A67 -> 39903 | Q67: 3.3566959 | R67: =R66*Q67/100+R66 -> 864086.39 | T67: =(R67/R64-1)*100 -> -12.607427
A68: 39933 | B68: =IF(A68>A67,1+B67,"-") -> 52 | C68: Model | D68: 5.3 | E68: =E67*D68/100+E67 -> 1067742.8 | J68: =A68 -> 39933 | K68: 11.891768 | L68: =L67*K68/100+L67 -> 885607.69 | P68: =$A68 -> 39933 | Q68: 5.4587025 | R68: =R67*Q68/100+R67 -> 911254.29
A69: 39964 | B69: =IF(A69>A68,1+B68,"-") -> 53 | C69: Model | D69: 4.73 | E69: =E68*D69/100+E68 -> 1118247 | J69: =A69 -> 39964 | K69: 10.086235 | L69: =L68*K69/100+L68 -> 974932.17 | P69: =$A69 -> 39964 | Q69: 6.6531165 | R69: =R68*Q69/100+R68 -> 971881.1
A70: 39994 | B70: =IF(A70>A69,1+B69,"-") -> 54 | C70: Model | D70: 1.28 | E70: =E69*D70/100+E69 -> 1132560.6 | G70: =(E70/E67-1)*100 -> 11.692283 | J70: =A70 -> 39994 | K70: -0.51440637 | L70: =L69*K70/100+L69 -> 969917.05 | N70: =(L70/L67-1)*100 -> 22.543802 | P70: =$A70 -> 39994 | Q70: 0.9008905 | R70: =R69*Q70/100+R69 -> 980636.69 | T70: =(R70/R67-1)*100 -> 13.488269
A71: 40025 | B71: =IF(A71>A70,1+B70,"-") -> 55 | C71: Model | D71: 6.15 | E71: =E70*D71/100+E70 -> 1202213.1 | J71: =A71 -> 40025 | K71: 8.8335735 | L71: =L70*K71/100+L70 -> 1055595.4 | P71: =$A71 -> 40025 | Q71: 5.9866531 | R71: =R70*Q71/100+R70 -> 1039344
A72: 40056 | B72: =IF(A72>A71,1+B71,"-") -> 56 | C72: Model | D72: 1.82 | E72: =E71*D72/100+E71 -> 1224093.3 | J72: =A72 -> 40056 | K72: 3.6294109 | L72: =L71*K72/100+L71 -> 1093907.3 | P72: =$A72 -> 40056 | Q72: 1.568187 | R72: =R71*Q72/100+R71 -> 1055642.9
A73: 40086 | B73: =IF(A73>A72,1+B72,"-") -> 57 | C73: Model | D73: 3.09 | E73: =E72*D73/100+E72 -> 1261917.8 | G73: =(E73/E70-1)*100 -> 11.421662 | J73: =A73 -> 40086 | K73: 4.6198655 | L73: =L72*K73/100+L72 -> 1144444.3 | N73: =(L73/L70-1)*100 -> 17.994041 | P73: =$A73 -> 40086 | Q73: 3.5345533 | R73: =R72*Q73/100+R72 -> 1092955.1 | T73: =(R73/R70-1)*100 -> 11.453623
A74: 40117 | B74: =IF(A74>A73,1+B73,"-") -> 58 | C74: Model | D74: -0.31 | E74: =E73*D74/100+E73 -> 1258005.9 | J74: =A74 -> 40117 | K74: -1.5227999 | L74: =L73*K74/100+L73 -> 1127016.7 | P74: =$A74 -> 40117 | Q74: -1.5477523 | R74: =R73*Q74/100+R73 -> 1076038.9
A75: 40147 | B75: =IF(A75>A74,1+B74,"-") -> 59 | C75: Model | D75: 5.62 | E75: =E74*D75/100+E74 -> 1328705.8 | J75: =A75 -> 40147 | K75: 4.165019 | L75: =L74*K75/100+L74 -> 1173957.2 | P75: =$A75 -> 40147 | Q75: 4.3187982 | R75: =R74*Q75/100+R74 -> 1122510.8
A76: 40178 | B76: =IF(A76>A75,1+B75,"-") -> 60 | C76: Model | D76: 2.25 | E76: =E75*D76/100+E75 -> 1358601.7 | F76: =(E76-E64)/E64*100 -> 19.706674 | G76: =(E76/E73-1)*100 -> 7.661661 | J76: =A76 -> 40178 | K76: 2.1222145 | L76: =L75*K76/100+L75 -> 1198871.1 | M76: =(L76-L64)/L64*100 -> 35.478787 | N76: =(L76/L73-1)*100 -> 4.7557363 | P76: =$A76 -> 40178 | Q76: 0.384 | R76: =R75*Q76/100+R75 -> 1126821.3 | S76: =(R76-R64)/R64*100 -> 13.965237 | T76: =(R76/R73-1)*100 -> 3.0985858
A77: 40209 | B77: =IF(A77>A76,1+B76,"-") -> 61 | C77: Model | D77: -2.34 | E77: =E76*D77/100+E76 -> 1326810.4 | J77: =A77 -> 40209 | K77: -4.3104601 | L77: =L76*K77/100+L76 -> 1147194.2 | P77: =$A77 -> 40209 | Q77: -2.5253028 | R77: =R76*Q77/100+R76 -> 1098365.6
A78: 40237 | B78: =IF(A78>A77,1+B77,"-") -> 62 | C78: Model | D78: 1.44 | E78: =E77*D78/100+E77 -> 1345916.5 | J78: =A78 -> 40237 | K78: 1.3136041 | L78: =L77*K78/100+L77 -> 1162263.8 | P78: =$A78 -> 40237 | Q78: 1.310182 | R78: =R77*Q78/100+R77 -> 1112756.2
A79: 40268 | B79: =IF(A79>A78,1+B78,"-") -> 63 | C79: Model | D79: 3.25 | E79: =E78*D79/100+E78 -> 1389658.8 | G79: =(E79/E76-1)*100 -> 2.2859589 | J79: =A79 -> 40268 | K79: 6.4905123 | L79: =L78*K79/100+L78 -> 1237700.7 | N79: =(L79/L76-1)*100 -> 3.2388476 | P79: =$A79 -> 40268 | Q79: 3.4287962 | R79: =R78*Q79/100+R78 -> 1150910.4 | T79: =(R79/R76-1)*100 -> 2.1377909
A80: 40298 | B80: =IF(A80>A79,1+B79,"-") -> 64 | C80: Model | D80: 0.03 | E80: =E79*D80/100+E79 -> 1390075.7 | J80: =A80 -> 40298 | K80: 0.21652668 | L80: =L79*K80/100+L79 -> 1240380.6 | P80: =$A80 -> 40298 | Q80: -0.35891934 | R80: =R79*Q80/100+R79 -> 1146779.5
A81: 40329 | B81: =IF(A81>A80,1+B80,"-") -> 65 | C81: Model | D81: -7.15 | E81: =E80*D81/100+E80 -> 1290685.2 | J81: =A81 -> 40329 | K81: -9.3928222 | L81: =L80*K81/100+L80 -> 1123873.9 | P81: =$A81 -> 40329 | Q81: -5.8485543 | R81: =R80*Q81/100+R80 -> 1079709.5
A82: 40359 | B82: =IF(A82>A81,1+B81,"-") -> 66 | C82: Model | D82: -1.9 | E82: =E81*D82/100+E81 -> 1266162.2 | G82: =(E82/E79-1)*100 -> -8.8868242 | J82: =A82 -> 40359 | K82: -3.0254131 | L82: =L81*K82/100+L81 -> 1089872.1 | N82: =(L82/L79-1)*100 -> -11.94381 | P82: =$A82 -> 40359 | Q82: 0.64145882 | R82: =R81*Q82/100+R81 -> 1086635.4 | T82: =(R82/R79-1)*100 -> -5.5847069
A83: 40390 | B83: =IF(A83>A82,1+B82,"-") -> 67 | C83: Model | D83: 4.96 | E83: =E82*D83/100+E82 -> 1328963.9 | J83: =A83 -> 40390 | K83: 8.1620392 | L83: =L82*K83/100+L82 -> 1178827.9 | P83: =$A83 -> 40390 | Q83: 4.4874179 | R83: =R82*Q83/100+R82 -> 1135397.3
A84: 40421 | B84: =IF(A84>A83,1+B83,"-") -> 68 | C84: Model | D84: -0.51 | E84: =E83*D84/100+E83 -> 1322186.2 | J84: =A84 -> 40421 | K84: -3.4500884 | L84: =L83*K84/100+L83 -> 1138157.2 | P84: =$A84 -> 40421 | Q84: 0.079092024 | R84: =R83*Q84/100+R83 -> 1136295.3
A85: 40451 | B85: =IF(A85>A84,1+B84,"-") -> 69 | C85: Model | D85: 7.1 | E85: =E84*D85/100+E84 -> 1416061.4 | G85: =(E85/E82-1)*100 -> 11.838858 | J85: =A85 -> 40451 | K85: 9.6104883 | L85: =L84*K85/100+L84 -> 1247539.7 | N85: =(L85/L82-1)*100 -> 14.46662 | P85: =$A85 -> 40451 | Q85: 5.6150472 | R85: =R84*Q85/100+R84 -> 1200098.8 | T85: =(R85/R82-1)*100 -> 10.441717
A86: 40482 | B86: =IF(A86>A85,1+B85,"-") -> 70 | C86: Model | D86: 1.98 | E86: =E85*D86/100+E85 -> 1444099.4 | J86: =A86 -> 40482 | K86: 3.6512748 | L86: =L85*K86/100+L85 -> 1293090.8 | P86: =$A86 -> 40482 | Q86: 2.6535843 | R86: =R85*Q86/100+R85 -> 1231944.4
A87: 40512 | B87: =IF(A87>A86,1+B86,"-") -> 71 | C87: Model | D87: -2.4 | E87: =E86*D87/100+E86 -> 1409441 | J87: =A87 -> 40512 | K87: -2.1768084 | L87: =L86*K87/100+L86 -> 1264942.7 | P87: =$A87 -> 40512 | Q87: -2.3426182 | R87: =R86*Q87/100+R86 -> 1203084.7
A88: 40543 | B88: =IF(A88>A87,1+B87,"-") -> 72 | C88: Model | D88: 4.57 | E88: =E87*D88/100+E87 -> 1473852.5 | F88: =(E88-E76)/E76*100 -> 8.4830438 | G88: =(E88/E85-1)*100 -> 4.0811143 | J88: =A88 -> 40543 | K88: 7.3759904 | L88: =L87*K88/100+L87 -> 1358244.8 | M88: =(L88-L76)/L76*100 -> 13.293646 | N88: =(L88/L85-1)*100 -> 8.8738696 | P88: =$A88 -> 40543 | Q88: 4.476665 | R88: =R87*Q88/100+R87 -> 1256942.7 | S88: =(R88-R76)/R76*100 -> 11.547657 | T88: =(R88/R85-1)*100 -> 4.7366058
A89: 40574 | B89: =IF(A89>A88,1+B88,"-") -> 73 | C89: Model | D89: 1.36 | E89: =E88*D89/100+E88 -> 1493896.9 | J89: =A89 -> 40574 | K89: 1.5819213 | L89: =L88*K89/100+L88 -> 1379731.1 | P89: =$A89 -> 40574 | Q89: -0.66800029 | R89: =R88*Q89/100+R88 -> 1248546.3
A90: 40602 | B90: =IF(A90>A89,1+B89,"-") -> 74 | C90: Model | D90: 2.95 | E90: =E89*D90/100+E89 -> 1537966.8 | J90: =A90 -> 40602 | K90: 2.9518462 | L90: =L89*K90/100+L89 -> 1420458.7 | P90: =$A90 -> 40602 | Q90: 1.7639443 | R90: =R89*Q90/100+R89 -> 1270570
A91: 40633 | B91: =IF(A91>A90,1+B90,"-") -> 75 | C91: Model | D91: -0.46 | E91: =E90*D91/100+E90 -> 1530892.2 | G91: =(E91/E88-1)*100 -> 3.8701094 | J91: =A91 -> 40633 | K91: -0.050006322 | L91: =L90*K91/100+L90 -> 1419748.3 | N91: =(L91/L88-1)*100 -> 4.5281665 | P91: =$A91 -> 40633 | Q91: 0.63433165 | R91: =R90*Q91/100+R90 -> 1278629.6 | T91: =(R91/R88-1)*100 -> 1.7253697
A92: 40663 | B92: =IF(A92>A91,1+B91,"-") -> 76 | C92: Model | D92: 4.33 | E92: =E91*D92/100+E91 -> 1597179.8 | J92: =A92 -> 40663 | K92: 4.1292566 | L92: =L91*K92/100+L91 -> 1478373.4 | P92: =$A92 -> 40663 | Q92: 4.0594164 | R92: =R91*Q92/100+R91 -> 1330534.5
A93: 40694 | B93: =IF(A93>A92,1+B92,"-") -> 77 | C93: Model | D93: 2.12 | E93: =E92*D93/100+E92 -> 1631040 | J93: =A93 -> 40694 | K93: -2.0649659 | L93: =L92*K93/100+L92 -> 1447845.5 | P93: =$A93 -> 40694 | Q93: 0.75844498 | R93: =R92*Q93/100+R92 -> 1340625.9
A94: 40724 | B94: =IF(A94>A93,1+B93,"-") -> 78 | C94: Model | D94: -1.49 | E94: =E93*D94/100+E93 -> 1606737.5 | G94: =(E94/E91-1)*100 -> 4.9543232 | J94: =A94 -> 40724 | K94: -1.5294423 | L94: =L93*K94/100+L93 -> 1425701.5 | N94: =(L94/L91-1)*100 -> 0.41931264 | P94: =$A94 -> 40724 | Q94: -1.2844236 | R94: =R93*Q94/100+R93 -> 1323406.6 | T94: =(R94/R91-1)*100 -> 3.5019489
A95: 40755 | B95: =IF(A95>A94,1+B94,"-") -> 79 | C95: Model | D95: -2.45 | E95: =E94*D95/100+E94 -> 1567372.4 | J95: =A95 -> 40755 | K95: -1.5961667 | L95: =L94*K95/100+L94 -> 1402945 | P95: =$A95 -> 40755 | Q95: -0.91096466 | R95: =R94*Q95/100+R94 -> 1311350.8
A96: 40786 | B96: =IF(A96>A95,1+B95,"-") -> 80 | C96: Model | D96: -0.87 | E96: =E95*D96/100+E95 -> 1553736.3 | J96: =A96 -> 40786 | K96: -7.2548281 | L96: =L95*K96/100+L95 -> 1301163.7 | P96: =$A96 -> 40786 | Q96: -1.7993032 | R96: =R95*Q96/100+R95 -> 1287755.7
A97: 40816 | B97: =IF(A97>A96,1+B96,"-") -> 81 | C97: Model | D97: -3.08 | E97: =E96*D97/100+E96 -> 1505881.2 | G97: =(E97/E94-1)*100 -> -6.2770855 | J97: =A97 -> 40816 | K97: -9.3941472 | L97: =L96*K97/100+L96 -> 1178930.5 | N97: =(L97/L94-1)*100 -> -17.308746 | P97: =$A97 -> 40816 | Q97: -4.6530278 | R97: =R96*Q97/100+R96 -> 1227836 | T97: =(R97/R94-1)*100 -> -7.2215578
A98: 40847 | B98: =IF(A98>A97,1+B97,"-") -> 82 | C98: Model | D98: 6.37 | E98: =E97*D98/100+E97 -> 1601805.9 | J98: =A98 -> 40847 | K98: 10.730995 | L98: =L97*K98/100+L97 -> 1305441.4 | P98: =$A98 -> 40847 | Q98: 4.7191977 | R98: =R97*Q98/100+R97 -> 1285780
A99: 40877 | B99: =IF(A99>A98,1+B98,"-") -> 83 | C99: Model | D99: -0.74 | E99: =E98*D99/100+E98 -> 1589952.5 | J99: =A99 -> 40877 | K99: -2.9296422 | L99: =L98*K99/100+L98 -> 1267196.7 | P99: =$A99 -> 40877 | Q99: -1.8848487 | R99: =R98*Q99/100+R98 -> 1261545
A100: 40908 | B100: =IF(A100>A99,1+B99,"-") -> 84 | C100: Model | D100: 2.51 | E100: =E99*D100/100+E99 -> 1629860.3 | F100: =(E100-E88)/E88*100 -> 10.585038 | G100: =(E100/E97-1)*100 -> 8.2329918 | J100: =A100 -> 40908 | K100: -0.14872021 | L100: =L99*K100/100+L99 -> 1265312.1 | M100: =(L100-L88)/L88*100 -> -6.8421143 | N100: =(L100/L97-1)*100 -> 7.3271178 | P100: =$A100 -> 40908 | Q100: 2.3116758 | R100: =R99*Q100/100+R99 -> 1290707.9 | S100: =(R100-R88)/R88*100 -> 2.6862899 | T100: =(R100/R97-1)*100 -> 5.1205398
A101: 40939 | B101: =IF(A101>A100,1+B100,"-") -> 85 | C101: Model | D101: 1.23 | E101: =E100*D101/100+E100 -> 1649907.6 | J101: =A101 -> 40939 | K101: 5.8327264 | L101: =L100*K101/100+L100 -> 1339114.3 | P101: =$A101 -> 40939 | Q101: 1.8150351 | R101: =R100*Q101/100+R100 -> 1314134.7
A102: 40968 | B102: =IF(A102>A101,1+B101,"-") -> 86 | C102: Model | D102: 1.93 | E102: =E101*D102/100+E101 -> 1681750.8 | J102: =A102 -> 40968 | K102: 5.086865 | L102: =L101*K102/100+L101 -> 1407233.2 | P102: =$A102 -> 40968 | Q102: 2.2627295 | R102: =R101*Q102/100+R101 -> 1343870 | W102: GIPS
A103: 40999 | B103: =IF(A103>A102,1+B102,"-") -> 87 | C103: Jolene Vanguard | D103: 2.14 | E103: =E102*D103/100+E102 -> 1717740.3 | G103: =(E103/E100-1)*100 -> 5.391871 | J103: =A103 -> 40999 | K103: 0.71833181 | L103: =L102*K103/100+L102 -> 1417341.8 | N103: =(L103/L100-1)*100 -> 12.015196 | P103: =$A103 -> 40999 | Q103: 0.7417307 | R103: =R102*Q103/100+R102 -> 1353837.9 | T103: =(R103/R100-1)*100 -> 4.8911153 | V103: =#REF!-W103 -> #REF! | W103: 2.14
...

Sheet Global (Net)
C1: Global (Net) | J1: MSCI ACWI® Index | P1: MSCI ACWI® Minimum Volatility Index
D4: Return | E4: Relative Return | F4: Beta | G4: Alpha | H4: stdevp | K4: Return | L4: Beta | M4: stdevp | Q4: Return | R4: Relative Return | S4: Beta | T4: stdevp
B5: 12 | C5: YTD | D5: {=IFERROR((GEOMEAN(1+OFFSET(D$16,MAX($B$16:$B$506)-$B$5+1,0,$B$5,1)/100)^$B$5-1)*100,"N/A")} -> 11.725899 | E5: =IFERROR(D5-$K5,"N/A") -> -11.166697 | F5: =IFERROR(SLOPE(OFFSET(D$16,MAX($B$16:$B$506)-$B$5+1,0,$B$5,1),OFFSET($K$16,MAX($B$16:$B$506)-$B$5+1,0,$B$5,1)),"N/A") -> 0.16337531 | G5: {=IFERROR(INTERCEPT(OFFSET(D$16,MAX($B$16:$B$506)-$B$5+1,0,$B$5,1),OFFSET($K$16,MAX($B$16:$B$506)-$B$5+1,0,$B$5,1))*12,"N/A")} -> 7.8751895 | H5: =IFERROR(STDEVP(OFFSET(D$16,MAX($B$16:$B$506)-$B$5+1,0,$B$5,1))*SQRT(12),"N/A") -> 6.2003629 | J5: YTD | K5: {=IFERROR((GEOMEAN(1+OFFSET(K$16,MAX($B$16:$B$506)-$B$5+1,0,$B$5,1)/100)^$B$5-1)*100,"N/A")} -> 22.892597 | L5: =IFERROR(SLOPE(OFFSET(K$16,MAX($B$16:$B$506)-$B$5+1,0,$B$5,1),OFFSET($K$16,MAX($B$16:$B$506)-$B$5+1,0,$B$5,1)),"N/A") -> 1 | M5: =IFERROR(STDEVP(OFFSET(K$16,MAX($B$16:$B$506)-$B$5+1,0,$B$5,1))*SQRT(12),"N/A") -> 8.5348447 | P5: YTD | Q5: {=IFERROR((GEOMEAN(1+OFFSET(Q$16,MAX($B$16:$B$506)-$B$5+1,0,$B$5,1)/100)^$B$5-1)*100,"N/A")} -> 11.218931 | R5: =IFERROR(Q5-$K5,"N/A") -> -11.673665 | S5: =IFERROR(SLOPE(OFFSET(Q$16,MAX($B$16:$B$506)-$B$5+1,0,$B$5,1),OFFSET($K$16,MAX($B$16:$B$506)-$B$5+1,0,$B$5,1)),"N/A") -> -0.014363083 | T5: =IFERROR(STDEVP(OFFSET(Q$16,MAX($B$16:$B$506)-$B$5+1,0,$B$5,1))*SQRT(12),"N/A") -> 4.9459417
C6: One Year | D6: {=IFERROR((GEOMEAN(1+OFFSET(D$16,MAX($B$16:$B$506)-11,0,12,1)/100)^12-1)*100,"N/A")} -> 11.725899 | E6: =IFERROR(D6-$K6,"N/A") -> -11.166697 | F6: =IFERROR(SLOPE(OFFSET(D$16,MAX($B$16:$B$506)-11,0,12,1),OFFSET(K$16,MAX($B$16:$B$506)-11,0,12,1)),"N/A") -> 0.16337531 | G6: =IFERROR(INTERCEPT(OFFSET($D$16,MAX($B$16:$B$506)-11,0,12,1),OFFSET($K$16,MAX($B$16:$B$506)-11,0,12,1))*12,"N/A") -> 7.8751895 | H6: =IFERROR(STDEVP(OFFSET(D$16,MAX($B$16:$B$506)-11,0,12,1))*SQRT(12),"N/A") -> 6.2003629 | J6: One Year | K6: {=IFERROR((GEOMEAN(1+OFFSET(K$16,MAX($B$16:$B$506)-11,0,12,1)/100)^12-1)*100,"N/A")} -> 22.892597 | L6: =IFERROR(SLOPE(OFFSET(K$16,MAX($B$16:$B$506)-11,0,12,1),OFFSET(K$16,MAX($B$16:$B$506)-11,0,12,1)),"N/A") -> 1 | M6: =IFERROR(STDEVP(OFFSET(K$16,MAX($B$16:$B$506)-11,0,12,1))*SQRT(12),"N/A") -> 8.5348447 | P6: One Year | Q6: {=IFERROR((GEOMEAN(1+OFFSET(Q$16,MAX($B$16:$B$506)-11,0,12,1)/100)^12-1)*100,"N/A")} -> 11.218931 | R6: =IFERROR(Q6-$K6,"N/A") -> -11.673665 | S6: =IFERROR(SLOPE(OFFSET(Q$16,MAX($B$16:$B$506)-11,0,12,1),OFFSET($K$16,MAX($B$16:$B$506)-11,0,12,1)),"N/A") -> -0.014363083 | T6: =IFERROR(STDEVP(OFFSET(Q$16,MAX($B$16:$B$506)-11,0,12,1))*SQRT(12),"N/A") -> 4.9459417
C7: Two Year | D7: {=IFERROR((GEOMEAN(1+OFFSET(D$16,MAX($B$16:$B$506)-23,0,24,1)/100)^12-1)*100,"N/A")} -> 10.465805 | E7: =IFERROR(D7-$K7,"N/A") -> -9.9709658 | F7: =IFERROR(SLOPE(OFFSET(D$16,MAX($B$16:$B$506)-23,0,24,1),OFFSET($K$16,MAX($B$16:$B$506)-23,0,24,1)),"N/A") -> 0.5623986 | G7: =IFERROR(INTERCEPT(OFFSET(D$16,MAX($B$16:$B$506)-23,0,24,1),OFFSET($K$16,MAX($B$16:$B$506)-23,0,24,1))*12,"N/A") -> -0.44456278 | H7: =IFERROR(STDEVP(OFFSET(D$16,MAX($B$16:$B$506)-23,0,24,1))*SQRT(12),"N/A") -> 7.8798025 | J7: Two Year | K7: {=IFERROR((GEOMEAN(1+OFFSET(K$16,MAX($B$16:$B$506)-23,0,24,1)/100)^12-1)*100,"N/A")} -> 20.436771 | L7: =IFERROR(SLOPE(OFFSET(K$16,MAX($B$16:$B$506)-23,0,24,1),OFFSET($K$16,MAX($B$16:$B$506)-23,0,24,1)),"N/A") -> 1 | M7: =IFERROR(STDEVP(OFFSET(K$16,MAX($B$16:$B$506)-23,0,24,1))*SQRT(12),"N/A") -> 8.6852357 | P7: Two Year | Q7: {=IFERROR((GEOMEAN(1+OFFSET(Q$16,MAX($B$16:$B$506)-23,0,24,1)/100)^12-1)*100,"N/A")} -> 11.573775 | R7: =IFERROR(Q7-$K7,"N/A") -> -8.8629954 | S7: =IFERROR(SLOPE(OFFSET(Q$16,MAX($B$16:$B$506)-23,0,24,1),OFFSET($K$16,MAX($B$16:$B$506)-23,0,24,1)),"N/A") -> 0.40552781 | T7: =IFERROR(STDEVP(OFFSET(Q$16,MAX($B$16:$B$506)-23,0,24,1))*SQRT(12),"N/A") -> 7.0941341
C8: Three Year | D8: {=IFERROR((GEOMEAN(1+OFFSET(D$16,MAX($B$16:$B$506)-35,0,36,1)/100)^12-1)*100,"N/A")} -> 11.445626 | E8: =IFERROR(D8-$K8,"N/A") -> -9.7650042 | F8: =IFERROR(SLOPE(OFFSET(D$16,MAX($B$16:$B$506)-35,0,36,1),OFFSET(K$16,MAX($B$16:$B$506)-35,0,36,1)),"N/A") -> 0.66538059 | G8: =IFERROR(INTERCEPT(OFFSET($D$16,MAX($B$16:$B$506)-35,0,36,1),OFFSET($K$16,MAX($B$16:$B$506)-35,0,36,1))*12,"N/A") -> -2.0017411 | H8: =IFERROR(STDEVP(OFFSET(D$16,MAX($B$16:$B$506)-35,0,36,1))*SQRT(12),"N/A") -> 9.2530862 | J8: Three Year | K8: {=IFERROR((GEOMEAN(1+OFFSET(K$16,MAX($B$16:$B$506)-35,0,36,1)/100)^12-1)*100,"N/A")} -> 21.21063 | L8: =IFERROR(SLOPE(OFFSET(K$16,MAX($B$16:$B$506)-35,0,36,1),OFFSET(K$16,MAX($B$16:$B$506)-35,0,36,1)),"N/A") -> 1 | M8: =IFERROR(STDEVP(OFFSET(K$16,MAX($B$16:$B$506)-35,0,36,1))*SQRT(12),"N/A") -> 11.184857 | P8: Three Year | Q8: {=IFERROR((GEOMEAN(1+OFFSET(Q$16,MAX($B$16:$B$506)-35,0,36,1)/100)^12-1)*100,"N/A")} -> 10.470772 | R8: =IFERROR(Q8-$K8,"N/A") -> -10.739858 | S8: =IFERROR(SLOPE(OFFSET(Q$16,MAX($B$16:$B$506)-35,0,36,1),OFFSET($K$16,MAX($B$16:$B$506)-35,0,36,1)),"N/A") -> 0.50975685 | T8: =IFERROR(STDEVP(OFFSET(Q$16,MAX($B$16:$B$506)-35,0,36,1))*SQRT(12),"N/A") -> 8.1967833
C9: Four Year | D9: {=IFERROR((GEOMEAN(1+OFFSET(D$16,MAX($B$16:$B$506)-47,0,48,1)/100)^12-1)*100,"N/A")} -> 4.7401616 | E9: =IFERROR(D9-$K9,"N/A") -> -5.2057395 | F9: =IFERROR(SLOPE(OFFSET(D$16,MAX($B$16:$B$506)-47,0,48,1),OFFSET($K$16,MAX($B$16:$B$506)-47,0,48,1)),"N/A") -> 0.73769712 | G9: =IFERROR(INTERCEPT(OFFSET(D$16,MAX($B$16:$B$506)-47,0,48,1),OFFSET($K$16,MAX($B$16:$B$506)-47,0,48,1))*12,"N/A") -> -2.4557185 | H9: =IFERROR(STDEVP(OFFSET(D$16,MAX($B$16:$B$506)-47,0,48,1))*SQRT(12),"N/A") -> 12.112078 | J9: Four Year | K9: {=IFERROR((GEOMEAN(1+OFFSET(K$16,MAX($B$16:$B$506)-47,0,48,1)/100)^12-1)*100,"N/A")} -> 9.9459012 | L9: =IFERROR(SLOPE(OFFSET(K$16,MAX($B$16:$B$506)-47,0,48,1),OFFSET($K$16,MAX($B$16:$B$506)-47,0,48,1)),"N/A") -> 1 | M9: =IFERROR(STDEVP(OFFSET(K$16,MAX($B$16:$B$506)-47,0,48,1))*SQRT(12),"N/A") -> 14.775176 | P9: Four Year | Q9: {=IFERROR((GEOMEAN(1+OFFSET(Q$16,MAX($B$16:$B$506)-47,0,48,1)/100)^12-1)*100,"N/A")} -> 5.0067674 | R9: =IFERROR(Q9-$K9,"N/A") -> -4.9391338 | S9: =IFERROR(SLOPE(OFFSET(Q$16,MAX($B$16:$B$506)-47,0,48,1),OFFSET($K$16,MAX($B$16:$B$506)-47,0,48,1)),"N/A") -> 0.57609941 | T9: =IFERROR(STDEVP(OFFSET(Q$16,MAX($B$16:$B$506)-47,0,48,1))*SQRT(12),"N/A") -> 10.175138
C10: Five Year | D10: {=IFERROR((GEOMEAN(1+OFFSET(D$16,MAX($B$16:$B$506)-59,0,60,1)/100)^12-1)*100,"N/A")} -> 6.9026703 | E10: =IFERROR(D10-$K10,"N/A") -> -4.8054656 | F10: =IFERROR(SLOPE(OFFSET(D$16,MAX($B$16:$B$506)-59,0,60,1),OFFSET(K$16,MAX($B$16:$B$506)-59,0,60,1)),"N/A") -> 0.7613683 | G10: =IFERROR(INTERCEPT(OFFSET($D$16,MAX($B$16:$B$506)-59,0,60,1),OFFSET($K$16,MAX($B$16:$B$506)-59,0,60,1))*12,"N/A") -> -1.8257864 | H10: =IFERROR(STDEVP(OFFSET(D$16,MAX($B$16:$B$506)-59,0,60,1))*SQRT(12),"N/A") -> 11.677008 | J10: Five Year | K10: {=IFERROR((GEOMEAN(1+OFFSET(K$16,MAX($B$16:$B$506)-59,0,60,1)/100)^12-1)*100,"N/A")} -> 11.708136 | L10: =IFERROR(SLOPE(OFFSET(K$16,MAX($B$16:$B$506)-59,0,60,1),OFFSET(K$16,MAX($B$16:$B$506)-59,0,60,1)),"N/A") -> 1 | M10: =IFERROR(STDEVP(OFFSET(K$16,MAX($B$16:$B$506)-59,0,60,1))*SQRT(12),"N/A") -> 13.847692 | P10: Five Year | Q10: {=IFERROR((GEOMEAN(1+OFFSET(Q$16,MAX($B$16:$B$506)-59,0,60,1)/100)^12-1)*100,"N/A")} -> 6.8376476 | R10: =IFERROR(Q10-$K10,"N/A") -> -4.8704884 | S10: =IFERROR(SLOPE(OFFSET(Q$16,MAX($B$16:$B$506)-59,0,60,1),OFFSET($K$16,MAX($B$16:$B$506)-59,0,60,1)),"N/A") -> 0.59992683 | T10: =IFERROR(STDEVP(OFFSET(Q$16,MAX($B$16:$B$506)-59,0,60,1))*SQRT(12),"N/A") -> 10.034055
C11: Ten Year | D11: {=IFERROR((GEOMEAN(1+OFFSET(D$16,MAX($B$16:$B$506)-119,0,120,1)/100)^12-1)*100,"N/A")} -> 8.9218933 | E11: =IFERROR(D11-$K11,"N/A") -> -3.3710831 | F11: =IF(D11="N/A","N/A",IFERROR(SLOPE(OFFSET(D$16,MAX($B$16:$B$506)-119,0,120,1),OFFSET(K$16,MAX($B$16:$B$506)-119,0,120,1)),"N/A")) -> 0.75459548 | G11: =IF(D11="N/A","N/A",IFERROR(INTERCEPT(OFFSET($D$16,MAX($B$16:$B$506)-119,0,120,1),OFFSET($K$16,MAX($B$16:$B$506)-119,0,120,1))*12,"N/A")) -> -0.27251474 | H11: =IFERROR(STDEVP(OFFSET(D$16,MAX($B$16:$B$506)-119,0,120,1))*SQRT(12),"N/A") -> 12.003122 | J11: Ten Year | K11: {=IFERROR((GEOMEAN(1+OFFSET(K$16,MAX($B$16:$B$506)-119,0,120,1)/100)^12-1)*100,"N/A")} -> 12.292976 | L11: =IF(D11="N/A","N/A",IFERROR(SLOPE(OFFSET(K$16,MAX($B$16:$B$506)-119,0,120,1),OFFSET(K$16,MAX($B$16:$B$506)-119,0,120,1)),"N/A")) -> 1 | M11: =IFERROR(STDEVP(OFFSET(K$16,MAX($B$16:$B$506)-119,0,120,1))*SQRT(12),"N/A") -> 14.412409 | P11: Ten Year | Q11: {=IFERROR((GEOMEAN(1+OFFSET(Q$16,MAX($B$16:$B$506)-119,0,120,1)/100)^12-1)*100,"N/A")} -> 8.3313349 | R11: =IFERROR(Q11-$K11,"N/A") -> -3.9616415 | S11: =IF(D11="N/A","N/A",IFERROR(SLOPE(OFFSET(Q$16,MAX($B$16:$B$506)-119,0,120,1),OFFSET($K$16,MAX($B$16:$B$506)-119,0,120,1)),"N/A")) -> 0.61355756 | T11: =IFERROR(STDEVP(OFFSET(Q$16,MAX($B$16:$B$506)-119,0,120,1))*SQRT(12),"N/A") -> 10.300705
C12: Model Incep. | D12: {=IFERROR((GEOMEAN(1+OFFSET(D$16,1,0,MAX($B$16:$B$506),1)/100)^12-1)*100,"N/A")} -> 8.8146699 | E12: =IFERROR(D12-$K12,"N/A") -> -0.080075371 | F12: =IFERROR(SLOPE(OFFSET(D$16,1,0,MAX($B$16:$B$506),1),OFFSET(K$16,1,0,MAX($B$16:$B$506),1)),"N/A") -> 0.63711401 | G12: =IFERROR(INTERCEPT(OFFSET($D$16,1,0,MAX($B$16:$B$506),1),OFFSET($K$16,1,0,MAX($B$16:$B$506),1))*12,"N/A") -> 2.8924258 | H12: =IFERROR(STDEVP(OFFSET(D$16,1,0,MAX($B$16:$B$506),1))*SQRT(12),"N/A") -> 11.169509 | J12: Model Incep. | K12: {=IFERROR((GEOMEAN(1+OFFSET(K$16,1,0,MAX($B$16:$B$506),1)/100)^12-1)*100,"N/A")} -> 8.8947453 | L12: =IFERROR(SLOPE(OFFSET(K$16,1,0,MAX($B$16:$B$506),1),OFFSET(K$16,1,0,MAX($B$16:$B$506),1)),"N/A") -> 1 | M12: =IFERROR(STDEVP(OFFSET(K$16,1,0,MAX($B$16:$B$506),1))*SQRT(12),"N/A") -> 15.404455 | P12: Model Incep. | Q12: {=IFERROR((GEOMEAN(1+OFFSET(Q$16,1,0,MAX($B$16:$B$506),1)/100)^12-1)*100,"N/A")} -> 7.1129851 | R12: =IFERROR(Q12-$K12,"N/A") -> -1.7817601 | S12: =IFERROR(SLOPE(OFFSET(Q$16,1,0,MAX($B$16:$B$506),1),OFFSET($K$16,1,0,MAX($B$16:$B$506),1)),"N/A") -> 0.61427714 | T12: =IFERROR(STDEVP(OFFSET(Q$16,1,0,MAX($B$16:$B$506),1))*SQRT(12),"N/A") -> 10.59435
C13: Mar'12 Incep. | D13: {=IFERROR((GEOMEAN(1+OFFSET(D$102,1,0,MAX($B$16:$B$506)-86,1)/100)^(MIN(COUNTA(OFFSET(D$102,1,0,MAX($B$16:$B$506)-86,1)),12))-1)*100,"N/A")} -> 9.4899055 | E13: =IFERROR(D13-$K13,"N/A") -> -1.5435679 | F13: =IFERROR(SLOPE(OFFSET(D$102,1,0,MAX($B$16:$B$506)-86,1),OFFSET($K$102,1,0,MAX($B$16:$B$506)-86,1)),"N/A") -> 0.72453863 | G13: =IFERROR(INTERCEPT(OFFSET(D$102,1,0,MAX($B$16:$B$506)-86,1),OFFSET($K$102,1,0,MAX($B$16:$B$506)-86,1))*12,"N/A") -> 1.4325452 | H13: =IFERROR(STDEVP(OFFSET(D$102,1,0,MAX($B$16:$B$506)-86,1))*SQRT(12),"N/A") -> 11.090191 | J13: Mar'12 Incep. | K13: {=IFERROR((GEOMEAN(1+OFFSET(K$102,1,0,MAX($B$16:$B$506)-86,1)/100)^(MIN(COUNTA(OFFSET(K$102,1,0,MAX($B$16:$B$506)-86,1)),12))-1)*100,"N/A")} -> 11.033473 | L13: =IFERROR(SLOPE(OFFSET(K$102,1,0,MAX($B$16:$B$506)-86,1),OFFSET($K$102,1,0,MAX($B$16:$B$506)-86,1)),"N/A") -> 1 | M13: =IFERROR(STDEVP(OFFSET(K$102,1,0,MAX($B$16:$B$506)-86,1))*SQRT(12),"N/A") -> 13.597562 | P13: Mar'12 Incep. | Q13: {=IFERROR((GEOMEAN(1+OFFSET(Q$102,1,0,MAX($B$16:$B$506)-86,1)/100)^(MIN(COUNTA(OFFSET(Q$102,1,0,MAX($B$16:$B$506)-86,1)),12))-1)*100,"N/A")} -> 8.6484819 | R13: =IFERROR(Q13-$K13,"N/A") -> -2.3849915 | S13: =IFERROR(SLOPE(OFFSET(Q$102,1,0,MAX($B$16:$B$506)-86,1),OFFSET($K$102,1,0,MAX($B$16:$B$506)-86,1)),"N/A") -> 0.61877706 | T13: =IFERROR(STDEVP(OFFSET(Q$102,1,0,MAX($B$16:$B$506)-86,1))*SQRT(12),"N/A") -> 9.8596387
A15: Date | B15: # | C15: Porfolio | D15: Net Return | E15: Growth | F15: Annual | G15: Quarterly | J15: Date | K15: Return | L15: Growth | M15: Annual | N15: Quarterly | P15: Date | Q15: Return | R15: Growth | S15: Annual | T15: Quarterly
A16: 38352 | B16: 0 | E16: 1000000 | J16: =A16 -> 38352 | L16: 1000000 | P16: =$A16 -> 38352 | R16: 1000000
A17: 38383 | B17: =IF(A17>A16,1+B16,"-") -> 1 | C17: Model | D17: -0.26113428 | E17: =E16*D17/100+E16 -> 997388.66 | J17: =A17 -> 38383 | K17: ='Global (Gross)'!K17 -> -2.1081822 | L17: =L16*K17/100+L16 -> 978918.18 | P17: =$A17 -> 38383 | Q17: ='Global (Gross)'!Q17 -> -1.81061 | R17: =R16*Q17/100+R16 -> 981893.9
A18: 38411 | B18: =IF(A18>A17,1+B17,"-") -> 2 | C18: Model | D18: 4.33 | E18: =E17*D18/100+E17 -> 1040575.6 | J18: =A18 -> 38411 | K18: ='Global (Gross)'!K18 -> 3.5050398 | L18: =L17*K18/100+L17 -> 1013229.6 | P18: =$A18 -> 38411 | Q18: ='Global (Gross)'!Q18 -> 3.115247 | R18: =R17*Q18/100+R17 -> 1012482.3
A19: 38442 | B19: =IF(A19>A18,1+B18,"-") -> 3 | C19: Model | D19: -1.05 | E19: =E18*D19/100+E18 -> 1029649.5 | G19: =(E19/E16-1)*100 -> 2.9649542 | J19: =A19 -> 38442 | K19: ='Global (Gross)'!K19 -> -2.1526681 | L19: =L18*K19/100+L18 -> 991418.18 | N19: =(L19/L16-1)*100 -> -0.8581822 | P19: =$A19 -> 38442 | Q19: ='Global (Gross)'!Q19 -> -1.781636 | R19: =R18*Q19/100+R18 -> 994443.57 | T19: =(R19/R16-1)*100 -> -0.55564286
A20: 38472 | B20: =IF(A20>A19,1+B19,"-") -> 4 | C20: Model | D20: 0.38 | E20: =E19*D20/100+E19 -> 1033562.2 | J20: =A20 -> 38472 | K20: ='Global (Gross)'!K20 -> -2.1392996 | L20: =L19*K20/100+L19 -> 970208.77 | P20: =$A20 -> 38472 | Q20: ='Global (Gross)'!Q20 -> -0.24720344 | R20: =R19*Q20/100+R19 -> 991985.27
A21: 38503 | B21: =IF(A21>A20,1+B20,"-") -> 5 | C21: Model | D21: 1.64 | E21: =E20*D21/100+E20 -> 1050512.6 | J21: =A21 -> 38503 | K21: ='Global (Gross)'!K21 -> 1.9416122 | L21: =L20*K21/100+L20 -> 989046.46 | P21: =$A21 -> 38503 | Q21: ='Global (Gross)'!Q21 -> 0.035078984 | R21: =R20*Q21/100+R20 -> 992333.25
A22: 38533 | B22: =IF(A22>A21,1+B21,"-") -> 6 | C22: Model | D22: 1.12 | E22: =E21*D22/100+E21 -> 1062278.4 | G22: =(E22/E19-1)*100 -> 3.1689258 | J22: =A22 -> 38533 | K22: ='Global (Gross)'!K22 -> 1.0632775 | L22: =L21*K22/100+L21 -> 999562.77 | N22: =(L22/L19-1)*100 -> 0.82150949 | P22: =$A22 -> 38533 | Q22: ='Global (Gross)'!Q22 -> 1.1526758 | R22: =R21*Q22/100+R21 -> 1003771.6 | T22: =(R22/R19-1)*100 -> 0.93801853
A23: 38564 | B23: =IF(A23>A22,1+B22,"-") -> 7 | C23: Model | D23: 3.05 | E23: =E22*D23/100+E22 -> 1094677.9 | J23: =A23 -> 38564 | K23: ='Global (Gross)'!K23 -> 3.7250928 | L23: =L22*K23/100+L22 -> 1036797.4 | P23: =$A23 -> 38564 | Q23: ='Global (Gross)'!Q23 -> 2.4300508 | R23: =R22*Q23/100+R22 -> 1028163.8
A24: 38595 | B24: =IF(A24>A23,1+B23,"-") -> 8 | C24: Model | D24: 0.98 | E24: =E23*D24/100+E23 -> 1105405.7 | J24: =A24 -> 38595 | K24: ='Global (Gross)'!K24 -> 0.8137914 | L24: =L23*K24/100+L23 -> 1045234.8 | P24: =$A24 -> 38595 | Q24: ='Global (Gross)'!Q24 -> 0.63322234 | R24: =R23*Q24/100+R23 -> 1034674.4
A25: 38625 | B25: =IF(A25>A24,1+B24,"-") -> 9 | C25: Model | D25: 0.65 | E25: =E24*D25/100+E24 -> 1112590.8 | G25: =(E25/E22-1)*100 -> 4.7362793 | J25: =A25 -> 38625 | K25: ='Global (Gross)'!K25 -> 3.0411897 | L25: =L24*K25/100+L24 -> 1077022.4 | N25: =(L25/L22-1)*100 -> 7.7493463 | P25: =$A25 -> 38625 | Q25: ='Global (Gross)'!Q25 -> 2.3129916 | R25: =R24*Q25/100+R24 -> 1058606.3 | T25: =(R25/R22-1)*100 -> 5.4628615
A26: 38656 | B26: =IF(A26>A25,1+B25,"-") -> 10 | C26: Model | D26: -3.13 | E26: =E25*D26/100+E25 -> 1077766.7 | J26: =A26 -> 38656 | K26: ='Global (Gross)'!K26 -> -2.675385 | L26: =L25*K26/100+L25 -> 1048207.9 | P26: =$A26 -> 38656 | Q26: ='Global (Gross)'!Q26 -> -3.5660131 | R26: =R25*Q26/100+R25 -> 1020856.3
A27: 38686 | B27: =IF(A27>A26,1+B26,"-") -> 11 | C27: Model | D27: 1.32 | E27: =E26*D27/100+E26 -> 1091993.3 | J27: =A27 -> 38686 | K27: ='Global (Gross)'!K27 -> 3.701061 | L27: =L26*K27/100+L26 -> 1087002.7 | P27: =$A27 -> 38686 | Q27: ='Global (Gross)'!Q27 -> 2.1221851 | R27: =R26*Q27/100+R26 -> 1042520.7
A28: 38717 | B28: =IF(A28>A27,1+B27,"-") -> 12 | C28: Model | D28: 1.87 | E28: =E27*D28/100+E27 -> 1112413.5 | F28: =(E28-E16)/E16*100 -> 11.241354 | G28: =(E28/E25-1)*100 -> -0.015935609 | J28: =A28 -> 38717 | K28: ='Global (Gross)'!K28 -> 2.5029585 | L28: =L27*K28/100+L27 -> 1114209.9 | M28: =(L28-L16)/L16*100 -> 11.42099 | N28: =(L28/L25-1)*100 -> 3.4528108 | P28: =$A28 -> 38717 | Q28: ='Global (Gross)'!Q28 -> 2.1426879 | R28: =R27*Q28/100+R27 -> 1064858.7 | S28: =(R28-R16)/R16*100 -> 6.4858676 | T28: =(R28/R25-1)*100 -> 0.59062424
A29: 38748 | B29: =IF(A29>A28,1+B28,"-") -> 13 | C29: Model | D29: 3.26 | E29: =E28*D29/100+E28 -> 1148678.2 | J29: =A29 -> 38748 | K29: ='Global (Gross)'!K29 -> 4.9319748 | L29: =L28*K29/100+L28 -> 1169162.4 | P29: =$A29 -> 38748 | Q29: ='Global (Gross)'!Q29 -> 4.0626581 | R29: =R28*Q29/100+R28 -> 1108120.2
A30: 38776 | B30: =IF(A30>A29,1+B29,"-") -> 14 | C30: Model | D30: -0.33 | E30: =E29*D30/100+E29 -> 1144887.6 | J30: =A30 -> 38776 | K30: ='Global (Gross)'!K30 -> -0.10753041 | L30: =L29*K30/100+L29 -> 1167905.2 | P30: =$A30 -> 38776 | Q30: ='Global (Gross)'!Q30 -> 0.37784396 | R30: =R29*Q30/100+R29 -> 1112307.2
A31: 38807 | B31: =IF(A31>A30,1+B30,"-") -> 15 | C31: Model | D31: 0.47 | E31: =E30*D31/100+E30 -> 1150268.6 | G31: =(E31/E28-1)*100 -> 3.4029624 | J31: =A31 -> 38807 | K31: ='Global (Gross)'!K31 -> 2.1593332 | L31: =L30*K31/100+L30 -> 1193124.2 | N31: =(L31/L28-1)*100 -> 7.0825355 | P31: =$A31 -> 38807 | Q31: ='Global (Gross)'!Q31 -> 1.2634851 | R31: =R30*Q31/100+R30 -> 1126361 | T31: =(R31/R28-1)*100 -> 5.7756367
A32: 38837 | B32: =IF(A32>A31,1+B31,"-") -> 16 | C32: Model | D32: 2.56 | E32: =E31*D32/100+E31 -> 1179715.4 | J32: =A32 -> 38837 | K32: ='Global (Gross)'!K32 -> 3.3753138 | L32: =L31*K32/100+L31 -> 1233395.9 | P32: =$A32 -> 38837 | Q32: ='Global (Gross)'!Q32 -> 3.0515332 | R32: =R31*Q32/100+R31 -> 1160732.3
A33: 38868 | B33: =IF(A33>A32,1+B32,"-") -> 17 | C33: Model | D33: -0.84 | E33: =E32*D33/100+E32 -> 1169805.8 | J33: =A33 -> 38868 | K33: ='Global (Gross)'!K33 -> -3.8580235 | L33: =L32*K33/100+L32 -> 1185811.2 | P33: =$A33 -> 38868 | Q33: ='Global (Gross)'!Q33 -> -2.9369953 | R33: =R32*Q33/100+R32 -> 1126641.7
A34: 38898 | B34: =IF(A34>A33,1+B33,"-") -> 18 | C34: Model | D34: 0 | E34: =E33*D34/100+E33 -> 1169805.8 | G34: =(E34/E31-1)*100 -> 1.698496 | J34: =A34 -> 38898 | K34: ='Global (Gross)'!K34 -> 0.0020154896 | L34: =L33*K34/100+L33 -> 1185835.1 | N34: =(L34/L31-1)*100 -> -0.61092705 | P34: =$A34 -> 38898 | Q34: ='Global (Gross)'!Q34 -> 0.2022557 | R34: =R33*Q34/100+R33 -> 1128920.4 | T34: =(R34/R31-1)*100 -> 0.22722063
A35: 38929 | B35: =IF(A35>A34,1+B34,"-") -> 19 | C35: Model | D35: 3.18 | E35: =E34*D35/100+E34 -> 1207005.7 | J35: =A35 -> 38929 | K35: ='Global (Gross)'!K35 -> 0.70265073 | L35: =L34*K35/100+L34 -> 1194167.4 | P35: =$A35 -> 38929 | Q35: ='Global (Gross)'!Q35 -> 1.9130763 | R35: =R34*Q35/100+R34 -> 1150517.5
A36: 38960 | B36: =IF(A36>A35,1+B35,"-") -> 20 | C36: Model | D36: 2.69 | E36: =E35*D36/100+E35 -> 1239474.1 | J36: =A36 -> 38960 | K36: ='Global (Gross)'!K36 -> 2.6488347 | L36: =L35*K36/100+L35 -> 1225798.9 | P36: =$A36 -> 38960 | Q36: ='Global (Gross)'!Q36 -> 2.2235231 | R36: =R35*Q36/100+R35 -> 1176099.5
A37: 38990 | B37: =IF(A37>A36,1+B36,"-") -> 21 | C37: Model | D37: 0 | E37: =E36*D37/100+E36 -> 1239474.1 | G37: =(E37/E34-1)*100 -> 5.955542 | J37: =A37 -> 38990 | K37: ='Global (Gross)'!K37 -> 1.2016998 | L37: =L36*K37/100+L36 -> 1240529.3 | N37: =(L37/L34-1)*100 -> 4.6122958 | P37: =$A37 -> 38990 | Q37: ='Global (Gross)'!Q37 -> 1.2646267 | R37: =R36*Q37/100+R36 -> 1190972.8 | T37: =(R37/R34-1)*100 -> 5.4966143
A38: 39021 | B38: =IF(A38>A37,1+B37,"-") -> 22 | C38: Model | D38: 3.17 | E38: =E37*D38/100+E37 -> 1278765.4 | J38: =A38 -> 39021 | K38: ='Global (Gross)'!K38 -> 3.7716947 | L38: =L37*K38/100+L37 -> 1287318.3 | P38: =$A38 -> 39021 | Q38: ='Global (Gross)'!Q38 -> 3.4882515 | R38: =R37*Q38/100+R37 -> 1232516.9
A39: 39051 | B39: =IF(A39>A38,1+B38,"-") -> 23 | C39: Model | D39: 2.44 | E39: =E38*D39/100+E38 -> 1309967.3 | J39: =A39 -> 39051 | K39: ='Global (Gross)'!K39 -> 2.8775939 | L39: =L38*K39/100+L38 -> 1324362.1 | P39: =$A39 -> 39051 | Q39: ='Global (Gross)'!Q39 -> 2.9881603 | R39: =R38*Q39/100+R38 -> 1269346.5
A40: 39082 | B40: =IF(A40>A39,1+B39,"-") -> 24 | C40: Model | D40: 1.01 | E40: =E39*D40/100+E39 -> 1323198 | F40: =(E40-E28)/E28*100 -> 18.948388 | G40: =(E40/E37-1)*100 -> 6.7547902 | J40: =A40 -> 39082 | K40: ='Global (Gross)'!K40 -> 2.2787232 | L40: =L39*K40/100+L39 -> 1354540.6 | M40: =(L40-L28)/L28*100 -> 21.56961 | N40: =(L40/L37-1)*100 -> 9.190538 | P40: =$A40 -> 39082 | Q40: ='Global (Gross)'!Q40 -> 2.5203173 | R40: =R39*Q40/100+R39 -> 1301338 | S40: =(R40-R28)/R28*100 -> 22.207581 | T40: =(R40/R37-1)*100 -> 9.2668168
A41: 39113 | B41: =IF(A41>A40,1+B40,"-") -> 25 | C41: Model | D41: 1.53 | E41: =E40*D41/100+E40 -> 1343442.9 | J41: =A41 -> 39113 | K41: ='Global (Gross)'!K41 -> 1.0069957 | L41: =L40*K41/100+L40 -> 1368180.8 | P41: =$A41 -> 39113 | Q41: ='Global (Gross)'!Q41 -> 1.2162407 | R41: =R40*Q41/100+R40 -> 1317165.4
A42: 39141 | B42: =IF(A42>A41,1+B41,"-") -> 26 | C42: Model | D42: -0.32 | E42: =E41*D42/100+E41 -> 1339143.9 | J42: =A42 -> 39141 | K42: ='Global (Gross)'!K42 -> -0.48449065 | L42: =L41*K42/100+L41 -> 1361552.1 | P42: =$A42 -> 39141 | Q42: ='Global (Gross)'!Q42 -> 0.019600992 | R42: =R41*Q42/100+R41 -> 1317423.6
A43: 39172 | B43: =IF(A43>A42,1+B42,"-") -> 27 | C43: Model | D43: 2.09 | E43: =E42*D43/100+E42 -> 1367132 | G43: =(E43/E40-1)*100 -> 3.3202907 | J43: =A43 -> 39172 | K43: ='Global (Gross)'!K43 -> 2.0520986 | L43: =L42*K43/100+L42 -> 1389492.5 | N43: =(L43/L40-1)*100 -> 2.580347 | P43: =$A43 -> 39172 | Q43: ='Global (Gross)'!Q43 -> 1.2695545 | R43: =R42*Q43/100+R42 -> 1334149 | T43: =(R43/R40-1)*100 -> 2.5213273
A44: 39202 | B44: =IF(A44>A43,1+B43,"-") -> 28 | C44: Model | D44: 3.72 | E44: =E43*D44/100+E43 -> 1417989.3 | J44: =A44 -> 39202 | K44: ='Global (Gross)'!K44 -> 4.4809459 | L44: =L43*K44/100+L43 -> 1451754.9 | P44: =$A44 -> 39202 | Q44: ='Global (Gross)'!Q44 -> 2.5459808 | R44: =R43*Q44/100+R43 -> 1368116.2
A45: 39233 | B45: =IF(A45>A44,1+B44,"-") -> 29 | C45: Model | D45: 2.74 | E45: =E44*D45/100+E44 -> 1456842.2 | J45: =A45 -> 39233 | K45: ='Global (Gross)'!K45 -> 3.07585 | L45: =L44*K45/100+L44 -> 1496408.7 | P45: =$A45 -> 39233 | Q45: ='Global (Gross)'!Q45 -> 1.2011815 | R45: =R44*Q45/100+R44 -> 1384549.8
A46: 39263 | B46: =IF(A46>A45,1+B45,"-") -> 30 | C46: Model | D46: -1.35 | E46: =E45*D46/100+E45 -> 1437174.8 | G46: =(E46/E43-1)*100 -> 5.123342 | J46: =A46 -> 39263 | K46: ='Global (Gross)'!K46 -> -0.25641315 | L46: =L45*K46/100+L45 -> 1492571.7 | N46: =(L46/L43-1)*100 -> 7.41848 | P46: =$A46 -> 39263 | Q46: ='Global (Gross)'!Q46 -> -2.1030614 | R46: =R45*Q46/100+R45 -> 1355431.8 | T46: =(R46/R43-1)*100 -> 1.5952345
A47: 39294 | B47: =IF(A47>A46,1+B46,"-") -> 31 | C47: Model | D47: -2.55 | E47: =E46*D47/100+E46 -> 1400526.9 | J47: =A47 -> 39294 | K47: ='Global (Gross)'!K47 -> -1.5107855 | L47: =L46*K47/100+L46 -> 1470022.1 | P47: =$A47 -> 39294 | Q47: ='Global (Gross)'!Q47 -> -2.2277433 | R47: =R46*Q47/100+R46 -> 1325236.3
A48: 39325 | B48: =IF(A48>A47,1+B47,"-") -> 32 | C48: Model | D48: 1.21 | E48: =E47*D48/100+E47 -> 1417473.3 | J48: =A48 -> 39325 | K48: ='Global (Gross)'!K48 -> -0.22543895 | L48: =L47*K48/100+L47 -> 1466708.1 | P48: =$A48 -> 39325 | Q48: ='Global (Gross)'!Q48 -> 0.91478909 | R48: =R47*Q48/100+R47 -> 1337359.4
A49: 39355 | B49: =IF(A49>A48,1+B48,"-") -> 33 | C49: Model | D49: 3.24 | E49: =E48*D49/100+E48 -> 1463399.4 | G49: =(E49/E46-1)*100 -> 1.8247293 | J49: =A49 -> 39355 | K49: ='Global (Gross)'!K49 -> 5.4063212 | L49: =L48*K49/100+L48 -> 1546003.1 | N49: =(L49/L46-1)*100 -> 3.5798209 | P49: =$A49 -> 39355 | Q49: ='Global (Gross)'!Q49 -> 3.5538022 | R49: =R48*Q49/100+R48 -> 1384886.5 | T49: =(R49/R46-1)*100 -> 2.1730849
A50: 39386 | B50: =IF(A50>A49,1+B49,"-") -> 34 | C50: Model | D50: 2.37 | E50: =E49*D50/100+E49 -> 1498082 | J50: =A50 -> 39386 | K50: ='Global (Gross)'!K50 -> 3.9223514 | L50: =L49*K50/100+L49 -> 1606642.8 | P50: =$A50 -> 39386 | Q50: ='Global (Gross)'!Q50 -> 2.4697262 | R50: =R49*Q50/100+R49 -> 1419089.4
A51: 39416 | B51: =IF(A51>A50,1+B50,"-") -> 35 | C51: Model | D51: -1.2 | E51: =E50*D51/100+E50 -> 1480105 | J51: =A51 -> 39416 | K51: ='Global (Gross)'!K51 -> -4.3203565 | L51: =L50*K51/100+L50 -> 1537230.1 | P51: =$A51 -> 39416 | Q51: ='Global (Gross)'!Q51 -> -2.5604923 | R51: =R50*Q51/100+R50 -> 1382753.7
A52: 39447 | B52: =IF(A52>A51,1+B51,"-") -> 36 | C52: Model | D52: -1.35 | E52: =E51*D52/100+E51 -> 1460123.6 | F52: =(E52-E40)/E40*100 -> 10.34808 | G52: =(E52/E49-1)*100 -> -0.22385106 | J52: =A52 -> 39447 | K52: ='Global (Gross)'!K52 -> -1.0547755 | L52: =L51*K52/100+L51 -> 1521015.7 | M52: =(L52-L40)/L40*100 -> 12.290153 | N52: =(L52/L49-1)*100 -> -1.6162547 | P52: =$A52 -> 39447 | Q52: ='Global (Gross)'!Q52 -> -1.4587933 | R52: =R51*Q52/100+R51 -> 1362582.2 | S52: =(R52-R40)/R40*100 -> 4.7062477 | T52: =(R52/R49-1)*100 -> -1.61055
A53: 39478 | B53: =IF(A53>A52,1+B52,"-") -> 37 | C53: Model | D53: -3.29 | E53: =E52*D53/100+E52 -> 1412085.5 | J53: =A53 -> 39478 | K53: ='Global (Gross)'!K53 -> -8.1778004 | L53: =L52*K53/100+L52 -> 1396630.1 | P53: =$A53 -> 39478 | Q53: ='Global (Gross)'!Q53 -> -5.1035119 | R53: =R52*Q53/100+R52 -> 1293042.7
A54: 39507 | B54: =IF(A54>A53,1+B53,"-") -> 38 | C54: Model | D54: -2.1 | E54: =E53*D54/100+E53 -> 1382431.7 | J54: =A54 -> 39507 | K54: ='Global (Gross)'!K54 -> 0.32632121 | L54: =L53*K54/100+L53 -> 1401187.6 | P54: =$A54 -> 39507 | Q54: ='Global (Gross)'!Q54 -> -0.11372318 | R54: =R53*Q54/100+R53 -> 1291572.2
A55: 39538 | B55: =IF(A55>A54,1+B54,"-") -> 39 | C55: Model | D55: 0.33 | E55: =E54*D55/100+E54 -> 1386993.7 | G55: =(E55/E52-1)*100 -> -5.008469 | J55: =A55 -> 39538 | K55: ='Global (Gross)'!K55 -> -1.4119843 | L55: =L54*K55/100+L54 -> 1381403.1 | N55: =(L55/L52-1)*100 -> -9.178911 | P55: =$A55 -> 39538 | Q55: ='Global (Gross)'!Q55 -> -0.85519855 | R55: =R54*Q55/100+R54 -> 1280526.7 | T55: =(R55/R52-1)*100 -> -6.0220617
A56: 39568 | B56: =IF(A56>A55,1+B55,"-") -> 40 | C56: Model | D56: 2.74 | E56: =E55*D56/100+E55 -> 1424997.4 | J56: =A56 -> 39568 | K56: ='Global (Gross)'!K56 -> 5.6487331 | L56: =L55*K56/100+L55 -> 1459434.8 | P56: =$A56 -> 39568 | Q56: ='Global (Gross)'!Q56 -> 2.1248806 | R56: =R55*Q56/100+R55 -> 1307736.3
A57: 39599 | B57: =IF(A57>A56,1+B56,"-") -> 41 | C57: Model | D57: 1.05 | E57: =E56*D57/100+E56 -> 1439959.8 | J57: =A57 -> 39599 | K57: ='Global (Gross)'!K57 -> 1.6884277 | L57: =L56*K57/100+L56 -> 1484076.3 | P57: =$A57 -> 39599 | Q57: ='Global (Gross)'!Q57 -> 1.1261706 | R57: =R56*Q57/100+R56 -> 1322463.7
A58: 39629 | B58: =IF(A58>A57,1+B57,"-") -> 42 | C58: Model | D58: -7.49 | E58: =E57*D58/100+E57 -> 1332106.8 | G58: =(E58/E55-1)*100 -> -3.9572559 | J58: =A58 -> 39629 | K58: ='Global (Gross)'!K58 -> -8.1762106 | L58: =L57*K58/100+L57 -> 1362735.1 | N58: =(L58/L55-1)*100 -> -1.3513747 | P58: =$A58 -> 39629 | Q58: ='Global (Gross)'!Q58 -> -5.9356777 | R58: =R57*Q58/100+R57 -> 1243966.5 | T58: =(R58/R55-1)*100 -> -2.8550891
A59: 39660 | B59: =IF(A59>A58,1+B58,"-") -> 43 | C59: Model | D59: 2.69 | E59: =E58*D59/100+E58 -> 1367940.5 | J59: =A59 -> 39660 | K59: ='Global (Gross)'!K59 -> -2.5668682 | L59: =L58*K59/100+L58 -> 1327755.5 | P59: =$A59 -> 39660 | Q59: ='Global (Gross)'!Q59 -> -0.37267641 | R59: =R58*Q59/100+R58 -> 1239330.5
A60: 39691 | B60: =IF(A60>A59,1+B59,"-") -> 44 | C60: Model | D60: 1.96 | E60: =E59*D60/100+E59 -> 1394752.1 | J60: =A60 -> 39691 | K60: ='Global (Gross)'!K60 -> -2.1051266 | L60: =L59*K60/100+L59 -> 1299804.6 | P60: =$A60 -> 39691 | Q60: ='Global (Gross)'!Q60 -> -0.34961551 | R60: =R59*Q60/100+R59 -> 1234997.6
A61: 39721 | B61: =IF(A61>A60,1+B60,"-") -> 45 | C61: Model | D61: -3.51 | E61: =E60*D61/100+E60 -> 1345796.3 | G61: =(E61/E58-1)*100 -> 1.0276584 | J61: =A61 -> 39721 | K61: ='Global (Gross)'!K61 -> -12.454153 | L61: =L60*K61/100+L60 -> 1137924.9 | N61: =(L61/L58-1)*100 -> -16.496985 | P61: =$A61 -> 39721 | Q61: ='Global (Gross)'!Q61 -> -6.2524427 | R61: =R60*Q61/100+R60 -> 1157780.1 | T61: =(R61/R58-1)*100 -> -6.9283523
A62: 39752 | B62: =IF(A62>A61,1+B61,"-") -> 46 | C62: Model | D62: -10.61 | E62: =E61*D62/100+E61 -> 1203007.3 | J62: =A62 -> 39752 | K62: ='Global (Gross)'!K62 -> -19.791427 | L62: =L61*K62/100+L61 -> 912713.34 | P62: =$A62 -> 39752 | Q62: ='Global (Gross)'!Q62 -> -14.402474 | R62: =R61*Q62/100+R61 -> 991031.14
A63: 39782 | B63: =IF(A63>A62,1+B62,"-") -> 47 | C63: Model | D63: -5.26 | E63: =E62*D63/100+E62 -> 1139729.2 | J63: =A63 -> 39782 | K63: ='Global (Gross)'!K63 -> -6.4962886 | L63: =L62*K63/100+L62 -> 853420.85 | P63: =$A63 -> 39782 | Q63: ='Global (Gross)'!Q63 -> -2.8328066 | R63: =R62*Q63/100+R62 -> 962957.14
A64: 39813 | B64: =IF(A64>A63,1+B63,"-") -> 48 | C64: Model | D64: -0.42 | E64: =E63*D64/100+E63 -> 1134942.3 | F64: =(E64-E52)/E52*100 -> -22.270804 | G64: =(E64/E61-1)*100 -> -15.667604 | J64: =A64 -> 39813 | K64: ='Global (Gross)'!K64 -> 3.6902535 | L64: =L63*K64/100+L63 -> 884914.24 | M64: =(L64-L52)/L52*100 -> -41.820836 | N64: =(L64/L61-1)*100 -> -22.234392 | P64: =$A64 -> 39813 | Q64: ='Global (Gross)'!Q64 -> 2.6775931 | R64: =R63*Q64/100+R63 -> 988741.22 | S64: =(R64-R52)/R52*100 -> -27.436216 | T64: =(R64/R61-1)*100 -> -14.60026
A65: 39844 | B65: =IF(A65>A64,1+B64,"-") -> 49 | C65: Model | D65: -3.78 | E65: =E64*D65/100+E64 -> 1092041.5 | J65: =A65 -> 39844 | K65: ='Global (Gross)'!K65 -> -8.5254818 | L65: =L64*K65/100+L64 -> 809471.04 | P65: =$A65 -> 39844 | Q65: ='Global (Gross)'!Q65 -> -6.8866864 | R65: =R64*Q65/100+R64 -> 920649.71
A66: 39872 | B66: =IF(A66>A65,1+B65,"-") -> 50 | C66: Model | D66: -10.13 | E66: =E65*D66/100+E65 -> 981417.68 | J66: =A66 -> 39872 | K66: ='Global (Gross)'!K66 -> -9.7234301 | L66: =L65*K66/100+L65 -> 730762.69 | P66: =$A66 -> 39872 | Q66: ='Global (Gross)'!Q66 -> -9.1919968 | R66: =R65*Q66/100+R65 -> 836023.62
A67: 39903 | B67: =IF(A67>A66,1+B66,"-") -> 51 | C67: Model | D67: 3.32 | E67: =E66*D67/100+E66 -> 1014000.7 | G67: =(E67/E64-1)*100 -> -10.656185 | J67: =A67 -> 39903 | K67: ='Global (Gross)'!K67 -> 8.3095818 | L67: =L66*K67/100+L66 -> 791486.01 | N67: =(L67/L64-1)*100 -> -10.557885 | P67: =$A67 -> 39903 | Q67: ='Global (Gross)'!Q67 -> 3.3566959 | R67: =R66*Q67/100+R66 -> 864086.39 | T67: =(R67/R64-1)*100 -> -12.607427
A68: 39933 | B68: =IF(A68>A67,1+B67,"-") -> 52 | C68: Model | D68: 5.3 | E68: =E67*D68/100+E67 -> 1067742.8 | J68: =A68 -> 39933 | K68: ='Global (Gross)'!K68 -> 11.891768 | L68: =L67*K68/100+L67 -> 885607.69 | P68: =$A68 -> 39933 | Q68: ='Global (Gross)'!Q68 -> 5.4587025 | R68: =R67*Q68/100+R67 -> 911254.29
A69: 39964 | B69: =IF(A69>A68,1+B68,"-") -> 53 | C69: Model | D69: 4.73 | E69: =E68*D69/100+E68 -> 1118247 | J69: =A69 -> 39964 | K69: ='Global (Gross)'!K69 -> 10.086235 | L69: =L68*K69/100+L68 -> 974932.17 | P69: =$A69 -> 39964 | Q69: ='Global (Gross)'!Q69 -> 6.6531165 | R69: =R68*Q69/100+R68 -> 971881.1
A70: 39994 | B70: =IF(A70>A69,1+B69,"-") -> 54 | C70: Model | D70: 1.28 | E70: =E69*D70/100+E69 -> 1132560.6 | G70: =(E70/E67-1)*100 -> 11.692283 | J70: =A70 -> 39994 | K70: ='Global (Gross)'!K70 -> -0.51440637 | L70: =L69*K70/100+L69 -> 969917.05 | N70: =(L70/L67-1)*100 -> 22.543802 | P70: =$A70 -> 39994 | Q70: ='Global (Gross)'!Q70 -> 0.9008905 | R70: =R69*Q70/100+R69 -> 980636.69 | T70: =(R70/R67-1)*100 -> 13.488269
A71: 40025 | B71: =IF(A71>A70,1+B70,"-") -> 55 | C71: Model | D71: 6.15 | E71: =E70*D71/100+E70 -> 1202213.1 | J71: =A71 -> 40025 | K71: ='Global (Gross)'!K71 -> 8.8335735 | L71: =L70*K71/100+L70 -> 1055595.4 | P71: =$A71 -> 40025 | Q71: ='Global (Gross)'!Q71 -> 5.9866531 | R71: =R70*Q71/100+R70 -> 1039344
A72: 40056 | B72: =IF(A72>A71,1+B71,"-") -> 56 | C72: Model | D72: 1.82 | E72: =E71*D72/100+E71 -> 1224093.3 | J72: =A72 -> 40056 | K72: ='Global (Gross)'!K72 -> 3.6294109 | L72: =L71*K72/100+L71 -> 1093907.3 | P72: =$A72 -> 40056 | Q72: ='Global (Gross)'!Q72 -> 1.568187 | R72: =R71*Q72/100+R71 -> 1055642.9
A73: 40086 | B73: =IF(A73>A72,1+B72,"-") -> 57 | C73: Model | D73: 3.09 | E73: =E72*D73/100+E72 -> 1261917.8 | G73: =(E73/E70-1)*100 -> 11.421662 | J73: =A73 -> 40086 | K73: ='Global (Gross)'!K73 -> 4.6198655 | L73: =L72*K73/100+L72 -> 1144444.3 | N73: =(L73/L70-1)*100 -> 17.994041 | P73: =$A73 -> 40086 | Q73: ='Global (Gross)'!Q73 -> 3.5345533 | R73: =R72*Q73/100+R72 -> 1092955.1 | T73: =(R73/R70-1)*100 -> 11.453623
A74: 40117 | B74: =IF(A74>A73,1+B73,"-") -> 58 | C74: Model | D74: -0.31 | E74: =E73*D74/100+E73 -> 1258005.9 | J74: =A74 -> 40117 | K74: ='Global (Gross)'!K74 -> -1.5227999 | L74: =L73*K74/100+L73 -> 1127016.7 | P74: =$A74 -> 40117 | Q74: ='Global (Gross)'!Q74 -> -1.5477523 | R74: =R73*Q74/100+R73 -> 1076038.9
A75: 40147 | B75: =IF(A75>A74,1+B74,"-") -> 59 | C75: Model | D75: 5.62 | E75: =E74*D75/100+E74 -> 1328705.8 | J75: =A75 -> 40147 | K75: ='Global (Gross)'!K75 -> 4.165019 | L75: =L74*K75/100+L74 -> 1173957.2 | P75: =$A75 -> 40147 | Q75: ='Global (Gross)'!Q75 -> 4.3187982 | R75: =R74*Q75/100+R74 -> 1122510.8
A76: 40178 | B76: =IF(A76>A75,1+B75,"-") -> 60 | C76: Model | D76: 2.25 | E76: =E75*D76/100+E75 -> 1358601.7 | F76: =(E76-E64)/E64*100 -> 19.706674 | G76: =(E76/E73-1)*100 -> 7.661661 | J76: =A76 -> 40178 | K76: ='Global (Gross)'!K76 -> 2.1222145 | L76: =L75*K76/100+L75 -> 1198871.1 | M76: =(L76-L64)/L64*100 -> 35.478787 | N76: =(L76/L73-1)*100 -> 4.7557363 | P76: =$A76 -> 40178 | Q76: ='Global (Gross)'!Q76 -> 0.384 | R76: =R75*Q76/100+R75 -> 1126821.3 | S76: =(R76-R64)/R64*100 -> 13.965237 | T76: =(R76/R73-1)*100 -> 3.0985858
A77: 40209 | B77: =IF(A77>A76,1+B76,"-") -> 61 | C77: Model | D77: -2.34 | E77: =E76*D77/100+E76 -> 1326810.4 | J77: =A77 -> 40209 | K77: ='Global (Gross)'!K77 -> -4.3104601 | L77: =L76*K77/100+L76 -> 1147194.2 | P77: =$A77 -> 40209 | Q77: ='Global (Gross)'!Q77 -> -2.5253028 | R77: =R76*Q77/100+R76 -> 1098365.6
A78: 40237 | B78: =IF(A78>A77,1+B77,"-") -> 62 | C78: Model | D78: 1.44 | E78: =E77*D78/100+E77 -> 1345916.5 | J78: =A78 -> 40237 | K78: ='Global (Gross)'!K78 -> 1.3136041 | L78: =L77*K78/100+L77 -> 1162263.8 | P78: =$A78 -> 40237 | Q78: ='Global (Gross)'!Q78 -> 1.310182 | R78: =R77*Q78/100+R77 -> 1112756.2
A79: 40268 | B79: =IF(A79>A78,1+B78,"-") -> 63 | C79: Model | D79: 3.25 | E79: =E78*D79/100+E78 -> 1389658.8 | G79: =(E79/E76-1)*100 -> 2.2859589 | J79: =A79 -> 40268 | K79: ='Global (Gross)'!K79 -> 6.4905123 | L79: =L78*K79/100+L78 -> 1237700.7 | N79: =(L79/L76-1)*100 -> 3.2388476 | P79: =$A79 -> 40268 | Q79: ='Global (Gross)'!Q79 -> 3.4287962 | R79: =R78*Q79/100+R78 -> 1150910.4 | T79: =(R79/R76-1)*100 -> 2.1377909
A80: 40298 | B80: =IF(A80>A79,1+B79,"-") -> 64 | C80: Model | D80: 0.03 | E80: =E79*D80/100+E79 -> 1390075.7 | J80: =A80 -> 40298 | K80: ='Global (Gross)'!K80 -> 0.21652668 | L80: =L79*K80/100+L79 -> 1240380.6 | P80: =$A80 -> 40298 | Q80: ='Global (Gross)'!Q80 -> -0.35891934 | R80: =R79*Q80/100+R79 -> 1146779.5
A81: 40329 | B81: =IF(A81>A80,1+B80,"-") -> 65 | C81: Model | D81: -7.15 | E81: =E80*D81/100+E80 -> 1290685.2 | J81: =A81 -> 40329 | K81: ='Global (Gross)'!K81 -> -9.3928222 | L81: =L80*K81/100+L80 -> 1123873.9 | P81: =$A81 -> 40329 | Q81: ='Global (Gross)'!Q81 -> -5.8485543 | R81: =R80*Q81/100+R80 -> 1079709.5
A82: 40359 | B82: =IF(A82>A81,1+B81,"-") -> 66 | C82: Model | D82: -1.9 | E82: =E81*D82/100+E81 -> 1266162.2 | G82: =(E82/E79-1)*100 -> -8.8868242 | J82: =A82 -> 40359 | K82: ='Global (Gross)'!K82 -> -3.0254131 | L82: =L81*K82/100+L81 -> 1089872.1 | N82: =(L82/L79-1)*100 -> -11.94381 | P82: =$A82 -> 40359 | Q82: ='Global (Gross)'!Q82 -> 0.64145882 | R82: =R81*Q82/100+R81 -> 1086635.4 | T82: =(R82/R79-1)*100 -> -5.5847069
A83: 40390 | B83: =IF(A83>A82,1+B82,"-") -> 67 | C83: Model | D83: 4.96 | E83: =E82*D83/100+E82 -> 1328963.9 | J83: =A83 -> 40390 | K83: ='Global (Gross)'!K83 -> 8.1620392 | L83: =L82*K83/100+L82 -> 1178827.9 | P83: =$A83 -> 40390 | Q83: ='Global (Gross)'!Q83 -> 4.4874179 | R83: =R82*Q83/100+R82 -> 1135397.3
A84: 40421 | B84: =IF(A84>A83,1+B83,"-") -> 68 | C84: Model | D84: -0.51 | E84: =E83*D84/100+E83 -> 1322186.2 | J84: =A84 -> 40421 | K84: ='Global (Gross)'!K84 -> -3.4500884 | L84: =L83*K84/100+L83 -> 1138157.2 | P84: =$A84 -> 40421 | Q84: ='Global (Gross)'!Q84 -> 0.079092024 | R84: =R83*Q84/100+R83 -> 1136295.3
A85: 40451 | B85: =IF(A85>A84,1+B84,"-") -> 69 | C85: Model | D85: 7.1 | E85: =E84*D85/100+E84 -> 1416061.4 | G85: =(E85/E82-1)*100 -> 11.838858 | J85: =A85 -> 40451 | K85: ='Global (Gross)'!K85 -> 9.6104883 | L85: =L84*K85/100+L84 -> 1247539.7 | N85: =(L85/L82-1)*100 -> 14.46662 | P85: =$A85 -> 40451 | Q85: ='Global (Gross)'!Q85 -> 5.6150472 | R85: =R84*Q85/100+R84 -> 1200098.8 | T85: =(R85/R82-1)*100 -> 10.441717
A86: 40482 | B86: =IF(A86>A85,1+B85,"-") -> 70 | C86: Model | D86: 1.98 | E86: =E85*D86/100+E85 -> 1444099.4 | J86: =A86 -> 40482 | K86: ='Global (Gross)'!K86 -> 3.6512748 | L86: =L85*K86/100+L85 -> 1293090.8 | P86: =$A86 -> 40482 | Q86: ='Global (Gross)'!Q86 -> 2.6535843 | R86: =R85*Q86/100+R85 -> 1231944.4
A87: 40512 | B87: =IF(A87>A86,1+B86,"-") -> 71 | C87: Model | D87: -2.4 | E87: =E86*D87/100+E86 -> 1409441 | J87: =A87 -> 40512 | K87: ='Global (Gross)'!K87 -> -2.1768084 | L87: =L86*K87/100+L86 -> 1264942.7 | P87: =$A87 -> 40512 | Q87: ='Global (Gross)'!Q87 -> -2.3426182 | R87: =R86*Q87/100+R86 -> 1203084.7
A88: 40543 | B88: =IF(A88>A87,1+B87,"-") -> 72 | C88: Model | D88: 4.57 | E88: =E87*D88/100+E87 -> 1473852.5 | F88: =(E88-E76)/E76*100 -> 8.4830438 | G88: =(E88/E85-1)*100 -> 4.0811143 | J88: =A88 -> 40543 | K88: ='Global (Gross)'!K88 -> 7.3759904 | L88: =L87*K88/100+L87 -> 1358244.8 | M88: =(L88-L76)/L76*100 -> 13.293646 | N88: =(L88/L85-1)*100 -> 8.8738696 | P88: =$A88 -> 40543 | Q88: ='Global (Gross)'!Q88 -> 4.476665 | R88: =R87*Q88/100+R87 -> 1256942.7 | S88: =(R88-R76)/R76*100 -> 11.547657 | T88: =(R88/R85-1)*100 -> 4.7366058
A89: 40574 | B89: =IF(A89>A88,1+B88,"-") -> 73 | C89: Model | D89: 1.36 | E89: =E88*D89/100+E88 -> 1493896.9 | J89: =A89 -> 40574 | K89: ='Global (Gross)'!K89 -> 1.5819213 | L89: =L88*K89/100+L88 -> 1379731.1 | P89: =$A89 -> 40574 | Q89: ='Global (Gross)'!Q89 -> -0.66800029 | R89: =R88*Q89/100+R88 -> 1248546.3
A90: 40602 | B90: =IF(A90>A89,1+B89,"-") -> 74 | C90: Model | D90: 2.95 | E90: =E89*D90/100+E89 -> 1537966.8 | J90: =A90 -> 40602 | K90: ='Global (Gross)'!K90 -> 2.9518462 | L90: =L89*K90/100+L89 -> 1420458.7 | P90: =$A90 -> 40602 | Q90: ='Global (Gross)'!Q90 -> 1.7639443 | R90: =R89*Q90/100+R89 -> 1270570
A91: 40633 | B91: =IF(A91>A90,1+B90,"-") -> 75 | C91: Model | D91: -0.46 | E91: =E90*D91/100+E90 -> 1530892.2 | G91: =(E91/E88-1)*100 -> 3.8701094 | J91: =A91 -> 40633 | K91: ='Global (Gross)'!K91 -> -0.050006322 | L91: =L90*K91/100+L90 -> 1419748.3 | N91: =(L91/L88-1)*100 -> 4.5281665 | P91: =$A91 -> 40633 | Q91: ='Global (Gross)'!Q91 -> 0.63433165 | R91: =R90*Q91/100+R90 -> 1278629.6 | T91: =(R91/R88-1)*100 -> 1.7253697
A92: 40663 | B92: =IF(A92>A91,1+B91,"-") -> 76 | C92: Model | D92: 4.33 | E92: =E91*D92/100+E91 -> 1597179.8 | J92: =A92 -> 40663 | K92: ='Global (Gross)'!K92 -> 4.1292566 | L92: =L91*K92/100+L91 -> 1478373.4 | P92: =$A92 -> 40663 | Q92: ='Global (Gross)'!Q92 -> 4.0594164 | R92: =R91*Q92/100+R91 -> 1330534.5
A93: 40694 | B93: =IF(A93>A92,1+B92,"-") -> 77 | C93: Model | D93: 2.12 | E93: =E92*D93/100+E92 -> 1631040 | J93: =A93 -> 40694 | K93: ='Global (Gross)'!K93 -> -2.0649659 | L93: =L92*K93/100+L92 -> 1447845.5 | P93: =$A93 -> 40694 | Q93: ='Global (Gross)'!Q93 -> 0.75844498 | R93: =R92*Q93/100+R92 -> 1340625.9
A94: 40724 | B94: =IF(A94>A93,1+B93,"-") -> 78 | C94: Model | D94: -1.49 | E94: =E93*D94/100+E93 -> 1606737.5 | G94: =(E94/E91-1)*100 -> 4.9543232 | J94: =A94 -> 40724 | K94: ='Global (Gross)'!K94 -> -1.5294423 | L94: =L93*K94/100+L93 -> 1425701.5 | N94: =(L94/L91-1)*100 -> 0.41931264 | P94: =$A94 -> 40724 | Q94: ='Global (Gross)'!Q94 -> -1.2844236 | R94: =R93*Q94/100+R93 -> 1323406.6 | T94: =(R94/R91-1)*100 -> 3.5019489
A95: 40755 | B95: =IF(A95>A94,1+B94,"-") -> 79 | C95: Model | D95: -2.45 | E95: =E94*D95/100+E94 -> 1567372.4 | J95: =A95 -> 40755 | K95: ='Global (Gross)'!K95 -> -1.5961667 | L95: =L94*K95/100+L94 -> 1402945 | P95: =$A95 -> 40755 | Q95: ='Global (Gross)'!Q95 -> -0.91096466 | R95: =R94*Q95/100+R94 -> 1311350.8
A96: 40786 | B96: =IF(A96>A95,1+B95,"-") -> 80 | C96: Model | D96: -0.87 | E96: =E95*D96/100+E95 -> 1553736.3 | J96: =A96 -> 40786 | K96: ='Global (Gross)'!K96 -> -7.2548281 | L96: =L95*K96/100+L95 -> 1301163.7 | P96: =$A96 -> 40786 | Q96: ='Global (Gross)'!Q96 -> -1.7993032 | R96: =R95*Q96/100+R95 -> 1287755.7
A97: 40816 | B97: =IF(A97>A96,1+B96,"-") -> 81 | C97: Model | D97: -3.08 | E97: =E96*D97/100+E96 -> 1505881.2 | G97: =(E97/E94-1)*100 -> -6.2770855 | J97: =A97 -> 40816 | K97: ='Global (Gross)'!K97 -> -9.3941472 | L97: =L96*K97/100+L96 -> 1178930.5 | N97: =(L97/L94-1)*100 -> -17.308746 | P97: =$A97 -> 40816 | Q97: ='Global (Gross)'!Q97 -> -4.6530278 | R97: =R96*Q97/100+R96 -> 1227836 | T97: =(R97/R94-1)*100 -> -7.2215578
A98: 40847 | B98: =IF(A98>A97,1+B97,"-") -> 82 | C98: Model | D98: 6.37 | E98: =E97*D98/100+E97 -> 1601805.9 | J98: =A98 -> 40847 | K98: ='Global (Gross)'!K98 -> 10.730995 | L98: =L97*K98/100+L97 -> 1305441.4 | P98: =$A98 -> 40847 | Q98: ='Global (Gross)'!Q98 -> 4.7191977 | R98: =R97*Q98/100+R97 -> 1285780
A99: 40877 | B99: =IF(A99>A98,1+B98,"-") -> 83 | C99: Model | D99: -0.74 | E99: =E98*D99/100+E98 -> 1589952.5 | J99: =A99 -> 40877 | K99: ='Global (Gross)'!K99 -> -2.9296422 | L99: =L98*K99/100+L98 -> 1267196.7 | P99: =$A99 -> 40877 | Q99: ='Global (Gross)'!Q99 -> -1.8848487 | R99: =R98*Q99/100+R98 -> 1261545
